Workbook

Sheet Cover

Sheet Dashboard
A1: Q2 2026 Project Portfolio Executive Review
A2: Six projects. One portfolio view. Clear decisions on cost, schedule, and risk — modeled after Project_Portfolio_Review.pptx and driven by live workbook tables.
A4: PORTFOLIO CPI | D4: COST VARIANCE | G4: PROJECT MIX | J4: PORTFOLIO EAC
A5: ='Portfolio Metrics'!B37 -> 0.91029936 | D5: =TEXT('Portfolio Metrics'!B36,"$#,##0,")&"K" -> -$468K | G5: ='Portfolio Metrics'!B39&" active" -> 3 active | J5: =TEXT('Portfolio Metrics'!B38,"$#,##0,,.0")&"M" -> $7.7M
A7: Target: > 1.00 | D7: EV minus AC | G7: 2 completed · 1 planned | J7: Typical variance forecast
A9: ="Story in brief: The portfolio earns "&TEXT('Portfolio Metrics'!B37,"0.00")&" per $1 spent, with earned value trailing actual cost by "&TEXT(ABS('Portfolio Metrics'!B36),"$#,##0")&". PRJ-001 is the primary cost exception at CPI "&TEXT(_xlfn.XLOOKUP("PRJ-001",Project_EVM[ProjectID],Project_EVM[CPI]),"0.00")&", while PRJ-006 closed under budget. Active delivery remains broadly stable, but fabrication capacity and supplier constraints need management attention." -> Story in brief: The portfolio earns 0.91 per $1 spent, with earned value trailing actual cost by $468,310. PRJ-001 is the primary cost exception at CPI 0.81, while PRJ-006 closed under budget. Active delivery remains broadly stable, but fabrication capacity and supplier constraints need management attention.
A13: PORTFOLIO HEALTH | G13: PROJECT CPI WATCHLIST
A33: EXECUTIVE PROJECT TABLE
A34: Project | B34: Alert | C34: Progress | D34: BAC | E34: Actual Cost | F34: CPI | G34: Variance | H34: Action
A35: ='Portfolio Metrics'!A24 -> PRJ-001 | B35: ='Portfolio Metrics'!T24 -> CRITICAL | C35: ='Portfolio Metrics'!H24 -> 0.995 | D35: ='Portfolio Metrics'!E24 -> 1500000 | E35: ='Portfolio Metrics'!M24 -> 1848810 | F35: ='Portfolio Metrics'!P24 -> 0.80727603 | G35: ='Portfolio Metrics'!N24 -> -356310 | H35: ='Portfolio Metrics'!U24 -> Renegotiate contractor rates and freeze variation orders
A36: ='Portfolio Metrics'!A25 -> PRJ-002 | B36: ='Portfolio Metrics'!T25 -> PLANNED | C36: ='Portfolio Metrics'!H25 -> 0 | D36: ='Portfolio Metrics'!E25 -> 800000 | E36: ='Portfolio Metrics'!M25 -> 0 | F36: ='Portfolio Metrics'!P25 | G36: ='Portfolio Metrics'!N25 -> 0 | H36: ='Portfolio Metrics'!U25 -> Prepare August design start and resource ramp
A37: ='Portfolio Metrics'!A26 -> PRJ-003 | B37: ='Portfolio Metrics'!T26 -> CRITICAL | C37: ='Portfolio Metrics'!H26 -> 0.3 | D37: ='Portfolio Metrics'!E26 -> 1200000 | E37: ='Portfolio Metrics'!M26 -> 382500 | F37: ='Portfolio Metrics'!P26 -> 0.94117647 | G37: ='Portfolio Metrics'!N26 -> -22500 | H37: ='Portfolio Metrics'!U26 -> Move cleanly from engineering to steel fabrication
A38: ='Portfolio Metrics'!A27 -> PRJ-004 | B38: ='Portfolio Metrics'!T27 -> CRITICAL | C38: ='Portfolio Metrics'!H27 -> 0.7 | D38: ='Portfolio Metrics'!E27 -> 2000000 | E38: ='Portfolio Metrics'!M27 -> 1476000 | F38: ='Portfolio Metrics'!P27 -> 0.94850949 | G38: ='Portfolio Metrics'!N27 -> -76000 | H38: ='Portfolio Metrics'!U27 -> Monitor welding productivity through completion
A39: ='Portfolio Metrics'!A28 -> PRJ-005 | B39: ='Portfolio Metrics'!T28 -> WATCH | C39: ='Portfolio Metrics'!H28 -> 0.9 | D39: ='Portfolio Metrics'!E28 -> 1000000 | E39: ='Portfolio Metrics'!M28 -> 927000 | F39: ='Portfolio Metrics'!P28 -> 0.97087379 | G39: ='Portfolio Metrics'!N28 -> -27000 | H39: ='Portfolio Metrics'!U28 -> Protect final 10% from cost leakage
A40: ='Portfolio Metrics'!A29 -> PRJ-006 | B40: ='Portfolio Metrics'!T29 -> ON TRACK | C40: ='Portfolio Metrics'!H29 -> 1 | D40: ='Portfolio Metrics'!E29 -> 600000 | E40: ='Portfolio Metrics'!M29 -> 586500 | F40: ='Portfolio Metrics'!P29 -> 1.0230179 | G40: ='Portfolio Metrics'!N29 -> 13500 | H40: ='Portfolio Metrics'!U29 -> Close out lessons learned and verification pack
H45: RAID & RECOMMENDATIONS
H46: Type | I46: Constraint | J46: Owner | K46: Status
H47: ='Portfolio Metrics'!AM2 -> Risk | I47: ='Portfolio Metrics'!AN2 -> Carbon sheet delivery delay from supplier | J47: ='Portfolio Metrics'!AO2 -> Morten Hansen | K47: ='Portfolio Metrics'!AP2 -> Active
H48: ='Portfolio Metrics'!AM3 -> Issue | I48: ='Portfolio Metrics'!AN3 -> Welder overtime limits exceeded in fabrication | J48: ='Portfolio Metrics'!AO3 -> Morten Hansen | K48: ='Portfolio Metrics'!AP3 -> Active
H49: ='Portfolio Metrics'!AM4 -> Dependency | I49: ='Portfolio Metrics'!AN4 -> Sea trials depend on DNV class approval | J49: ='Portfolio Metrics'!AO4 -> Frank Ellingsen | K49: ='Portfolio Metrics'!AP4 -> Active
H51: RECOMMENDED ACTIONS
H52: ='Portfolio Metrics'!AR2&". "&'Portfolio Metrics'!AS2 -> 1. Renegotiate outfitting contractor rates (WBS 1 & 3)
A76: RAG Legend | B76: Red | C76: Amber | D76: Green
A77: Rules | B77: CPI < 0.95 / negative CV | C77: CPI 0.95–<1.00, planned/watch, or zero CV | D77: CPI ≥ 1.00 / positive CV

Sheet Portfolio Metrics
A1: Portfolio Metrics Engine | W1: Project | X1: BAC | Y1: EV | Z1: AC | AB1: Project | AC1: CPI | AE1: Project | AF1: Labor AC | AG1: Material AC | AI1: Project | AJ1: Start Offset | AK1: Duration | AM1: Type | AN1: Description | AO1: Owner | AP1: Status | AR1: No. | AS1: Recommendation
A2: Live EVM calculations supporting the executive dashboard. Formulas follow EV = BAC × progress, CV = EV − AC, CPI = EV / AC, SPI = EV / PV, and EAC = BAC / CPI. | W2: PRJ-001 | X2: =_xlfn.XLOOKUP($W2,Project_EVM[ProjectID],Project_EVM[BAC]) -> 1500000 | Y2: =_xlfn.XLOOKUP($W2,Project_EVM[ProjectID],Project_EVM[EV]) -> 1492500 | Z2: =_xlfn.XLOOKUP($W2,Project_EVM[ProjectID],Project_EVM[AC]) -> 1848810 | AB2: PRJ-001 | AC2: =_xlfn.XLOOKUP($AB2,Project_EVM[ProjectID],Project_EVM[CPI]) -> 0.80727603 | AE2: PRJ-001 | AF2: =_xlfn.XLOOKUP($AE2,Project_EVM[ProjectID],Project_EVM[Labor AC]) -> 1326810 | AG2: =_xlfn.XLOOKUP($AE2,Project_EVM[ProjectID],Project_EVM[Material AC]) -> 522000 | AI2: PRJ-006 | AJ2: =_xlfn.XLOOKUP($AI2,Project_EVM[ProjectID],Project_EVM[Start])-$AJ$8 -> 0 | AK2: =_xlfn.XLOOKUP($AI2,Project_EVM[ProjectID],Project_EVM[End])-_xlfn.XLOOKUP($AI2,Project_EVM[ProjectID],Project_EVM[Start]) -> 181 | AM2: Risk | AN2: Carbon sheet delivery delay from supplier | AO2: Morten Hansen | AP2: Active | AR2: 1 | AS2: Renegotiate outfitting contractor rates (WBS 1 & 3)
W3: PRJ-002 | X3: =_xlfn.XLOOKUP($W3,Project_EVM[ProjectID],Project_EVM[BAC]) -> 800000 | Y3: =_xlfn.XLOOKUP($W3,Project_EVM[ProjectID],Project_EVM[EV]) -> 0 | Z3: =_xlfn.XLOOKUP($W3,Project_EVM[ProjectID],Project_EVM[AC]) -> 0 | AB3: PRJ-002 | AC3: =_xlfn.XLOOKUP($AB3,Project_EVM[ProjectID],Project_EVM[CPI]) | AE3: PRJ-002 | AF3: =_xlfn.XLOOKUP($AE3,Project_EVM[ProjectID],Project_EVM[Labor AC]) -> 0 | AG3: =_xlfn.XLOOKUP($AE3,Project_EVM[ProjectID],Project_EVM[Material AC]) -> 0 | AI3: PRJ-005 | AJ3: =_xlfn.XLOOKUP($AI3,Project_EVM[ProjectID],Project_EVM[Start])-$AJ$8 -> 123 | AK3: =_xlfn.XLOOKUP($AI3,Project_EVM[ProjectID],Project_EVM[End])-_xlfn.XLOOKUP($AI3,Project_EVM[ProjectID],Project_EVM[Start]) -> 180 | AM3: Issue | AN3: Welder overtime limits exceeded in fabrication | AO3: Morten Hansen | AP3: Active | AR3: 2 | AS3: Shift composite fabricators to outfitting to optimize
A4: Report Date | B4: 46203 | W4: PRJ-003 | X4: =_xlfn.XLOOKUP($W4,Project_EVM[ProjectID],Project_EVM[BAC]) -> 1200000 | Y4: =_xlfn.XLOOKUP($W4,Project_EVM[ProjectID],Project_EVM[EV]) -> 360000 | Z4: =_xlfn.XLOOKUP($W4,Project_EVM[ProjectID],Project_EVM[AC]) -> 382500 | AB4: PRJ-003 | AC4: =_xlfn.XLOOKUP($AB4,Project_EVM[ProjectID],Project_EVM[CPI]) -> 0.94117647 | AE4: PRJ-003 | AF4: =_xlfn.XLOOKUP($AE4,Project_EVM[ProjectID],Project_EVM[Labor AC]) -> 332500 | AG4: =_xlfn.XLOOKUP($AE4,Project_EVM[ProjectID],Project_EVM[Material AC]) -> 50000 | AI4: PRJ-004 | AJ4: =_xlfn.XLOOKUP($AI4,Project_EVM[ProjectID],Project_EVM[Start])-$AJ$8 -> 151 | AK4: =_xlfn.XLOOKUP($AI4,Project_EVM[ProjectID],Project_EVM[End])-_xlfn.XLOOKUP($AI4,Project_EVM[ProjectID],Project_EVM[Start]) -> 183 | AM4: Dependency | AN4: Sea trials depend on DNV class approval | AO4: Frank Ellingsen | AP4: Active | AR4: 3 | AS4: Enforce double-shift schedules to recover sea trials
W5: PRJ-004 | X5: =_xlfn.XLOOKUP($W5,Project_EVM[ProjectID],Project_EVM[BAC]) -> 2000000 | Y5: =_xlfn.XLOOKUP($W5,Project_EVM[ProjectID],Project_EVM[EV]) -> 1400000 | Z5: =_xlfn.XLOOKUP($W5,Project_EVM[ProjectID],Project_EVM[AC]) -> 1476000 | AB5: PRJ-004 | AC5: =_xlfn.XLOOKUP($AB5,Project_EVM[ProjectID],Project_EVM[CPI]) -> 0.94850949 | AE5: PRJ-004 | AF5: =_xlfn.XLOOKUP($AE5,Project_EVM[ProjectID],Project_EVM[Labor AC]) -> 1226000 | AG5: =_xlfn.XLOOKUP($AE5,Project_EVM[ProjectID],Project_EVM[Material AC]) -> 250000 | AI5: PRJ-003 | AJ5: =_xlfn.XLOOKUP($AI5,Project_EVM[ProjectID],Project_EVM[Start])-$AJ$8 -> 212 | AK5: =_xlfn.XLOOKUP($AI5,Project_EVM[ProjectID],Project_EVM[End])-_xlfn.XLOOKUP($AI5,Project_EVM[ProjectID],Project_EVM[Start]) -> 183 | AR5: 4 | AS5: Integrate DuckDB tracking into future estimations
A6: WBS_ID | B6: ProjectID | C6: WBS Code | D6: Element Name | E6: Planned Cost | F6: Planned Hours | G6: Latest Progress | H6: EV | I6: Labor AC | J6: Material AC | K6: AC | L6: CV | M6: CPI | W6: PRJ-005 | X6: =_xlfn.XLOOKUP($W6,Project_EVM[ProjectID],Project_EVM[BAC]) -> 1000000 | Y6: =_xlfn.XLOOKUP($W6,Project_EVM[ProjectID],Project_EVM[EV]) -> 900000 | Z6: =_xlfn.XLOOKUP($W6,Project_EVM[ProjectID],Project_EVM[AC]) -> 927000 | AB6: PRJ-005 | AC6: =_xlfn.XLOOKUP($AB6,Project_EVM[ProjectID],Project_EVM[CPI]) -> 0.97087379 | AE6: PRJ-005 | AF6: =_xlfn.XLOOKUP($AE6,Project_EVM[ProjectID],Project_EVM[Labor AC]) -> 747000 | AG6: =_xlfn.XLOOKUP($AE6,Project_EVM[ProjectID],Project_EVM[Material AC]) -> 180000 | AI6: PRJ-002 | AJ6: =_xlfn.XLOOKUP($AI6,Project_EVM[ProjectID],Project_EVM[Start])-$AJ$8 -> 304 | AK6: =_xlfn.XLOOKUP($AI6,Project_EVM[ProjectID],Project_EVM[End])-_xlfn.XLOOKUP($AI6,Project_EVM[ProjectID],Project_EVM[Start]) -> 152
A7: WBS-001 | B7: =_xlfn.XLOOKUP($A7,wbs_elements[WBS_ID],wbs_elements[ProjectID]) -> PRJ-001 | C7: =_xlfn.XLOOKUP($A7,wbs_elements[WBS_ID],wbs_elements[WBS_Code]) -> 1 | D7: =_xlfn.XLOOKUP($A7,wbs_elements[WBS_ID],wbs_elements[ElementName]) -> Project Management & Engineering | E7: =_xlfn.XLOOKUP($A7,wbs_elements[WBS_ID],wbs_elements[PlannedCost]) -> 300000 | F7: =_xlfn.XLOOKUP($A7,wbs_elements[WBS_ID],wbs_elements[PlannedHours]) -> 400 | G7: =IFERROR(SUMIFS(physical_progress[PercentComplete],physical_progress[WBS_ID],$A7,physical_progress[RecordDate],_xlfn.MAXIFS(physical_progress[RecordDate],physical_progress[WBS_ID],$A7)),0) -> 0.975 | H7: =$E7*$G7 -> 292500 | I7: {=SUMPRODUCT(SUMIFS(timesheets[HoursWorked],timesheets[WBS_ID],$A7,timesheets[ResourceID],resources[ResourceID],timesheets[ApprovalStatus],"Approved")*resources[HourlyRate])} -> 419230 | J7: =SUMIFS(material_costs[TotalActualCost],material_costs[WBS_ID],$A7) -> 0 | K7: =$I7+$J7 -> 419230 | L7: =$H7-$K7 -> -126730 | M7: =IFERROR($H7/$K7,"") -> 0.6977077 | W7: PRJ-006 | X7: =_xlfn.XLOOKUP($W7,Project_EVM[ProjectID],Project_EVM[BAC]) -> 600000 | Y7: =_xlfn.XLOOKUP($W7,Project_EVM[ProjectID],Project_EVM[EV]) -> 600000 | Z7: =_xlfn.XLOOKUP($W7,Project_EVM[ProjectID],Project_EVM[AC]) -> 586500 | AB7: PRJ-006 | AC7: =_xlfn.XLOOKUP($AB7,Project_EVM[ProjectID],Project_EVM[CPI]) -> 1.0230179 | AE7: PRJ-006 | AF7: =_xlfn.XLOOKUP($AE7,Project_EVM[ProjectID],Project_EVM[Labor AC]) -> 516500 | AG7: =_xlfn.XLOOKUP($AE7,Project_EVM[ProjectID],Project_EVM[Material AC]) -> 70000 | AI7: PRJ-001 | AJ7: =_xlfn.XLOOKUP($AI7,Project_EVM[ProjectID],Project_EVM[Start])-$AJ$8 -> 92 | AK7: =_xlfn.XLOOKUP($AI7,Project_EVM[ProjectID],Project_EVM[End])-_xlfn.XLOOKUP($AI7,Project_EVM[ProjectID],Project_EVM[Start]) -> 180
A8: WBS-002 | B8: =_xlfn.XLOOKUP($A8,wbs_elements[WBS_ID],wbs_elements[ProjectID]) -> PRJ-001 | C8: =_xlfn.XLOOKUP($A8,wbs_elements[WBS_ID],wbs_elements[WBS_Code]) -> 2 | D8: =_xlfn.XLOOKUP($A8,wbs_elements[WBS_ID],wbs_elements[ElementName]) -> Hull Fabrication & Assembly | E8: =_xlfn.XLOOKUP($A8,wbs_elements[WBS_ID],wbs_elements[PlannedCost]) -> 600000 | F8: =_xlfn.XLOOKUP($A8,wbs_elements[WBS_ID],wbs_elements[PlannedHours]) -> 1200 | G8: =IFERROR(SUMIFS(physical_progress[PercentComplete],physical_progress[WBS_ID],$A8,physical_progress[RecordDate],_xlfn.MAXIFS(physical_progress[RecordDate],physical_progress[WBS_ID],$A8)),0) -> 1 | H8: =$E8*$G8 -> 600000 | I8: {=SUMPRODUCT(SUMIFS(timesheets[HoursWorked],timesheets[WBS_ID],$A8,timesheets[ResourceID],resources[ResourceID],timesheets[ApprovalStatus],"Approved")*resources[HourlyRate])} -> 374950 | J8: =SUMIFS(material_costs[TotalActualCost],material_costs[WBS_ID],$A8) -> 245500 | K8: =$I8+$J8 -> 620450 | L8: =$H8-$K8 -> -20450 | M8: =IFERROR($H8/$K8,"") -> 0.96704005 | AJ8: =MIN(Project_EVM[Start]) -> 45931
A9: WBS-003 | B9: =_xlfn.XLOOKUP($A9,wbs_elements[WBS_ID],wbs_elements[ProjectID]) -> PRJ-001 | C9: =_xlfn.XLOOKUP($A9,wbs_elements[WBS_ID],wbs_elements[WBS_Code]) -> 3 | D9: =_xlfn.XLOOKUP($A9,wbs_elements[WBS_ID],wbs_elements[ElementName]) -> Outfitting & Integration | E9: =_xlfn.XLOOKUP($A9,wbs_elements[WBS_ID],wbs_elements[PlannedCost]) -> 400000 | F9: =_xlfn.XLOOKUP($A9,wbs_elements[WBS_ID],wbs_elements[PlannedHours]) -> 800 | G9: =IFERROR(SUMIFS(physical_progress[PercentComplete],physical_progress[WBS_ID],$A9,physical_progress[RecordDate],_xlfn.MAXIFS(physical_progress[RecordDate],physical_progress[WBS_ID],$A9)),0) -> 1 | H9: =$E9*$G9 -> 400000 | I9: {=SUMPRODUCT(SUMIFS(timesheets[HoursWorked],timesheets[WBS_ID],$A9,timesheets[ResourceID],resources[ResourceID],timesheets[ApprovalStatus],"Approved")*resources[HourlyRate])} -> 297445 | J9: =SUMIFS(material_costs[TotalActualCost],material_costs[WBS_ID],$A9) -> 243000 | K9: =$I9+$J9 -> 540445 | L9: =$H9-$K9 -> -140445 | M9: =IFERROR($H9/$K9,"") -> 0.74013082
A10: WBS-004 | B10: =_xlfn.XLOOKUP($A10,wbs_elements[WBS_ID],wbs_elements[ProjectID]) -> PRJ-001 | C10: =_xlfn.XLOOKUP($A10,wbs_elements[WBS_ID],wbs_elements[WBS_Code]) -> 4 | D10: =_xlfn.XLOOKUP($A10,wbs_elements[WBS_ID],wbs_elements[ElementName]) -> Sea Trials & Handover | E10: =_xlfn.XLOOKUP($A10,wbs_elements[WBS_ID],wbs_elements[PlannedCost]) -> 200000 | F10: =_xlfn.XLOOKUP($A10,wbs_elements[WBS_ID],wbs_elements[PlannedHours]) -> 300 | G10: =IFERROR(SUMIFS(physical_progress[PercentComplete],physical_progress[WBS_ID],$A10,physical_progress[RecordDate],_xlfn.MAXIFS(physical_progress[RecordDate],physical_progress[WBS_ID],$A10)),0) -> 1 | H10: =$E10*$G10 -> 200000 | I10: {=SUMPRODUCT(SUMIFS(timesheets[HoursWorked],timesheets[WBS_ID],$A10,timesheets[ResourceID],resources[ResourceID],timesheets[ApprovalStatus],"Approved")*resources[HourlyRate])} -> 235185 | J10: =SUMIFS(material_costs[TotalActualCost],material_costs[WBS_ID],$A10) -> 33500 | K10: =$I10+$J10 -> 268685 | L10: =$H10-$K10 -> -68685 | M10: =IFERROR($H10/$K10,"") -> 0.74436608
A11: WBS-005 | B11: =_xlfn.XLOOKUP($A11,wbs_elements[WBS_ID],wbs_elements[ProjectID]) -> PRJ-002 | C11: =_xlfn.XLOOKUP($A11,wbs_elements[WBS_ID],wbs_elements[WBS_Code]) -> 1 | D11: =_xlfn.XLOOKUP($A11,wbs_elements[WBS_ID],wbs_elements[ElementName]) -> Design & CFD Analysis | E11: =_xlfn.XLOOKUP($A11,wbs_elements[WBS_ID],wbs_elements[PlannedCost]) -> 300000 | F11: =_xlfn.XLOOKUP($A11,wbs_elements[WBS_ID],wbs_elements[PlannedHours]) -> 300 | G11: =IFERROR(SUMIFS(physical_progress[PercentComplete],physical_progress[WBS_ID],$A11,physical_progress[RecordDate],_xlfn.MAXIFS(physical_progress[RecordDate],physical_progress[WBS_ID],$A11)),0) -> 0 | H11: =$E11*$G11 -> 0 | I11: {=SUMPRODUCT(SUMIFS(timesheets[HoursWorked],timesheets[WBS_ID],$A11,timesheets[ResourceID],resources[ResourceID],timesheets[ApprovalStatus],"Approved")*resources[HourlyRate])} -> 0 | J11: =SUMIFS(material_costs[TotalActualCost],material_costs[WBS_ID],$A11) -> 0 | K11: =$I11+$J11 -> 0 | L11: =$H11-$K11 -> 0 | M11: =IFERROR($H11/$K11,"")
A12: WBS-006 | B12: =_xlfn.XLOOKUP($A12,wbs_elements[WBS_ID],wbs_elements[ProjectID]) -> PRJ-002 | C12: =_xlfn.XLOOKUP($A12,wbs_elements[WBS_ID],wbs_elements[WBS_Code]) -> 2 | D12: =_xlfn.XLOOKUP($A12,wbs_elements[WBS_ID],wbs_elements[ElementName]) -> Material Procurement | E12: =_xlfn.XLOOKUP($A12,wbs_elements[WBS_ID],wbs_elements[PlannedCost]) -> 500000 | F12: =_xlfn.XLOOKUP($A12,wbs_elements[WBS_ID],wbs_elements[PlannedHours]) -> 0 | G12: =IFERROR(SUMIFS(physical_progress[PercentComplete],physical_progress[WBS_ID],$A12,physical_progress[RecordDate],_xlfn.MAXIFS(physical_progress[RecordDate],physical_progress[WBS_ID],$A12)),0) -> 0 | H12: =$E12*$G12 -> 0 | I12: {=SUMPRODUCT(SUMIFS(timesheets[HoursWorked],timesheets[WBS_ID],$A12,timesheets[ResourceID],resources[ResourceID],timesheets[ApprovalStatus],"Approved")*resources[HourlyRate])} -> 0 | J12: =SUMIFS(material_costs[TotalActualCost],material_costs[WBS_ID],$A12) -> 0 | K12: =$I12+$J12 -> 0 | L12: =$H12-$K12 -> 0 | M12: =IFERROR($H12/$K12,"")
A13: WBS-007 | B13: =_xlfn.XLOOKUP($A13,wbs_elements[WBS_ID],wbs_elements[ProjectID]) -> PRJ-003 | C13: =_xlfn.XLOOKUP($A13,wbs_elements[WBS_ID],wbs_elements[WBS_Code]) -> 1 | D13: =_xlfn.XLOOKUP($A13,wbs_elements[WBS_ID],wbs_elements[ElementName]) -> Structural Frame Engineering | E13: =_xlfn.XLOOKUP($A13,wbs_elements[WBS_ID],wbs_elements[PlannedCost]) -> 400000 | F13: =_xlfn.XLOOKUP($A13,wbs_elements[WBS_ID],wbs_elements[PlannedHours]) -> 400 | G13: =IFERROR(SUMIFS(physical_progress[PercentComplete],physical_progress[WBS_ID],$A13,physical_progress[RecordDate],_xlfn.MAXIFS(physical_progress[RecordDate],physical_progress[WBS_ID],$A13)),0) -> 0.9 | H13: =$E13*$G13 -> 360000 | I13: {=SUMPRODUCT(SUMIFS(timesheets[HoursWorked],timesheets[WBS_ID],$A13,timesheets[ResourceID],resources[ResourceID],timesheets[ApprovalStatus],"Approved")*resources[HourlyRate])} -> 332500 | J13: =SUMIFS(material_costs[TotalActualCost],material_costs[WBS_ID],$A13) -> 0 | K13: =$I13+$J13 -> 332500 | L13: =$H13-$K13 -> 27500 | M13: =IFERROR($H13/$K13,"") -> 1.0827068
A14: WBS-008 | B14: =_xlfn.XLOOKUP($A14,wbs_elements[WBS_ID],wbs_elements[ProjectID]) -> PRJ-003 | C14: =_xlfn.XLOOKUP($A14,wbs_elements[WBS_ID],wbs_elements[WBS_Code]) -> 2 | D14: =_xlfn.XLOOKUP($A14,wbs_elements[WBS_ID],wbs_elements[ElementName]) -> Steel Fabrication | E14: =_xlfn.XLOOKUP($A14,wbs_elements[WBS_ID],wbs_elements[PlannedCost]) -> 800000 | F14: =_xlfn.XLOOKUP($A14,wbs_elements[WBS_ID],wbs_elements[PlannedHours]) -> 1000 | G14: =IFERROR(SUMIFS(physical_progress[PercentComplete],physical_progress[WBS_ID],$A14,physical_progress[RecordDate],_xlfn.MAXIFS(physical_progress[RecordDate],physical_progress[WBS_ID],$A14)),0) -> 0 | H14: =$E14*$G14 -> 0 | I14: {=SUMPRODUCT(SUMIFS(timesheets[HoursWorked],timesheets[WBS_ID],$A14,timesheets[ResourceID],resources[ResourceID],timesheets[ApprovalStatus],"Approved")*resources[HourlyRate])} -> 0 | J14: =SUMIFS(material_costs[TotalActualCost],material_costs[WBS_ID],$A14) -> 50000 | K14: =$I14+$J14 -> 50000 | L14: =$H14-$K14 -> -50000 | M14: =IFERROR($H14/$K14,"") -> 0
A15: WBS-009 | B15: =_xlfn.XLOOKUP($A15,wbs_elements[WBS_ID],wbs_elements[ProjectID]) -> PRJ-004 | C15: =_xlfn.XLOOKUP($A15,wbs_elements[WBS_ID],wbs_elements[WBS_Code]) -> 1 | D15: =_xlfn.XLOOKUP($A15,wbs_elements[WBS_ID],wbs_elements[ElementName]) -> Engineering Drawings & Class Approval | E15: =_xlfn.XLOOKUP($A15,wbs_elements[WBS_ID],wbs_elements[PlannedCost]) -> 500000 | F15: =_xlfn.XLOOKUP($A15,wbs_elements[WBS_ID],wbs_elements[PlannedHours]) -> 500 | G15: =IFERROR(SUMIFS(physical_progress[PercentComplete],physical_progress[WBS_ID],$A15,physical_progress[RecordDate],_xlfn.MAXIFS(physical_progress[RecordDate],physical_progress[WBS_ID],$A15)),0) -> 1 | H15: =$E15*$G15 -> 500000 | I15: {=SUMPRODUCT(SUMIFS(timesheets[HoursWorked],timesheets[WBS_ID],$A15,timesheets[ResourceID],resources[ResourceID],timesheets[ApprovalStatus],"Approved")*resources[HourlyRate])} -> 456000 | J15: =SUMIFS(material_costs[TotalActualCost],material_costs[WBS_ID],$A15) -> 0 | K15: =$I15+$J15 -> 456000 | L15: =$H15-$K15 -> 44000 | M15: =IFERROR($H15/$K15,"") -> 1.0964912
A16: WBS-010 | B16: =_xlfn.XLOOKUP($A16,wbs_elements[WBS_ID],wbs_elements[ProjectID]) -> PRJ-004 | C16: =_xlfn.XLOOKUP($A16,wbs_elements[WBS_ID],wbs_elements[WBS_Code]) -> 2 | D16: =_xlfn.XLOOKUP($A16,wbs_elements[WBS_ID],wbs_elements[ElementName]) -> Hull Welding & Assembly | E16: =_xlfn.XLOOKUP($A16,wbs_elements[WBS_ID],wbs_elements[PlannedCost]) -> 1500000 | F16: =_xlfn.XLOOKUP($A16,wbs_elements[WBS_ID],wbs_elements[PlannedHours]) -> 2000 | G16: =IFERROR(SUMIFS(physical_progress[PercentComplete],physical_progress[WBS_ID],$A16,physical_progress[RecordDate],_xlfn.MAXIFS(physical_progress[RecordDate],physical_progress[WBS_ID],$A16)),0) -> 0.6 | H16: =$E16*$G16 -> 900000 | I16: {=SUMPRODUCT(SUMIFS(timesheets[HoursWorked],timesheets[WBS_ID],$A16,timesheets[ResourceID],resources[ResourceID],timesheets[ApprovalStatus],"Approved")*resources[HourlyRate])} -> 770000 | J16: =SUMIFS(material_costs[TotalActualCost],material_costs[WBS_ID],$A16) -> 250000 | K16: =$I16+$J16 -> 1020000 | L16: =$H16-$K16 -> -120000 | M16: =IFERROR($H16/$K16,"") -> 0.88235294
A17: WBS-011 | B17: =_xlfn.XLOOKUP($A17,wbs_elements[WBS_ID],wbs_elements[ProjectID]) -> PRJ-005 | C17: =_xlfn.XLOOKUP($A17,wbs_elements[WBS_ID],wbs_elements[WBS_Code]) -> 1 | D17: =_xlfn.XLOOKUP($A17,wbs_elements[WBS_ID],wbs_elements[ElementName]) -> Project Control & PM | E17: =_xlfn.XLOOKUP($A17,wbs_elements[WBS_ID],wbs_elements[PlannedCost]) -> 200000 | F17: =_xlfn.XLOOKUP($A17,wbs_elements[WBS_ID],wbs_elements[PlannedHours]) -> 250 | G17: =IFERROR(SUMIFS(physical_progress[PercentComplete],physical_progress[WBS_ID],$A17,physical_progress[RecordDate],_xlfn.MAXIFS(physical_progress[RecordDate],physical_progress[WBS_ID],$A17)),0) -> 1 | H17: =$E17*$G17 -> 200000 | I17: {=SUMPRODUCT(SUMIFS(timesheets[HoursWorked],timesheets[WBS_ID],$A17,timesheets[ResourceID],resources[ResourceID],timesheets[ApprovalStatus],"Approved")*resources[HourlyRate])} -> 187000 | J17: =SUMIFS(material_costs[TotalActualCost],material_costs[WBS_ID],$A17) -> 0 | K17: =$I17+$J17 -> 187000 | L17: =$H17-$K17 -> 13000 | M17: =IFERROR($H17/$K17,"") -> 1.0695187
A18: WBS-012 | B18: =_xlfn.XLOOKUP($A18,wbs_elements[WBS_ID],wbs_elements[ProjectID]) -> PRJ-005 | C18: =_xlfn.XLOOKUP($A18,wbs_elements[WBS_ID],wbs_elements[WBS_Code]) -> 2 | D18: =_xlfn.XLOOKUP($A18,wbs_elements[WBS_ID],wbs_elements[ElementName]) -> Pontoon Assembly & Painting | E18: =_xlfn.XLOOKUP($A18,wbs_elements[WBS_ID],wbs_elements[PlannedCost]) -> 800000 | F18: =_xlfn.XLOOKUP($A18,wbs_elements[WBS_ID],wbs_elements[PlannedHours]) -> 1000 | G18: =IFERROR(SUMIFS(physical_progress[PercentComplete],physical_progress[WBS_ID],$A18,physical_progress[RecordDate],_xlfn.MAXIFS(physical_progress[RecordDate],physical_progress[WBS_ID],$A18)),0) -> 0.875 | H18: =$E18*$G18 -> 700000 | I18: {=SUMPRODUCT(SUMIFS(timesheets[HoursWorked],timesheets[WBS_ID],$A18,timesheets[ResourceID],resources[ResourceID],timesheets[ApprovalStatus],"Approved")*resources[HourlyRate])} -> 560000 | J18: =SUMIFS(material_costs[TotalActualCost],material_costs[WBS_ID],$A18) -> 180000 | K18: =$I18+$J18 -> 740000 | L18: =$H18-$K18 -> -40000 | M18: =IFERROR($H18/$K18,"") -> 0.94594595
A19: WBS-013 | B19: =_xlfn.XLOOKUP($A19,wbs_elements[WBS_ID],wbs_elements[ProjectID]) -> PRJ-006 | C19: =_xlfn.XLOOKUP($A19,wbs_elements[WBS_ID],wbs_elements[WBS_Code]) -> 1 | D19: =_xlfn.XLOOKUP($A19,wbs_elements[WBS_ID],wbs_elements[ElementName]) -> Hatch Engineering & FEA | E19: =_xlfn.XLOOKUP($A19,wbs_elements[WBS_ID],wbs_elements[PlannedCost]) -> 200000 | F19: =_xlfn.XLOOKUP($A19,wbs_elements[WBS_ID],wbs_elements[PlannedHours]) -> 200 | G19: =IFERROR(SUMIFS(physical_progress[PercentComplete],physical_progress[WBS_ID],$A19,physical_progress[RecordDate],_xlfn.MAXIFS(physical_progress[RecordDate],physical_progress[WBS_ID],$A19)),0) -> 1 | H19: =$E19*$G19 -> 200000 | I19: {=SUMPRODUCT(SUMIFS(timesheets[HoursWorked],timesheets[WBS_ID],$A19,timesheets[ResourceID],resources[ResourceID],timesheets[ApprovalStatus],"Approved")*resources[HourlyRate])} -> 180500 | J19: =SUMIFS(material_costs[TotalActualCost],material_costs[WBS_ID],$A19) -> 0 | K19: =$I19+$J19 -> 180500 | L19: =$H19-$K19 -> 19500 | M19: =IFERROR($H19/$K19,"") -> 1.1080332
A20: WBS-014 | B20: =_xlfn.XLOOKUP($A20,wbs_elements[WBS_ID],wbs_elements[ProjectID]) -> PRJ-006 | C20: =_xlfn.XLOOKUP($A20,wbs_elements[WBS_ID],wbs_elements[WBS_Code]) -> 2 | D20: =_xlfn.XLOOKUP($A20,wbs_elements[WBS_ID],wbs_elements[ElementName]) -> Molding & Testing | E20: =_xlfn.XLOOKUP($A20,wbs_elements[WBS_ID],wbs_elements[PlannedCost]) -> 400000 | F20: =_xlfn.XLOOKUP($A20,wbs_elements[WBS_ID],wbs_elements[PlannedHours]) -> 500 | G20: =IFERROR(SUMIFS(physical_progress[PercentComplete],physical_progress[WBS_ID],$A20,physical_progress[RecordDate],_xlfn.MAXIFS(physical_progress[RecordDate],physical_progress[WBS_ID],$A20)),0) -> 1 | H20: =$E20*$G20 -> 400000 | I20: {=SUMPRODUCT(SUMIFS(timesheets[HoursWorked],timesheets[WBS_ID],$A20,timesheets[ResourceID],resources[ResourceID],timesheets[ApprovalStatus],"Approved")*resources[HourlyRate])} -> 336000 | J20: =SUMIFS(material_costs[TotalActualCost],material_costs[WBS_ID],$A20) -> 70000 | K20: =$I20+$J20 -> 406000 | L20: =$H20-$K20 -> -6000 | M20: =IFERROR($H20/$K20,"") -> 0.98522167
A23: ProjectID | B23: Project Name | C23: Manager | D23: Status | E23: BAC | F23: Start | G23: End | H23: Progress | I23: EV | J23: PV | K23: Labor AC | L23: Material AC | M23: AC | N23: CV | O23: SV | P23: CPI | Q23: SPI | R23: EAC | S23: Forecast Variance | T23: Alert | U23: Recommended Action
A24: PRJ-001 | B24: =_xlfn.XLOOKUP($A24,projects[ProjectID],projects[ProjectName]) -> Composite Maritime Vessel Construction | C24: =_xlfn.XLOOKUP($A24,projects[ProjectID],projects[ProjectManager]) -> Morten Hansen | D24: =_xlfn.XLOOKUP($A24,projects[ProjectID],projects[Status]) -> Completed | E24: =_xlfn.XLOOKUP($A24,projects[ProjectID],projects[BudgetAtCompletion_BAC]) -> 1500000 | F24: =_xlfn.XLOOKUP($A24,projects[ProjectID],projects[StartDate]) -> 46023 | G24: =_xlfn.XLOOKUP($A24,projects[ProjectID],projects[EndDate]) -> 46203 | H24: =IFERROR($I24/$E24,0) -> 0.995 | I24: =SUMIFS(WBS_Metrics[EV],WBS_Metrics[ProjectID],$A24) -> 1492500 | J24: =$E24*MAX(0,MIN(1,($B$4-$F24)/($G24-$F24))) -> 1500000 | K24: =SUMIFS(WBS_Metrics[Labor AC],WBS_Metrics[ProjectID],$A24) -> 1326810 | L24: =SUMIFS(WBS_Metrics[Material AC],WBS_Metrics[ProjectID],$A24) -> 522000 | M24: =$K24+$L24 -> 1848810 | N24: =$I24-$M24 -> -356310 | O24: =$I24-$J24 -> -7500 | P24: =IFERROR($I24/$M24,"") -> 0.80727603 | Q24: =IFERROR($I24/$J24,"") -> 0.995 | R24: =IFERROR($E24/$P24,$M24+($E24-$I24)) -> 1858100.5 | S24: =$E24-$R24 -> -358100.5 | T24: =IF($D24="Planned","PLANNED",IF($P24<0.95,"CRITICAL",IF($P24<1,"WATCH","ON TRACK"))) -> CRITICAL | U24: =IF($A24="PRJ-001","Renegotiate contractor rates and freeze variation orders",IF($A24="PRJ-002","Prepare August design start and resource ramp",IF($A24="PRJ-003","Move cleanly from engineering to steel fabrication",IF($A24="PRJ-004","Monitor welding productivity through completion",IF($A24="PRJ-005","Protect final 10% from cost leakage","Close out lessons learned and verification pack"))))) -> Renegotiate contractor rates and freeze variation orders
A25: PRJ-002 | B25: =_xlfn.XLOOKUP($A25,projects[ProjectID],projects[ProjectName]) -> PRJ-002: Patrol Vessel Carbon Mold Design | C25: =_xlfn.XLOOKUP($A25,projects[ProjectID],projects[ProjectManager]) -> Morten Hansen | D25: =_xlfn.XLOOKUP($A25,projects[ProjectID],projects[Status]) -> Planned | E25: =_xlfn.XLOOKUP($A25,projects[ProjectID],projects[BudgetAtCompletion_BAC]) -> 800000 | F25: =_xlfn.XLOOKUP($A25,projects[ProjectID],projects[StartDate]) -> 46235 | G25: =_xlfn.XLOOKUP($A25,projects[ProjectID],projects[EndDate]) -> 46387 | H25: =IFERROR($I25/$E25,0) -> 0 | I25: =SUMIFS(WBS_Metrics[EV],WBS_Metrics[ProjectID],$A25) -> 0 | J25: =$E25*MAX(0,MIN(1,($B$4-$F25)/($G25-$F25))) -> 0 | K25: =SUMIFS(WBS_Metrics[Labor AC],WBS_Metrics[ProjectID],$A25) -> 0 | L25: =SUMIFS(WBS_Metrics[Material AC],WBS_Metrics[ProjectID],$A25) -> 0 | M25: =$K25+$L25 -> 0 | N25: =$I25-$M25 -> 0 | O25: =$I25-$J25 -> 0 | P25: =IFERROR($I25/$M25,"") | Q25: =IFERROR($I25/$J25,"") | R25: =IFERROR($E25/$P25,$M25+($E25-$I25)) -> 800000 | S25: =$E25-$R25 -> 0 | T25: =IF($D25="Planned","PLANNED",IF($P25<0.95,"CRITICAL",IF($P25<1,"WATCH","ON TRACK"))) -> PLANNED | U25: =IF($A25="PRJ-001","Renegotiate contractor rates and freeze variation orders",IF($A25="PRJ-002","Prepare August design start and resource ramp",IF($A25="PRJ-003","Move cleanly from engineering to steel fabrication",IF($A25="PRJ-004","Monitor welding productivity through completion",IF($A25="PRJ-005","Protect final 10% from cost leakage","Close out lessons learned and verification pack"))))) -> Prepare August design start and resource ramp
A26: PRJ-003 | B26: =_xlfn.XLOOKUP($A26,projects[ProjectID],projects[ProjectName]) -> PRJ-003: Subsea Cable Installation Frame | C26: =_xlfn.XLOOKUP($A26,projects[ProjectID],projects[ProjectManager]) -> Erik Johansen | D26: =_xlfn.XLOOKUP($A26,projects[ProjectID],projects[Status]) -> Active | E26: =_xlfn.XLOOKUP($A26,projects[ProjectID],projects[BudgetAtCompletion_BAC]) -> 1200000 | F26: =_xlfn.XLOOKUP($A26,projects[ProjectID],projects[StartDate]) -> 46143 | G26: =_xlfn.XLOOKUP($A26,projects[ProjectID],projects[EndDate]) -> 46326 | H26: =IFERROR($I26/$E26,0) -> 0.3 | I26: =SUMIFS(WBS_Metrics[EV],WBS_Metrics[ProjectID],$A26) -> 360000 | J26: =$E26*MAX(0,MIN(1,($B$4-$F26)/($G26-$F26))) -> 393442.62 | K26: =SUMIFS(WBS_Metrics[Labor AC],WBS_Metrics[ProjectID],$A26) -> 332500 | L26: =SUMIFS(WBS_Metrics[Material AC],WBS_Metrics[ProjectID],$A26) -> 50000 | M26: =$K26+$L26 -> 382500 | N26: =$I26-$M26 -> -22500 | O26: =$I26-$J26 -> -33442.623 | P26: =IFERROR($I26/$M26,"") -> 0.94117647 | Q26: =IFERROR($I26/$J26,"") -> 0.915 | R26: =IFERROR($E26/$P26,$M26+($E26-$I26)) -> 1275000 | S26: =$E26-$R26 -> -75000 | T26: =IF($D26="Planned","PLANNED",IF($P26<0.95,"CRITICAL",IF($P26<1,"WATCH","ON TRACK"))) -> CRITICAL | U26: =IF($A26="PRJ-001","Renegotiate contractor rates and freeze variation orders",IF($A26="PRJ-002","Prepare August design start and resource ramp",IF($A26="PRJ-003","Move cleanly from engineering to steel fabrication",IF($A26="PRJ-004","Monitor welding productivity through completion",IF($A26="PRJ-005","Protect final 10% from cost leakage","Close out lessons learned and verification pack"))))) -> Move cleanly from engineering to steel fabrication
A27: PRJ-004 | B27: =_xlfn.XLOOKUP($A27,projects[ProjectID],projects[ProjectName]) -> PRJ-004: Autonomous Workboat Hull Weldments | C27: =_xlfn.XLOOKUP($A27,projects[ProjectID],projects[ProjectManager]) -> Astrid Nilsen | D27: =_xlfn.XLOOKUP($A27,projects[ProjectID],projects[Status]) -> Active | E27: =_xlfn.XLOOKUP($A27,projects[ProjectID],projects[BudgetAtCompletion_BAC]) -> 2000000 | F27: =_xlfn.XLOOKUP($A27,projects[ProjectID],projects[StartDate]) -> 46082 | G27: =_xlfn.XLOOKUP($A27,projects[ProjectID],projects[EndDate]) -> 46265 | H27: =IFERROR($I27/$E27,0) -> 0.7 | I27: =SUMIFS(WBS_Metrics[EV],WBS_Metrics[ProjectID],$A27) -> 1400000 | J27: =$E27*MAX(0,MIN(1,($B$4-$F27)/($G27-$F27))) -> 1322404.4 | K27: =SUMIFS(WBS_Metrics[Labor AC],WBS_Metrics[ProjectID],$A27) -> 1226000 | L27: =SUMIFS(WBS_Metrics[Material AC],WBS_Metrics[ProjectID],$A27) -> 250000 | M27: =$K27+$L27 -> 1476000 | N27: =$I27-$M27 -> -76000 | O27: =$I27-$J27 -> 77595.628 | P27: =IFERROR($I27/$M27,"") -> 0.94850949 | Q27: =IFERROR($I27/$J27,"") -> 1.0586777 | R27: =IFERROR($E27/$P27,$M27+($E27-$I27)) -> 2108571.4 | S27: =$E27-$R27 -> -108571.43 | T27: =IF($D27="Planned","PLANNED",IF($P27<0.95,"CRITICAL",IF($P27<1,"WATCH","ON TRACK"))) -> CRITICAL | U27: =IF($A27="PRJ-001","Renegotiate contractor rates and freeze variation orders",IF($A27="PRJ-002","Prepare August design start and resource ramp",IF($A27="PRJ-003","Move cleanly from engineering to steel fabrication",IF($A27="PRJ-004","Monitor welding productivity through completion",IF($A27="PRJ-005","Protect final 10% from cost leakage","Close out lessons learned and verification pack"))))) -> Monitor welding productivity through completion
A28: PRJ-005 | B28: =_xlfn.XLOOKUP($A28,projects[ProjectID],projects[ProjectName]) -> PRJ-005: Defense Logistics Pontoon Build | C28: =_xlfn.XLOOKUP($A28,projects[ProjectID],projects[ProjectManager]) -> Frank Ellingsen | D28: =_xlfn.XLOOKUP($A28,projects[ProjectID],projects[Status]) -> Active | E28: =_xlfn.XLOOKUP($A28,projects[ProjectID],projects[BudgetAtCompletion_BAC]) -> 1000000 | F28: =_xlfn.XLOOKUP($A28,projects[ProjectID],projects[StartDate]) -> 46054 | G28: =_xlfn.XLOOKUP($A28,projects[ProjectID],projects[EndDate]) -> 46234 | H28: =IFERROR($I28/$E28,0) -> 0.9 | I28: =SUMIFS(WBS_Metrics[EV],WBS_Metrics[ProjectID],$A28) -> 900000 | J28: =$E28*MAX(0,MIN(1,($B$4-$F28)/($G28-$F28))) -> 827777.78 | K28: =SUMIFS(WBS_Metrics[Labor AC],WBS_Metrics[ProjectID],$A28) -> 747000 | L28: =SUMIFS(WBS_Metrics[Material AC],WBS_Metrics[ProjectID],$A28) -> 180000 | M28: =$K28+$L28 -> 927000 | N28: =$I28-$M28 -> -27000 | O28: =$I28-$J28 -> 72222.222 | P28: =IFERROR($I28/$M28,"") -> 0.97087379 | Q28: =IFERROR($I28/$J28,"") -> 1.0872483 | R28: =IFERROR($E28/$P28,$M28+($E28-$I28)) -> 1030000 | S28: =$E28-$R28 -> -30000 | T28: =IF($D28="Planned","PLANNED",IF($P28<0.95,"CRITICAL",IF($P28<1,"WATCH","ON TRACK"))) -> WATCH | U28: =IF($A28="PRJ-001","Renegotiate contractor rates and freeze variation orders",IF($A28="PRJ-002","Prepare August design start and resource ramp",IF($A28="PRJ-003","Move cleanly from engineering to steel fabrication",IF($A28="PRJ-004","Monitor welding productivity through completion",IF($A28="PRJ-005","Protect final 10% from cost leakage","Close out lessons learned and verification pack"))))) -> Protect final 10% from cost leakage
A29: PRJ-006 | B29: =_xlfn.XLOOKUP($A29,projects[ProjectID],projects[ProjectName]) -> PRJ-006: Lightweight Composite Cargo Hatch | C29: =_xlfn.XLOOKUP($A29,projects[ProjectID],projects[ProjectManager]) -> Morten Hansen | D29: =_xlfn.XLOOKUP($A29,projects[ProjectID],projects[Status]) -> Completed | E29: =_xlfn.XLOOKUP($A29,projects[ProjectID],projects[BudgetAtCompletion_BAC]) -> 600000 | F29: =_xlfn.XLOOKUP($A29,projects[ProjectID],projects[StartDate]) -> 45931 | G29: =_xlfn.XLOOKUP($A29,projects[ProjectID],projects[EndDate]) -> 46112 | H29: =IFERROR($I29/$E29,0) -> 1 | I29: =SUMIFS(WBS_Metrics[EV],WBS_Metrics[ProjectID],$A29) -> 600000 | J29: =$E29*MAX(0,MIN(1,($B$4-$F29)/($G29-$F29))) -> 600000 | K29: =SUMIFS(WBS_Metrics[Labor AC],WBS_Metrics[ProjectID],$A29) -> 516500 | L29: =SUMIFS(WBS_Metrics[Material AC],WBS_Metrics[ProjectID],$A29) -> 70000 | M29: =$K29+$L29 -> 586500 | N29: =$I29-$M29 -> 13500 | O29: =$I29-$J29 -> 0 | P29: =IFERROR($I29/$M29,"") -> 1.0230179 | Q29: =IFERROR($I29/$J29,"") -> 1 | R29: =IFERROR($E29/$P29,$M29+($E29-$I29)) -> 586500 | S29: =$E29-$R29 -> 13500 | T29: =IF($D29="Planned","PLANNED",IF($P29<0.95,"CRITICAL",IF($P29<1,"WATCH","ON TRACK"))) -> ON TRACK | U29: =IF($A29="PRJ-001","Renegotiate contractor rates and freeze variation orders",IF($A29="PRJ-002","Prepare August design start and resource ramp",IF($A29="PRJ-003","Move cleanly from engineering to steel fabrication",IF($A29="PRJ-004","Monitor welding productivity through completion",IF($A29="PRJ-005","Protect final 10% from cost leakage","Close out lessons learned and verification pack"))))) -> Close out lessons learned and verification pack
A32: Metric | B32: Value
A33: Portfolio BAC | B33: =SUM(Project_EVM[BAC]) -> 7100000
A34: Earned Value | B34: =SUM(Project_EVM[EV]) -> 4752500
A35: Actual Cost | B35: =SUM(Project_EVM[AC]) -> 5220810
A36: Cost Variance | B36: =B34-B35 -> -468310
A37: Portfolio CPI | B37: =IFERROR(B34/B35,"") -> 0.91029936
A38: Portfolio EAC | B38: =SUM(Project_EVM[EAC]) -> 7658171.9
A39: Active Projects | B39: =COUNTIF(Project_EVM[Status],"Active") -> 3
A40: Completed Projects | B40: =COUNTIF(Project_EVM[Status],"Completed") -> 2
A41: Planned Projects | B41: =COUNTIF(Project_EVM[Status],"Planned") -> 1
A42: Critical Projects | B42: =COUNTIF(Project_EVM[Alert],"CRITICAL") -> 3

Sheet Data Model
A1: Project Portfolio Data Model
A2: Relational map inferred from the 8 workbook tables. Native Power Pivot model creation is not exposed here, so this sheet documents the model and keeps integrity checks live with workbook formulas.
A4: Story in brief: Projects and resources are the two master dimensions. WBS elements are the central bridge connecting planned work, labor actuals, material actuals, and physical progress. All tested foreign-key relationships currently resolve with no unmatched keys; raid_log should be normalized before it is joined into reporting.
A6: Table | B6: Primary key | C6: Grain | D6: Rows | E6: Purpose | F6: Notes | G6: Column1 | H6: Column2
A7: projects | B7: ProjectID | C7: 1 row per project | D7: 6 | E7: Portfolio project master: dates, owner, BAC, status | F7: Parent for WBS; project manager can map to resources by name
A8: resources | B8: ResourceID | C8: 1 row per person/resource | D8: 5 | E8: Labor resource master with role and hourly rate | F8: Parent for timesheets and assignments
A9: wbs_elements | B9: WBS_ID | C9: 1 row per WBS element | D9: 14 | E9: Work breakdown structure under each project | F9: Central bridge between projects, labor, materials, and progress
A10: resource_assignments | B10: AssignmentID | C10: 1 row per planned resource allocation to WBS | D10: 17 | E10: Planned hours by resource and WBS | F10: Fact table for planned labor allocation
A11: material_costs | B11: PurchaseID | C11: 1 row per material purchase | D11: 14 | E11: Actual material purchases and cost by WBS | F11: Fact table for material actuals
A12: timesheets | B12: TimesheetID | C12: 1 row per resource/WBS work entry | D12: 299 | E12: Actual labor hours by date, resource, and WBS | F12: Fact table for labor actuals
A13: physical_progress | B13: ProgressID | C13: 1 row per progress update | D13: 57 | E13: Reported percent complete by WBS and date | F13: Fact table for earned progress
A14: ="Model coverage: " & COUNTA(projects[ProjectID]) & " projects, " & COUNTA(wbs_elements[WBS_ID]) & " WBS elements, " & COUNTA(timesheets[TimesheetID]) & " timesheet rows, " & COUNTA(material_costs[PurchaseID]) & " material purchases, " & COUNTA(physical_progress[ProgressID]) & " progress records." -> Model coverage: 6 projects, 14 WBS elements, 299 timesheet rows, 14 material purchases, 57 progress records.
A17: From table | B17: From key | C17: To table | D17: To key | E17: Cardinality | F17: Rows tested | G17: Unmatched FK | H17: Status
A18: projects | B18: ProjectManager | C18: resources | D18: ResourceName | E18: Many-to-one by name | F18: =COUNTA(projects[ProjectManager]) -> 6 | G18: {=SUMPRODUCT(--ISNA(MATCH(projects[ProjectManager],resources[ResourceName],0)))} -> 0 | H18: =IF(G18=0,"OK","CHECK") -> OK
A19: wbs_elements | B19: ProjectID | C19: projects | D19: ProjectID | E19: Many-to-one | F19: =COUNTA(wbs_elements[ProjectID]) -> 14 | G19: {=SUMPRODUCT(--ISNA(MATCH(wbs_elements[ProjectID],projects[ProjectID],0)))} -> 0 | H19: =IF(G19=0,"OK","CHECK") -> OK
A20: resource_assignments | B20: WBS_ID | C20: wbs_elements | D20: WBS_ID | E20: Many-to-one | F20: =COUNTA(resource_assignments[WBS_ID]) -> 17 | G20: {=SUMPRODUCT(--ISNA(MATCH(resource_assignments[WBS_ID],wbs_elements[WBS_ID],0)))} -> 0 | H20: =IF(G20=0,"OK","CHECK") -> OK
A21: resource_assignments | B21: ResourceID | C21: resources | D21: ResourceID | E21: Many-to-one | F21: =COUNTA(resource_assignments[ResourceID]) -> 17 | G21: {=SUMPRODUCT(--ISNA(MATCH(resource_assignments[ResourceID],resources[ResourceID],0)))} -> 0 | H21: =IF(G21=0,"OK","CHECK") -> OK
A22: material_costs | B22: WBS_ID | C22: wbs_elements | D22: WBS_ID | E22: Many-to-one | F22: =COUNTA(material_costs[WBS_ID]) -> 14 | G22: {=SUMPRODUCT(--ISNA(MATCH(material_costs[WBS_ID],wbs_elements[WBS_ID],0)))} -> 0 | H22: =IF(G22=0,"OK","CHECK") -> OK
A23: timesheets | B23: WBS_ID | C23: wbs_elements | D23: WBS_ID | E23: Many-to-one | F23: =COUNTA(timesheets[WBS_ID]) -> 299 | G23: {=SUMPRODUCT(--ISNA(MATCH(timesheets[WBS_ID],wbs_elements[WBS_ID],0)))} -> 0 | H23: =IF(G23=0,"OK","CHECK") -> OK
A24: timesheets | B24: ResourceID | C24: resources | D24: ResourceID | E24: Many-to-one | F24: =COUNTA(timesheets[ResourceID]) -> 299 | G24: {=SUMPRODUCT(--ISNA(MATCH(timesheets[ResourceID],resources[ResourceID],0)))} -> 0 | H24: =IF(G24=0,"OK","CHECK") -> OK
A25: physical_progress | B25: WBS_ID | C25: wbs_elements | D25: WBS_ID | E25: Many-to-one | F25: =COUNTA(physical_progress[WBS_ID]) -> 57 | G25: {=SUMPRODUCT(--ISNA(MATCH(physical_progress[WBS_ID],wbs_elements[WBS_ID],0)))} -> 0 | H25: =IF(G25=0,"OK","CHECK") -> OK
A26: physical_progress | B26: ReportedBy | C26: resources | D26: ResourceName | E26: Many-to-one by name | F26: =COUNTA(physical_progress[ReportedBy]) -> 57 | G26: {=SUMPRODUCT(--ISNA(MATCH(physical_progress[ReportedBy],resources[ResourceName],0)))} -> 0 | H26: =IF(G26=0,"OK","CHECK") -> OK
A29: Table | B29: Field | C29: Role | D29: Description
A30: projects | B30: ProjectID | C30: Primary key | D30: Project identifier
A31: projects | B31: ProjectName | C31: Attribute | D31: Project display name
A32: projects | B32: ProjectManager | C32: Foreign key by name | D32: Maps to resources[ResourceName]
A33: projects | B33: BudgetAtCompletion_BAC | C33: Measure base | D33: Approved baseline budget
A34: projects | B34: StartDate | C34: Date | D34: Planned/actual start
A35: projects | B35: EndDate | C35: Date | D35: Planned/actual finish
A36: projects | B36: Status | C36: Attribute | D36: Project lifecycle status
A37: resources | B37: ResourceID | C37: Primary key | D37: Resource identifier
A38: resources | B38: ResourceName | C38: Alternate key | D38: Person/resource name
A39: resources | B39: Role | C39: Attribute | D39: Resource role
A40: resources | B40: HourlyRate | C40: Measure base | D40: Cost rate per hour
... A76: raid_log | B76: Status* | C76: Attribute | D76: RAID status

Sheet projects
A1: ProjectID | B1: ProjectName | C1: ProjectManager | D1: BudgetAtCompletion_BAC | E1: StartDate | F1: EndDate | G1: Status
A2: PRJ-001 | B2: Composite Maritime Vessel Construction | C2: Morten Hansen | D2: 1500000 | E2: 46023 | F2: 46203 | G2: Completed
A3: PRJ-002 | B3: PRJ-002: Patrol Vessel Carbon Mold Design | C3: Morten Hansen | D3: 800000 | E3: 46235 | F3: 46387 | G3: Planned
A4: PRJ-003 | B4: PRJ-003: Subsea Cable Installation Frame | C4: Erik Johansen | D4: 1200000 | E4: 46143 | F4: 46326 | G4: Active
A5: PRJ-004 | B5: PRJ-004: Autonomous Workboat Hull Weldments | C5: Astrid Nilsen | D5: 2000000 | E5: 46082 | F5: 46265 | G5: Active
A6: PRJ-005 | B6: PRJ-005: Defense Logistics Pontoon Build | C6: Frank Ellingsen | D6: 1000000 | E6: 46054 | F6: 46234 | G6: Active
A7: PRJ-006 | B7: PRJ-006: Lightweight Composite Cargo Hatch | C7: Morten Hansen | D7: 600000 | E7: 45931 | F7: 46112 | G7: Completed

Sheet resources
A1: ResourceID | B1: ResourceName | C1: Role | D1: HourlyRate
A2: RES-001 | B2: Frank Ellingsen | C2: Project Controller | D2: 850
A3: RES-002 | B3: Morten Hansen | C3: Project Manager | D3: 1000
A4: RES-003 | B4: Erik Johansen | C4: Senior Design Engineer | D4: 950
A5: RES-004 | B5: Astrid Nilsen | C5: Structural Welder | D5: 700
A6: RES-005 | B6: Lars Olsen | C6: Marine Electrician | D6: 750

Sheet wbs_elements
A1: WBS_ID | B1: ProjectID | C1: WBS_Code | D1: ElementName | E1: PlannedCost | F1: PlannedHours
A2: WBS-001 | B2: PRJ-001 | C2: 1 | D2: Project Management & Engineering | E2: 300000 | F2: 400
A3: WBS-002 | B3: PRJ-001 | C3: 2 | D3: Hull Fabrication & Assembly | E3: 600000 | F3: 1200
A4: WBS-003 | B4: PRJ-001 | C4: 3 | D4: Outfitting & Integration | E4: 400000 | F4: 800
A5: WBS-004 | B5: PRJ-001 | C5: 4 | D5: Sea Trials & Handover | E5: 200000 | F5: 300
A6: WBS-005 | B6: PRJ-002 | C6: 1 | D6: Design & CFD Analysis | E6: 300000 | F6: 300
A7: WBS-006 | B7: PRJ-002 | C7: 2 | D7: Material Procurement | E7: 500000 | F7: 0
A8: WBS-007 | B8: PRJ-003 | C8: 1 | D8: Structural Frame Engineering | E8: 400000 | F8: 400
A9: WBS-008 | B9: PRJ-003 | C9: 2 | D9: Steel Fabrication | E9: 800000 | F9: 1000
A10: WBS-009 | B10: PRJ-004 | C10: 1 | D10: Engineering Drawings & Class Approval | E10: 500000 | F10: 500
A11: WBS-010 | B11: PRJ-004 | C11: 2 | D11: Hull Welding & Assembly | E11: 1500000 | F11: 2000
A12: WBS-011 | B12: PRJ-005 | C12: 1 | D12: Project Control & PM | E12: 200000 | F12: 250
A13: WBS-012 | B13: PRJ-005 | C13: 2 | D13: Pontoon Assembly & Painting | E13: 800000 | F13: 1000
... A15: WBS-014 | B15: PRJ-006 | C15: 2 | D15: Molding & Testing | E15: 400000 | F15: 500

Sheet resource_assignments
A1: AssignmentID | B1: WBS_ID | C1: ResourceID | D1: AllocatedHours
A2: ASG-001 | B2: WBS-001 | C2: RES-001 | D2: 100
A3: ASG-002 | B3: WBS-001 | C3: RES-002 | D3: 200
A4: ASG-003 | B4: WBS-001 | C4: RES-003 | D4: 100
A5: ASG-004 | B5: WBS-002 | C5: RES-004 | D5: 1000
A6: ASG-005 | B6: WBS-002 | C6: RES-003 | D6: 200
A7: ASG-006 | B7: WBS-003 | C7: RES-005 | D7: 600
A8: ASG-007 | B8: WBS-003 | C8: RES-004 | D8: 200
A9: ASG-008 | B9: WBS-004 | C9: RES-002 | D9: 100
A10: ASG-009 | B10: WBS-004 | C10: RES-005 | D10: 150
A11: ASG-010 | B11: WBS-004 | C11: RES-001 | D11: 50
A12: ASG-011 | B12: WBS-008 | C12: RES-004 | D12: 1000
A13: ASG-012 | B13: WBS-009 | C13: RES-003 | D13: 500
... A18: ASG-017 | B18: WBS-014 | C18: RES-004 | D18: 500

Sheet material_costs
A1: PurchaseID | B1: WBS_ID | C1: PurchaseDate | D1: Description | E1: Quantity | F1: UnitPrice | G1: TotalActualCost
A2: INV-001 | B2: WBS-002 | C2: 46058 | D2: Structural Composite Carbon Sheets | E2: 10 | F2: 15000 | G2: 150000
A3: INV-002 | B3: WBS-002 | C3: 46065 | D3: Epoxy Resin Infusion Kit | E3: 20 | F3: 2500 | G3: 50000
A4: INV-003 | B4: WBS-002 | C4: 46081 | D4: Steel Support Beam Frames | E4: 4 | F4: 8000 | G4: 32000
A5: INV-004 | B5: WBS-002 | C5: 46091 | D5: Additional Epoxies (Overrun material) | E5: 5 | F5: 2700 | G5: 13500
A6: INV-005 | B6: WBS-003 | C6: 46117 | D6: Marine Cabin Electrical Wiring | E6: 2 | F6: 12000 | G6: 24000
A7: INV-006 | B7: WBS-003 | C7: 46132 | D7: Simrad Integrated Marine Dashboard | E7: 1 | F7: 45000 | G7: 45000
A8: INV-007 | B8: WBS-003 | C8: 46144 | D8: Twin Electric Inboard Engines | E8: 2 | F8: 65000 | G8: 130000
A9: INV-008 | B9: WBS-003 | C9: 46160 | D9: Battery Storage Bank Lithium 10kWh | E9: 2 | F9: 22000 | G9: 44000
A10: INV-009 | B10: WBS-004 | C10: 46178 | D10: DNV Safety & Compliance Certification | E10: 1 | F10: 25000 | G10: 25000
A11: INV-010 | B11: WBS-004 | C11: 46188 | D11: Test Trial Bio-Fuel & Supplies | E11: 1 | F11: 8500 | G11: 8500
A12: MAT-3001 | B12: WBS-008 | C12: 46152 | D12: Steel Frame Pre-payment Deposit | E12: 1 | F12: 50000 | G12: 50000
A13: MAT-4001 | B13: WBS-010 | C13: 46106 | D13: Consumables & Steel Plates | E13: 1 | F13: 250000 | G13: 250000
... A15: MAT-6001 | B15: WBS-014 | C15: 45962 | D15: Composite Cutting Fiber | E15: 1 | F15: 70000 | G15: 70000

Sheet timesheets
A1: TimesheetID | B1: ResourceID | C1: WBS_ID | D1: WorkDate | E1: HoursWorked | F1: ApprovalStatus
A2: TS-0001 | B2: RES-001 | C2: WBS-001 | D2: 46024 | E2: 4.1 | F2: Approved
A3: TS-0002 | B3: RES-001 | C3: WBS-001 | D3: 46031 | E3: 3.5 | F3: Approved
A4: TS-0003 | B4: RES-001 | C4: WBS-001 | D4: 46038 | E4: 3.8 | F4: Approved
A5: TS-0004 | B5: RES-001 | C5: WBS-001 | D5: 46045 | E5: 3.7 | F5: Approved
A6: TS-0005 | B6: RES-001 | C6: WBS-001 | D6: 46052 | E6: 4.2 | F6: Approved
A7: TS-0006 | B7: RES-001 | C7: WBS-001 | D7: 46059 | E7: 4.2 | F7: Approved
A8: TS-0007 | B8: RES-001 | C8: WBS-001 | D8: 46066 | E8: 4.4 | F8: Approved
A9: TS-0008 | B9: RES-001 | C9: WBS-001 | D9: 46073 | E9: 3.6 | F9: Approved
A10: TS-0009 | B10: RES-001 | C10: WBS-001 | D10: 46080 | E10: 3.9 | F10: Approved
A11: TS-0010 | B11: RES-001 | C11: WBS-001 | D11: 46087 | E11: 3.5 | F11: Approved
A12: TS-0011 | B12: RES-001 | C12: WBS-001 | D12: 46094 | E12: 3.7 | F12: Approved
A13: TS-0012 | B13: RES-001 | C13: WBS-001 | D13: 46101 | E13: 4 | F13: Approved
... A300: TS-6002 | B300: RES-004 | C300: WBS-014 | D300: 45981 | E300: 480 | F300: Approved

Sheet physical_progress
A1: ProgressID | B1: WBS_ID | C1: RecordDate | D1: PercentComplete | E1: ReportedBy
A2: PRG-0001 | B2: WBS-001 | C2: 46029 | D2: 0.039 | E2: Frank Ellingsen
A3: PRG-0002 | B3: WBS-001 | C3: 46036 | D3: 0.078 | E3: Frank Ellingsen
A4: PRG-0003 | B4: WBS-001 | C4: 46043 | D4: 0.117 | E4: Frank Ellingsen
A5: PRG-0004 | B5: WBS-001 | C5: 46050 | D5: 0.156 | E5: Frank Ellingsen
A6: PRG-0005 | B6: WBS-001 | C6: 46057 | D6: 0.195 | E6: Frank Ellingsen
A7: PRG-0006 | B7: WBS-001 | C7: 46064 | D7: 0.234 | E7: Frank Ellingsen
A8: PRG-0007 | B8: WBS-001 | C8: 46071 | D8: 0.273 | E8: Frank Ellingsen
A9: PRG-0008 | B9: WBS-001 | C9: 46078 | D9: 0.312 | E9: Frank Ellingsen
A10: PRG-0009 | B10: WBS-001 | C10: 46085 | D10: 0.351 | E10: Frank Ellingsen
A11: PRG-0010 | B11: WBS-001 | C11: 46092 | D11: 0.39 | E11: Frank Ellingsen
A12: PRG-0011 | B12: WBS-001 | C12: 46099 | D12: 0.429 | E12: Frank Ellingsen
A13: PRG-0012 | B13: WBS-001 | C13: 46106 | D13: 0.468 | E13: Frank Ellingsen
... A58: PRG-6002 | B58: WBS-014 | C58: 46112 | D58: 1 | E58: Frank Ellingsen

Sheet raid_log
A1: Column1 | B1: Column2 | C1: Column3 | D1: Column4 | E1: Column5 | F1: Column6 | G1: Column7 | H1: Column8
A2: RiskID | B2: Type | C2: Description | D2: Impact | E2: Probability | F2: MitigationStrategy | G2: Owner | H2: Status
A3: R-001 | B3: Risk | C3: Delay in composite carbon sheet deliveries from overseas supplier | D3: High | E3: Medium | F3: Pre-order early or source alternative local supplier | G3: Morten Hansen | H3: Active
A4: A-001 | B4: Assumption | C4: Subcontractor electrician rates remain fixed under contract | D4: Medium | E4: Low | F4: Keep signed SLA agreements as references | G4: Frank Ellingsen | H4: Closed
A5: I-001 | B5: Issue | C5: Astrid Nilsen welder overtime limit breached due to recovery fabrication schedule | D5: Medium | E5: High | F5: Allocate junior welder to assist with low-priority tasks | G5: Morten Hansen | H5: Active
A6: D-001 | B6: Dependency | C6: Sea trials (WBS 4.0) depend on DNV safety and compliance certification approval | D6: High | E6: High | F6: Submit compliance paperwork 2 weeks in advance of handover date | G6: Frank Ellingsen | H6: Active
