Workbook
Name Figurnotasjon: 'Tilordning av figurnotasjon'!$A$2:$A$16

Sheet Project Init
A1: PROJECT INITIATION DOCUMENT | E1: 1 | F1: BUSINESS CASE | J1: 2 | K1: PROJECT SCOPE | M1: < Cost, Quality or Time? > | P1: Identify Driver | V1: > Step 1 - Define the project
F2: <Insert the Business Case if you have one. > | K2: 2.1. In Scope / Included in the Project | V2: > Step 2 - List the tasks | Level of granularity
A3: PROJECT NAME: | F3: • Why this project | K3: 2.2. Out of Scope / Excluded from the Project | V3: > Step 3 - Establishing task order
A4: PROJECT NUMBER: | F4: • Why now? | K4: 2.3. Dependencies | V4: > Step 4 - Estimating time
A5: PROJECT RISK LEVEL: H/M/L | F5: • Options considered | K5: <Describe how the project impacts or will be impacted by other projects or programmes > | V5: > Step 5 - Margin check & reality check
A6: Prepared by: | F6: • What if we don’t do it? | V6: > Step 6 - Gantt Chart
A7: Date: | F7: • Benefits | K7: 2.4. Constraints | V7: > Step 7 - Resource allocation
A8: Persons consulted: | F8: • Payback period | K8: <Describe any constraints within which the project must be delivered, e.g. government deadlines; | V8: > Step 8 - Predicting & reducing risk
K9: budget limits; resource limitations. > | V9: > Step 9 - Monitoring progress
A10: KEY ACTIONS PROPOSED TO DELIVER THE PROJECT | K10: 2.5. Assumptions | V10: > Step 10 - Monitoring cost
A11: You MUST Include a high-level or detailed Gantt chart | K11: < Describe any assumptions that are being worked from at this point (for example, that you will | V11: > Step 11 - Adjusting the plan
A12: Communications Plan | K12: get planning permission). > | V12: > Step 12 - Review & lessons
A13: What | K13: 2.6 – What’s the key driver of your project, and why do you think that?
A14: How
A15: Who | K15: Project Initiation Document
A16: Version <version no. > | K16: 3.1. Quality Plan
A17: When | K17: <Describe how it is intended to meet, and shown to meet, the customer’s quality expectations >
A18: Cost | K18: 4. PROJECT CONTROLS AND REPORTING
K19: < Describe how progress will be reported to the Project Board if there is one. >
A20: Task Acceptance Criteria | K20: 5. RISK CONTROL
A21: Frequency / timing | K21: <Attach a risk chart, or for small, low-risk projects, insert below in this document. >
A22: (monthly, stage end, etc) | K22: 6. FINANCIAL IMPLICATIONS
A23: How will the Control be reported Responsibility for | K23: I have considered the benefits against the project costs and assessed the project plan
A24: production
A25: Project Risk Containment Measures | K25: RISKS:
A26: Q1 Q2 Q3 Q4 Total | K26: How likely?
A27: Amount Year 1 | K27: How serious?
A28: Amount Year 2 | K28: What impact?
A29: Amount Year 3
A30: Amount Year 4
A31: Amount Year 5

Sheet tblTaskList
A1: Task ID | B1: Task Name | C1: Resource | D1: IsInCriticalPath | E1: Predecessor Tasks | F1: Duration (Weeks) | G1: Progress | H1: Hours | I1: Cost | J1: Actual Cost | K1: Start wk | L1: Finish wk | N1: Project | O1: Budget | P1: Start Date | Q1: total hours | R1: total cost | S1: ActCost | T1: Diff
A2: 2 | B2: Planning permission | C2: FE | D2: Yes | E2: Wait for planning permission | F2: 6 | G2: 1 | K2: =_xlfn.XLOOKUP(tblTaskList[[#This Row],[Task Name]],'Gantt-frame'!$E$8:$E$25,'Gantt-frame'!$G$8:$G$25,"") -> 1 | L2: =_xlfn.LET(_xlpm.s,tblTaskList[[#This Row],[Start wk]],_xlpm.d,IF(tblTaskList[[#This Row],[Duration (Weeks)]]="",_xlfn.XLOOKUP(tblTaskList[[#This Row],[Task Name]],'Gantt-frame'!$E$8:$E$25,'Gantt-frame'!$B$8:$B$25,0),tblTaskList[[#This Row],[Duration (Weeks)]]),IF(_xlpm.s="","",_xlpm.s+MAX(_xlpm.d,1)-1)) -> 6 | N2: New Garden Shed | O2: 20000 | P2: 01.06.2026 | Q2: =SUM(tblTaskList[Hours]) -> 70 | R2: =SUM(tblTaskList[Cost]) -> 18800 | S2: =SUM(tblTaskList[Actual Cost]) -> 19450 | T2: =tblBudget[[#This Row],[total cost]]-tblBudget[[#This Row],[ActCost]] -> -650
A3: 3 | B3: Wait for planning permission | C3: FE | D3: Yes | E3: Hire digger | F3: 10 | G3: 0.2 | I3: 100 | J3: 100 | K3: =_xlfn.XLOOKUP(tblTaskList[[#This Row],[Task Name]],'Gantt-frame'!$E$8:$E$25,'Gantt-frame'!$G$8:$G$25,"") -> 7 | L3: =_xlfn.LET(_xlpm.s,tblTaskList[[#This Row],[Start wk]],_xlpm.d,IF(tblTaskList[[#This Row],[Duration (Weeks)]]="",_xlfn.XLOOKUP(tblTaskList[[#This Row],[Task Name]],'Gantt-frame'!$E$8:$E$25,'Gantt-frame'!$B$8:$B$25,0),tblTaskList[[#This Row],[Duration (Weeks)]]),IF(_xlpm.s="","",_xlpm.s+MAX(_xlpm.d,1)-1)) -> 16
A4: 6 | B4: Dig trench | C4: NN | D4: Yes | E4: Wire down the garden | F4: 1 | G4: 0 | H4: 4 | I4: 350 | J4: 400 | K4: =_xlfn.XLOOKUP(tblTaskList[[#This Row],[Task Name]],'Gantt-frame'!$E$8:$E$25,'Gantt-frame'!$G$8:$G$25,"") -> 17 | L4: =_xlfn.LET(_xlpm.s,tblTaskList[[#This Row],[Start wk]],_xlpm.d,IF(tblTaskList[[#This Row],[Duration (Weeks)]]="",_xlfn.XLOOKUP(tblTaskList[[#This Row],[Task Name]],'Gantt-frame'!$E$8:$E$25,'Gantt-frame'!$B$8:$B$25,0),tblTaskList[[#This Row],[Duration (Weeks)]]),IF(_xlpm.s="","",_xlpm.s+MAX(_xlpm.d,1)-1)) -> 17
A5: 7 | B5: Hire digger | C5: FE | D5: Yes | E5: Dig trench | F5: 2 | G5: 0 | K5: =_xlfn.XLOOKUP(tblTaskList[[#This Row],[Task Name]],'Gantt-frame'!$E$8:$E$25,'Gantt-frame'!$G$8:$G$25,"") -> 18 | L5: =_xlfn.LET(_xlpm.s,tblTaskList[[#This Row],[Start wk]],_xlpm.d,IF(tblTaskList[[#This Row],[Duration (Weeks)]]="",_xlfn.XLOOKUP(tblTaskList[[#This Row],[Task Name]],'Gantt-frame'!$E$8:$E$25,'Gantt-frame'!$B$8:$B$25,0),tblTaskList[[#This Row],[Duration (Weeks)]]),IF(_xlpm.s="","",_xlpm.s+MAX(_xlpm.d,1)-1)) -> 19
A6: 9 | B6: Fill with concrete | C6: NN | D6: Yes | E6: Level the base | F6: 1 | G6: 0 | H6: 3 | I6: 700 | J6: 800 | K6: =_xlfn.XLOOKUP(tblTaskList[[#This Row],[Task Name]],'Gantt-frame'!$E$8:$E$25,'Gantt-frame'!$G$8:$G$25,"") -> 20 | L6: =_xlfn.LET(_xlpm.s,tblTaskList[[#This Row],[Start wk]],_xlpm.d,IF(tblTaskList[[#This Row],[Duration (Weeks)]]="",_xlfn.XLOOKUP(tblTaskList[[#This Row],[Task Name]],'Gantt-frame'!$E$8:$E$25,'Gantt-frame'!$B$8:$B$25,0),tblTaskList[[#This Row],[Duration (Weeks)]]),IF(_xlpm.s="","",_xlpm.s+MAX(_xlpm.d,1)-1)) -> 20
A7: 10 | B7: Level the base | C7: NN | D7: Yes | E7: Assembly | F7: 1 | G7: 0 | H7: 5 | I7: 100 | J7: 100 | K7: =_xlfn.XLOOKUP(tblTaskList[[#This Row],[Task Name]],'Gantt-frame'!$E$8:$E$25,'Gantt-frame'!$G$8:$G$25,"") -> 21 | L7: =_xlfn.LET(_xlpm.s,tblTaskList[[#This Row],[Start wk]],_xlpm.d,IF(tblTaskList[[#This Row],[Duration (Weeks)]]="",_xlfn.XLOOKUP(tblTaskList[[#This Row],[Task Name]],'Gantt-frame'!$E$8:$E$25,'Gantt-frame'!$B$8:$B$25,0),tblTaskList[[#This Row],[Duration (Weeks)]]),IF(_xlpm.s="","",_xlpm.s+MAX(_xlpm.d,1)-1)) -> 21
A8: 17 | B8: the Finish | C8: FE | D8: Yes | F8: 4 | G8: 0 | H8: 34 | I8: 8000 | J8: 8500 | K8: =_xlfn.XLOOKUP(tblTaskList[[#This Row],[Task Name]],'Gantt-frame'!$E$8:$E$25,'Gantt-frame'!$G$8:$G$25,"") -> 22 | L8: =_xlfn.LET(_xlpm.s,tblTaskList[[#This Row],[Start wk]],_xlpm.d,IF(tblTaskList[[#This Row],[Duration (Weeks)]]="",_xlfn.XLOOKUP(tblTaskList[[#This Row],[Task Name]],'Gantt-frame'!$E$8:$E$25,'Gantt-frame'!$B$8:$B$25,0),tblTaskList[[#This Row],[Duration (Weeks)]]),IF(_xlpm.s="","",_xlpm.s+MAX(_xlpm.d,1)-1)) -> 25
A9: 19 | B9: Delivery | C9: NN | D9: Yes | E9: Wait for Delivery | F9: 0 | G9: 0 | K9: =_xlfn.XLOOKUP(tblTaskList[[#This Row],[Task Name]],'Gantt-frame'!$E$8:$E$25,'Gantt-frame'!$G$8:$G$25,"") -> 22 | L9: =_xlfn.LET(_xlpm.s,tblTaskList[[#This Row],[Start wk]],_xlpm.d,IF(tblTaskList[[#This Row],[Duration (Weeks)]]="",_xlfn.XLOOKUP(tblTaskList[[#This Row],[Task Name]],'Gantt-frame'!$E$8:$E$25,'Gantt-frame'!$B$8:$B$25,0),tblTaskList[[#This Row],[Duration (Weeks)]]),IF(_xlpm.s="","",_xlpm.s+MAX(_xlpm.d,1)-1)) -> 22
A10: 1 | B10: Check funds | C10: FE | D10: Float | E10: Demolish old shed | F10: 0 | G10: 1 | K10: =_xlfn.XLOOKUP(tblTaskList[[#This Row],[Task Name]],'Gantt-frame'!$E$8:$E$25,'Gantt-frame'!$G$8:$G$25,"") -> 2 | L10: =_xlfn.LET(_xlpm.s,tblTaskList[[#This Row],[Start wk]],_xlpm.d,IF(tblTaskList[[#This Row],[Duration (Weeks)]]="",_xlfn.XLOOKUP(tblTaskList[[#This Row],[Task Name]],'Gantt-frame'!$E$8:$E$25,'Gantt-frame'!$B$8:$B$25,0),tblTaskList[[#This Row],[Duration (Weeks)]]),IF(_xlpm.s="","",_xlpm.s+MAX(_xlpm.d,1)-1)) -> 2
A11: 4 | B11: Demolish old shed | C11: NN | D11: Float | E11: Cut foliage back | F11: 1 | G11: 0 | H11: 6 | I11: 300 | J11: 300 | K11: =_xlfn.XLOOKUP(tblTaskList[[#This Row],[Task Name]],'Gantt-frame'!$E$8:$E$25,'Gantt-frame'!$G$8:$G$25,"") -> 3 | L11: =_xlfn.LET(_xlpm.s,tblTaskList[[#This Row],[Start wk]],_xlpm.d,IF(tblTaskList[[#This Row],[Duration (Weeks)]]="",_xlfn.XLOOKUP(tblTaskList[[#This Row],[Task Name]],'Gantt-frame'!$E$8:$E$25,'Gantt-frame'!$B$8:$B$25,0),tblTaskList[[#This Row],[Duration (Weeks)]]),IF(_xlpm.s="","",_xlpm.s+MAX(_xlpm.d,1)-1)) -> 3 | Y11: Critical
A12: 5 | B12: Cut foliage back | C12: NN | D12: Float | E12: Dig trench | F12: 4 | G12: 0 | H12: 10 | I12: 500 | J12: 500 | K12: =_xlfn.XLOOKUP(tblTaskList[[#This Row],[Task Name]],'Gantt-frame'!$E$8:$E$25,'Gantt-frame'!$G$8:$G$25,"") -> 8 | L12: =_xlfn.LET(_xlpm.s,tblTaskList[[#This Row],[Start wk]],_xlpm.d,IF(tblTaskList[[#This Row],[Duration (Weeks)]]="",_xlfn.XLOOKUP(tblTaskList[[#This Row],[Task Name]],'Gantt-frame'!$E$8:$E$25,'Gantt-frame'!$B$8:$B$25,0),tblTaskList[[#This Row],[Duration (Weeks)]]),IF(_xlpm.s="","",_xlpm.s+MAX(_xlpm.d,1)-1)) -> 11 | Y12: Path
A13: 8 | B13: Connect Power | C13: NN | D13: Float | E13: the Finish | G13: 0 | K13: =_xlfn.XLOOKUP(tblTaskList[[#This Row],[Task Name]],'Gantt-frame'!$E$8:$E$25,'Gantt-frame'!$G$8:$G$25,"") -> 13 | L13: =_xlfn.LET(_xlpm.s,tblTaskList[[#This Row],[Start wk]],_xlpm.d,IF(tblTaskList[[#This Row],[Duration (Weeks)]]="",_xlfn.XLOOKUP(tblTaskList[[#This Row],[Task Name]],'Gantt-frame'!$E$8:$E$25,'Gantt-frame'!$B$8:$B$25,0),tblTaskList[[#This Row],[Duration (Weeks)]]),IF(_xlpm.s="","",_xlpm.s+MAX(_xlpm.d,1)-1)) -> 13 | Y13: (Weeks)
A14: 11 | B14: Find suppliers | C14: FE | D14: Float | E14: Get quotes | F14: 1 | G14: 1 | K14: =_xlfn.XLOOKUP(tblTaskList[[#This Row],[Task Name]],'Gantt-frame'!$E$8:$E$25,'Gantt-frame'!$G$8:$G$25,"") -> 4 | L14: =_xlfn.LET(_xlpm.s,tblTaskList[[#This Row],[Start wk]],_xlpm.d,IF(tblTaskList[[#This Row],[Duration (Weeks)]]="",_xlfn.XLOOKUP(tblTaskList[[#This Row],[Task Name]],'Gantt-frame'!$E$8:$E$25,'Gantt-frame'!$B$8:$B$25,0),tblTaskList[[#This Row],[Duration (Weeks)]]),IF(_xlpm.s="","",_xlpm.s+MAX(_xlpm.d,1)-1)) -> 4 | Y14: =6+10+2+1+2+1+4 -> 26
A15: 12 | B15: Get quotes | C15: FE | D15: Float | E15: Buy the shed | F15: 3 | G15: 0 | K15: =_xlfn.XLOOKUP(tblTaskList[[#This Row],[Task Name]],'Gantt-frame'!$E$8:$E$25,'Gantt-frame'!$G$8:$G$25,"") -> 7 | L15: =_xlfn.LET(_xlpm.s,tblTaskList[[#This Row],[Start wk]],_xlpm.d,IF(tblTaskList[[#This Row],[Duration (Weeks)]]="",_xlfn.XLOOKUP(tblTaskList[[#This Row],[Task Name]],'Gantt-frame'!$E$8:$E$25,'Gantt-frame'!$B$8:$B$25,0),tblTaskList[[#This Row],[Duration (Weeks)]]),IF(_xlpm.s="","",_xlpm.s+MAX(_xlpm.d,1)-1)) -> 9
A16: 13 | B16: Buy the shed | C16: FE | D16: Float | F16: 0 | G16: 0 | I16: 8000 | J16: 8000 | K16: =_xlfn.XLOOKUP(tblTaskList[[#This Row],[Task Name]],'Gantt-frame'!$E$8:$E$25,'Gantt-frame'!$G$8:$G$25,"") -> 8 | L16: =_xlfn.LET(_xlpm.s,tblTaskList[[#This Row],[Start wk]],_xlpm.d,IF(tblTaskList[[#This Row],[Duration (Weeks)]]="",_xlfn.XLOOKUP(tblTaskList[[#This Row],[Task Name]],'Gantt-frame'!$E$8:$E$25,'Gantt-frame'!$B$8:$B$25,0),tblTaskList[[#This Row],[Duration (Weeks)]]),IF(_xlpm.s="","",_xlpm.s+MAX(_xlpm.d,1)-1)) -> 8
A17: 14 | B17: Wait for Delivery | C17: FE | D17: Float | E17: Assembly | F17: 6 | G17: 0 | K17: =_xlfn.XLOOKUP(tblTaskList[[#This Row],[Task Name]],'Gantt-frame'!$E$8:$E$25,'Gantt-frame'!$G$8:$G$25,"") -> 7 | L17: =_xlfn.LET(_xlpm.s,tblTaskList[[#This Row],[Start wk]],_xlpm.d,IF(tblTaskList[[#This Row],[Duration (Weeks)]]="",_xlfn.XLOOKUP(tblTaskList[[#This Row],[Task Name]],'Gantt-frame'!$E$8:$E$25,'Gantt-frame'!$B$8:$B$25,0),tblTaskList[[#This Row],[Duration (Weeks)]]),IF(_xlpm.s="","",_xlpm.s+MAX(_xlpm.d,1)-1)) -> 12
A18: 15 | B18: Wire down the garden | C18: NN | D18: Float | E18: Connect Power | F18: 1 | G18: 0 | H18: 8 | K18: =_xlfn.XLOOKUP(tblTaskList[[#This Row],[Task Name]],'Gantt-frame'!$E$8:$E$25,'Gantt-frame'!$G$8:$G$25,"") -> 22 | L18: =_xlfn.LET(_xlpm.s,tblTaskList[[#This Row],[Start wk]],_xlpm.d,IF(tblTaskList[[#This Row],[Duration (Weeks)]]="",_xlfn.XLOOKUP(tblTaskList[[#This Row],[Task Name]],'Gantt-frame'!$E$8:$E$25,'Gantt-frame'!$B$8:$B$25,0),tblTaskList[[#This Row],[Duration (Weeks)]]),IF(_xlpm.s="","",_xlpm.s+MAX(_xlpm.d,1)-1)) -> 22
A19: 16 | B19: Assembly | C19: NN | D19: Float | F19: 1 | G19: 0 | I19: 750 | J19: 750 | K19: =_xlfn.XLOOKUP(tblTaskList[[#This Row],[Task Name]],'Gantt-frame'!$E$8:$E$25,'Gantt-frame'!$G$8:$G$25,"") -> 23 | L19: =_xlfn.LET(_xlpm.s,tblTaskList[[#This Row],[Start wk]],_xlpm.d,IF(tblTaskList[[#This Row],[Duration (Weeks)]]="",_xlfn.XLOOKUP(tblTaskList[[#This Row],[Task Name]],'Gantt-frame'!$E$8:$E$25,'Gantt-frame'!$B$8:$B$25,0),tblTaskList[[#This Row],[Duration (Weeks)]]),IF(_xlpm.s="","",_xlpm.s+MAX(_xlpm.d,1)-1)) -> 23
N23: Start with Running Order Regardless of Time => Then Estimate Time for Each Task (Independently of Running Order)
N25: Critical Path => The Longest Path
N27: Parallell Floaters | O27: What comes Before/After?
N29: Safety Margin -> Add /Blend into Critical Path (50% of worst case =>90% Reliable)
N32: Time Down => Money Up or Quality Down | Overlapping Tasks

Sheet EVM Data
A1: EVM Data Model — Required Task-Level Reporting Table
A2: Modeled from tblTaskList. Fill the yellow input columns where blank; calculated EVM columns update automatically from those inputs and the status week.
A4: Project | B4: =INDEX(tblBudget[Project],1) -> New Garden Shed | D4: Metric | E4: Formula | F4: Value | H4: Metric | I4: Formula | J4: Value | L4: Metric | M4: Formula | N4: Value | P4: How to complete
A5: Status week | B5: ='Gantt-frame'!$G$4 -> 32 | D5: Total EV | E5: SUM(tblEVMData[Earned Value]) | F5: =SUM(tblEVMData[Earned Value]) -> 20 | H5: SV | I5: EV - PV | J5: =F5-F6 -> -18780 | L5: EAC | M5: BAC / CPI | N5: =IFERROR($B$7/J8,"") -> 18283000 | P5: 1. Fill yellow columns if blank: Baseline Cost, Actual Cost, Hours, Actual % Complete.
A6: Status date | B6: ='Gantt-frame'!$F$4 -> 46240 | D6: Total PV | E6: SUM(tblEVMData[Planned Value]) | F6: =SUM(tblEVMData[Planned Value]) -> 18800 | H6: CV | I6: EV - AC | J6: =F5-F7 -> -19430 | L6: ETC | M6: EAC - AC | N6: =IFERROR(N5-F7,"") -> 18263550
A7: Budget at Completion | B7: =INDEX(tblBudget[total cost],1) -> 18800 | D7: Total AC | E7: SUM(tblEVMData[Actual Cost]) | F7: =SUM(tblEVMData[Actual Cost]) -> 19450 | H7: SPI | I7: EV / PV | J7: =IFERROR(F5/F6,"") -> 0.0010638298 | L7: VAC | M7: BAC - EAC | N7: =IFERROR($B$7-N5,"") -> -18264200
H8: CPI | I8: EV / AC | J8: =IFERROR(F5/F7,"") -> 0.0010282776 | L8: TCPI | M8: (BAC-EV)/(BAC-AC) | N8: =IFERROR(($B$7-F5)/($B$7-F7),"") -> -28.892308
A9: Task ID | B9: Task Name | C9: Resource | D9: Critical Path | E9: Predecessor Tasks | F9: Start wk | G9: Finish wk | H9: Duration (Weeks) | I9: Baseline Cost | J9: Actual Cost | K9: Hours | L9: Actual % Complete | M9: Planned % Complete | N9: Earned Value | O9: Planned Value | P9: Schedule Variance | Q9: Cost Variance | R9: SPI | S9: CPI | T9: Data Gap / Action Needed
A10: {=IFERROR(INDEX(tblTaskList[Task ID],ROWS($A$10:A10)),"")} -> 2 | B10: {=IFERROR(INDEX(tblTaskList[Task Name],ROWS($A$10:A10)),"")} -> Planning permission | C10: {=IFERROR(INDEX(tblTaskList[Resource],ROWS($A$10:A10)),"")} -> FE | D10: {=IFERROR(INDEX(tblTaskList[IsInCriticalPath],ROWS($A$10:A10)),"")} -> Yes | E10: {=IFERROR(INDEX(tblTaskList[Predecessor Tasks],ROWS($A$10:A10)),"")} -> Wait for planning permission | F10: {=IFERROR(INDEX(tblTaskList[Start wk],ROWS($A$10:A10)),"")} -> 1 | G10: {=IFERROR(INDEX(tblTaskList[Finish wk],ROWS($A$10:A10)),"")} -> 6 | H10: {=IFERROR(INDEX(tblTaskList[Duration (Weeks)],ROWS($A$10:A10)),"")} -> 6 | I10: {=IFERROR(INDEX(tblTaskList[Cost],ROWS($A$10:A10)),"")} -> 0 | J10: {=IFERROR(INDEX(tblTaskList[Actual Cost],ROWS($A$10:A10)),"")} -> 0 | K10: {=IFERROR(INDEX(tblTaskList[Hours],ROWS($A$10:A10)),"")} -> 0 | L10: {=IFERROR(INDEX(tblTaskList[Progress],ROWS($A$10:A10)),"")} -> 1 | M10: =IF(OR(tblEVMData[[#This Row],[Start wk]]="",tblEVMData[[#This Row],[Finish wk]]="",tblEVMData[[#This Row],[Baseline Cost]]=""),"",IF($B$5<tblEVMData[[#This Row],[Start wk]],0,IF($B$5>tblEVMData[[#This Row],[Finish wk]],1,($B$5-tblEVMData[[#This Row],[Start wk]]+1)/MAX(1,tblEVMData[[#This Row],[Finish wk]]-tblEVMData[[#This Row],[Start wk]]+1)))) -> 1 | N10: =IFERROR(tblEVMData[[#This Row],[Baseline Cost]]*tblEVMData[[#This Row],[Actual % Complete]],"") -> 0 | O10: =IFERROR(tblEVMData[[#This Row],[Baseline Cost]]*tblEVMData[[#This Row],[Planned % Complete]],"") -> 0 | P10: =IFERROR(tblEVMData[[#This Row],[Earned Value]]-tblEVMData[[#This Row],[Planned Value]],"") -> 0 | Q10: =IFERROR(tblEVMData[[#This Row],[Earned Value]]-tblEVMData[[#This Row],[Actual Cost]],"") -> 0 | R10: =IFERROR(tblEVMData[[#This Row],[Earned Value]]/tblEVMData[[#This Row],[Planned Value]],"") | S10: =IFERROR(tblEVMData[[#This Row],[Earned Value]]/tblEVMData[[#This Row],[Actual Cost]],"") | T10: =_xlfn.TEXTJOIN("; ",TRUE,IF(tblEVMData[[#This Row],[Baseline Cost]]="","Add baseline cost", ""),IF(tblEVMData[[#This Row],[Actual Cost]]="","Add actual cost", ""),IF(tblEVMData[[#This Row],[Hours]]="","Add hours", ""),IF(tblEVMData[[#This Row],[Duration (Weeks)]]="","Add duration", ""),IF(tblEVMData[[#This Row],[Actual % Complete]]="","Add progress", ""),IF(tblEVMData[[#This Row],[Start wk]]="","Add start week", ""),IF(tblEVMData[[#This Row],[Finish wk]]="","Add finish week", ""))
A11: {=IFERROR(INDEX(tblTaskList[Task ID],ROWS($A$10:A11)),"")} -> 3 | B11: {=IFERROR(INDEX(tblTaskList[Task Name],ROWS($A$10:A11)),"")} -> Wait for planning permission | C11: {=IFERROR(INDEX(tblTaskList[Resource],ROWS($A$10:A11)),"")} -> FE | D11: {=IFERROR(INDEX(tblTaskList[IsInCriticalPath],ROWS($A$10:A11)),"")} -> Yes | E11: {=IFERROR(INDEX(tblTaskList[Predecessor Tasks],ROWS($A$10:A11)),"")} -> Hire digger | F11: {=IFERROR(INDEX(tblTaskList[Start wk],ROWS($A$10:A11)),"")} -> 7 | G11: {=IFERROR(INDEX(tblTaskList[Finish wk],ROWS($A$10:A11)),"")} -> 16 | H11: {=IFERROR(INDEX(tblTaskList[Duration (Weeks)],ROWS($A$10:A11)),"")} -> 10 | I11: {=IFERROR(INDEX(tblTaskList[Cost],ROWS($A$10:A11)),"")} -> 100 | J11: {=IFERROR(INDEX(tblTaskList[Actual Cost],ROWS($A$10:A11)),"")} -> 100 | K11: {=IFERROR(INDEX(tblTaskList[Hours],ROWS($A$10:A11)),"")} -> 0 | L11: {=IFERROR(INDEX(tblTaskList[Progress],ROWS($A$10:A11)),"")} -> 0.2 | M11: =IF(OR(tblEVMData[[#This Row],[Start wk]]="",tblEVMData[[#This Row],[Finish wk]]="",tblEVMData[[#This Row],[Baseline Cost]]=""),"",IF($B$5<tblEVMData[[#This Row],[Start wk]],0,IF($B$5>tblEVMData[[#This Row],[Finish wk]],1,($B$5-tblEVMData[[#This Row],[Start wk]]+1)/MAX(1,tblEVMData[[#This Row],[Finish wk]]-tblEVMData[[#This Row],[Start wk]]+1)))) -> 1 | N11: =IFERROR(tblEVMData[[#This Row],[Baseline Cost]]*tblEVMData[[#This Row],[Actual % Complete]],"") -> 20 | O11: =IFERROR(tblEVMData[[#This Row],[Baseline Cost]]*tblEVMData[[#This Row],[Planned % Complete]],"") -> 100 | P11: =IFERROR(tblEVMData[[#This Row],[Earned Value]]-tblEVMData[[#This Row],[Planned Value]],"") -> -80 | Q11: =IFERROR(tblEVMData[[#This Row],[Earned Value]]-tblEVMData[[#This Row],[Actual Cost]],"") -> -80 | R11: =IFERROR(tblEVMData[[#This Row],[Earned Value]]/tblEVMData[[#This Row],[Planned Value]],"") -> 0.2 | S11: =IFERROR(tblEVMData[[#This Row],[Earned Value]]/tblEVMData[[#This Row],[Actual Cost]],"") -> 0.2 | T11: =_xlfn.TEXTJOIN("; ",TRUE,IF(tblEVMData[[#This Row],[Baseline Cost]]="","Add baseline cost", ""),IF(tblEVMData[[#This Row],[Actual Cost]]="","Add actual cost", ""),IF(tblEVMData[[#This Row],[Hours]]="","Add hours", ""),IF(tblEVMData[[#This Row],[Duration (Weeks)]]="","Add duration", ""),IF(tblEVMData[[#This Row],[Actual % Complete]]="","Add progress", ""),IF(tblEVMData[[#This Row],[Start wk]]="","Add start week", ""),IF(tblEVMData[[#This Row],[Finish wk]]="","Add finish week", ""))
A12: {=IFERROR(INDEX(tblTaskList[Task ID],ROWS($A$10:A12)),"")} -> 6 | B12: {=IFERROR(INDEX(tblTaskList[Task Name],ROWS($A$10:A12)),"")} -> Dig trench | C12: {=IFERROR(INDEX(tblTaskList[Resource],ROWS($A$10:A12)),"")} -> NN | D12: {=IFERROR(INDEX(tblTaskList[IsInCriticalPath],ROWS($A$10:A12)),"")} -> Yes | E12: {=IFERROR(INDEX(tblTaskList[Predecessor Tasks],ROWS($A$10:A12)),"")} -> Wire down the garden | F12: {=IFERROR(INDEX(tblTaskList[Start wk],ROWS($A$10:A12)),"")} -> 17 | G12: {=IFERROR(INDEX(tblTaskList[Finish wk],ROWS($A$10:A12)),"")} -> 17 | H12: {=IFERROR(INDEX(tblTaskList[Duration (Weeks)],ROWS($A$10:A12)),"")} -> 1 | I12: {=IFERROR(INDEX(tblTaskList[Cost],ROWS($A$10:A12)),"")} -> 350 | J12: {=IFERROR(INDEX(tblTaskList[Actual Cost],ROWS($A$10:A12)),"")} -> 400 | K12: {=IFERROR(INDEX(tblTaskList[Hours],ROWS($A$10:A12)),"")} -> 4 | L12: {=IFERROR(INDEX(tblTaskList[Progress],ROWS($A$10:A12)),"")} -> 0 | M12: =IF(OR(tblEVMData[[#This Row],[Start wk]]="",tblEVMData[[#This Row],[Finish wk]]="",tblEVMData[[#This Row],[Baseline Cost]]=""),"",IF($B$5<tblEVMData[[#This Row],[Start wk]],0,IF($B$5>tblEVMData[[#This Row],[Finish wk]],1,($B$5-tblEVMData[[#This Row],[Start wk]]+1)/MAX(1,tblEVMData[[#This Row],[Finish wk]]-tblEVMData[[#This Row],[Start wk]]+1)))) -> 1 | N12: =IFERROR(tblEVMData[[#This Row],[Baseline Cost]]*tblEVMData[[#This Row],[Actual % Complete]],"") -> 0 | O12: =IFERROR(tblEVMData[[#This Row],[Baseline Cost]]*tblEVMData[[#This Row],[Planned % Complete]],"") -> 350 | P12: =IFERROR(tblEVMData[[#This Row],[Earned Value]]-tblEVMData[[#This Row],[Planned Value]],"") -> -350 | Q12: =IFERROR(tblEVMData[[#This Row],[Earned Value]]-tblEVMData[[#This Row],[Actual Cost]],"") -> -400 | R12: =IFERROR(tblEVMData[[#This Row],[Earned Value]]/tblEVMData[[#This Row],[Planned Value]],"") -> 0 | S12: =IFERROR(tblEVMData[[#This Row],[Earned Value]]/tblEVMData[[#This Row],[Actual Cost]],"") -> 0 | T12: =_xlfn.TEXTJOIN("; ",TRUE,IF(tblEVMData[[#This Row],[Baseline Cost]]="","Add baseline cost", ""),IF(tblEVMData[[#This Row],[Actual Cost]]="","Add actual cost", ""),IF(tblEVMData[[#This Row],[Hours]]="","Add hours", ""),IF(tblEVMData[[#This Row],[Duration (Weeks)]]="","Add duration", ""),IF(tblEVMData[[#This Row],[Actual % Complete]]="","Add progress", ""),IF(tblEVMData[[#This Row],[Start wk]]="","Add start week", ""),IF(tblEVMData[[#This Row],[Finish wk]]="","Add finish week", ""))
A13: {=IFERROR(INDEX(tblTaskList[Task ID],ROWS($A$10:A13)),"")} -> 7 | B13: {=IFERROR(INDEX(tblTaskList[Task Name],ROWS($A$10:A13)),"")} -> Hire digger | C13: {=IFERROR(INDEX(tblTaskList[Resource],ROWS($A$10:A13)),"")} -> FE | D13: {=IFERROR(INDEX(tblTaskList[IsInCriticalPath],ROWS($A$10:A13)),"")} -> Yes | E13: {=IFERROR(INDEX(tblTaskList[Predecessor Tasks],ROWS($A$10:A13)),"")} -> Dig trench | F13: {=IFERROR(INDEX(tblTaskList[Start wk],ROWS($A$10:A13)),"")} -> 18 | G13: {=IFERROR(INDEX(tblTaskList[Finish wk],ROWS($A$10:A13)),"")} -> 19 | H13: {=IFERROR(INDEX(tblTaskList[Duration (Weeks)],ROWS($A$10:A13)),"")} -> 2 | I13: {=IFERROR(INDEX(tblTaskList[Cost],ROWS($A$10:A13)),"")} -> 0 | J13: {=IFERROR(INDEX(tblTaskList[Actual Cost],ROWS($A$10:A13)),"")} -> 0 | K13: {=IFERROR(INDEX(tblTaskList[Hours],ROWS($A$10:A13)),"")} -> 0 | L13: {=IFERROR(INDEX(tblTaskList[Progress],ROWS($A$10:A13)),"")} -> 0 | M13: =IF(OR(tblEVMData[[#This Row],[Start wk]]="",tblEVMData[[#This Row],[Finish wk]]="",tblEVMData[[#This Row],[Baseline Cost]]=""),"",IF($B$5<tblEVMData[[#This Row],[Start wk]],0,IF($B$5>tblEVMData[[#This Row],[Finish wk]],1,($B$5-tblEVMData[[#This Row],[Start wk]]+1)/MAX(1,tblEVMData[[#This Row],[Finish wk]]-tblEVMData[[#This Row],[Start wk]]+1)))) -> 1 | N13: =IFERROR(tblEVMData[[#This Row],[Baseline Cost]]*tblEVMData[[#This Row],[Actual % Complete]],"") -> 0 | O13: =IFERROR(tblEVMData[[#This Row],[Baseline Cost]]*tblEVMData[[#This Row],[Planned % Complete]],"") -> 0 | P13: =IFERROR(tblEVMData[[#This Row],[Earned Value]]-tblEVMData[[#This Row],[Planned Value]],"") -> 0 | Q13: =IFERROR(tblEVMData[[#This Row],[Earned Value]]-tblEVMData[[#This Row],[Actual Cost]],"") -> 0 | R13: =IFERROR(tblEVMData[[#This Row],[Earned Value]]/tblEVMData[[#This Row],[Planned Value]],"") | S13: =IFERROR(tblEVMData[[#This Row],[Earned Value]]/tblEVMData[[#This Row],[Actual Cost]],"") | T13: =_xlfn.TEXTJOIN("; ",TRUE,IF(tblEVMData[[#This Row],[Baseline Cost]]="","Add baseline cost", ""),IF(tblEVMData[[#This Row],[Actual Cost]]="","Add actual cost", ""),IF(tblEVMData[[#This Row],[Hours]]="","Add hours", ""),IF(tblEVMData[[#This Row],[Duration (Weeks)]]="","Add duration", ""),IF(tblEVMData[[#This Row],[Actual % Complete]]="","Add progress", ""),IF(tblEVMData[[#This Row],[Start wk]]="","Add start week", ""),IF(tblEVMData[[#This Row],[Finish wk]]="","Add finish week", ""))
A14: {=IFERROR(INDEX(tblTaskList[Task ID],ROWS($A$10:A14)),"")} -> 9 | B14: {=IFERROR(INDEX(tblTaskList[Task Name],ROWS($A$10:A14)),"")} -> Fill with concrete | C14: {=IFERROR(INDEX(tblTaskList[Resource],ROWS($A$10:A14)),"")} -> NN | D14: {=IFERROR(INDEX(tblTaskList[IsInCriticalPath],ROWS($A$10:A14)),"")} -> Yes | E14: {=IFERROR(INDEX(tblTaskList[Predecessor Tasks],ROWS($A$10:A14)),"")} -> Level the base | F14: {=IFERROR(INDEX(tblTaskList[Start wk],ROWS($A$10:A14)),"")} -> 20 | G14: {=IFERROR(INDEX(tblTaskList[Finish wk],ROWS($A$10:A14)),"")} -> 20 | H14: {=IFERROR(INDEX(tblTaskList[Duration (Weeks)],ROWS($A$10:A14)),"")} -> 1 | I14: {=IFERROR(INDEX(tblTaskList[Cost],ROWS($A$10:A14)),"")} -> 700 | J14: {=IFERROR(INDEX(tblTaskList[Actual Cost],ROWS($A$10:A14)),"")} -> 800 | K14: {=IFERROR(INDEX(tblTaskList[Hours],ROWS($A$10:A14)),"")} -> 3 | L14: {=IFERROR(INDEX(tblTaskList[Progress],ROWS($A$10:A14)),"")} -> 0 | M14: =IF(OR(tblEVMData[[#This Row],[Start wk]]="",tblEVMData[[#This Row],[Finish wk]]="",tblEVMData[[#This Row],[Baseline Cost]]=""),"",IF($B$5<tblEVMData[[#This Row],[Start wk]],0,IF($B$5>tblEVMData[[#This Row],[Finish wk]],1,($B$5-tblEVMData[[#This Row],[Start wk]]+1)/MAX(1,tblEVMData[[#This Row],[Finish wk]]-tblEVMData[[#This Row],[Start wk]]+1)))) -> 1 | N14: =IFERROR(tblEVMData[[#This Row],[Baseline Cost]]*tblEVMData[[#This Row],[Actual % Complete]],"") -> 0 | O14: =IFERROR(tblEVMData[[#This Row],[Baseline Cost]]*tblEVMData[[#This Row],[Planned % Complete]],"") -> 700 | P14: =IFERROR(tblEVMData[[#This Row],[Earned Value]]-tblEVMData[[#This Row],[Planned Value]],"") -> -700 | Q14: =IFERROR(tblEVMData[[#This Row],[Earned Value]]-tblEVMData[[#This Row],[Actual Cost]],"") -> -800 | R14: =IFERROR(tblEVMData[[#This Row],[Earned Value]]/tblEVMData[[#This Row],[Planned Value]],"") -> 0 | S14: =IFERROR(tblEVMData[[#This Row],[Earned Value]]/tblEVMData[[#This Row],[Actual Cost]],"") -> 0 | T14: =_xlfn.TEXTJOIN("; ",TRUE,IF(tblEVMData[[#This Row],[Baseline Cost]]="","Add baseline cost", ""),IF(tblEVMData[[#This Row],[Actual Cost]]="","Add actual cost", ""),IF(tblEVMData[[#This Row],[Hours]]="","Add hours", ""),IF(tblEVMData[[#This Row],[Duration (Weeks)]]="","Add duration", ""),IF(tblEVMData[[#This Row],[Actual % Complete]]="","Add progress", ""),IF(tblEVMData[[#This Row],[Start wk]]="","Add start week", ""),IF(tblEVMData[[#This Row],[Finish wk]]="","Add finish week", ""))
A15: {=IFERROR(INDEX(tblTaskList[Task ID],ROWS($A$10:A15)),"")} -> 10 | B15: {=IFERROR(INDEX(tblTaskList[Task Name],ROWS($A$10:A15)),"")} -> Level the base | C15: {=IFERROR(INDEX(tblTaskList[Resource],ROWS($A$10:A15)),"")} -> NN | D15: {=IFERROR(INDEX(tblTaskList[IsInCriticalPath],ROWS($A$10:A15)),"")} -> Yes | E15: {=IFERROR(INDEX(tblTaskList[Predecessor Tasks],ROWS($A$10:A15)),"")} -> Assembly | F15: {=IFERROR(INDEX(tblTaskList[Start wk],ROWS($A$10:A15)),"")} -> 21 | G15: {=IFERROR(INDEX(tblTaskList[Finish wk],ROWS($A$10:A15)),"")} -> 21 | H15: {=IFERROR(INDEX(tblTaskList[Duration (Weeks)],ROWS($A$10:A15)),"")} -> 1 | I15: {=IFERROR(INDEX(tblTaskList[Cost],ROWS($A$10:A15)),"")} -> 100 | J15: {=IFERROR(INDEX(tblTaskList[Actual Cost],ROWS($A$10:A15)),"")} -> 100 | K15: {=IFERROR(INDEX(tblTaskList[Hours],ROWS($A$10:A15)),"")} -> 5 | L15: {=IFERROR(INDEX(tblTaskList[Progress],ROWS($A$10:A15)),"")} -> 0 | M15: =IF(OR(tblEVMData[[#This Row],[Start wk]]="",tblEVMData[[#This Row],[Finish wk]]="",tblEVMData[[#This Row],[Baseline Cost]]=""),"",IF($B$5<tblEVMData[[#This Row],[Start wk]],0,IF($B$5>tblEVMData[[#This Row],[Finish wk]],1,($B$5-tblEVMData[[#This Row],[Start wk]]+1)/MAX(1,tblEVMData[[#This Row],[Finish wk]]-tblEVMData[[#This Row],[Start wk]]+1)))) -> 1 | N15: =IFERROR(tblEVMData[[#This Row],[Baseline Cost]]*tblEVMData[[#This Row],[Actual % Complete]],"") -> 0 | O15: =IFERROR(tblEVMData[[#This Row],[Baseline Cost]]*tblEVMData[[#This Row],[Planned % Complete]],"") -> 100 | P15: =IFERROR(tblEVMData[[#This Row],[Earned Value]]-tblEVMData[[#This Row],[Planned Value]],"") -> -100 | Q15: =IFERROR(tblEVMData[[#This Row],[Earned Value]]-tblEVMData[[#This Row],[Actual Cost]],"") -> -100 | R15: =IFERROR(tblEVMData[[#This Row],[Earned Value]]/tblEVMData[[#This Row],[Planned Value]],"") -> 0 | S15: =IFERROR(tblEVMData[[#This Row],[Earned Value]]/tblEVMData[[#This Row],[Actual Cost]],"") -> 0 | T15: =_xlfn.TEXTJOIN("; ",TRUE,IF(tblEVMData[[#This Row],[Baseline Cost]]="","Add baseline cost", ""),IF(tblEVMData[[#This Row],[Actual Cost]]="","Add actual cost", ""),IF(tblEVMData[[#This Row],[Hours]]="","Add hours", ""),IF(tblEVMData[[#This Row],[Duration (Weeks)]]="","Add duration", ""),IF(tblEVMData[[#This Row],[Actual % Complete]]="","Add progress", ""),IF(tblEVMData[[#This Row],[Start wk]]="","Add start week", ""),IF(tblEVMData[[#This Row],[Finish wk]]="","Add finish week", ""))
A16: {=IFERROR(INDEX(tblTaskList[Task ID],ROWS($A$10:A16)),"")} -> 17 | B16: {=IFERROR(INDEX(tblTaskList[Task Name],ROWS($A$10:A16)),"")} -> the Finish | C16: {=IFERROR(INDEX(tblTaskList[Resource],ROWS($A$10:A16)),"")} -> FE | D16: {=IFERROR(INDEX(tblTaskList[IsInCriticalPath],ROWS($A$10:A16)),"")} -> Yes | E16: {=IFERROR(INDEX(tblTaskList[Predecessor Tasks],ROWS($A$10:A16)),"")} -> 0 | F16: {=IFERROR(INDEX(tblTaskList[Start wk],ROWS($A$10:A16)),"")} -> 22 | G16: {=IFERROR(INDEX(tblTaskList[Finish wk],ROWS($A$10:A16)),"")} -> 25 | H16: {=IFERROR(INDEX(tblTaskList[Duration (Weeks)],ROWS($A$10:A16)),"")} -> 4 | I16: {=IFERROR(INDEX(tblTaskList[Cost],ROWS($A$10:A16)),"")} -> 8000 | J16: {=IFERROR(INDEX(tblTaskList[Actual Cost],ROWS($A$10:A16)),"")} -> 8500 | K16: {=IFERROR(INDEX(tblTaskList[Hours],ROWS($A$10:A16)),"")} -> 34 | L16: {=IFERROR(INDEX(tblTaskList[Progress],ROWS($A$10:A16)),"")} -> 0 | M16: =IF(OR(tblEVMData[[#This Row],[Start wk]]="",tblEVMData[[#This Row],[Finish wk]]="",tblEVMData[[#This Row],[Baseline Cost]]=""),"",IF($B$5<tblEVMData[[#This Row],[Start wk]],0,IF($B$5>tblEVMData[[#This Row],[Finish wk]],1,($B$5-tblEVMData[[#This Row],[Start wk]]+1)/MAX(1,tblEVMData[[#This Row],[Finish wk]]-tblEVMData[[#This Row],[Start wk]]+1)))) -> 1 | N16: =IFERROR(tblEVMData[[#This Row],[Baseline Cost]]*tblEVMData[[#This Row],[Actual % Complete]],"") -> 0 | O16: =IFERROR(tblEVMData[[#This Row],[Baseline Cost]]*tblEVMData[[#This Row],[Planned % Complete]],"") -> 8000 | P16: =IFERROR(tblEVMData[[#This Row],[Earned Value]]-tblEVMData[[#This Row],[Planned Value]],"") -> -8000 | Q16: =IFERROR(tblEVMData[[#This Row],[Earned Value]]-tblEVMData[[#This Row],[Actual Cost]],"") -> -8500 | R16: =IFERROR(tblEVMData[[#This Row],[Earned Value]]/tblEVMData[[#This Row],[Planned Value]],"") -> 0 | S16: =IFERROR(tblEVMData[[#This Row],[Earned Value]]/tblEVMData[[#This Row],[Actual Cost]],"") -> 0 | T16: =_xlfn.TEXTJOIN("; ",TRUE,IF(tblEVMData[[#This Row],[Baseline Cost]]="","Add baseline cost", ""),IF(tblEVMData[[#This Row],[Actual Cost]]="","Add actual cost", ""),IF(tblEVMData[[#This Row],[Hours]]="","Add hours", ""),IF(tblEVMData[[#This Row],[Duration (Weeks)]]="","Add duration", ""),IF(tblEVMData[[#This Row],[Actual % Complete]]="","Add progress", ""),IF(tblEVMData[[#This Row],[Start wk]]="","Add start week", ""),IF(tblEVMData[[#This Row],[Finish wk]]="","Add finish week", ""))
A17: {=IFERROR(INDEX(tblTaskList[Task ID],ROWS($A$10:A17)),"")} -> 19 | B17: {=IFERROR(INDEX(tblTaskList[Task Name],ROWS($A$10:A17)),"")} -> Delivery | C17: {=IFERROR(INDEX(tblTaskList[Resource],ROWS($A$10:A17)),"")} -> NN | D17: {=IFERROR(INDEX(tblTaskList[IsInCriticalPath],ROWS($A$10:A17)),"")} -> Yes | E17: {=IFERROR(INDEX(tblTaskList[Predecessor Tasks],ROWS($A$10:A17)),"")} -> Wait for Delivery | F17: {=IFERROR(INDEX(tblTaskList[Start wk],ROWS($A$10:A17)),"")} -> 22 | G17: {=IFERROR(INDEX(tblTaskList[Finish wk],ROWS($A$10:A17)),"")} -> 22 | H17: {=IFERROR(INDEX(tblTaskList[Duration (Weeks)],ROWS($A$10:A17)),"")} -> 0 | I17: {=IFERROR(INDEX(tblTaskList[Cost],ROWS($A$10:A17)),"")} -> 0 | J17: {=IFERROR(INDEX(tblTaskList[Actual Cost],ROWS($A$10:A17)),"")} -> 0 | K17: {=IFERROR(INDEX(tblTaskList[Hours],ROWS($A$10:A17)),"")} -> 0 | L17: {=IFERROR(INDEX(tblTaskList[Progress],ROWS($A$10:A17)),"")} -> 0 | M17: =IF(OR(tblEVMData[[#This Row],[Start wk]]="",tblEVMData[[#This Row],[Finish wk]]="",tblEVMData[[#This Row],[Baseline Cost]]=""),"",IF($B$5<tblEVMData[[#This Row],[Start wk]],0,IF($B$5>tblEVMData[[#This Row],[Finish wk]],1,($B$5-tblEVMData[[#This Row],[Start wk]]+1)/MAX(1,tblEVMData[[#This Row],[Finish wk]]-tblEVMData[[#This Row],[Start wk]]+1)))) -> 1 | N17: =IFERROR(tblEVMData[[#This Row],[Baseline Cost]]*tblEVMData[[#This Row],[Actual % Complete]],"") -> 0 | O17: =IFERROR(tblEVMData[[#This Row],[Baseline Cost]]*tblEVMData[[#This Row],[Planned % Complete]],"") -> 0 | P17: =IFERROR(tblEVMData[[#This Row],[Earned Value]]-tblEVMData[[#This Row],[Planned Value]],"") -> 0 | Q17: =IFERROR(tblEVMData[[#This Row],[Earned Value]]-tblEVMData[[#This Row],[Actual Cost]],"") -> 0 | R17: =IFERROR(tblEVMData[[#This Row],[Earned Value]]/tblEVMData[[#This Row],[Planned Value]],"") | S17: =IFERROR(tblEVMData[[#This Row],[Earned Value]]/tblEVMData[[#This Row],[Actual Cost]],"") | T17: =_xlfn.TEXTJOIN("; ",TRUE,IF(tblEVMData[[#This Row],[Baseline Cost]]="","Add baseline cost", ""),IF(tblEVMData[[#This Row],[Actual Cost]]="","Add actual cost", ""),IF(tblEVMData[[#This Row],[Hours]]="","Add hours", ""),IF(tblEVMData[[#This Row],[Duration (Weeks)]]="","Add duration", ""),IF(tblEVMData[[#This Row],[Actual % Complete]]="","Add progress", ""),IF(tblEVMData[[#This Row],[Start wk]]="","Add start week", ""),IF(tblEVMData[[#This Row],[Finish wk]]="","Add finish week", ""))
A18: {=IFERROR(INDEX(tblTaskList[Task ID],ROWS($A$10:A18)),"")} -> 1 | B18: {=IFERROR(INDEX(tblTaskList[Task Name],ROWS($A$10:A18)),"")} -> Check funds | C18: {=IFERROR(INDEX(tblTaskList[Resource],ROWS($A$10:A18)),"")} -> FE | D18: {=IFERROR(INDEX(tblTaskList[IsInCriticalPath],ROWS($A$10:A18)),"")} -> Float | E18: {=IFERROR(INDEX(tblTaskList[Predecessor Tasks],ROWS($A$10:A18)),"")} -> Demolish old shed | F18: {=IFERROR(INDEX(tblTaskList[Start wk],ROWS($A$10:A18)),"")} -> 2 | G18: {=IFERROR(INDEX(tblTaskList[Finish wk],ROWS($A$10:A18)),"")} -> 2 | H18: {=IFERROR(INDEX(tblTaskList[Duration (Weeks)],ROWS($A$10:A18)),"")} -> 0 | I18: {=IFERROR(INDEX(tblTaskList[Cost],ROWS($A$10:A18)),"")} -> 0 | J18: {=IFERROR(INDEX(tblTaskList[Actual Cost],ROWS($A$10:A18)),"")} -> 0 | K18: {=IFERROR(INDEX(tblTaskList[Hours],ROWS($A$10:A18)),"")} -> 0 | L18: {=IFERROR(INDEX(tblTaskList[Progress],ROWS($A$10:A18)),"")} -> 1 | M18: =IF(OR(tblEVMData[[#This Row],[Start wk]]="",tblEVMData[[#This Row],[Finish wk]]="",tblEVMData[[#This Row],[Baseline Cost]]=""),"",IF($B$5<tblEVMData[[#This Row],[Start wk]],0,IF($B$5>tblEVMData[[#This Row],[Finish wk]],1,($B$5-tblEVMData[[#This Row],[Start wk]]+1)/MAX(1,tblEVMData[[#This Row],[Finish wk]]-tblEVMData[[#This Row],[Start wk]]+1)))) -> 1 | N18: =IFERROR(tblEVMData[[#This Row],[Baseline Cost]]*tblEVMData[[#This Row],[Actual % Complete]],"") -> 0 | O18: =IFERROR(tblEVMData[[#This Row],[Baseline Cost]]*tblEVMData[[#This Row],[Planned % Complete]],"") -> 0 | P18: =IFERROR(tblEVMData[[#This Row],[Earned Value]]-tblEVMData[[#This Row],[Planned Value]],"") -> 0 | Q18: =IFERROR(tblEVMData[[#This Row],[Earned Value]]-tblEVMData[[#This Row],[Actual Cost]],"") -> 0 | R18: =IFERROR(tblEVMData[[#This Row],[Earned Value]]/tblEVMData[[#This Row],[Planned Value]],"") | S18: =IFERROR(tblEVMData[[#This Row],[Earned Value]]/tblEVMData[[#This Row],[Actual Cost]],"") | T18: =_xlfn.TEXTJOIN("; ",TRUE,IF(tblEVMData[[#This Row],[Baseline Cost]]="","Add baseline cost", ""),IF(tblEVMData[[#This Row],[Actual Cost]]="","Add actual cost", ""),IF(tblEVMData[[#This Row],[Hours]]="","Add hours", ""),IF(tblEVMData[[#This Row],[Duration (Weeks)]]="","Add duration", ""),IF(tblEVMData[[#This Row],[Actual % Complete]]="","Add progress", ""),IF(tblEVMData[[#This Row],[Start wk]]="","Add start week", ""),IF(tblEVMData[[#This Row],[Finish wk]]="","Add finish week", ""))
A19: {=IFERROR(INDEX(tblTaskList[Task ID],ROWS($A$10:A19)),"")} -> 4 | B19: {=IFERROR(INDEX(tblTaskList[Task Name],ROWS($A$10:A19)),"")} -> Demolish old shed | C19: {=IFERROR(INDEX(tblTaskList[Resource],ROWS($A$10:A19)),"")} -> NN | D19: {=IFERROR(INDEX(tblTaskList[IsInCriticalPath],ROWS($A$10:A19)),"")} -> Float | E19: {=IFERROR(INDEX(tblTaskList[Predecessor Tasks],ROWS($A$10:A19)),"")} -> Cut foliage back | F19: {=IFERROR(INDEX(tblTaskList[Start wk],ROWS($A$10:A19)),"")} -> 3 | G19: {=IFERROR(INDEX(tblTaskList[Finish wk],ROWS($A$10:A19)),"")} -> 3 | H19: {=IFERROR(INDEX(tblTaskList[Duration (Weeks)],ROWS($A$10:A19)),"")} -> 1 | I19: {=IFERROR(INDEX(tblTaskList[Cost],ROWS($A$10:A19)),"")} -> 300 | J19: {=IFERROR(INDEX(tblTaskList[Actual Cost],ROWS($A$10:A19)),"")} -> 300 | K19: {=IFERROR(INDEX(tblTaskList[Hours],ROWS($A$10:A19)),"")} -> 6 | L19: {=IFERROR(INDEX(tblTaskList[Progress],ROWS($A$10:A19)),"")} -> 0 | M19: =IF(OR(tblEVMData[[#This Row],[Start wk]]="",tblEVMData[[#This Row],[Finish wk]]="",tblEVMData[[#This Row],[Baseline Cost]]=""),"",IF($B$5<tblEVMData[[#This Row],[Start wk]],0,IF($B$5>tblEVMData[[#This Row],[Finish wk]],1,($B$5-tblEVMData[[#This Row],[Start wk]]+1)/MAX(1,tblEVMData[[#This Row],[Finish wk]]-tblEVMData[[#This Row],[Start wk]]+1)))) -> 1 | N19: =IFERROR(tblEVMData[[#This Row],[Baseline Cost]]*tblEVMData[[#This Row],[Actual % Complete]],"") -> 0 | O19: =IFERROR(tblEVMData[[#This Row],[Baseline Cost]]*tblEVMData[[#This Row],[Planned % Complete]],"") -> 300 | P19: =IFERROR(tblEVMData[[#This Row],[Earned Value]]-tblEVMData[[#This Row],[Planned Value]],"") -> -300 | Q19: =IFERROR(tblEVMData[[#This Row],[Earned Value]]-tblEVMData[[#This Row],[Actual Cost]],"") -> -300 | R19: =IFERROR(tblEVMData[[#This Row],[Earned Value]]/tblEVMData[[#This Row],[Planned Value]],"") -> 0 | S19: =IFERROR(tblEVMData[[#This Row],[Earned Value]]/tblEVMData[[#This Row],[Actual Cost]],"") -> 0 | T19: =_xlfn.TEXTJOIN("; ",TRUE,IF(tblEVMData[[#This Row],[Baseline Cost]]="","Add baseline cost", ""),IF(tblEVMData[[#This Row],[Actual Cost]]="","Add actual cost", ""),IF(tblEVMData[[#This Row],[Hours]]="","Add hours", ""),IF(tblEVMData[[#This Row],[Duration (Weeks)]]="","Add duration", ""),IF(tblEVMData[[#This Row],[Actual % Complete]]="","Add progress", ""),IF(tblEVMData[[#This Row],[Start wk]]="","Add start week", ""),IF(tblEVMData[[#This Row],[Finish wk]]="","Add finish week", ""))
A20: {=IFERROR(INDEX(tblTaskList[Task ID],ROWS($A$10:A20)),"")} -> 5 | B20: {=IFERROR(INDEX(tblTaskList[Task Name],ROWS($A$10:A20)),"")} -> Cut foliage back | C20: {=IFERROR(INDEX(tblTaskList[Resource],ROWS($A$10:A20)),"")} -> NN | D20: {=IFERROR(INDEX(tblTaskList[IsInCriticalPath],ROWS($A$10:A20)),"")} -> Float | E20: {=IFERROR(INDEX(tblTaskList[Predecessor Tasks],ROWS($A$10:A20)),"")} -> Dig trench | F20: {=IFERROR(INDEX(tblTaskList[Start wk],ROWS($A$10:A20)),"")} -> 8 | G20: {=IFERROR(INDEX(tblTaskList[Finish wk],ROWS($A$10:A20)),"")} -> 11 | H20: {=IFERROR(INDEX(tblTaskList[Duration (Weeks)],ROWS($A$10:A20)),"")} -> 4 | I20: {=IFERROR(INDEX(tblTaskList[Cost],ROWS($A$10:A20)),"")} -> 500 | J20: {=IFERROR(INDEX(tblTaskList[Actual Cost],ROWS($A$10:A20)),"")} -> 500 | K20: {=IFERROR(INDEX(tblTaskList[Hours],ROWS($A$10:A20)),"")} -> 10 | L20: {=IFERROR(INDEX(tblTaskList[Progress],ROWS($A$10:A20)),"")} -> 0 | M20: =IF(OR(tblEVMData[[#This Row],[Start wk]]="",tblEVMData[[#This Row],[Finish wk]]="",tblEVMData[[#This Row],[Baseline Cost]]=""),"",IF($B$5<tblEVMData[[#This Row],[Start wk]],0,IF($B$5>tblEVMData[[#This Row],[Finish wk]],1,($B$5-tblEVMData[[#This Row],[Start wk]]+1)/MAX(1,tblEVMData[[#This Row],[Finish wk]]-tblEVMData[[#This Row],[Start wk]]+1)))) -> 1 | N20: =IFERROR(tblEVMData[[#This Row],[Baseline Cost]]*tblEVMData[[#This Row],[Actual % Complete]],"") -> 0 | O20: =IFERROR(tblEVMData[[#This Row],[Baseline Cost]]*tblEVMData[[#This Row],[Planned % Complete]],"") -> 500 | P20: =IFERROR(tblEVMData[[#This Row],[Earned Value]]-tblEVMData[[#This Row],[Planned Value]],"") -> -500 | Q20: =IFERROR(tblEVMData[[#This Row],[Earned Value]]-tblEVMData[[#This Row],[Actual Cost]],"") -> -500 | R20: =IFERROR(tblEVMData[[#This Row],[Earned Value]]/tblEVMData[[#This Row],[Planned Value]],"") -> 0 | S20: =IFERROR(tblEVMData[[#This Row],[Earned Value]]/tblEVMData[[#This Row],[Actual Cost]],"") -> 0 | T20: =_xlfn.TEXTJOIN("; ",TRUE,IF(tblEVMData[[#This Row],[Baseline Cost]]="","Add baseline cost", ""),IF(tblEVMData[[#This Row],[Actual Cost]]="","Add actual cost", ""),IF(tblEVMData[[#This Row],[Hours]]="","Add hours", ""),IF(tblEVMData[[#This Row],[Duration (Weeks)]]="","Add duration", ""),IF(tblEVMData[[#This Row],[Actual % Complete]]="","Add progress", ""),IF(tblEVMData[[#This Row],[Start wk]]="","Add start week", ""),IF(tblEVMData[[#This Row],[Finish wk]]="","Add finish week", ""))
A21: {=IFERROR(INDEX(tblTaskList[Task ID],ROWS($A$10:A21)),"")} -> 8 | B21: {=IFERROR(INDEX(tblTaskList[Task Name],ROWS($A$10:A21)),"")} -> Connect Power | C21: {=IFERROR(INDEX(tblTaskList[Resource],ROWS($A$10:A21)),"")} -> NN | D21: {=IFERROR(INDEX(tblTaskList[IsInCriticalPath],ROWS($A$10:A21)),"")} -> Float | E21: {=IFERROR(INDEX(tblTaskList[Predecessor Tasks],ROWS($A$10:A21)),"")} -> the Finish | F21: {=IFERROR(INDEX(tblTaskList[Start wk],ROWS($A$10:A21)),"")} -> 13 | G21: {=IFERROR(INDEX(tblTaskList[Finish wk],ROWS($A$10:A21)),"")} -> 13 | H21: {=IFERROR(INDEX(tblTaskList[Duration (Weeks)],ROWS($A$10:A21)),"")} -> 0 | I21: {=IFERROR(INDEX(tblTaskList[Cost],ROWS($A$10:A21)),"")} -> 0 | J21: {=IFERROR(INDEX(tblTaskList[Actual Cost],ROWS($A$10:A21)),"")} -> 0 | K21: {=IFERROR(INDEX(tblTaskList[Hours],ROWS($A$10:A21)),"")} -> 0 | L21: {=IFERROR(INDEX(tblTaskList[Progress],ROWS($A$10:A21)),"")} -> 0 | M21: =IF(OR(tblEVMData[[#This Row],[Start wk]]="",tblEVMData[[#This Row],[Finish wk]]="",tblEVMData[[#This Row],[Baseline Cost]]=""),"",IF($B$5<tblEVMData[[#This Row],[Start wk]],0,IF($B$5>tblEVMData[[#This Row],[Finish wk]],1,($B$5-tblEVMData[[#This Row],[Start wk]]+1)/MAX(1,tblEVMData[[#This Row],[Finish wk]]-tblEVMData[[#This Row],[Start wk]]+1)))) -> 1 | N21: =IFERROR(tblEVMData[[#This Row],[Baseline Cost]]*tblEVMData[[#This Row],[Actual % Complete]],"") -> 0 | O21: =IFERROR(tblEVMData[[#This Row],[Baseline Cost]]*tblEVMData[[#This Row],[Planned % Complete]],"") -> 0 | P21: =IFERROR(tblEVMData[[#This Row],[Earned Value]]-tblEVMData[[#This Row],[Planned Value]],"") -> 0 | Q21: =IFERROR(tblEVMData[[#This Row],[Earned Value]]-tblEVMData[[#This Row],[Actual Cost]],"") -> 0 | R21: =IFERROR(tblEVMData[[#This Row],[Earned Value]]/tblEVMData[[#This Row],[Planned Value]],"") | S21: =IFERROR(tblEVMData[[#This Row],[Earned Value]]/tblEVMData[[#This Row],[Actual Cost]],"") | T21: =_xlfn.TEXTJOIN("; ",TRUE,IF(tblEVMData[[#This Row],[Baseline Cost]]="","Add baseline cost", ""),IF(tblEVMData[[#This Row],[Actual Cost]]="","Add actual cost", ""),IF(tblEVMData[[#This Row],[Hours]]="","Add hours", ""),IF(tblEVMData[[#This Row],[Duration (Weeks)]]="","Add duration", ""),IF(tblEVMData[[#This Row],[Actual % Complete]]="","Add progress", ""),IF(tblEVMData[[#This Row],[Start wk]]="","Add start week", ""),IF(tblEVMData[[#This Row],[Finish wk]]="","Add finish week", ""))
... A27: {=IFERROR(INDEX(tblTaskList[Task ID],ROWS($A$10:A27)),"")} -> 16 | B27: {=IFERROR(INDEX(tblTaskList[Task Name],ROWS($A$10:A27)),"")} -> Assembly | C27: {=IFERROR(INDEX(tblTaskList[Resource],ROWS($A$10:A27)),"")} -> NN | D27: {=IFERROR(INDEX(tblTaskList[IsInCriticalPath],ROWS($A$10:A27)),"")} -> Float | E27: {=IFERROR(INDEX(tblTaskList[Predecessor Tasks],ROWS($A$10:A27)),"")} -> 0 | F27: {=IFERROR(INDEX(tblTaskList[Start wk],ROWS($A$10:A27)),"")} -> 23 | G27: {=IFERROR(INDEX(tblTaskList[Finish wk],ROWS($A$10:A27)),"")} -> 23 | H27: {=IFERROR(INDEX(tblTaskList[Duration (Weeks)],ROWS($A$10:A27)),"")} -> 1 | I27: {=IFERROR(INDEX(tblTaskList[Cost],ROWS($A$10:A27)),"")} -> 750 | J27: {=IFERROR(INDEX(tblTaskList[Actual Cost],ROWS($A$10:A27)),"")} -> 750 | K27: {=IFERROR(INDEX(tblTaskList[Hours],ROWS($A$10:A27)),"")} -> 0 | L27: {=IFERROR(INDEX(tblTaskList[Progress],ROWS($A$10:A27)),"")} -> 0 | M27: =IF(OR(tblEVMData[[#This Row],[Start wk]]="",tblEVMData[[#This Row],[Finish wk]]="",tblEVMData[[#This Row],[Baseline Cost]]=""),"",IF($B$5<tblEVMData[[#This Row],[Start wk]],0,IF($B$5>tblEVMData[[#This Row],[Finish wk]],1,($B$5-tblEVMData[[#This Row],[Start wk]]+1)/MAX(1,tblEVMData[[#This Row],[Finish wk]]-tblEVMData[[#This Row],[Start wk]]+1)))) -> 1 | N27: =IFERROR(tblEVMData[[#This Row],[Baseline Cost]]*tblEVMData[[#This Row],[Actual % Complete]],"") -> 0 | O27: =IFERROR(tblEVMData[[#This Row],[Baseline Cost]]*tblEVMData[[#This Row],[Planned % Complete]],"") -> 750 | P27: =IFERROR(tblEVMData[[#This Row],[Earned Value]]-tblEVMData[[#This Row],[Planned Value]],"") -> -750 | Q27: =IFERROR(tblEVMData[[#This Row],[Earned Value]]-tblEVMData[[#This Row],[Actual Cost]],"") -> -750 | R27: =IFERROR(tblEVMData[[#This Row],[Earned Value]]/tblEVMData[[#This Row],[Planned Value]],"") -> 0 | S27: =IFERROR(tblEVMData[[#This Row],[Earned Value]]/tblEVMData[[#This Row],[Actual Cost]],"") -> 0 | T27: =_xlfn.TEXTJOIN("; ",TRUE,IF(tblEVMData[[#This Row],[Baseline Cost]]="","Add baseline cost", ""),IF(tblEVMData[[#This Row],[Actual Cost]]="","Add actual cost", ""),IF(tblEVMData[[#This Row],[Hours]]="","Add hours", ""),IF(tblEVMData[[#This Row],[Duration (Weeks)]]="","Add duration", ""),IF(tblEVMData[[#This Row],[Actual % Complete]]="","Add progress", ""),IF(tblEVMData[[#This Row],[Start wk]]="","Add start week", ""),IF(tblEVMData[[#This Row],[Finish wk]]="","Add finish week", ""))

Sheet Gantt-frame
A3: =[1]tblTaskList!N2 -> New Garden Shed | J3: Hours | K3: =SUMIFS($I$8:$I$25,$G$8:$G$25,K$7) -> 0 | L3: =SUMIFS($I$8:$I$25,$G$8:$G$25,L$7) -> 0 | M3: =SUMIFS($I$8:$I$25,$G$8:$G$25,M$7) -> 6 | N3: =SUMIFS($I$8:$I$25,$G$8:$G$25,N$7) -> 0 | O3: =SUMIFS($I$8:$I$25,$G$8:$G$25,O$7) -> 0 | P3: =SUMIFS($I$8:$I$25,$G$8:$G$25,P$7) -> 0 | Q3: =SUMIFS($I$8:$I$25,$G$8:$G$25,Q$7) -> 0 | R3: =SUMIFS($I$8:$I$25,$G$8:$G$25,R$7) -> 10 | ... BJ3: =SUMIFS($I$8:$I$25,$G$8:$G$25,BJ$7) -> 0
E4: Today | F4: =TODAY() -> 46240 | G4: =WEEKNUM(F4) -> 32 | J4: Cost | K4: =SUMIFS($J$8:$J$25,$G$8:$G$25,K$7) -> 0 | L4: =SUMIFS($J$8:$J$25,$G$8:$G$25,L$7) -> 0 | M4: =SUMIFS($J$8:$J$25,$G$8:$G$25,M$7) -> 300 | N4: =SUMIFS($J$8:$J$25,$G$8:$G$25,N$7) -> 0 | O4: =SUMIFS($J$8:$J$25,$G$8:$G$25,O$7) -> 0 | P4: =SUMIFS($J$8:$J$25,$G$8:$G$25,P$7) -> 0 | Q4: =SUMIFS($J$8:$J$25,$G$8:$G$25,Q$7) -> 100 | R4: =SUMIFS($J$8:$J$25,$G$8:$G$25,R$7) -> 8500 | ... BJ4: =SUMIFS($J$8:$J$25,$G$8:$G$25,BJ$7) -> 0
E5: Start | F5: =INDEX([1]!tblBudget[Start Date],1) -> 01.06.2026 | G5: 1 | K5: =DATE(RIGHT($F$5,4),MID($F$5,4,2),LEFT($F$5,2))+K$7*7 -> 46181 | L5: =DATE(RIGHT($F$5,4),MID($F$5,4,2),LEFT($F$5,2))+L$7*7 -> 46188 | M5: =DATE(RIGHT($F$5,4),MID($F$5,4,2),LEFT($F$5,2))+M$7*7 -> 46195 | N5: =DATE(RIGHT($F$5,4),MID($F$5,4,2),LEFT($F$5,2))+N$7*7 -> 46202 | O5: =DATE(RIGHT($F$5,4),MID($F$5,4,2),LEFT($F$5,2))+O$7*7 -> 46209 | P5: =DATE(RIGHT($F$5,4),MID($F$5,4,2),LEFT($F$5,2))+P$7*7 -> 46216 | Q5: =DATE(RIGHT($F$5,4),MID($F$5,4,2),LEFT($F$5,2))+Q$7*7 -> 46223 | R5: =DATE(RIGHT($F$5,4),MID($F$5,4,2),LEFT($F$5,2))+R$7*7 -> 46230 | ... BJ5: =DATE(RIGHT($F$5,4),MID($F$5,4,2),LEFT($F$5,2))+BJ$7*7 -> 46538
E6: Finish | F6: =_xlfn.XLOOKUP(G6,K7:BJ7,K5:BJ5,"na",0,1) -> 46356 | G6: {=_xlfn.AGGREGATE(14,6,($G$8:$G$24+$B$8:$B$24)/($A$8:$A$24="Yes"),1)} -> 26 | I6: =SUM(_xlfn.ANCHORARRAY(I8)) -> 70 | J6: =SUM(_xlfn.ANCHORARRAY(J8)) -> 18800 | K6: =WEEKNUM(K5) -> 24 | L6: =WEEKNUM(L5) -> 25 | M6: =WEEKNUM(M5) -> 26 | N6: =WEEKNUM(N5) -> 27 | O6: =WEEKNUM(O5) -> 28 | P6: =WEEKNUM(P5) -> 29 | Q6: =WEEKNUM(Q5) -> 30 | R6: =WEEKNUM(R5) -> 31 | ... BJ6: =WEEKNUM(BJ5) -> 23
A7: critical path | B7: duration (wk) | C7: Progress | D7: Actual wk | E7: TASK | F7: Resource | G7: Start wk | H7: Finish wk | I7: Hours | J7: Cost | K7: 1 | L7: 2 | M7: 3 | N7: 4 | O7: 5 | P7: 6 | Q7: 7 | R7: 8 | S7: 9 | T7: 10 | U7: 11 | V7: 12 | W7: 13 | X7: 14 | Y7: 15 | Z7: 16 | AA7: 17 | AB7: 18 | AC7: 19 | AD7: 20 | AE7: 21 | AF7: 22 | AG7: 23 | AH7: 24 | AI7: 25 | AJ7: 26 | AK7: 27 | AL7: 28 | AM7: 29 | AN7: 30 | AO7: 31 | AP7: 32 | AQ7: 33 | AR7: 34 | AS7: 35 | AT7: 36 | AU7: 37 | AV7: 38 | AW7: 39 | AX7: 40 | AY7: 41 | AZ7: 42 | BA7: 43 | BB7: 44 | BC7: 45 | BD7: 46 | BE7: 47 | BF7: 48 | BG7: 49 | BH7: 50 | BI7: 51 | BJ7: 52
A8: {=[1]!tblTaskList[IsInCriticalPath]} -> Yes | B8: {=[1]!tblTaskList[Duration (Weeks)]} -> 6 | C8: {=[1]!tblTaskList[Progress]} -> 1 | D8: =IF(OR($C8<=0,$G8=""),0,IF($B8=0,$G8,$G8+ROUNDUP($B8*$C8,0)-1)) -> 6 | E8: {=[1]!tblTaskList[Task Name]} -> Planning permission | F8: {=[1]!tblTaskList[Resource]} -> FE | G8: =IF($A8="Yes",1,"") -> 1 | H8: {=[1]!tblTaskList[Finish wk]} -> 6 | I8: {=[1]!tblTaskList[Hours]} -> 0 | J8: {=[1]!tblTaskList[Cost]} -> 0 | K8: =IF(AND($D8>0,K$7=$D8),"●","") | L8: =IF(AND($D8>0,L$7=$D8),"●","") | M8: =IF(AND($D8>0,M$7=$D8),"●","") | N8: =IF(AND($D8>0,N$7=$D8),"●","") | O8: =IF(AND($D8>0,O$7=$D8),"●","") | P8: =IF(AND($D8>0,P$7=$D8),"●","") -> ● | Q8: =IF(AND($D8>0,Q$7=$D8),"●","") | R8: =IF(AND($D8>0,R$7=$D8),"●","") | ... BJ8: =IF(AND($D8>0,BJ$7=$D8),"●","")
A9: Yes | B9: 10 | C9: 0.2 | D9: =IF(OR($C9<=0,$G9=""),0,IF($B9=0,$G9,$G9+ROUNDUP($B9*$C9,0)-1)) -> 8 | E9: Wait for planning permission | F9: FE | G9: =IF($A9="Yes",SUMIF($A$8:$A8,"Yes",$B$8:$B8)+1,"") -> 7 | H9: 16 | I9: 0 | J9: 100 | K9: =IF(AND($D9>0,K$7=$D9),"●","") | L9: =IF(AND($D9>0,L$7=$D9),"●","") | M9: =IF(AND($D9>0,M$7=$D9),"●","") | N9: =IF(AND($D9>0,N$7=$D9),"●","") | O9: =IF(AND($D9>0,O$7=$D9),"●","") | P9: =IF(AND($D9>0,P$7=$D9),"●","") | Q9: =IF(AND($D9>0,Q$7=$D9),"●","") | R9: =IF(AND($D9>0,R$7=$D9),"●","") -> ● | ... BJ9: =IF(AND($D9>0,BJ$7=$D9),"●","")
A10: Yes | B10: 1 | C10: 0 | D10: =IF(OR($C10<=0,$G10=""),0,IF($B10=0,$G10,$G10+ROUNDUP($B10*$C10,0)-1)) -> 0 | E10: Dig trench | F10: NN | G10: =IF($A10="Yes",SUMIF($A$8:$A9,"Yes",$B$8:$B9)+1,"") -> 17 | H10: 17 | I10: 4 | J10: 350 | K10: =IF(AND($D10>0,K$7=$D10),"●","") | L10: =IF(AND($D10>0,L$7=$D10),"●","") | M10: =IF(AND($D10>0,M$7=$D10),"●","") | N10: =IF(AND($D10>0,N$7=$D10),"●","") | O10: =IF(AND($D10>0,O$7=$D10),"●","") | P10: =IF(AND($D10>0,P$7=$D10),"●","") | Q10: =IF(AND($D10>0,Q$7=$D10),"●","") | R10: =IF(AND($D10>0,R$7=$D10),"●","") | ... BJ10: =IF(AND($D10>0,BJ$7=$D10),"●","")
A11: Yes | B11: 2 | C11: 0 | D11: =IF(OR($C11<=0,$G11=""),0,IF($B11=0,$G11,$G11+ROUNDUP($B11*$C11,0)-1)) -> 0 | E11: Hire digger | F11: FE | G11: =IF($A11="Yes",SUMIF($A$8:$A10,"Yes",$B$8:$B10)+1,"") -> 18 | H11: 19 | I11: 0 | J11: 0 | K11: =IF(AND($D11>0,K$7=$D11),"●","") | L11: =IF(AND($D11>0,L$7=$D11),"●","") | M11: =IF(AND($D11>0,M$7=$D11),"●","") | N11: =IF(AND($D11>0,N$7=$D11),"●","") | O11: =IF(AND($D11>0,O$7=$D11),"●","") | P11: =IF(AND($D11>0,P$7=$D11),"●","") | Q11: =IF(AND($D11>0,Q$7=$D11),"●","") | R11: =IF(AND($D11>0,R$7=$D11),"●","") | ... BJ11: =IF(AND($D11>0,BJ$7=$D11),"●","")
A12: Yes | B12: 1 | C12: 0 | D12: =IF(OR($C12<=0,$G12=""),0,IF($B12=0,$G12,$G12+ROUNDUP($B12*$C12,0)-1)) -> 0 | E12: Fill with concrete | F12: NN | G12: =IF($A12="Yes",SUMIF($A$8:$A11,"Yes",$B$8:$B11)+1,"") -> 20 | H12: 20 | I12: 3 | J12: 700 | K12: =IF(AND($D12>0,K$7=$D12),"●","") | L12: =IF(AND($D12>0,L$7=$D12),"●","") | M12: =IF(AND($D12>0,M$7=$D12),"●","") | N12: =IF(AND($D12>0,N$7=$D12),"●","") | O12: =IF(AND($D12>0,O$7=$D12),"●","") | P12: =IF(AND($D12>0,P$7=$D12),"●","") | Q12: =IF(AND($D12>0,Q$7=$D12),"●","") | R12: =IF(AND($D12>0,R$7=$D12),"●","") | ... BJ12: =IF(AND($D12>0,BJ$7=$D12),"●","")
A13: Yes | B13: 1 | C13: 0 | D13: =IF(OR($C13<=0,$G13=""),0,IF($B13=0,$G13,$G13+ROUNDUP($B13*$C13,0)-1)) -> 0 | E13: Level the base | F13: NN | G13: =IF($A13="Yes",SUMIF($A$8:$A12,"Yes",$B$8:$B12)+1,"") -> 21 | H13: 21 | I13: 5 | J13: 100 | K13: =IF(AND($D13>0,K$7=$D13),"●","") | L13: =IF(AND($D13>0,L$7=$D13),"●","") | M13: =IF(AND($D13>0,M$7=$D13),"●","") | N13: =IF(AND($D13>0,N$7=$D13),"●","") | O13: =IF(AND($D13>0,O$7=$D13),"●","") | P13: =IF(AND($D13>0,P$7=$D13),"●","") | Q13: =IF(AND($D13>0,Q$7=$D13),"●","") | R13: =IF(AND($D13>0,R$7=$D13),"●","") | ... BJ13: =IF(AND($D13>0,BJ$7=$D13),"●","")
A14: Yes | B14: 4 | C14: 0 | D14: =IF(OR($C14<=0,$G14=""),0,IF($B14=0,$G14,$G14+ROUNDUP($B14*$C14,0)-1)) -> 0 | E14: the Finish | F14: FE | G14: =IF($A14="Yes",SUMIF($A$8:$A13,"Yes",$B$8:$B13)+1,"") -> 22 | H14: 25 | I14: 34 | J14: 8000 | K14: =IF(AND($D14>0,K$7=$D14),"●","") | L14: =IF(AND($D14>0,L$7=$D14),"●","") | M14: =IF(AND($D14>0,M$7=$D14),"●","") | N14: =IF(AND($D14>0,N$7=$D14),"●","") | O14: =IF(AND($D14>0,O$7=$D14),"●","") | P14: =IF(AND($D14>0,P$7=$D14),"●","") | Q14: =IF(AND($D14>0,Q$7=$D14),"●","") | R14: =IF(AND($D14>0,R$7=$D14),"●","") | ... BJ14: =IF(AND($D14>0,BJ$7=$D14),"●","")
A15: Yes | B15: 0 | C15: 0 | D15: =IF(OR($C15<=0,$G15=""),0,IF($B15=0,$G15,$G15+ROUNDUP($B15*$C15,0)-1)) -> 0 | E15: Delivery | F15: NN | G15: 22 | H15: 22 | I15: 0 | J15: 0 | K15: =IF(AND($D15>0,K$7=$D15),"●","") | L15: =IF(AND($D15>0,L$7=$D15),"●","") | M15: =IF(AND($D15>0,M$7=$D15),"●","") | N15: =IF(AND($D15>0,N$7=$D15),"●","") | O15: =IF(AND($D15>0,O$7=$D15),"●","") | P15: =IF(AND($D15>0,P$7=$D15),"●","") | Q15: =IF(AND($D15>0,Q$7=$D15),"●","") | R15: =IF(AND($D15>0,R$7=$D15),"●","") | ... BJ15: =IF(AND($D15>0,BJ$7=$D15),"●","")
A16: Float | B16: 0 | C16: 1 | D16: =IF(OR($C16<=0,$G16=""),0,IF($B16=0,$G16,$G16+ROUNDUP($B16*$C16,0)-1)) -> 2 | E16: Check funds | F16: FE | G16: 2 | H16: 2 | I16: 0 | J16: 0 | K16: =IF(AND($D16>0,K$7=$D16),"●","") | L16: =IF(AND($D16>0,L$7=$D16),"●","") -> ● | M16: =IF(AND($D16>0,M$7=$D16),"●","") | N16: =IF(AND($D16>0,N$7=$D16),"●","") | O16: =IF(AND($D16>0,O$7=$D16),"●","") | P16: =IF(AND($D16>0,P$7=$D16),"●","") | Q16: =IF(AND($D16>0,Q$7=$D16),"●","") | R16: =IF(AND($D16>0,R$7=$D16),"●","") | ... BJ16: =IF(AND($D16>0,BJ$7=$D16),"●","")
A17: Float | B17: 1 | C17: 0 | D17: =IF(OR($C17<=0,$G17=""),0,IF($B17=0,$G17,$G17+ROUNDUP($B17*$C17,0)-1)) -> 0 | E17: Demolish old shed | F17: NN | G17: 3 | H17: 3 | I17: 6 | J17: 300 | K17: =IF(AND($D17>0,K$7=$D17),"●","") | L17: =IF(AND($D17>0,L$7=$D17),"●","") | M17: =IF(AND($D17>0,M$7=$D17),"●","") | N17: =IF(AND($D17>0,N$7=$D17),"●","") | O17: =IF(AND($D17>0,O$7=$D17),"●","") | P17: =IF(AND($D17>0,P$7=$D17),"●","") | Q17: =IF(AND($D17>0,Q$7=$D17),"●","") | R17: =IF(AND($D17>0,R$7=$D17),"●","") | ... BJ17: =IF(AND($D17>0,BJ$7=$D17),"●","")
A18: Float | B18: 4 | C18: 0 | D18: =IF(OR($C18<=0,$G18=""),0,IF($B18=0,$G18,$G18+ROUNDUP($B18*$C18,0)-1)) -> 0 | E18: Cut foliage back | F18: NN | G18: 8 | H18: 11 | I18: 10 | J18: 500 | K18: =IF(AND($D18>0,K$7=$D18),"●","") | L18: =IF(AND($D18>0,L$7=$D18),"●","") | M18: =IF(AND($D18>0,M$7=$D18),"●","") | N18: =IF(AND($D18>0,N$7=$D18),"●","") | O18: =IF(AND($D18>0,O$7=$D18),"●","") | P18: =IF(AND($D18>0,P$7=$D18),"●","") | Q18: =IF(AND($D18>0,Q$7=$D18),"●","") | R18: =IF(AND($D18>0,R$7=$D18),"●","") | ... BJ18: =IF(AND($D18>0,BJ$7=$D18),"●","")
A19: Float | B19: 0 | C19: 0 | D19: =IF(OR($C19<=0,$G19=""),0,IF($B19=0,$G19,$G19+ROUNDUP($B19*$C19,0)-1)) -> 0 | E19: Connect Power | F19: NN | G19: 13 | H19: 13 | I19: 0 | J19: 0 | K19: =IF(AND($D19>0,K$7=$D19),"●","") | L19: =IF(AND($D19>0,L$7=$D19),"●","") | M19: =IF(AND($D19>0,M$7=$D19),"●","") | N19: =IF(AND($D19>0,N$7=$D19),"●","") | O19: =IF(AND($D19>0,O$7=$D19),"●","") | P19: =IF(AND($D19>0,P$7=$D19),"●","") | Q19: =IF(AND($D19>0,Q$7=$D19),"●","") | R19: =IF(AND($D19>0,R$7=$D19),"●","") | ... BJ19: =IF(AND($D19>0,BJ$7=$D19),"●","")
A20: Float | B20: 1 | C20: 1 | D20: =IF(OR($C20<=0,$G20=""),0,IF($B20=0,$G20,$G20+ROUNDUP($B20*$C20,0)-1)) -> 4 | E20: Find suppliers | F20: FE | G20: 4 | H20: 4 | I20: 0 | J20: 0 | K20: =IF(AND($D20>0,K$7=$D20),"●","") | L20: =IF(AND($D20>0,L$7=$D20),"●","") | M20: =IF(AND($D20>0,M$7=$D20),"●","") | N20: =IF(AND($D20>0,N$7=$D20),"●","") -> ● | O20: =IF(AND($D20>0,O$7=$D20),"●","") | P20: =IF(AND($D20>0,P$7=$D20),"●","") | Q20: =IF(AND($D20>0,Q$7=$D20),"●","") | R20: =IF(AND($D20>0,R$7=$D20),"●","") | ... BJ20: =IF(AND($D20>0,BJ$7=$D20),"●","")
A21: Float | B21: 3 | C21: 0 | D21: =IF(OR($C21<=0,$G21=""),0,IF($B21=0,$G21,$G21+ROUNDUP($B21*$C21,0)-1)) -> 0 | E21: Get quotes | F21: FE | G21: 7 | H21: 9 | I21: 0 | J21: 0 | K21: =IF(AND($D21>0,K$7=$D21),"●","") | L21: =IF(AND($D21>0,L$7=$D21),"●","") | M21: =IF(AND($D21>0,M$7=$D21),"●","") | N21: =IF(AND($D21>0,N$7=$D21),"●","") | O21: =IF(AND($D21>0,O$7=$D21),"●","") | P21: =IF(AND($D21>0,P$7=$D21),"●","") | Q21: =IF(AND($D21>0,Q$7=$D21),"●","") | R21: =IF(AND($D21>0,R$7=$D21),"●","") | ... BJ21: =IF(AND($D21>0,BJ$7=$D21),"●","")
A22: Float | B22: 0 | C22: 0 | D22: =IF(OR($C22<=0,$G22=""),0,IF($B22=0,$G22,$G22+ROUNDUP($B22*$C22,0)-1)) -> 0 | E22: Buy the shed | F22: FE | G22: 8 | H22: 8 | I22: 0 | J22: 8000 | K22: =IF(AND($D22>0,K$7=$D22),"●","") | L22: =IF(AND($D22>0,L$7=$D22),"●","") | M22: =IF(AND($D22>0,M$7=$D22),"●","") | N22: =IF(AND($D22>0,N$7=$D22),"●","") | O22: =IF(AND($D22>0,O$7=$D22),"●","") | P22: =IF(AND($D22>0,P$7=$D22),"●","") | Q22: =IF(AND($D22>0,Q$7=$D22),"●","") | R22: =IF(AND($D22>0,R$7=$D22),"●","") | ... BJ22: =IF(AND($D22>0,BJ$7=$D22),"●","")
A23: Float | B23: 6 | C23: 0 | D23: =IF(OR($C23<=0,$G23=""),0,IF($B23=0,$G23,$G23+ROUNDUP($B23*$C23,0)-1)) -> 0 | E23: Wait for Delivery | F23: FE | G23: 7 | H23: 12 | I23: 0 | J23: 0 | K23: =IF(AND($D23>0,K$7=$D23),"●","") | L23: =IF(AND($D23>0,L$7=$D23),"●","") | M23: =IF(AND($D23>0,M$7=$D23),"●","") | N23: =IF(AND($D23>0,N$7=$D23),"●","") | O23: =IF(AND($D23>0,O$7=$D23),"●","") | P23: =IF(AND($D23>0,P$7=$D23),"●","") | Q23: =IF(AND($D23>0,Q$7=$D23),"●","") | R23: =IF(AND($D23>0,R$7=$D23),"●","") | ... BJ23: =IF(AND($D23>0,BJ$7=$D23),"●","")
A24: Float | B24: 1 | C24: 0 | D24: =IF(OR($C24<=0,$G24=""),0,IF($B24=0,$G24,$G24+ROUNDUP($B24*$C24,0)-1)) -> 0 | E24: Wire down the garden | F24: NN | G24: 22 | H24: 22 | I24: 8 | J24: 0 | K24: =IF(AND($D24>0,K$7=$D24),"●","") | L24: =IF(AND($D24>0,L$7=$D24),"●","") | M24: =IF(AND($D24>0,M$7=$D24),"●","") | N24: =IF(AND($D24>0,N$7=$D24),"●","") | O24: =IF(AND($D24>0,O$7=$D24),"●","") | P24: =IF(AND($D24>0,P$7=$D24),"●","") | Q24: =IF(AND($D24>0,Q$7=$D24),"●","") | R24: =IF(AND($D24>0,R$7=$D24),"●","") | ... BJ24: =IF(AND($D24>0,BJ$7=$D24),"●","")
A25: Float | B25: 1 | C25: 0 | D25: =IF(OR($C25<=0,$G25=""),0,IF($B25=0,$G25,$G25+ROUNDUP($B25*$C25,0)-1)) -> 0 | E25: Assembly | F25: NN | G25: 23 | H25: 23 | I25: 0 | J25: 750 | K25: =IF(AND($D25>0,K$7=$D25),"●","") | L25: =IF(AND($D25>0,L$7=$D25),"●","") | M25: =IF(AND($D25>0,M$7=$D25),"●","") | N25: =IF(AND($D25>0,N$7=$D25),"●","") | O25: =IF(AND($D25>0,O$7=$D25),"●","") | P25: =IF(AND($D25>0,P$7=$D25),"●","") | Q25: =IF(AND($D25>0,Q$7=$D25),"●","") | R25: =IF(AND($D25>0,R$7=$D25),"●","") | ... BJ25: =IF(AND($D25>0,BJ$7=$D25),"●","")
E26: ● Actual progress marker

Sheet EVM
A1: Earned Value Management (EVM) Essentials
A2: A practical reference for measuring schedule, cost, and delivery performance using the project plan in this workbook.
A4: STORY IN BRIEF
A5: Earned Value Management compares what should have been delivered by the status date (Planned Value), what has actually been delivered in budget terms (Earned Value), and what has actually been spent (Actual Cost). It turns progress reporting into objective schedule and cost indicators: SPI below 1.0 means the project is behind plan, while CPI below 1.0 means it is costing more than the value earned. Use EVM as an early-warning system: the ratios are most useful when reviewed trend-by-trend, not as a one-off score.
A10: LIVE PROJECT KPI SNAPSHOT
A11: Metric | B11: Formula / Source | C11: Value | D11: Interpretation
A12: Project | B12: tblBudget[Project] | C12: =INDEX(tblBudget[Project],1) -> New Garden Shed | D12: Current project in the workbook
A13: Budget at Completion (BAC) | B13: tblBudget[total cost] | C13: =INDEX(tblBudget[total cost],1) -> 18800 | D13: Approved baseline budget for all planned work
A14: Actual Cost (AC) | B14: tblBudget[ActCost] | C14: =INDEX(tblBudget[ActCost],1) -> 19450 | D14: Actual cost recorded so far
A15: Earned Value (EV) | B15: SUMPRODUCT(Cost, Progress) | C15: =SUMPRODUCT(tblTaskList[Cost],tblTaskList[Progress]) -> 20 | D15: Budgeted value of completed work
A16: Planned Value (PV) | B16: Status-date estimate using task start/finish weeks | C16: {=SUMPRODUCT(tblTaskList[Cost],IF(MATCH('Gantt-frame'!$G$4,'Gantt-frame'!$K$6:$BJ$6,0)<tblTaskList[Start wk],0,IF(MATCH('Gantt-frame'!$G$4,'Gantt-frame'!$K$6:$BJ$6,0)>tblTaskList[Finish wk],1,(MATCH('Gantt-frame'!$G$4,'Gantt-frame'!$K$6:$BJ$6,0)-tblTaskList[Start wk]+1)/(tblTaskList[Finish wk]-tblTaskList[Start wk]+1))))} -> 8580 | D16: Budgeted value of work planned by the current status week
A17: Schedule Variance (SV) | B17: EV - PV | C17: =C15-C16 -> -8560 | D17: Positive = ahead of schedule; negative = behind schedule
A18: Cost Variance (CV) | B18: EV - AC | C18: =C15-C14 -> -19430 | D18: Positive = under budget; negative = over budget
A19: Schedule Performance Index (SPI) | B19: EV / PV | C19: =IFERROR(C15/C16,0) -> 0.0023310023 | D19: Above 1.0 = ahead; below 1.0 = behind
A20: Cost Performance Index (CPI) | B20: EV / AC | C20: =IFERROR(C15/C14,0) -> 0.0010282776 | D20: Above 1.0 = cost efficient; below 1.0 = cost overrun
A21: Estimate at Completion (EAC) | B21: BAC / CPI | C21: =IFERROR(C13/C20,C13) -> 18283000 | D21: Forecast final cost at current cost efficiency
A22: Estimate to Complete (ETC) | B22: EAC - AC | C22: =C21-C14 -> 18263550 | D22: Forecast remaining spend
A23: Variance at Completion (VAC) | B23: BAC - EAC | C23: =C13-C21 -> -18264200 | D23: Positive = forecast underrun; negative = forecast overrun
A24: To-Complete Performance Index (TCPI) | B24: (BAC-EV)/(BAC-AC) | C24: =IFERROR((C13-C15)/(C13-C14),0) -> -28.892308 | D24: Required future cost efficiency to meet the original budget
A25: % Complete | B25: EV / BAC | C25: =IFERROR(C15/C13,0) -> 0.0010638298 | D25: Budget-weighted completion percentage based on earned value
A26: ESSENTIAL EVM CONCEPTS
A27: Concept | B27: What it means | C27: Why it matters
A28: PV — Planned Value | B28: The budgeted value of work scheduled to be complete by the status date. | C28: Defines the schedule baseline: what should have been earned by now.
A29: EV — Earned Value | B29: The budgeted value of work actually completed. | C29: Converts physical progress into comparable money terms.
A30: AC — Actual Cost | B30: The real cost incurred for the work performed. | C30: Shows the cash or cost consumed to earn the value.
A31: BAC — Budget at Completion | B31: The total approved budget for the full scope. | C31: Anchor for EAC, VAC, and TCPI forecasts.
A32: Status date | B32: The date or reporting cut-off used for the EVM calculation. | C32: All PV, EV, and AC comparisons must use the same cut-off.
A33: Baseline | B33: The approved scope, schedule, and budget plan. | C33: Without a stable baseline, EVM ratios lose meaning.
A35: GLOSSARY OF TERMS, RATIOS & IMPORTANT KPIs
A36: Term / KPI | B36: Type | C36: Formula | D36: Interpretation / rule of thumb
A37: PV | B37: Core value | C37: Budgeted cost of scheduled work | D37: Planned work expressed in budget value.
A38: EV | B38: Core value | C38: Budgeted cost of performed work | D38: Completed work expressed in budget value.
A39: AC | B39: Core value | C39: Actual cost of performed work | D39: Actual spend or incurred cost.
A40: SV | B40: Variance | C40: EV - PV | D40: > 0 ahead of schedule; < 0 behind schedule.
A41: CV | B41: Variance | C41: EV - AC | D41: > 0 under budget; < 0 over budget.
A42: SPI | B42: Ratio | C42: EV / PV | D42: > 1.0 ahead of plan; < 1.0 behind plan.
A43: CPI | B43: Ratio | C43: EV / AC | D43: > 1.0 cost efficient; < 1.0 cost overrun.
A44: BAC | B44: Budget | C44: Total approved budget | D44: Final target budget for the full project scope.
A45: EAC | B45: Forecast | C45: BAC / CPI | D45: Forecast final cost if current efficiency continues.
A46: ETC | B46: Forecast | C46: EAC - AC | D46: Expected remaining cost from today to completion.
A47: VAC | B47: Forecast variance | C47: BAC - EAC | D47: > 0 underrun; < 0 expected overrun at completion.
... A51: Float | B51: Schedule concept | C51: Slack before task affects finish date | D51: Can absorb delays without moving the finish date.
A53: QUICK INTERPRETATION THRESHOLDS
A54: Indicator | B54: Green | C54: Amber | D54: Red | E54: Action
A55: SPI | B55: ≥ 1.00 | C55: 0.90–0.99 | D55: < 0.90 | E55: Review critical path, blockers, and recovery options.
A56: CPI | B56: ≥ 1.00 | C56: 0.90–0.99 | D56: < 0.90 | E56: Review cost drivers, scope growth, rework, and procurement.
A57: VAC | B57: ≥ 0 | C57: Slightly negative | D57: Materially negative | E57: Update forecast and agree corrective action.
A58: TCPI | B58: ≤ CPI trend | C58: Slightly above CPI trend | D58: Unrealistically above CPI trend | E58: Budget target may be unrealistic without scope/schedule change.
A60: HOW TO USE THIS SHEET
A61: Update task progress, costs, and actual costs in tblTaskList and tblBudget. The live KPI snapshot recalculates EV, AC, CPI, EAC, ETC, VAC, and TCPI automatically. Review SPI/CPI together: schedule recovery that burns excessive cost can improve SPI while damaging CPI.
A66: DATA GAPS FOR FULL EVM REPORTING
A67: These gaps explain why the current EVM figures are not yet reliable for full reporting. Fill task-level cost, actual cost, hours, and the one missing duration to support EV, PV, CPI, SPI, EAC, ETC, VAC, TCPI, resource, and schedule reporting.
A70: Missing field | B70: Missing count | C70: Impact on key figures | D70: Priority
A71: Cost | B71: =COUNTBLANK(tblTaskList[Cost]) -> 9 | C71: EV, PV, BAC-by-task, SV, SPI, % Complete | D71: High
A72: Actual Cost | B72: =COUNTBLANK(tblTaskList[Actual Cost]) -> 9 | C72: AC, CV, CPI, EAC, ETC, VAC, TCPI | D72: High
A73: Hours | B73: =COUNTBLANK(tblTaskList[Hours]) -> 11 | C73: Resource loading, labor effort, productivity KPIs | D73: Medium
A74: Duration (Weeks) | B74: =COUNTBLANK(tblTaskList[Duration (Weeks)]) -> 1 | C74: Schedule baseline, PV timing, SPI, Gantt | D74: High
A75: Predecessor Tasks | B75: =COUNTBLANK(tblTaskList[Predecessor Tasks]) -> 3 | C75: Dependency chain / process map completeness | D75: Review
A76: Start wk | B76: =COUNTBLANK(tblTaskList[Start wk]) -> 0 | C76: PV timing, schedule baseline | D76: High
A77: Finish wk | B77: =COUNTBLANK(tblTaskList[Finish wk]) -> 0 | C77: PV timing, schedule baseline | D77: High
A78: Progress | B78: =COUNTBLANK(tblTaskList[Progress]) -> 0 | C78: EV, % Complete, SPI/CPI | D78: High
A81: Row | B81: Task ID | C81: Task | D81: Missing / needs review | E81: Reporting impact
A82: 2 | B82: 2 | C82: Planning permission | D82: Cost; Actual Cost; Hours | E82: EV/PV/CPI/CV/EAC and labor reporting
A83: 3 | B83: 3 | C83: Wait for planning permission | D83: Hours | E83: Labor/resource reporting
A84: 5 | B84: 7 | C84: Hire digger | D84: Cost; Actual Cost; Hours | E84: EV/PV/CPI/CV/EAC and labor reporting
A85: 9 | B85: 19 | C85: Delivery | D85: Cost; Actual Cost; Hours | E85: EV/PV/CPI/CV/EAC and labor reporting
A86: 10 | B86: 1 | C86: Check funds | D86: Cost; Actual Cost; Hours | E86: EV/PV/CPI/CV/EAC and labor reporting
A87: 13 | B87: 8 | C87: Connect Power | D87: Cost; Actual Cost; Hours; Duration | E87: EVM cost ratios plus PV/SPI schedule baseline
A88: 14 | B88: 11 | C88: Find suppliers | D88: Cost; Actual Cost; Hours | E88: EV/PV/CPI/CV/EAC and labor reporting
A89: 15 | B89: 12 | C89: Get quotes | D89: Cost; Actual Cost; Hours | E89: EV/PV/CPI/CV/EAC and labor reporting
A90: 16 | B90: 13 | C90: Buy the shed | D90: Hours; predecessor blank | E90: Labor/resource reporting; dependency review
A91: 17 | B91: 14 | C91: Wait for Delivery | D91: Cost; Actual Cost; Hours | E91: EV/PV/CPI/CV/EAC and labor reporting
A92: 18 | B92: 15 | C92: Wire down the garden | D92: Cost; Actual Cost | E92: EV/PV/CPI/CV/EAC
A93: 19 | B93: 16 | C93: Assembly | D93: Hours; predecessor blank | E93: Labor/resource reporting; dependency review
A94: 8 | B94: 17 | C94: the Finish | D94: Predecessor blank | E94: Dependency review; may be intentional if milestone/end marker

Sheet S-Curve
A1: Project S-Curve — New Garden Shed
A2: Cumulative Planned Value, Earned Value, and Actual Cost by week using live formulas from tblEVMData.
A4: Metric | B4: Source | C4: Value | D4: Interpretation
A5: Status week | B5: EVM Data!B5 | C5: ='EVM Data'!B5 -> 32 | D5: Current reporting week used for the S-curve cut-off.
A6: Budget at Completion (BAC) | B6: EVM Data!B7 | C6: ='EVM Data'!B7 -> 18800 | D6: Total baseline budget for all planned work.
A7: Total Planned Value (PV) | B7: SCurveData[Planned Value] | C7: =MAX(SCurveData[Planned Value]) -> 18800 | D7: Cumulative planned budget by the status week.
A8: Total Actual Cost (AC) | B8: SCurveData[Actual Cost] | C8: =_xlfn.AGGREGATE(14,6,SCurveData[Actual Cost],1) -> 19450 | D8: Cumulative actual cost recorded by the status week.
A11: Week | B11: Week Start | C11: Planned Value | D11: Earned Value | E11: Actual Cost
A12: 1 | B12: =IF(ISNUMBER('Gantt-frame'!$F$5),'Gantt-frame'!$F$5,DATE(VALUE(RIGHT('Gantt-frame'!$F$5,4)),VALUE(MID('Gantt-frame'!$F$5,4,2)),VALUE(LEFT('Gantt-frame'!$F$5,2))))+(SCurveData[[#This Row],[Week]]-1)*7 -> 46174 | C12: {=SUMPRODUCT(tblEVMData[Baseline Cost]*IF(SCurveData[[#This Row],[Week]]<tblEVMData[Start wk],0,IF(SCurveData[[#This Row],[Week]]>=tblEVMData[Finish wk],1,(SCurveData[[#This Row],[Week]]-tblEVMData[Start wk]+1)/tblEVMData[Duration (Weeks)])))} -> 0 | D12: {=IF(SCurveData[[#This Row],[Week]]>'EVM Data'!$B$5,NA(),SUMPRODUCT(tblEVMData[Earned Value]*--(tblEVMData[Finish wk]<=SCurveData[[#This Row],[Week]])))} -> 0 | E12: {=IF(SCurveData[[#This Row],[Week]]>'EVM Data'!$B$5,NA(),SUMPRODUCT(tblEVMData[Actual Cost]*--(tblEVMData[Finish wk]<=SCurveData[[#This Row],[Week]])))} -> 0
A13: 2 | B13: =IF(ISNUMBER('Gantt-frame'!$F$5),'Gantt-frame'!$F$5,DATE(VALUE(RIGHT('Gantt-frame'!$F$5,4)),VALUE(MID('Gantt-frame'!$F$5,4,2)),VALUE(LEFT('Gantt-frame'!$F$5,2))))+(SCurveData[[#This Row],[Week]]-1)*7 -> 46181 | C13: {=SUMPRODUCT(tblEVMData[Baseline Cost]*IF(SCurveData[[#This Row],[Week]]<tblEVMData[Start wk],0,IF(SCurveData[[#This Row],[Week]]>=tblEVMData[Finish wk],1,(SCurveData[[#This Row],[Week]]-tblEVMData[Start wk]+1)/tblEVMData[Duration (Weeks)])))} -> 0 | D13: {=IF(SCurveData[[#This Row],[Week]]>'EVM Data'!$B$5,NA(),SUMPRODUCT(tblEVMData[Earned Value]*--(tblEVMData[Finish wk]<=SCurveData[[#This Row],[Week]])))} -> 0 | E13: {=IF(SCurveData[[#This Row],[Week]]>'EVM Data'!$B$5,NA(),SUMPRODUCT(tblEVMData[Actual Cost]*--(tblEVMData[Finish wk]<=SCurveData[[#This Row],[Week]])))} -> 0
A14: 3 | B14: =IF(ISNUMBER('Gantt-frame'!$F$5),'Gantt-frame'!$F$5,DATE(VALUE(RIGHT('Gantt-frame'!$F$5,4)),VALUE(MID('Gantt-frame'!$F$5,4,2)),VALUE(LEFT('Gantt-frame'!$F$5,2))))+(SCurveData[[#This Row],[Week]]-1)*7 -> 46188 | C14: {=SUMPRODUCT(tblEVMData[Baseline Cost]*IF(SCurveData[[#This Row],[Week]]<tblEVMData[Start wk],0,IF(SCurveData[[#This Row],[Week]]>=tblEVMData[Finish wk],1,(SCurveData[[#This Row],[Week]]-tblEVMData[Start wk]+1)/tblEVMData[Duration (Weeks)])))} -> 300 | D14: {=IF(SCurveData[[#This Row],[Week]]>'EVM Data'!$B$5,NA(),SUMPRODUCT(tblEVMData[Earned Value]*--(tblEVMData[Finish wk]<=SCurveData[[#This Row],[Week]])))} -> 0 | E14: {=IF(SCurveData[[#This Row],[Week]]>'EVM Data'!$B$5,NA(),SUMPRODUCT(tblEVMData[Actual Cost]*--(tblEVMData[Finish wk]<=SCurveData[[#This Row],[Week]])))} -> 300
A15: 4 | B15: =IF(ISNUMBER('Gantt-frame'!$F$5),'Gantt-frame'!$F$5,DATE(VALUE(RIGHT('Gantt-frame'!$F$5,4)),VALUE(MID('Gantt-frame'!$F$5,4,2)),VALUE(LEFT('Gantt-frame'!$F$5,2))))+(SCurveData[[#This Row],[Week]]-1)*7 -> 46195 | C15: {=SUMPRODUCT(tblEVMData[Baseline Cost]*IF(SCurveData[[#This Row],[Week]]<tblEVMData[Start wk],0,IF(SCurveData[[#This Row],[Week]]>=tblEVMData[Finish wk],1,(SCurveData[[#This Row],[Week]]-tblEVMData[Start wk]+1)/tblEVMData[Duration (Weeks)])))} -> 300 | D15: {=IF(SCurveData[[#This Row],[Week]]>'EVM Data'!$B$5,NA(),SUMPRODUCT(tblEVMData[Earned Value]*--(tblEVMData[Finish wk]<=SCurveData[[#This Row],[Week]])))} -> 0 | E15: {=IF(SCurveData[[#This Row],[Week]]>'EVM Data'!$B$5,NA(),SUMPRODUCT(tblEVMData[Actual Cost]*--(tblEVMData[Finish wk]<=SCurveData[[#This Row],[Week]])))} -> 300
A16: 5 | B16: =IF(ISNUMBER('Gantt-frame'!$F$5),'Gantt-frame'!$F$5,DATE(VALUE(RIGHT('Gantt-frame'!$F$5,4)),VALUE(MID('Gantt-frame'!$F$5,4,2)),VALUE(LEFT('Gantt-frame'!$F$5,2))))+(SCurveData[[#This Row],[Week]]-1)*7 -> 46202 | C16: {=SUMPRODUCT(tblEVMData[Baseline Cost]*IF(SCurveData[[#This Row],[Week]]<tblEVMData[Start wk],0,IF(SCurveData[[#This Row],[Week]]>=tblEVMData[Finish wk],1,(SCurveData[[#This Row],[Week]]-tblEVMData[Start wk]+1)/tblEVMData[Duration (Weeks)])))} -> 300 | D16: {=IF(SCurveData[[#This Row],[Week]]>'EVM Data'!$B$5,NA(),SUMPRODUCT(tblEVMData[Earned Value]*--(tblEVMData[Finish wk]<=SCurveData[[#This Row],[Week]])))} -> 0 | E16: {=IF(SCurveData[[#This Row],[Week]]>'EVM Data'!$B$5,NA(),SUMPRODUCT(tblEVMData[Actual Cost]*--(tblEVMData[Finish wk]<=SCurveData[[#This Row],[Week]])))} -> 300
A17: 6 | B17: =IF(ISNUMBER('Gantt-frame'!$F$5),'Gantt-frame'!$F$5,DATE(VALUE(RIGHT('Gantt-frame'!$F$5,4)),VALUE(MID('Gantt-frame'!$F$5,4,2)),VALUE(LEFT('Gantt-frame'!$F$5,2))))+(SCurveData[[#This Row],[Week]]-1)*7 -> 46209 | C17: {=SUMPRODUCT(tblEVMData[Baseline Cost]*IF(SCurveData[[#This Row],[Week]]<tblEVMData[Start wk],0,IF(SCurveData[[#This Row],[Week]]>=tblEVMData[Finish wk],1,(SCurveData[[#This Row],[Week]]-tblEVMData[Start wk]+1)/tblEVMData[Duration (Weeks)])))} -> 300 | D17: {=IF(SCurveData[[#This Row],[Week]]>'EVM Data'!$B$5,NA(),SUMPRODUCT(tblEVMData[Earned Value]*--(tblEVMData[Finish wk]<=SCurveData[[#This Row],[Week]])))} -> 0 | E17: {=IF(SCurveData[[#This Row],[Week]]>'EVM Data'!$B$5,NA(),SUMPRODUCT(tblEVMData[Actual Cost]*--(tblEVMData[Finish wk]<=SCurveData[[#This Row],[Week]])))} -> 300
A18: 7 | B18: =IF(ISNUMBER('Gantt-frame'!$F$5),'Gantt-frame'!$F$5,DATE(VALUE(RIGHT('Gantt-frame'!$F$5,4)),VALUE(MID('Gantt-frame'!$F$5,4,2)),VALUE(LEFT('Gantt-frame'!$F$5,2))))+(SCurveData[[#This Row],[Week]]-1)*7 -> 46216 | C18: {=SUMPRODUCT(tblEVMData[Baseline Cost]*IF(SCurveData[[#This Row],[Week]]<tblEVMData[Start wk],0,IF(SCurveData[[#This Row],[Week]]>=tblEVMData[Finish wk],1,(SCurveData[[#This Row],[Week]]-tblEVMData[Start wk]+1)/tblEVMData[Duration (Weeks)])))} -> 310 | D18: {=IF(SCurveData[[#This Row],[Week]]>'EVM Data'!$B$5,NA(),SUMPRODUCT(tblEVMData[Earned Value]*--(tblEVMData[Finish wk]<=SCurveData[[#This Row],[Week]])))} -> 0 | E18: {=IF(SCurveData[[#This Row],[Week]]>'EVM Data'!$B$5,NA(),SUMPRODUCT(tblEVMData[Actual Cost]*--(tblEVMData[Finish wk]<=SCurveData[[#This Row],[Week]])))} -> 300
A19: 8 | B19: =IF(ISNUMBER('Gantt-frame'!$F$5),'Gantt-frame'!$F$5,DATE(VALUE(RIGHT('Gantt-frame'!$F$5,4)),VALUE(MID('Gantt-frame'!$F$5,4,2)),VALUE(LEFT('Gantt-frame'!$F$5,2))))+(SCurveData[[#This Row],[Week]]-1)*7 -> 46223 | C19: {=SUMPRODUCT(tblEVMData[Baseline Cost]*IF(SCurveData[[#This Row],[Week]]<tblEVMData[Start wk],0,IF(SCurveData[[#This Row],[Week]]>=tblEVMData[Finish wk],1,(SCurveData[[#This Row],[Week]]-tblEVMData[Start wk]+1)/tblEVMData[Duration (Weeks)])))} -> 8445 | D19: {=IF(SCurveData[[#This Row],[Week]]>'EVM Data'!$B$5,NA(),SUMPRODUCT(tblEVMData[Earned Value]*--(tblEVMData[Finish wk]<=SCurveData[[#This Row],[Week]])))} -> 0 | E19: {=IF(SCurveData[[#This Row],[Week]]>'EVM Data'!$B$5,NA(),SUMPRODUCT(tblEVMData[Actual Cost]*--(tblEVMData[Finish wk]<=SCurveData[[#This Row],[Week]])))} -> 8300
A20: 9 | B20: =IF(ISNUMBER('Gantt-frame'!$F$5),'Gantt-frame'!$F$5,DATE(VALUE(RIGHT('Gantt-frame'!$F$5,4)),VALUE(MID('Gantt-frame'!$F$5,4,2)),VALUE(LEFT('Gantt-frame'!$F$5,2))))+(SCurveData[[#This Row],[Week]]-1)*7 -> 46230 | C20: {=SUMPRODUCT(tblEVMData[Baseline Cost]*IF(SCurveData[[#This Row],[Week]]<tblEVMData[Start wk],0,IF(SCurveData[[#This Row],[Week]]>=tblEVMData[Finish wk],1,(SCurveData[[#This Row],[Week]]-tblEVMData[Start wk]+1)/tblEVMData[Duration (Weeks)])))} -> 8580 | D20: {=IF(SCurveData[[#This Row],[Week]]>'EVM Data'!$B$5,NA(),SUMPRODUCT(tblEVMData[Earned Value]*--(tblEVMData[Finish wk]<=SCurveData[[#This Row],[Week]])))} -> 0 | E20: {=IF(SCurveData[[#This Row],[Week]]>'EVM Data'!$B$5,NA(),SUMPRODUCT(tblEVMData[Actual Cost]*--(tblEVMData[Finish wk]<=SCurveData[[#This Row],[Week]])))} -> 8300
A21: 10 | B21: =IF(ISNUMBER('Gantt-frame'!$F$5),'Gantt-frame'!$F$5,DATE(VALUE(RIGHT('Gantt-frame'!$F$5,4)),VALUE(MID('Gantt-frame'!$F$5,4,2)),VALUE(LEFT('Gantt-frame'!$F$5,2))))+(SCurveData[[#This Row],[Week]]-1)*7 -> 46237 | C21: {=SUMPRODUCT(tblEVMData[Baseline Cost]*IF(SCurveData[[#This Row],[Week]]<tblEVMData[Start wk],0,IF(SCurveData[[#This Row],[Week]]>=tblEVMData[Finish wk],1,(SCurveData[[#This Row],[Week]]-tblEVMData[Start wk]+1)/tblEVMData[Duration (Weeks)])))} -> 8715 | D21: {=IF(SCurveData[[#This Row],[Week]]>'EVM Data'!$B$5,NA(),SUMPRODUCT(tblEVMData[Earned Value]*--(tblEVMData[Finish wk]<=SCurveData[[#This Row],[Week]])))} -> 0 | E21: {=IF(SCurveData[[#This Row],[Week]]>'EVM Data'!$B$5,NA(),SUMPRODUCT(tblEVMData[Actual Cost]*--(tblEVMData[Finish wk]<=SCurveData[[#This Row],[Week]])))} -> 8300
A22: 11 | B22: =IF(ISNUMBER('Gantt-frame'!$F$5),'Gantt-frame'!$F$5,DATE(VALUE(RIGHT('Gantt-frame'!$F$5,4)),VALUE(MID('Gantt-frame'!$F$5,4,2)),VALUE(LEFT('Gantt-frame'!$F$5,2))))+(SCurveData[[#This Row],[Week]]-1)*7 -> 46244 | C22: {=SUMPRODUCT(tblEVMData[Baseline Cost]*IF(SCurveData[[#This Row],[Week]]<tblEVMData[Start wk],0,IF(SCurveData[[#This Row],[Week]]>=tblEVMData[Finish wk],1,(SCurveData[[#This Row],[Week]]-tblEVMData[Start wk]+1)/tblEVMData[Duration (Weeks)])))} -> 8850 | D22: {=IF(SCurveData[[#This Row],[Week]]>'EVM Data'!$B$5,NA(),SUMPRODUCT(tblEVMData[Earned Value]*--(tblEVMData[Finish wk]<=SCurveData[[#This Row],[Week]])))} -> 0 | E22: {=IF(SCurveData[[#This Row],[Week]]>'EVM Data'!$B$5,NA(),SUMPRODUCT(tblEVMData[Actual Cost]*--(tblEVMData[Finish wk]<=SCurveData[[#This Row],[Week]])))} -> 8800
A23: 12 | B23: =IF(ISNUMBER('Gantt-frame'!$F$5),'Gantt-frame'!$F$5,DATE(VALUE(RIGHT('Gantt-frame'!$F$5,4)),VALUE(MID('Gantt-frame'!$F$5,4,2)),VALUE(LEFT('Gantt-frame'!$F$5,2))))+(SCurveData[[#This Row],[Week]]-1)*7 -> 46251 | C23: {=SUMPRODUCT(tblEVMData[Baseline Cost]*IF(SCurveData[[#This Row],[Week]]<tblEVMData[Start wk],0,IF(SCurveData[[#This Row],[Week]]>=tblEVMData[Finish wk],1,(SCurveData[[#This Row],[Week]]-tblEVMData[Start wk]+1)/tblEVMData[Duration (Weeks)])))} -> 8860 | D23: {=IF(SCurveData[[#This Row],[Week]]>'EVM Data'!$B$5,NA(),SUMPRODUCT(tblEVMData[Earned Value]*--(tblEVMData[Finish wk]<=SCurveData[[#This Row],[Week]])))} -> 0 | E23: {=IF(SCurveData[[#This Row],[Week]]>'EVM Data'!$B$5,NA(),SUMPRODUCT(tblEVMData[Actual Cost]*--(tblEVMData[Finish wk]<=SCurveData[[#This Row],[Week]])))} -> 8800
... A26: 15 | B26: =IF(ISNUMBER('Gantt-frame'!$F$5),'Gantt-frame'!$F$5,DATE(VALUE(RIGHT('Gantt-frame'!$F$5,4)),VALUE(MID('Gantt-frame'!$F$5,4,2)),VALUE(LEFT('Gantt-frame'!$F$5,2))))+(SCurveData[[#This Row],[Week]]-1)*7 -> 46272 | C26: {=SUMPRODUCT(tblEVMData[Baseline Cost]*IF(SCurveData[[#This Row],[Week]]<tblEVMData[Start wk],0,IF(SCurveData[[#This Row],[Week]]>=tblEVMData[Finish wk],1,(SCurveData[[#This Row],[Week]]-tblEVMData[Start wk]+1)/tblEVMData[Duration (Weeks)])))} -> 8890 | D26: {=IF(SCurveData[[#This Row],[Week]]>'EVM Data'!$B$5,NA(),SUMPRODUCT(tblEVMData[Earned Value]*--(tblEVMData[Finish wk]<=SCurveData[[#This Row],[Week]])))} -> 0 | E26: {=IF(SCurveData[[#This Row],[Week]]>'EVM Data'!$B$5,NA(),SUMPRODUCT(tblEVMData[Actual Cost]*--(tblEVMData[Finish wk]<=SCurveData[[#This Row],[Week]])))} -> 8800
A27: 16 | B27: =IF(ISNUMBER('Gantt-frame'!$F$5),'Gantt-frame'!$F$5,DATE(VALUE(RIGHT('Gantt-frame'!$F$5,4)),VALUE(MID('Gantt-frame'!$F$5,4,2)),VALUE(LEFT('Gantt-frame'!$F$5,2))))+(SCurveData[[#This Row],[Week]]-1)*7 -> 46279 | C27: {=SUMPRODUCT(tblEVMData[Baseline Cost]*IF(SCurveData[[#This Row],[Week]]<tblEVMData[Start wk],0,IF(SCurveData[[#This Row],[Week]]>=tblEVMData[Finish wk],1,(SCurveData[[#This Row],[Week]]-tblEVMData[Start wk]+1)/tblEVMData[Duration (Weeks)])))} -> 8900 | D27: {=IF(SCurveData[[#This Row],[Week]]>'EVM Data'!$B$5,NA(),SUMPRODUCT(tblEVMData[Earned Value]*--(tblEVMData[Finish wk]<=SCurveData[[#This Row],[Week]])))} -> 20 | E27: {=IF(SCurveData[[#This Row],[Week]]>'EVM Data'!$B$5,NA(),SUMPRODUCT(tblEVMData[Actual Cost]*--(tblEVMData[Finish wk]<=SCurveData[[#This Row],[Week]])))} -> 8900 | G27: Reading the chart
A28: 17 | B28: =IF(ISNUMBER('Gantt-frame'!$F$5),'Gantt-frame'!$F$5,DATE(VALUE(RIGHT('Gantt-frame'!$F$5,4)),VALUE(MID('Gantt-frame'!$F$5,4,2)),VALUE(LEFT('Gantt-frame'!$F$5,2))))+(SCurveData[[#This Row],[Week]]-1)*7 -> 46286 | C28: {=SUMPRODUCT(tblEVMData[Baseline Cost]*IF(SCurveData[[#This Row],[Week]]<tblEVMData[Start wk],0,IF(SCurveData[[#This Row],[Week]]>=tblEVMData[Finish wk],1,(SCurveData[[#This Row],[Week]]-tblEVMData[Start wk]+1)/tblEVMData[Duration (Weeks)])))} -> 9250 | D28: {=IF(SCurveData[[#This Row],[Week]]>'EVM Data'!$B$5,NA(),SUMPRODUCT(tblEVMData[Earned Value]*--(tblEVMData[Finish wk]<=SCurveData[[#This Row],[Week]])))} -> 20 | E28: {=IF(SCurveData[[#This Row],[Week]]>'EVM Data'!$B$5,NA(),SUMPRODUCT(tblEVMData[Actual Cost]*--(tblEVMData[Finish wk]<=SCurveData[[#This Row],[Week]])))} -> 9300 | G28: ="At status week "&'EVM Data'!$B$5&", PV is "&TEXT(INDEX(SCurveData[Planned Value],MATCH('EVM Data'!$B$5,SCurveData[Week],0)),"#,##0")&", EV is "&TEXT(INDEX(SCurveData[Earned Value],MATCH('EVM Data'!$B$5,SCurveData[Week],0)),"#,##0")&", and AC is "&TEXT(INDEX(SCurveData[Actual Cost],MATCH('EVM Data'!$B$5,SCurveData[Week],0)),"#,##0")&"." -> At status week 32, PV is 18,800, EV is 20, and AC is 19,450.
A29: 18 | B29: =IF(ISNUMBER('Gantt-frame'!$F$5),'Gantt-frame'!$F$5,DATE(VALUE(RIGHT('Gantt-frame'!$F$5,4)),VALUE(MID('Gantt-frame'!$F$5,4,2)),VALUE(LEFT('Gantt-frame'!$F$5,2))))+(SCurveData[[#This Row],[Week]]-1)*7 -> 46293 | C29: {=SUMPRODUCT(tblEVMData[Baseline Cost]*IF(SCurveData[[#This Row],[Week]]<tblEVMData[Start wk],0,IF(SCurveData[[#This Row],[Week]]>=tblEVMData[Finish wk],1,(SCurveData[[#This Row],[Week]]-tblEVMData[Start wk]+1)/tblEVMData[Duration (Weeks)])))} -> 9250 | D29: {=IF(SCurveData[[#This Row],[Week]]>'EVM Data'!$B$5,NA(),SUMPRODUCT(tblEVMData[Earned Value]*--(tblEVMData[Finish wk]<=SCurveData[[#This Row],[Week]])))} -> 20 | E29: {=IF(SCurveData[[#This Row],[Week]]>'EVM Data'!$B$5,NA(),SUMPRODUCT(tblEVMData[Actual Cost]*--(tblEVMData[Finish wk]<=SCurveData[[#This Row],[Week]])))} -> 9300
A30: 19 | B30: =IF(ISNUMBER('Gantt-frame'!$F$5),'Gantt-frame'!$F$5,DATE(VALUE(RIGHT('Gantt-frame'!$F$5,4)),VALUE(MID('Gantt-frame'!$F$5,4,2)),VALUE(LEFT('Gantt-frame'!$F$5,2))))+(SCurveData[[#This Row],[Week]]-1)*7 -> 46300 | C30: {=SUMPRODUCT(tblEVMData[Baseline Cost]*IF(SCurveData[[#This Row],[Week]]<tblEVMData[Start wk],0,IF(SCurveData[[#This Row],[Week]]>=tblEVMData[Finish wk],1,(SCurveData[[#This Row],[Week]]-tblEVMData[Start wk]+1)/tblEVMData[Duration (Weeks)])))} -> 9250 | D30: {=IF(SCurveData[[#This Row],[Week]]>'EVM Data'!$B$5,NA(),SUMPRODUCT(tblEVMData[Earned Value]*--(tblEVMData[Finish wk]<=SCurveData[[#This Row],[Week]])))} -> 20 | E30: {=IF(SCurveData[[#This Row],[Week]]>'EVM Data'!$B$5,NA(),SUMPRODUCT(tblEVMData[Actual Cost]*--(tblEVMData[Finish wk]<=SCurveData[[#This Row],[Week]])))} -> 9300
A31: 20 | B31: =IF(ISNUMBER('Gantt-frame'!$F$5),'Gantt-frame'!$F$5,DATE(VALUE(RIGHT('Gantt-frame'!$F$5,4)),VALUE(MID('Gantt-frame'!$F$5,4,2)),VALUE(LEFT('Gantt-frame'!$F$5,2))))+(SCurveData[[#This Row],[Week]]-1)*7 -> 46307 | C31: {=SUMPRODUCT(tblEVMData[Baseline Cost]*IF(SCurveData[[#This Row],[Week]]<tblEVMData[Start wk],0,IF(SCurveData[[#This Row],[Week]]>=tblEVMData[Finish wk],1,(SCurveData[[#This Row],[Week]]-tblEVMData[Start wk]+1)/tblEVMData[Duration (Weeks)])))} -> 9950 | D31: {=IF(SCurveData[[#This Row],[Week]]>'EVM Data'!$B$5,NA(),SUMPRODUCT(tblEVMData[Earned Value]*--(tblEVMData[Finish wk]<=SCurveData[[#This Row],[Week]])))} -> 20 | E31: {=IF(SCurveData[[#This Row],[Week]]>'EVM Data'!$B$5,NA(),SUMPRODUCT(tblEVMData[Actual Cost]*--(tblEVMData[Finish wk]<=SCurveData[[#This Row],[Week]])))} -> 10100
A32: 21 | B32: =IF(ISNUMBER('Gantt-frame'!$F$5),'Gantt-frame'!$F$5,DATE(VALUE(RIGHT('Gantt-frame'!$F$5,4)),VALUE(MID('Gantt-frame'!$F$5,4,2)),VALUE(LEFT('Gantt-frame'!$F$5,2))))+(SCurveData[[#This Row],[Week]]-1)*7 -> 46314 | C32: {=SUMPRODUCT(tblEVMData[Baseline Cost]*IF(SCurveData[[#This Row],[Week]]<tblEVMData[Start wk],0,IF(SCurveData[[#This Row],[Week]]>=tblEVMData[Finish wk],1,(SCurveData[[#This Row],[Week]]-tblEVMData[Start wk]+1)/tblEVMData[Duration (Weeks)])))} -> 10050 | D32: {=IF(SCurveData[[#This Row],[Week]]>'EVM Data'!$B$5,NA(),SUMPRODUCT(tblEVMData[Earned Value]*--(tblEVMData[Finish wk]<=SCurveData[[#This Row],[Week]])))} -> 20 | E32: {=IF(SCurveData[[#This Row],[Week]]>'EVM Data'!$B$5,NA(),SUMPRODUCT(tblEVMData[Actual Cost]*--(tblEVMData[Finish wk]<=SCurveData[[#This Row],[Week]])))} -> 10200
A33: 22 | B33: =IF(ISNUMBER('Gantt-frame'!$F$5),'Gantt-frame'!$F$5,DATE(VALUE(RIGHT('Gantt-frame'!$F$5,4)),VALUE(MID('Gantt-frame'!$F$5,4,2)),VALUE(LEFT('Gantt-frame'!$F$5,2))))+(SCurveData[[#This Row],[Week]]-1)*7 -> 46321 | C33: {=SUMPRODUCT(tblEVMData[Baseline Cost]*IF(SCurveData[[#This Row],[Week]]<tblEVMData[Start wk],0,IF(SCurveData[[#This Row],[Week]]>=tblEVMData[Finish wk],1,(SCurveData[[#This Row],[Week]]-tblEVMData[Start wk]+1)/tblEVMData[Duration (Weeks)])))} -> 12050 | D33: {=IF(SCurveData[[#This Row],[Week]]>'EVM Data'!$B$5,NA(),SUMPRODUCT(tblEVMData[Earned Value]*--(tblEVMData[Finish wk]<=SCurveData[[#This Row],[Week]])))} -> 20 | E33: {=IF(SCurveData[[#This Row],[Week]]>'EVM Data'!$B$5,NA(),SUMPRODUCT(tblEVMData[Actual Cost]*--(tblEVMData[Finish wk]<=SCurveData[[#This Row],[Week]])))} -> 10200
A34: 23 | B34: =IF(ISNUMBER('Gantt-frame'!$F$5),'Gantt-frame'!$F$5,DATE(VALUE(RIGHT('Gantt-frame'!$F$5,4)),VALUE(MID('Gantt-frame'!$F$5,4,2)),VALUE(LEFT('Gantt-frame'!$F$5,2))))+(SCurveData[[#This Row],[Week]]-1)*7 -> 46328 | C34: {=SUMPRODUCT(tblEVMData[Baseline Cost]*IF(SCurveData[[#This Row],[Week]]<tblEVMData[Start wk],0,IF(SCurveData[[#This Row],[Week]]>=tblEVMData[Finish wk],1,(SCurveData[[#This Row],[Week]]-tblEVMData[Start wk]+1)/tblEVMData[Duration (Weeks)])))} -> 14800 | D34: {=IF(SCurveData[[#This Row],[Week]]>'EVM Data'!$B$5,NA(),SUMPRODUCT(tblEVMData[Earned Value]*--(tblEVMData[Finish wk]<=SCurveData[[#This Row],[Week]])))} -> 20 | E34: {=IF(SCurveData[[#This Row],[Week]]>'EVM Data'!$B$5,NA(),SUMPRODUCT(tblEVMData[Actual Cost]*--(tblEVMData[Finish wk]<=SCurveData[[#This Row],[Week]])))} -> 10950
A35: 24 | B35: =IF(ISNUMBER('Gantt-frame'!$F$5),'Gantt-frame'!$F$5,DATE(VALUE(RIGHT('Gantt-frame'!$F$5,4)),VALUE(MID('Gantt-frame'!$F$5,4,2)),VALUE(LEFT('Gantt-frame'!$F$5,2))))+(SCurveData[[#This Row],[Week]]-1)*7 -> 46335 | C35: {=SUMPRODUCT(tblEVMData[Baseline Cost]*IF(SCurveData[[#This Row],[Week]]<tblEVMData[Start wk],0,IF(SCurveData[[#This Row],[Week]]>=tblEVMData[Finish wk],1,(SCurveData[[#This Row],[Week]]-tblEVMData[Start wk]+1)/tblEVMData[Duration (Weeks)])))} -> 16800 | D35: {=IF(SCurveData[[#This Row],[Week]]>'EVM Data'!$B$5,NA(),SUMPRODUCT(tblEVMData[Earned Value]*--(tblEVMData[Finish wk]<=SCurveData[[#This Row],[Week]])))} -> 20 | E35: {=IF(SCurveData[[#This Row],[Week]]>'EVM Data'!$B$5,NA(),SUMPRODUCT(tblEVMData[Actual Cost]*--(tblEVMData[Finish wk]<=SCurveData[[#This Row],[Week]])))} -> 10950
A36: 25 | B36: =IF(ISNUMBER('Gantt-frame'!$F$5),'Gantt-frame'!$F$5,DATE(VALUE(RIGHT('Gantt-frame'!$F$5,4)),VALUE(MID('Gantt-frame'!$F$5,4,2)),VALUE(LEFT('Gantt-frame'!$F$5,2))))+(SCurveData[[#This Row],[Week]]-1)*7 -> 46342 | C36: {=SUMPRODUCT(tblEVMData[Baseline Cost]*IF(SCurveData[[#This Row],[Week]]<tblEVMData[Start wk],0,IF(SCurveData[[#This Row],[Week]]>=tblEVMData[Finish wk],1,(SCurveData[[#This Row],[Week]]-tblEVMData[Start wk]+1)/tblEVMData[Duration (Weeks)])))} -> 18800 | D36: {=IF(SCurveData[[#This Row],[Week]]>'EVM Data'!$B$5,NA(),SUMPRODUCT(tblEVMData[Earned Value]*--(tblEVMData[Finish wk]<=SCurveData[[#This Row],[Week]])))} -> 20 | E36: {=IF(SCurveData[[#This Row],[Week]]>'EVM Data'!$B$5,NA(),SUMPRODUCT(tblEVMData[Actual Cost]*--(tblEVMData[Finish wk]<=SCurveData[[#This Row],[Week]])))} -> 19450
A37: 26 | B37: =IF(ISNUMBER('Gantt-frame'!$F$5),'Gantt-frame'!$F$5,DATE(VALUE(RIGHT('Gantt-frame'!$F$5,4)),VALUE(MID('Gantt-frame'!$F$5,4,2)),VALUE(LEFT('Gantt-frame'!$F$5,2))))+(SCurveData[[#This Row],[Week]]-1)*7 -> 46349 | C37: {=SUMPRODUCT(tblEVMData[Baseline Cost]*IF(SCurveData[[#This Row],[Week]]<tblEVMData[Start wk],0,IF(SCurveData[[#This Row],[Week]]>=tblEVMData[Finish wk],1,(SCurveData[[#This Row],[Week]]-tblEVMData[Start wk]+1)/tblEVMData[Duration (Weeks)])))} -> 18800 | D37: {=IF(SCurveData[[#This Row],[Week]]>'EVM Data'!$B$5,NA(),SUMPRODUCT(tblEVMData[Earned Value]*--(tblEVMData[Finish wk]<=SCurveData[[#This Row],[Week]])))} -> 20 | E37: {=IF(SCurveData[[#This Row],[Week]]>'EVM Data'!$B$5,NA(),SUMPRODUCT(tblEVMData[Actual Cost]*--(tblEVMData[Finish wk]<=SCurveData[[#This Row],[Week]])))} -> 19450
A38: 27 | B38: =IF(ISNUMBER('Gantt-frame'!$F$5),'Gantt-frame'!$F$5,DATE(VALUE(RIGHT('Gantt-frame'!$F$5,4)),VALUE(MID('Gantt-frame'!$F$5,4,2)),VALUE(LEFT('Gantt-frame'!$F$5,2))))+(SCurveData[[#This Row],[Week]]-1)*7 -> 46356 | C38: {=SUMPRODUCT(tblEVMData[Baseline Cost]*IF(SCurveData[[#This Row],[Week]]<tblEVMData[Start wk],0,IF(SCurveData[[#This Row],[Week]]>=tblEVMData[Finish wk],1,(SCurveData[[#This Row],[Week]]-tblEVMData[Start wk]+1)/tblEVMData[Duration (Weeks)])))} -> 18800 | D38: {=IF(SCurveData[[#This Row],[Week]]>'EVM Data'!$B$5,NA(),SUMPRODUCT(tblEVMData[Earned Value]*--(tblEVMData[Finish wk]<=SCurveData[[#This Row],[Week]])))} -> 20 | E38: {=IF(SCurveData[[#This Row],[Week]]>'EVM Data'!$B$5,NA(),SUMPRODUCT(tblEVMData[Actual Cost]*--(tblEVMData[Finish wk]<=SCurveData[[#This Row],[Week]])))} -> 19450
A39: 28 | B39: =IF(ISNUMBER('Gantt-frame'!$F$5),'Gantt-frame'!$F$5,DATE(VALUE(RIGHT('Gantt-frame'!$F$5,4)),VALUE(MID('Gantt-frame'!$F$5,4,2)),VALUE(LEFT('Gantt-frame'!$F$5,2))))+(SCurveData[[#This Row],[Week]]-1)*7 -> 46363 | C39: {=SUMPRODUCT(tblEVMData[Baseline Cost]*IF(SCurveData[[#This Row],[Week]]<tblEVMData[Start wk],0,IF(SCurveData[[#This Row],[Week]]>=tblEVMData[Finish wk],1,(SCurveData[[#This Row],[Week]]-tblEVMData[Start wk]+1)/tblEVMData[Duration (Weeks)])))} -> 18800 | D39: {=IF(SCurveData[[#This Row],[Week]]>'EVM Data'!$B$5,NA(),SUMPRODUCT(tblEVMData[Earned Value]*--(tblEVMData[Finish wk]<=SCurveData[[#This Row],[Week]])))} -> 20 | E39: {=IF(SCurveData[[#This Row],[Week]]>'EVM Data'!$B$5,NA(),SUMPRODUCT(tblEVMData[Actual Cost]*--(tblEVMData[Finish wk]<=SCurveData[[#This Row],[Week]])))} -> 19450
A40: 29 | B40: =IF(ISNUMBER('Gantt-frame'!$F$5),'Gantt-frame'!$F$5,DATE(VALUE(RIGHT('Gantt-frame'!$F$5,4)),VALUE(MID('Gantt-frame'!$F$5,4,2)),VALUE(LEFT('Gantt-frame'!$F$5,2))))+(SCurveData[[#This Row],[Week]]-1)*7 -> 46370 | C40: {=SUMPRODUCT(tblEVMData[Baseline Cost]*IF(SCurveData[[#This Row],[Week]]<tblEVMData[Start wk],0,IF(SCurveData[[#This Row],[Week]]>=tblEVMData[Finish wk],1,(SCurveData[[#This Row],[Week]]-tblEVMData[Start wk]+1)/tblEVMData[Duration (Weeks)])))} -> 18800 | D40: {=IF(SCurveData[[#This Row],[Week]]>'EVM Data'!$B$5,NA(),SUMPRODUCT(tblEVMData[Earned Value]*--(tblEVMData[Finish wk]<=SCurveData[[#This Row],[Week]])))} -> 20 | E40: {=IF(SCurveData[[#This Row],[Week]]>'EVM Data'!$B$5,NA(),SUMPRODUCT(tblEVMData[Actual Cost]*--(tblEVMData[Finish wk]<=SCurveData[[#This Row],[Week]])))} -> 19450
... A63: 52 | B63: =IF(ISNUMBER('Gantt-frame'!$F$5),'Gantt-frame'!$F$5,DATE(VALUE(RIGHT('Gantt-frame'!$F$5,4)),VALUE(MID('Gantt-frame'!$F$5,4,2)),VALUE(LEFT('Gantt-frame'!$F$5,2))))+(SCurveData[[#This Row],[Week]]-1)*7 -> 46531 | C63: {=SUMPRODUCT(tblEVMData[Baseline Cost]*IF(SCurveData[[#This Row],[Week]]<tblEVMData[Start wk],0,IF(SCurveData[[#This Row],[Week]]>=tblEVMData[Finish wk],1,(SCurveData[[#This Row],[Week]]-tblEVMData[Start wk]+1)/tblEVMData[Duration (Weeks)])))} -> 18800 | D63: {=IF(SCurveData[[#This Row],[Week]]>'EVM Data'!$B$5,NA(),SUMPRODUCT(tblEVMData[Earned Value]*--(tblEVMData[Finish wk]<=SCurveData[[#This Row],[Week]])))} -> #N/A | E63: {=IF(SCurveData[[#This Row],[Week]]>'EVM Data'!$B$5,NA(),SUMPRODUCT(tblEVMData[Actual Cost]*--(tblEVMData[Finish wk]<=SCurveData[[#This Row],[Week]])))} -> #N/A

Sheet Visio-datavisualiserer
B2: Grunnleggende flytskjema – Datavisualiserer
B3: Tre enkle trinn for å opprette prosessdiagrammer fra dataene dine.
F5: 1 | G5: Legg til prosessdataene Bruk denne Excel-malen til å legge til prosessdata i arket med tittelen «Prosesskart».
F7: 2 | G7: Eksporter til Visio Velg tabellen i Prosesskart-arket for å se Utforming-fanen for tabellverktøy. Klikk på Eksporter-alternativet, og klikk deretter på Eksporter tabell til Visio-diagram for å opprette diagrammet i Visio.
F9: 3 | G9: Få diagrammet Visio oppretter figurene og koblingene, og det lager oppsettet for deg automatisk.
G13: Obs! Funksjonen er bare tilgjengelig i Visio-abonnement 2 for M365. Hvis du ikke har installert Visio-abonnement 2, er ikke alternativet Eksporter tabell til Visio-diagram tilgjengelig.

Sheet Forstå prosesskartet
B2: Grunnleggende flytskjema – Datavisualiserer
B3: Dette arket vil hjelpe deg med å forstå betydningen av datakolonnene i prosesskartet.
B5: ID for prosesstrinnet
B6: Verdiene i denne kolonnen skal identifisere prosesstrinnene dine, for eksempel 1, 2, 3... eller P100, P200, P300... Dette er et obligatorisk felt.
B8: Beskrivelse av prosesstrinnet
B9: Legg til en kort beskrivelse av prosesstrinnene i denne kolonnen. Denne beskrivelsen vises som figurtekst for prosesstrinn i Visio.
B11: ID for neste trinn
B12: Legg til prosesstrinn-ID-en i neste trinn i denne kolonnen. Merk: Hvis et prosesstrinn har flere neste trinn, skal disse representeres som kommadelte verdier, for eksempel «2, 3» eller «P200, P300».
B14: Koblingsetiketter
B15: Legg til koblingsteksten for utgående koblinger for eventuelle prosesstrinn i denne kolonnen. Merk: Etikettene for flere neste trinn for en prosess skal representeres som kommadelte verdier, for eksempel «ja, nei», i samme rekkefølge som for de utgående trinnene.
B17: Formtype
B18: Legg til nøkkelord for figurtype i denne kolonnen. Denne kolonnen inneholder en liste over alle tilgjengelige flytskjemafigurer i Visio. Anbefales: Velg en figurtypeverdi fra de tilgjengelige verdiene i rullegardinlisten.
... B21: Resten av kolonnene er metriske eller metadatakolonner for prosesstrinnene. Du kan legge til et hvilket som helst antall tilleggskolonner.

Sheet Prosesskart
B2: Prosesskart: New Garden Shed
B3: Tilpasset fra prosjektplanen: hver oppgave i tblTaskList er ett prosesstrinn; ID for neste trinn er slått opp fra oppgavekoblingene i kolonnen Predecessor Tasks.
B5: ID for prosesstrinnet | C5: Beskrivelse av prosesstrinnet | D5: ID for neste trinn | E5: Koblingsetikett | F5: Formtype | G5: Eier | H5: Kostnader | I5: Startdato | J5: Sluttdato | K5: Status | L5: Alternativ beskrivelse
B6: T002 | C6: Planning permission | D6: T003 | E6: kritisk | F6: Start | G6: FE | I6: 46174 | J6: 46209 | K6: Fullført | L6: Kritisk bane: Yes; varighet: 6 uker; timer: 0; faktisk kostnad: 0
B7: T003 | C7: Wait for planning permission | D7: T007 | E7: kritisk | F7: Prosess | G7: FE | H7: 100 | I7: 46216 | J7: 46279 | K7: Pågår | L7: Kritisk bane: Yes; varighet: 10 uker; timer: 0; faktisk kostnad: 100
B8: T006 | C8: Dig trench | D8: T015 | E8: kritisk | F8: Prosess | G8: NN | H8: 350 | I8: 46286 | J8: 46286 | K8: Ikke startet | L8: Kritisk bane: Yes; varighet: 1 uker; timer: 4; faktisk kostnad: 400
B9: T007 | C9: Hire digger | D9: T006 | E9: kritisk | F9: Prosess | G9: FE | I9: 46293 | J9: 46300 | K9: Ikke startet | L9: Kritisk bane: Yes; varighet: 2 uker; timer: 0; faktisk kostnad: 0
B10: T009 | C10: Fill with concrete | D10: T010 | E10: kritisk | F10: Start | G10: NN | H10: 700 | I10: 46307 | J10: 46307 | K10: Ikke startet | L10: Kritisk bane: Yes; varighet: 1 uker; timer: 3; faktisk kostnad: 800
B11: T010 | C11: Level the base | D11: T016 | E11: kritisk | F11: Prosess | G11: NN | H11: 100 | I11: 46314 | J11: 46314 | K11: Ikke startet | L11: Kritisk bane: Yes; varighet: 1 uker; timer: 5; faktisk kostnad: 100
B12: T017 | C12: the Finish | F12: Slutt | G12: FE | H12: 8000 | I12: 46321 | J12: 46342 | K12: Ikke startet | L12: Kritisk bane: Yes; varighet: 4 uker; timer: 34; faktisk kostnad: 8500
B13: T019 | C13: Delivery | D13: T014 | E13: kritisk | F13: Start | G13: NN | I13: 46321 | J13: 46321 | K13: Ikke startet | L13: Kritisk bane: Yes; varighet: 0 uker; timer: 0; faktisk kostnad: 0
B14: T001 | C14: Check funds | D14: T004 | E14: flyt | F14: Start | G14: FE | I14: 46181 | J14: 46181 | K14: Fullført | L14: Kritisk bane: Float; varighet: 0 uker; timer: 0; faktisk kostnad: 0
B15: T004 | C15: Demolish old shed | D15: T005 | E15: flyt | F15: Prosess | G15: NN | H15: 300 | I15: 46188 | J15: 46188 | K15: Ikke startet | L15: Kritisk bane: Float; varighet: 1 uker; timer: 6; faktisk kostnad: 300
B16: T005 | C16: Cut foliage back | D16: T006 | E16: flyt | F16: Prosess | G16: NN | H16: 500 | I16: 46223 | J16: 46244 | K16: Ikke startet | L16: Kritisk bane: Float; varighet: 4 uker; timer: 10; faktisk kostnad: 500
B17: T008 | C17: Connect Power | D17: T017 | E17: flyt | F17: Prosess | G17: NN | I17: 46258 | J17: 46258 | K17: Ikke startet | L17: Kritisk bane: Float; varighet: ikke angitt; timer: 0; faktisk kostnad: 0
B18: T011 | C18: Find suppliers | D18: T012 | E18: flyt | F18: Start | G18: FE | I18: 46195 | J18: 46195 | K18: Fullført | L18: Kritisk bane: Float; varighet: 1 uker; timer: 0; faktisk kostnad: 0
B19: T012 | C19: Get quotes | D19: T013 | E19: flyt | F19: Prosess | G19: FE | I19: 46216 | J19: 46230 | K19: Ikke startet | L19: Kritisk bane: Float; varighet: 3 uker; timer: 0; faktisk kostnad: 0
B20: T013 | C20: Buy the shed | F20: Slutt | G20: FE | H20: 8000 | I20: 46223 | J20: 46223 | K20: Ikke startet | L20: Kritisk bane: Float; varighet: 0 uker; timer: 0; faktisk kostnad: 8000
B21: T014 | C21: Wait for Delivery | D21: T016 | E21: flyt | F21: Prosess | G21: FE | I21: 46216 | J21: 46251 | K21: Ikke startet | L21: Kritisk bane: Float; varighet: 6 uker; timer: 0; faktisk kostnad: 0
B22: T015 | C22: Wire down the garden | D22: T008 | E22: flyt | F22: Prosess | G22: NN | I22: 46321 | J22: 46321 | K22: Ikke startet | L22: Kritisk bane: Float; varighet: 1 uker; timer: 8; faktisk kostnad: 0
B23: T016 | C23: Assembly | F23: Slutt | G23: NN | H23: 750 | I23: 46328 | J23: 46328 | K23: Ikke startet | L23: Kritisk bane: Float; varighet: 1 uker; timer: 0; faktisk kostnad: 750

Sheet Flytskjema
A1: Flytskjema: New Garden Shed
A2: Bokser er hentet fra Prosesskart-tabellen. Grønn = fullført, gul = pågår, blå = ikke startet. Rød farge på pil/ramme markerer kritisk bane.
A4: Flyten går fra venstre mot høyre basert på ID for neste trinn i Prosesskart.
A28: Metrikk | B28: Verdi | D28: Status | E28: Antall
A29: Prosess-steg | B29: 18 | D29: Fullført | E29: 3
A30: Koblinger | B30: 15 | D30: Pågår | E30: 1
A31: Sluttpunkter | B31: 3 | D31: Ikke startet | E31: 14

Sheet Prøveversjon av Visio
B2: Vil du prøve denne funksjonen?
B3: Prøv Visio-abonnement 2 gratis!

Sheet Notater

Sheet Tilordning av figurnotasjon
A1: Figurnotasjon | B1: Representasjon
A2: Prosess
A3: Beslutning
A4: Delprosess
A5: Start
A6: Slutt
A7: Dokument
A8: Data
A9: Database
A10: Eksterne data
A11: Referanse til samme side
A12: Referanse til andre sider
A13: Egendefinert 1
... A16: Egendefinert 4
