Workbook

Sheet Cover
A1: Office Fit-Out Project Control Workbook
A2: PM-EVM compliant workbook map: setup controls, task plan, Gantt, EVM S-curve, dashboard, source dimensions, and fact tables.
A4: Sheet | B4: Purpose | D4: Tab Color Legend
A5: Setup | B5: Project-level controls: project metadata, status date, reporting period, and RAG thresholds. | D5: Color | E5: Category | F5: Sheets
A6: Task Plan | B6: Integrated WBS/task control table linking baseline dates, BAC, progress, AC, EV, variances, forecasts, and RAG status. | E6: Navigation / Reference | F6: Cover, Glossary
A7: EVM | B7: Weekly EVM reporting table with cumulative PV, AC, EV, SV, CV, SPI, CPI, EAC, ETC, and VAC. | E7: Method / Governance | F7: Method Roadmap, PID, PM-EVM Compliance, Review
A8: EVM Charts | B8: Baseline Gantt schedule and EVM S-curve generated from the same WBS, budget, progress, and actual-cost data. | E8: Controls / Planning | F8: Setup, Task Plan, Task Capture, Resource Grid
A9: EVM Dashboard | B9: Management view with KPI tiles, WBS performance breakdown, trends, and RAG coloring. | E9: Management Outputs | F9: EVM Dashboard, EVM, EVM Charts
A10: PM-EVM Compliance | B10: Checklist mapping the workbook to the attached PM-EVM guideline. | E10: Dimension Data | F10: Dim_Project, Dim_WBS, Dim_Resource, Dim_Calendar
A11: Dim_* / Fact_* | B11: Star-schema source data used by the live formulas and charts. | E11: Fact Data | F11: Fact_Baseline_PV, Fact_Actual_Costs, Fact_Physical_Progress
A12: Glossary | B12: Definitions for the EVM, WBS, Gantt, schedule, cost, RAG, and data-model terms used in the workbook.
A13: Method Roadmap | B13: 12-step project management method mapped to workbook sheets and current project controls. | D13: Input / Control / Output Classification
A14: PID | B14: Project Initiation Document template with business case, scope, controls, risk and financial sections. | D14: Class | E14: Meaning | F14: Sheets
A15: Task Capture | B15: Task-list brainstorming sheet based on the attached list-the-tasks method, linked to current WBS. | D15: Input | E15: Source data or user-entered templates that feed calculations. | F15: Dim_Project, Dim_WBS, Dim_Resource, Dim_Calendar, Fact_Baseline_PV, Fact_Actual_Costs, Fact_Physical_Progress, PID, Task Capture, Review
A16: Resource Grid | B16: Weekly hours/cost resource allocation grid adapted from the attached Gantt template. | D16: Control | E16: Assumptions, governance, validation, methods, and planning logic that manage how inputs are interpreted. | F16: Setup, Method Roadmap, PM-EVM Compliance, Task Plan, Resource Grid
A17: Review | B17: GOOD / BAD / BETTER review template and action log. | D17: Output | E17: Management-facing reports, charts, dashboards, and reference views produced from inputs and controls. | F17: Cover, Glossary, EVM Dashboard, EVM, EVM Charts
A18: Garden Gantt Model | B18: Attached garden-office Gantt template implemented with current project weekly hours and cost data.
A19: PERT Diagram | B19: Visio-style PERT network diagram reflecting the current WBS, schedule, progress and RAG status. | D19: Sheet | E19: Class | F19: Reason
D20: Cover | E20: Output | F20: Workbook navigation and summary.
D21: Glossary | E21: Output
D22: Review | E22: Input
D23: Setup | E23: Control
D24: PID | E24: Input
D25: Method Roadmap | E25: Control
D26: PM-EVM Compliance | E26: Control
D27: Task Plan | E27: Control
D28: Task Capture | E28: Input
D29: EVM Dashboard | E29: Output
D30: Resource Grid | E30: Control
D31: Dim_Project | E31: Input
D32: Dim_WBS | E32: Input
... D39: EVM Charts | E39: Output

Sheet Glossary
A1: Project Control Glossary
A2: Definitions for the EVM, WBS, Gantt, schedule, cost, and RAG terms used across this workbook.
A4: Category | B4: Term | C4: Abbrev. | D4: Definition | E4: Workbook reference
A5: Project setup | B5: Project Start | D5: Approved start date for the project control baseline. | E5: Setup!B7 / Dim_Project!C2
A6: Project setup | B6: Project End | D6: Approved planned end date for the project. | E6: Setup!B8 / Dim_Project!D2
A7: Project setup | B7: Status Date | D7: Cut-off date for reported progress, actual costs, and EVM metrics. | E7: Setup!B9 / EVM Dashboard!B4
A8: Scope / WBS | B8: Work Breakdown Structure | C8: WBS | D8: Hierarchical breakdown of project scope into controllable work packages or activities. | E8: Dim_WBS / Task Plan
A9: Scope / WBS | B9: WBS ID | D9: Unique identifier used to connect WBS activities to baseline PV, actual costs, and progress facts. | E9: Dim_WBS!A:A
A10: Scope / WBS | B10: Activity / Task | D10: A controllable unit of project work with budget, schedule, progress, and cost tracking. | E10: Task Plan!C:C
A11: Schedule | B11: Baseline Start | D11: Planned start date for a WBS activity from the approved baseline. | E11: Task Plan!E:E
A12: Schedule | B12: Baseline Finish | D12: Planned finish date for a WBS activity from the approved baseline. | E12: Task Plan!F:F
A13: Schedule | B13: Duration Days | D13: Calendar-day span between baseline start and finish dates. | E13: Task Plan!G:G
A14: Schedule | B14: Gantt Chart | D14: Timeline chart showing planned activity timing and duration by WBS activity. | E14: EVM Charts!Gantt Schedule
A15: Cost / EVM | B15: Budget at Completion | C15: BAC | D15: Approved total budget for the project or WBS activity. | E15: Setup!B11 / Task Plan!H:H
A16: Cost / EVM | B16: Planned Value | C16: PV | D16: Budgeted value of work planned to be complete by a given date. | E16: Task Plan!I:I / EVM!C:C
A17: Cost / EVM | B17: Actual Cost | C17: AC | D17: Actual cost incurred by a given date. | E17: Task Plan!J:J / EVM!D:D
A18: Cost / EVM | B18: Physical Progress | C18: Progress % | D18: Latest reported percent complete for each WBS activity as of the status date. | E18: Task Plan!K:K
A19: Cost / EVM | B19: Earned Value | C19: EV | D19: Budgeted value of the work actually completed; calculated as BAC × progress. | E19: Task Plan!L:L / EVM!E:E
A20: Variance | B20: Schedule Variance | C20: SV | D20: EV minus PV; negative means less work completed than planned. | E20: Task Plan!M:M / EVM!F:F
A21: Variance | B21: Cost Variance | C21: CV | D21: EV minus AC; negative means cost overrun for completed work. | E21: Task Plan!N:N / EVM!G:G
A22: Performance index | B22: Schedule Performance Index | C22: SPI | D22: EV divided by PV; below 1.0 indicates unfavorable schedule efficiency. | E22: Task Plan!O:O / EVM!H:H
A23: Performance index | B23: Cost Performance Index | C23: CPI | D23: EV divided by AC; below 1.0 indicates unfavorable cost efficiency. | E23: Task Plan!P:P / EVM!I:I
A24: Forecast | B24: Estimate at Completion | C24: EAC | D24: Forecast final project or WBS cost, typically BAC divided by CPI. | E24: Task Plan!Q:Q / EVM!K:K
A25: Forecast | B25: Estimate to Complete | C25: ETC | D25: Forecast remaining cost to complete the work; EAC minus AC. | E25: Task Plan!R:R / EVM!L:L
A26: Forecast | B26: Variance at Completion | C26: VAC | D26: Expected budget variance at completion; BAC minus EAC. | E26: Task Plan!S:S / EVM!M:M
A27: Chart | B27: EVM S-Curve | D27: Line chart comparing cumulative PV, EV, and AC over time. | E27: EVM Charts!EVM S-Curve
A28: RAG | B28: Green | D28: Good condition: on/above plan, favorable variance, or acceptable performance threshold. | E28: Setup!A18:D18
A29: RAG | B29: Amber | D29: Watch condition: close to threshold or mid-progress; monitor closely. | E29: Setup!A19:D19
A30: RAG | B30: Red | D30: Action condition: negative variance, low progress, CPI/SPI below threshold, or overrun. | E30: Setup!A20:D20
A31: Reporting | B31: Dashboard | D31: Management summary view showing KPIs, WBS performance, trend data, and RAG status. | E31: EVM Dashboard!A1:P47
A32: Reporting | B32: Tie-out | D32: Validation that dashboard KPIs match the detailed EVM reporting table at the status date. | E32: EVM!H19:M25
A33: Data model | B33: Dimension Table | C33: Dim | D33: Reference table describing projects, WBS, resources, or calendar dates. | E33: Dim_Project / Dim_WBS / Dim_Resource / Dim_Calendar
A34: Data model | B34: Fact Table | C34: Fact | D34: Transaction or event table containing planned values, actual costs, or progress observations. | E34: Fact_Baseline_PV / Fact_Actual_Costs / Fact_Physical_Progress
A36: Workbook classification | B36: Input | D36: Source data or user-entered content that feeds project calculations and reports. | E36: Cover!D13:H39
A37: Workbook classification | B37: Control | D37: Assumptions, thresholds, validation, governance, and planning logic used to interpret inputs. | E37: Cover!D13:H39
A38: Workbook classification | B38: Output | D38: Reports, charts, dashboards, and references produced from the input data and control logic. | E38: Cover!D13:H39

Sheet Review
A1: Project Review & Lessons
A2: Review template from attachment: GOOD / BAD / BETTER plus action log for plan adjustments and lessons learned.
A4: Project Description | B4: =Dim_Project!B2 -> Office Fit-Out
A5: Project Period | B5: =TEXT(Dim_Project!C2,"yyyy-mm-dd")&" to "&TEXT(Dim_Project!D2,"yyyy-mm-dd") -> 2026-05-04 to 2026-07-26
A6: Status Date | B6: =Setup!B9 -> 46203
A7: Review Owner | B7: Frank Ellingsen
A8: Review Date | B8: =TODAY() -> 46238
A10: GOOD — what went well that others should repeat?
A15: BAD — what mistakes were made or unexpected issues occurred?
A20: BETTER / ACTION LOG | B20: Owner | C20: Due date | D20: Decision required? | E20: RAG | F20: Linked workbook evidence
A21: Investigate schedule slippage driving SPI below 1.0 | B21: Project Controls | D21: Yes | E21: Red | F21: EVM Dashboard!J10 / Task Plan!O17
A22: Review cost efficiency and current EAC forecast | B22: Project Controls | D22: Yes | E22: Red | F22: EVM Dashboard!G10 / Task Plan!Q17
A23: Confirm mitigation for red WBS activities in Gantt | B23: Project Manager | D23: Yes | E23: Red | F23: EVM Charts!Gantt Schedule
A24: Check future material/subcontractor dependencies | B24: Planner | D24: No | E24: Amber | F24: Task Plan / Resource Grid
A25: Capture lessons from completed WBS items | B25: Project Team | D25: No | E25: Amber | F25: Task Capture / Review
A30: Review source | B30: 13.1.2 Review Template.pdf

Sheet PID
A1: Project Initiation Document (PID)
A2: PID template from the attached method, prefilled with current workbook metadata where available. Fill yellow cells during project definition.
A4: Project header
A5: Project Name | B5: =Dim_Project!B2 -> Office Fit-Out
A6: Project Number | B6: =Dim_Project!A2 -> P101
A7: Project Risk Level | B7: H/M/L
A8: Prepared by | B8: Frank Ellingsen
A9: Date | B9: =TODAY() -> 46238
A10: Persons consulted
A11: Key Driver | B11: Cost / Quality / Time
A13: 1. Business Case
A14: Why this project; why now; options considered; what if we do not do it; benefits; payback period.
A18: 2.1 In Scope / Included
A19: Work and deliverables included in the project.
A23: 2.2 Out of Scope / Excluded
A24: Work explicitly excluded from the project.
A28: 2.3 Dependencies
A29: How the project impacts or is impacted by other projects or programmes.
A33: 2.4 Constraints
A34: Deadlines, budget limits, resource limitations or other delivery constraints.
A38: 2.5 Assumptions
A39: Assumptions currently being used for planning.
... A49: How progress will be reported, frequency, method and responsibility.
A53: Frequency / timing | B53: How control is reported | C53: Responsibility | D53: Next report date | E53: Status
A54: Weekly | B54: EVM Dashboard + EVM Charts | C54: Project Controls | E54: Active
A55: Stage end | B55: PID / Review pack | C55: Project Manager | E55: Planned
A56: Monthly | B56: Board summary | C56: Project Manager | E56: Planned
A58: 5. Risk Control
A59: Project risks and containment measures.
A63: Project Risk | B63: Containment Measures | C63: Owner | D63: Due Date | E63: RAG
A64: Schedule slippage | B64: Monitor SPI and Gantt status line; escalate red WBS tasks. | C64: Project Controls | E64: Red
A65: Cost overrun | B65: Monitor CPI/CV/EAC and review WBS cost drivers. | C65: Project Controls | E65: Red
A66: Resource availability | B66: Use weekly Resource Grid to identify conflicts. | C66: Resource Manager | E66: Amber
A67: Scope creep | B67: Confirm in/out of scope and change-control route in PID. | C67: Project Manager | E67: Amber
A68: Quality issue | B68: Define acceptance criteria and quality checks by task. | C68: Project Manager | E68: Amber
A69: Supplier delay | B69: Track procurement/material activities and delivery milestones. | C69: Project Manager | E69: Amber
A72: 6. Financial Implications
A73: Quarterly/annual financial profile adapted from the PID template; Year 1 is linked to the current baseline planned value.
A74: Financial Implications | B74: Q1 | C74: Q2 | D74: Q3 | E74: Q4 | F74: Total
A75: Amount Year 1 | B75: =SUMIFS(Fact_Baseline_PV!$C$2:$C$44,Fact_Baseline_PV!$A$2:$A$44,"<="&DATE(2026,6,30)) -> 220233.34 | C75: =SUMIFS(Fact_Baseline_PV!$C$2:$C$44,Fact_Baseline_PV!$A$2:$A$44,">"&DATE(2026,6,30),Fact_Baseline_PV!$A$2:$A$44,"<="&DATE(2026,9,30)) -> 48416.66 | D75: 0 | E75: 0 | F75: =SUM(B75:E75) -> 268650
A76: Amount Year 2 | B76: 0 | C76: 0 | D76: 0 | E76: 0 | F76: =SUM(B76:E76) -> 0
A77: Amount Year 3 | B77: 0 | C77: 0 | D77: 0 | E77: 0 | F77: =SUM(B77:E77) -> 0
A78: Amount Year 4 | B78: 0 | C78: 0 | D78: 0 | E78: 0 | F78: =SUM(B78:E78) -> 0
A79: Amount Year 5 | B79: 0 | C79: 0 | D79: 0 | E79: 0 | F79: =SUM(B79:E79) -> 0

Sheet Method Roadmap
A1: 12-Step Project Management Method Roadmap
A2: Course method embedded into the workbook: define, list, sequence, estimate, check, Gantt, resource, risk, monitor progress/cost, adjust, and review.
A4: Step | B4: Method step | C4: Purpose | D4: Workbook implementation | E4: Primary sheet / range | F4: Owner | G4: Status | H4: Source
A5: 1 | B5: Define the project | C5: Create the project definition and controls. | D5: PID template added with live project metadata. | E5: PID!A1:H50 | F5: Project Manager | G5: Active | H5: 1.2 12 Step Process / 2.1.2 PID template
A6: 2 | B6: List the tasks | C6: Capture all tasks without initially worrying about order, cost, or time. | D6: Task Capture sheet added; WBS imported from current Dim_WBS and grouped by type. | E6: Task Capture!A4:J18 | F6: Project Team | G6: Active | H6: 3.1.5 List the Tasks / 4.1 List of Tasks
A7: 3 | B7: Establish task order | C7: Convert brainstormed tasks into planned sequencing. | D7: Task Plan and Gantt use WBS order and baseline dates. | E7: Task Plan!A4:T17 | F7: Planner | G7: Active | H7: 1.2 12 Step Process
A8: 4 | B8: Estimate time | C8: Estimate duration by task. | D8: Baseline start, finish, and duration calculated per WBS. | E8: Task Plan!E5:G17 | F8: Planner | G8: Active | H8: 1.2 12 Step Process
A9: 5 | B9: Margin check & reality check | C9: Check whether dates, budget, and resource assumptions are feasible. | D9: Status tie-out, EVM checks, and RAG indicators added. | E9: EVM!H19:M25 | F9: Project Controls | G9: Active | H9: 1.2 12 Step Process
A10: 6 | B10: Gantt Chart | C10: Show planned timing and status. | D10: Gantt chart with RAG bars and status-date marker exists. | E10: EVM Charts!Gantt Schedule | F10: Project Controls | G10: Active | H10: 8.1.2 Gantt templates
A11: 7 | B11: Resource allocation | C11: Map tasks to people/resources and weekly loading. | D11: Resource Grid added with weekly hours and costs by WBS. | E11: Resource Grid!A4:Z35 | F11: Resource Manager | G11: Active | H11: 8.1.2 Gantt template from garden office
A12: 8 | B12: Predicting & reducing risk | C12: Identify project risks and containment measures. | D12: PID risk-control register added. | E12: PID!A63:E70 | F12: Project Manager | G12: Template ready | H12: 2.1.2 PID template
A13: 9 | B13: Monitoring progress | C13: Track completion against plan. | D13: Progress is linked from Fact_Physical_Progress to Task Plan and dashboard. | E13: Task Plan!K5:K17 | F13: Project Controls | G13: Active | H13: 1.2 12 Step Process
A14: 10 | B14: Monitoring cost | C14: Track actual cost and forecast. | D14: EVM reporting monitors AC, CV, CPI, EAC, ETC, VAC. | E14: EVM!A4:N16 | F14: Project Controls | G14: Active | H14: 1.2 12 Step Process
A15: 11 | B15: Adjusting the plan | C15: Use EVM and RAG exceptions to trigger decisions. | D15: Decision/action log added to Review. | E15: Review!A20:F28 | F15: Project Board | G15: Template ready | H15: 1.2 12 Step Process
A16: 12 | B16: Review & lessons | C16: Capture good, bad, better after delivery. | D16: Review sheet added with GOOD / BAD / BETTER structure. | E16: Review!A4:F17 | F16: Project Team | G16: Template ready | H16: 13.1.2 Review Template

Sheet PM-EVM Compliance
A1: PM-EVM Compliance Checklist
A2: Workbook compliance map against the attached PM-EVM guideline: WBS, Gantt, EVM, dashboard, live formulas, and exception-focused reporting.
A4: Guideline requirement | B4: Workbook implementation | C4: Location | D4: Status | E4: Evidence
A5: Setup controls: project metadata, status date, reporting period, rates/thresholds | B5: Added setup control sheet with live project metadata and thresholds | C5: Setup!A4:D20 | D5: Compliant | E5: PM-EVM.md lines 117-126
A6: Task Plan as integrated WBS/task control view | B6: Added live task table combining WBS, dates, BAC, PV, AC, progress, EV, variances, forecasts and RAG | C6: Task Plan!A4:T17 | D6: Compliant | E6: PM-EVM.md lines 120-125
A7: Gantt display tied to WBS baseline dates | B7: Existing EVM Charts Gantt uses WBS activities, baseline start/finish and duration | C7: EVM Charts!Gantt Schedule | D7: Compliant | E7: PM-EVM.md lines 122-125
A8: EVM by reporting period with PV, EV, AC, SV, CV, SPI, CPI, BAC, EAC, ETC, VAC | B8: Added EVM reporting table with weekly live formulas | C8: EVM!A4:N16 | D8: Compliant | E8: PM-EVM.md lines 123-124
A9: S-curve shows cumulative PV, EV, and AC over time | B9: Existing EVM S-curve chart is sourced from weekly cumulative helper table | C9: EVM Charts!EVM S-Curve | D9: Compliant | E9: PM-EVM.md lines 50-54
A10: Dashboard summarizes management KPIs and top WBS exceptions | B10: Existing dashboard has KPI tiles, WBS table, RAG, variance/status fields | C10: EVM Dashboard!A1:P47 | D10: Compliant | E10: PM-EVM.md lines 781-785
A11: Exception-focused reporting with RAG / traffic-light indicators | B11: RAG rules applied across performance indices, progress, variances, and status cells | C11: EVM Dashboard, Task Plan, EVM | D11: Compliant | E11: PM-EVM.md lines 781-785
A12: Consistent WBS codes, budgets, dates, and actuals across views | B12: Task Plan, EVM, Gantt and dashboard all reference Dim_WBS and fact tables | C12: Dim_WBS / Fact_* | D12: Compliant | E12: PM-EVM.md lines 270-274
A13: Validate formulas and totals | B13: Added formula validation and status-date tie-out to dashboard KPIs | C13: EVM!H19:M25 | D13: Compliant | E13: PM-EVM.md lines 783-785

Sheet Setup
A1: Setup Controls
A2: Single place to review project metadata, status date, reporting period, and RAG thresholds used by the control workbook.
A4: Control | B4: Value
A5: Project ID | B5: =Dim_Project!A2 -> P101
A6: Project Name | B6: =Dim_Project!B2 -> Office Fit-Out
A7: Project Start | B7: =Dim_Project!C2 -> 46146
A8: Project End | B8: =Dim_Project!D2 -> 46229
A9: Status Date | B9: ='EVM Dashboard'!B4 -> 46203
A10: Reporting Period | B10: Weekly
A11: Budget at Completion (BAC) | B11: =SUM(Dim_WBS!E:E) -> 268650
A12: CPI/SPI Red Threshold | B12: 0.95
A13: CPI/SPI Green Threshold | B13: 1
A14: Progress Amber Threshold | B14: 0.5
A15: Progress Green Threshold | B15: 0.8
A17: RAG | B17: Metric | C17: Rule | D17: Interpretation
A18: Green | B18: CPI/SPI | C18: >= 1.00 | D18: On or above plan
A19: Amber | B19: CPI/SPI | C19: 0.95 to < 1.00 | D19: Near threshold / watch
A20: Red | B20: CPI/SPI | C20: < 0.95 | D20: Action required

Sheet Task Plan
A1: Task Plan
A2: Integrated WBS control table: one live task-level view for scope, schedule, budget, progress, actuals, forecasts, and RAG status.
A4: WBS ID | B4: WBS Code | C4: Task / Activity | D4: Type | E4: Baseline Start | F4: Baseline Finish | G4: Duration Days | H4: BAC (NOK) | I4: PV @ Status | J4: AC @ Status | K4: Progress % | L4: EV @ Status | M4: SV | N4: CV | O4: SPI | P4: CPI | Q4: EAC | R4: ETC | S4: VAC | T4: Status
A5: =Dim_WBS!A2 -> WBS-01 | B5: =Dim_WBS!B2 -> 1 | C5: =Dim_WBS!C2 -> Project Management | D5: =Dim_WBS!D2 -> Labor | E5: =_xlfn.MINIFS(Fact_Baseline_PV!$A:$A,Fact_Baseline_PV!$B:$B,A5) -> 46146 | F5: =_xlfn.MAXIFS(Fact_Baseline_PV!$A:$A,Fact_Baseline_PV!$B:$B,A5)+6 -> 46229 | G5: =F5-E5+1 -> 84 | H5: =Dim_WBS!E2 -> 18000 | I5: =SUMIFS(Fact_Baseline_PV!$C:$C,Fact_Baseline_PV!$B:$B,A5,Fact_Baseline_PV!$A:$A,"<="&Setup!$B$9) -> 13500 | J5: =SUMIFS(Fact_Actual_Costs!$D:$D,Fact_Actual_Costs!$B:$B,A5,Fact_Actual_Costs!$A:$A,"<="&Setup!$B$9) -> 9600 | K5: {=IFERROR(LOOKUP(2,1/(Fact_Physical_Progress!$B$2:$B$35=A5)/(Fact_Physical_Progress!$A$2:$A$35<=Setup!$B$9),Fact_Physical_Progress!$C$2:$C$35),0)} -> 0.5 | L5: =H5*K5 -> 9000 | M5: =L5-I5 -> -4500 | N5: =L5-J5 -> -600 | O5: =IFERROR(L5/I5,1) -> 0.66666667 | P5: =IFERROR(L5/J5,1) -> 0.9375 | Q5: =IF(P5>0,H5/P5,H5) -> 19200 | R5: =Q5-J5 -> 9600 | S5: =H5-Q5 -> -1200 | T5: =IF(OR(N5<0,P5<Setup!$B$12,O5<Setup!$B$12),"Red",IF(OR(P5<Setup!$B$13,O5<Setup!$B$13),"Amber","Green")) -> Red
A6: =Dim_WBS!A3 -> WBS-02 | B6: =Dim_WBS!B3 -> 2 | C6: =Dim_WBS!C3 -> Site Survey & Mobilization | D6: =Dim_WBS!D3 -> Labor | E6: =_xlfn.MINIFS(Fact_Baseline_PV!$A:$A,Fact_Baseline_PV!$B:$B,A6) -> 46146 | F6: =_xlfn.MAXIFS(Fact_Baseline_PV!$A:$A,Fact_Baseline_PV!$B:$B,A6)+6 -> 46152 | G6: =F6-E6+1 -> 7 | H6: =Dim_WBS!E3 -> 8500 | I6: =SUMIFS(Fact_Baseline_PV!$C:$C,Fact_Baseline_PV!$B:$B,A6,Fact_Baseline_PV!$A:$A,"<="&Setup!$B$9) -> 8500 | J6: =SUMIFS(Fact_Actual_Costs!$D:$D,Fact_Actual_Costs!$B:$B,A6,Fact_Actual_Costs!$A:$A,"<="&Setup!$B$9) -> 8700 | K6: {=IFERROR(LOOKUP(2,1/(Fact_Physical_Progress!$B$2:$B$35=A6)/(Fact_Physical_Progress!$A$2:$A$35<=Setup!$B$9),Fact_Physical_Progress!$C$2:$C$35),0)} -> 1 | L6: =H6*K6 -> 8500 | M6: =L6-I6 -> 0 | N6: =L6-J6 -> -200 | O6: =IFERROR(L6/I6,1) -> 1 | P6: =IFERROR(L6/J6,1) -> 0.97701149 | Q6: =IF(P6>0,H6/P6,H6) -> 8700 | R6: =Q6-J6 -> 0 | S6: =H6-Q6 -> -200 | T6: =IF(OR(N6<0,P6<Setup!$B$12,O6<Setup!$B$12),"Red",IF(OR(P6<Setup!$B$13,O6<Setup!$B$13),"Amber","Green")) -> Red
A7: =Dim_WBS!A4 -> WBS-03 | B7: =Dim_WBS!B4 -> 3 | C7: =Dim_WBS!C4 -> Design & Engineering | D7: =Dim_WBS!D4 -> Labor | E7: =_xlfn.MINIFS(Fact_Baseline_PV!$A:$A,Fact_Baseline_PV!$B:$B,A7) -> 46146 | F7: =_xlfn.MAXIFS(Fact_Baseline_PV!$A:$A,Fact_Baseline_PV!$B:$B,A7)+6 -> 46166 | G7: =F7-E7+1 -> 21 | H7: =Dim_WBS!E4 -> 19200 | I7: =SUMIFS(Fact_Baseline_PV!$C:$C,Fact_Baseline_PV!$B:$B,A7,Fact_Baseline_PV!$A:$A,"<="&Setup!$B$9) -> 19200 | J7: =SUMIFS(Fact_Actual_Costs!$D:$D,Fact_Actual_Costs!$B:$B,A7,Fact_Actual_Costs!$A:$A,"<="&Setup!$B$9) -> 18195.04 | K7: {=IFERROR(LOOKUP(2,1/(Fact_Physical_Progress!$B$2:$B$35=A7)/(Fact_Physical_Progress!$A$2:$A$35<=Setup!$B$9),Fact_Physical_Progress!$C$2:$C$35),0)} -> 1 | L7: =H7*K7 -> 19200 | M7: =L7-I7 -> 0 | N7: =L7-J7 -> 1004.96 | O7: =IFERROR(L7/I7,1) -> 1 | P7: =IFERROR(L7/J7,1) -> 1.0552326 | Q7: =IF(P7>0,H7/P7,H7) -> 18195.04 | R7: =Q7-J7 -> 0 | S7: =H7-Q7 -> 1004.96 | T7: =IF(OR(N7<0,P7<Setup!$B$12,O7<Setup!$B$12),"Red",IF(OR(P7<Setup!$B$13,O7<Setup!$B$13),"Amber","Green")) -> Green
A8: =Dim_WBS!A5 -> WBS-04 | B8: =Dim_WBS!B5 -> 4 | C8: =Dim_WBS!C5 -> Procurement - Materials | D8: =Dim_WBS!D5 -> Material | E8: =_xlfn.MINIFS(Fact_Baseline_PV!$A:$A,Fact_Baseline_PV!$B:$B,A8) -> 46153 | F8: =_xlfn.MAXIFS(Fact_Baseline_PV!$A:$A,Fact_Baseline_PV!$B:$B,A8)+6 -> 46180 | G8: =F8-E8+1 -> 28 | H8: =Dim_WBS!E5 -> 42000 | I8: =SUMIFS(Fact_Baseline_PV!$C:$C,Fact_Baseline_PV!$B:$B,A8,Fact_Baseline_PV!$A:$A,"<="&Setup!$B$9) -> 42000 | J8: =SUMIFS(Fact_Actual_Costs!$D:$D,Fact_Actual_Costs!$B:$B,A8,Fact_Actual_Costs!$A:$A,"<="&Setup!$B$9) -> 41300 | K8: {=IFERROR(LOOKUP(2,1/(Fact_Physical_Progress!$B$2:$B$35=A8)/(Fact_Physical_Progress!$A$2:$A$35<=Setup!$B$9),Fact_Physical_Progress!$C$2:$C$35),0)} -> 1 | L8: =H8*K8 -> 42000 | M8: =L8-I8 -> 0 | N8: =L8-J8 -> 700 | O8: =IFERROR(L8/I8,1) -> 1 | P8: =IFERROR(L8/J8,1) -> 1.0169492 | Q8: =IF(P8>0,H8/P8,H8) -> 41300 | R8: =Q8-J8 -> 0 | S8: =H8-Q8 -> 700 | T8: =IF(OR(N8<0,P8<Setup!$B$12,O8<Setup!$B$12),"Red",IF(OR(P8<Setup!$B$13,O8<Setup!$B$13),"Amber","Green")) -> Green
A9: =Dim_WBS!A6 -> WBS-05 | B9: =Dim_WBS!B6 -> 5 | C9: =Dim_WBS!C6 -> Demolition & Prep | D9: =Dim_WBS!D6 -> Labor | E9: =_xlfn.MINIFS(Fact_Baseline_PV!$A:$A,Fact_Baseline_PV!$B:$B,A9) -> 46153 | F9: =_xlfn.MAXIFS(Fact_Baseline_PV!$A:$A,Fact_Baseline_PV!$B:$B,A9)+6 -> 46173 | G9: =F9-E9+1 -> 21 | H9: =Dim_WBS!E6 -> 13200 | I9: =SUMIFS(Fact_Baseline_PV!$C:$C,Fact_Baseline_PV!$B:$B,A9,Fact_Baseline_PV!$A:$A,"<="&Setup!$B$9) -> 13200 | J9: =SUMIFS(Fact_Actual_Costs!$D:$D,Fact_Actual_Costs!$B:$B,A9,Fact_Actual_Costs!$A:$A,"<="&Setup!$B$9) -> 13408.16 | K9: {=IFERROR(LOOKUP(2,1/(Fact_Physical_Progress!$B$2:$B$35=A9)/(Fact_Physical_Progress!$A$2:$A$35<=Setup!$B$9),Fact_Physical_Progress!$C$2:$C$35),0)} -> 1 | L9: =H9*K9 -> 13200 | M9: =L9-I9 -> 0 | N9: =L9-J9 -> -208.16 | O9: =IFERROR(L9/I9,1) -> 1 | P9: =IFERROR(L9/J9,1) -> 0.98447513 | Q9: =IF(P9>0,H9/P9,H9) -> 13408.16 | R9: =Q9-J9 -> 0 | S9: =H9-Q9 -> -208.16 | T9: =IF(OR(N9<0,P9<Setup!$B$12,O9<Setup!$B$12),"Red",IF(OR(P9<Setup!$B$13,O9<Setup!$B$13),"Amber","Green")) -> Red
A10: =Dim_WBS!A7 -> WBS-06 | B10: =Dim_WBS!B7 -> 6 | C10: =Dim_WBS!C7 -> Electrical Rough-In | D10: =Dim_WBS!D7 -> Labor | E10: =_xlfn.MINIFS(Fact_Baseline_PV!$A:$A,Fact_Baseline_PV!$B:$B,A10) -> 46167 | F10: =_xlfn.MAXIFS(Fact_Baseline_PV!$A:$A,Fact_Baseline_PV!$B:$B,A10)+6 -> 46187 | G10: =F10-E10+1 -> 21 | H10: =Dim_WBS!E7 -> 26000 | I10: =SUMIFS(Fact_Baseline_PV!$C:$C,Fact_Baseline_PV!$B:$B,A10,Fact_Baseline_PV!$A:$A,"<="&Setup!$B$9) -> 26000 | J10: =SUMIFS(Fact_Actual_Costs!$D:$D,Fact_Actual_Costs!$B:$B,A10,Fact_Actual_Costs!$A:$A,"<="&Setup!$B$9) -> 26206.24 | K10: {=IFERROR(LOOKUP(2,1/(Fact_Physical_Progress!$B$2:$B$35=A10)/(Fact_Physical_Progress!$A$2:$A$35<=Setup!$B$9),Fact_Physical_Progress!$C$2:$C$35),0)} -> 0.7 | L10: =H10*K10 -> 18200 | M10: =L10-I10 -> -7800 | N10: =L10-J10 -> -8006.24 | O10: =IFERROR(L10/I10,1) -> 0.7 | P10: =IFERROR(L10/J10,1) -> 0.69449108 | Q10: =IF(P10>0,H10/P10,H10) -> 37437.486 | R10: =Q10-J10 -> 11231.246 | S10: =H10-Q10 -> -11437.486 | T10: =IF(OR(N10<0,P10<Setup!$B$12,O10<Setup!$B$12),"Red",IF(OR(P10<Setup!$B$13,O10<Setup!$B$13),"Amber","Green")) -> Red
A11: =Dim_WBS!A8 -> WBS-07 | B11: =Dim_WBS!B8 -> 7 | C11: =Dim_WBS!C8 -> HVAC Installation | D11: =Dim_WBS!D8 -> Subcontractor | E11: =_xlfn.MINIFS(Fact_Baseline_PV!$A:$A,Fact_Baseline_PV!$B:$B,A11) -> 46174 | F11: =_xlfn.MAXIFS(Fact_Baseline_PV!$A:$A,Fact_Baseline_PV!$B:$B,A11)+6 -> 46201 | G11: =F11-E11+1 -> 28 | H11: =Dim_WBS!E8 -> 36000 | I11: =SUMIFS(Fact_Baseline_PV!$C:$C,Fact_Baseline_PV!$B:$B,A11,Fact_Baseline_PV!$A:$A,"<="&Setup!$B$9) -> 36000 | J11: =SUMIFS(Fact_Actual_Costs!$D:$D,Fact_Actual_Costs!$B:$B,A11,Fact_Actual_Costs!$A:$A,"<="&Setup!$B$9) -> 17476.8 | K11: {=IFERROR(LOOKUP(2,1/(Fact_Physical_Progress!$B$2:$B$35=A11)/(Fact_Physical_Progress!$A$2:$A$35<=Setup!$B$9),Fact_Physical_Progress!$C$2:$C$35),0)} -> 0.4 | L11: =H11*K11 -> 14400 | M11: =L11-I11 -> -21600 | N11: =L11-J11 -> -3076.8 | O11: =IFERROR(L11/I11,1) -> 0.4 | P11: =IFERROR(L11/J11,1) -> 0.82394946 | Q11: =IF(P11>0,H11/P11,H11) -> 43692 | R11: =Q11-J11 -> 26215.2 | S11: =H11-Q11 -> -7692 | T11: =IF(OR(N11<0,P11<Setup!$B$12,O11<Setup!$B$12),"Red",IF(OR(P11<Setup!$B$13,O11<Setup!$B$13),"Amber","Green")) -> Red
A12: =Dim_WBS!A9 -> WBS-08 | B12: =Dim_WBS!B9 -> 8 | C12: =Dim_WBS!C9 -> Partitions & Drywall | D12: =Dim_WBS!D9 -> Subcontractor | E12: =_xlfn.MINIFS(Fact_Baseline_PV!$A:$A,Fact_Baseline_PV!$B:$B,A12) -> 46181 | F12: =_xlfn.MAXIFS(Fact_Baseline_PV!$A:$A,Fact_Baseline_PV!$B:$B,A12)+6 -> 46208 | G12: =F12-E12+1 -> 28 | H12: =Dim_WBS!E9 -> 28000 | I12: =SUMIFS(Fact_Baseline_PV!$C:$C,Fact_Baseline_PV!$B:$B,A12,Fact_Baseline_PV!$A:$A,"<="&Setup!$B$9) -> 28000 | J12: =SUMIFS(Fact_Actual_Costs!$D:$D,Fact_Actual_Costs!$B:$B,A12,Fact_Actual_Costs!$A:$A,"<="&Setup!$B$9) -> 7099.2 | K12: {=IFERROR(LOOKUP(2,1/(Fact_Physical_Progress!$B$2:$B$35=A12)/(Fact_Physical_Progress!$A$2:$A$35<=Setup!$B$9),Fact_Physical_Progress!$C$2:$C$35),0)} -> 0.248857 | L12: =H12*K12 -> 6967.996 | M12: =L12-I12 -> -21032.004 | N12: =L12-J12 -> -131.204 | O12: =IFERROR(L12/I12,1) -> 0.248857 | P12: =IFERROR(L12/J12,1) -> 0.98151848 | Q12: =IF(P12>0,H12/P12,H12) -> 28527.226 | R12: =Q12-J12 -> 21428.026 | S12: =H12-Q12 -> -527.22648 | T12: =IF(OR(N12<0,P12<Setup!$B$12,O12<Setup!$B$12),"Red",IF(OR(P12<Setup!$B$13,O12<Setup!$B$13),"Amber","Green")) -> Red
A13: =Dim_WBS!A10 -> WBS-09 | B13: =Dim_WBS!B10 -> 9 | C13: =Dim_WBS!C10 -> Flooring | D13: =Dim_WBS!D10 -> Material | E13: =_xlfn.MINIFS(Fact_Baseline_PV!$A:$A,Fact_Baseline_PV!$B:$B,A13) -> 46195 | F13: =_xlfn.MAXIFS(Fact_Baseline_PV!$A:$A,Fact_Baseline_PV!$B:$B,A13)+6 -> 46215 | G13: =F13-E13+1 -> 21 | H13: =Dim_WBS!E10 -> 35750 | I13: =SUMIFS(Fact_Baseline_PV!$C:$C,Fact_Baseline_PV!$B:$B,A13,Fact_Baseline_PV!$A:$A,"<="&Setup!$B$9) -> 23833.34 | J13: =SUMIFS(Fact_Actual_Costs!$D:$D,Fact_Actual_Costs!$B:$B,A13,Fact_Actual_Costs!$A:$A,"<="&Setup!$B$9) -> 0 | K13: {=IFERROR(LOOKUP(2,1/(Fact_Physical_Progress!$B$2:$B$35=A13)/(Fact_Physical_Progress!$A$2:$A$35<=Setup!$B$9),Fact_Physical_Progress!$C$2:$C$35),0)} -> 0 | L13: =H13*K13 -> 0 | M13: =L13-I13 -> -23833.34 | N13: =L13-J13 -> 0 | O13: =IFERROR(L13/I13,1) -> 0 | P13: =IFERROR(L13/J13,1) -> 1 | Q13: =IF(P13>0,H13/P13,H13) -> 35750 | R13: =Q13-J13 -> 35750 | S13: =H13-Q13 -> 0 | T13: =IF(OR(N13<0,P13<Setup!$B$12,O13<Setup!$B$12),"Red",IF(OR(P13<Setup!$B$13,O13<Setup!$B$13),"Amber","Green")) -> Red
A14: =Dim_WBS!A11 -> WBS-10 | B14: =Dim_WBS!B11 -> 10 | C14: =Dim_WBS!C11 -> Fixtures & Furniture | D14: =Dim_WBS!D11 -> Material | E14: =_xlfn.MINIFS(Fact_Baseline_PV!$A:$A,Fact_Baseline_PV!$B:$B,A14) -> 46202 | F14: =_xlfn.MAXIFS(Fact_Baseline_PV!$A:$A,Fact_Baseline_PV!$B:$B,A14)+6 -> 46222 | G14: =F14-E14+1 -> 21 | H14: =Dim_WBS!E11 -> 30000 | I14: =SUMIFS(Fact_Baseline_PV!$C:$C,Fact_Baseline_PV!$B:$B,A14,Fact_Baseline_PV!$A:$A,"<="&Setup!$B$9) -> 10000 | J14: =SUMIFS(Fact_Actual_Costs!$D:$D,Fact_Actual_Costs!$B:$B,A14,Fact_Actual_Costs!$A:$A,"<="&Setup!$B$9) -> 0 | K14: {=IFERROR(LOOKUP(2,1/(Fact_Physical_Progress!$B$2:$B$35=A14)/(Fact_Physical_Progress!$A$2:$A$35<=Setup!$B$9),Fact_Physical_Progress!$C$2:$C$35),0)} -> 0 | L14: =H14*K14 -> 0 | M14: =L14-I14 -> -10000 | N14: =L14-J14 -> 0 | O14: =IFERROR(L14/I14,1) -> 0 | P14: =IFERROR(L14/J14,1) -> 1 | Q14: =IF(P14>0,H14/P14,H14) -> 30000 | R14: =Q14-J14 -> 30000 | S14: =H14-Q14 -> 0 | T14: =IF(OR(N14<0,P14<Setup!$B$12,O14<Setup!$B$12),"Red",IF(OR(P14<Setup!$B$13,O14<Setup!$B$13),"Amber","Green")) -> Red
A15: =Dim_WBS!A12 -> WBS-11 | B15: =Dim_WBS!B12 -> 11 | C15: =Dim_WBS!C12 -> Testing / Commissioning | D15: =Dim_WBS!D12 -> Labor | E15: =_xlfn.MINIFS(Fact_Baseline_PV!$A:$A,Fact_Baseline_PV!$B:$B,A15) -> 46216 | F15: =_xlfn.MAXIFS(Fact_Baseline_PV!$A:$A,Fact_Baseline_PV!$B:$B,A15)+6 -> 46229 | G15: =F15-E15+1 -> 14 | H15: =Dim_WBS!E12 -> 8400 | I15: =SUMIFS(Fact_Baseline_PV!$C:$C,Fact_Baseline_PV!$B:$B,A15,Fact_Baseline_PV!$A:$A,"<="&Setup!$B$9) -> 0 | J15: =SUMIFS(Fact_Actual_Costs!$D:$D,Fact_Actual_Costs!$B:$B,A15,Fact_Actual_Costs!$A:$A,"<="&Setup!$B$9) -> 0 | K15: {=IFERROR(LOOKUP(2,1/(Fact_Physical_Progress!$B$2:$B$35=A15)/(Fact_Physical_Progress!$A$2:$A$35<=Setup!$B$9),Fact_Physical_Progress!$C$2:$C$35),0)} -> 0 | L15: =H15*K15 -> 0 | M15: =L15-I15 -> 0 | N15: =L15-J15 -> 0 | O15: =IFERROR(L15/I15,1) -> 1 | P15: =IFERROR(L15/J15,1) -> 1 | Q15: =IF(P15>0,H15/P15,H15) -> 8400 | R15: =Q15-J15 -> 8400 | S15: =H15-Q15 -> 0 | T15: =IF(OR(N15<0,P15<Setup!$B$12,O15<Setup!$B$12),"Red",IF(OR(P15<Setup!$B$13,O15<Setup!$B$13),"Amber","Green")) -> Green
A16: =Dim_WBS!A13 -> WBS-12 | B16: =Dim_WBS!B13 -> 12 | C16: =Dim_WBS!C13 -> Handover & Closeout | D16: =Dim_WBS!D13 -> Labor | E16: =_xlfn.MINIFS(Fact_Baseline_PV!$A:$A,Fact_Baseline_PV!$B:$B,A16) -> 46223 | F16: =_xlfn.MAXIFS(Fact_Baseline_PV!$A:$A,Fact_Baseline_PV!$B:$B,A16)+6 -> 46229 | G16: =F16-E16+1 -> 7 | H16: =Dim_WBS!E13 -> 3600 | I16: =SUMIFS(Fact_Baseline_PV!$C:$C,Fact_Baseline_PV!$B:$B,A16,Fact_Baseline_PV!$A:$A,"<="&Setup!$B$9) -> 0 | J16: =SUMIFS(Fact_Actual_Costs!$D:$D,Fact_Actual_Costs!$B:$B,A16,Fact_Actual_Costs!$A:$A,"<="&Setup!$B$9) -> 0 | K16: {=IFERROR(LOOKUP(2,1/(Fact_Physical_Progress!$B$2:$B$35=A16)/(Fact_Physical_Progress!$A$2:$A$35<=Setup!$B$9),Fact_Physical_Progress!$C$2:$C$35),0)} -> 0 | L16: =H16*K16 -> 0 | M16: =L16-I16 -> 0 | N16: =L16-J16 -> 0 | O16: =IFERROR(L16/I16,1) -> 1 | P16: =IFERROR(L16/J16,1) -> 1 | Q16: =IF(P16>0,H16/P16,H16) -> 3600 | R16: =Q16-J16 -> 3600 | S16: =H16-Q16 -> 0 | T16: =IF(OR(N16<0,P16<Setup!$B$12,O16<Setup!$B$12),"Red",IF(OR(P16<Setup!$B$13,O16<Setup!$B$13),"Amber","Green")) -> Green
A17: Total / Project Portfolio | G17: =MAX(F5:F16)-MIN(E5:E16)+1 -> 84 | H17: =SUM(H5:H16) -> 268650 | I17: =SUM(I5:I16) -> 220233.34 | J17: =SUM(J5:J16) -> 141985.44 | K17: =SUMPRODUCT(H5:H16,K5:K16)/SUM(H5:H16) -> 0.48936533 | L17: =SUM(L5:L16) -> 131468 | M17: =SUM(M5:M16) -> -88765.344 | N17: =SUM(N5:N16) -> -10517.444 | O17: =IFERROR(L17/I17,1) -> 0.59694865 | P17: =IFERROR(L17/J17,1) -> 0.9259259 | Q17: =IF(P17>0,H17/P17,H17) -> 290142.01 | R17: =Q17-J17 -> 148156.57 | S17: =H17-Q17 -> -21492.009 | T17: =IF(OR(N17<0,P17<Setup!$B$12,O17<Setup!$B$12),"Red",IF(OR(P17<Setup!$B$13,O17<Setup!$B$13),"Amber","Green")) -> Red

Sheet Task Capture
A1: Task Capture / List the Tasks
A2: Method: first list all tasks without worrying about order, cost, or time; then group into phases and convert into the controlled Task Plan.
A4: Phase / Area | B4: Task | C4: WBS ID | D4: Type | E4: Included? | F4: Event / Milestone? | G4: Owner | H4: Notes | I4: Source / next action | J4: Mapped to Task Plan
A5: =Dim_WBS!D2 -> Labor | B5: =Dim_WBS!C2 -> Project Management | C5: =Dim_WBS!A2 -> WBS-01 | D5: =Dim_WBS!D2 -> Labor | E5: Yes | I5: Imported from current WBS | J5: =IFERROR(MATCH(C5,'Task Plan'!A:A,0),"") -> 5
A6: =Dim_WBS!D3 -> Labor | B6: =Dim_WBS!C3 -> Site Survey & Mobilization | C6: =Dim_WBS!A3 -> WBS-02 | D6: =Dim_WBS!D3 -> Labor | E6: Yes | I6: Imported from current WBS | J6: =IFERROR(MATCH(C6,'Task Plan'!A:A,0),"") -> 6
A7: =Dim_WBS!D4 -> Labor | B7: =Dim_WBS!C4 -> Design & Engineering | C7: =Dim_WBS!A4 -> WBS-03 | D7: =Dim_WBS!D4 -> Labor | E7: Yes | I7: Imported from current WBS | J7: =IFERROR(MATCH(C7,'Task Plan'!A:A,0),"") -> 7
A8: =Dim_WBS!D5 -> Material | B8: =Dim_WBS!C5 -> Procurement - Materials | C8: =Dim_WBS!A5 -> WBS-04 | D8: =Dim_WBS!D5 -> Material | E8: Yes | I8: Imported from current WBS | J8: =IFERROR(MATCH(C8,'Task Plan'!A:A,0),"") -> 8
A9: =Dim_WBS!D6 -> Labor | B9: =Dim_WBS!C6 -> Demolition & Prep | C9: =Dim_WBS!A6 -> WBS-05 | D9: =Dim_WBS!D6 -> Labor | E9: Yes | I9: Imported from current WBS | J9: =IFERROR(MATCH(C9,'Task Plan'!A:A,0),"") -> 9
A10: =Dim_WBS!D7 -> Labor | B10: =Dim_WBS!C7 -> Electrical Rough-In | C10: =Dim_WBS!A7 -> WBS-06 | D10: =Dim_WBS!D7 -> Labor | E10: Yes | I10: Imported from current WBS | J10: =IFERROR(MATCH(C10,'Task Plan'!A:A,0),"") -> 10
A11: =Dim_WBS!D8 -> Subcontractor | B11: =Dim_WBS!C8 -> HVAC Installation | C11: =Dim_WBS!A8 -> WBS-07 | D11: =Dim_WBS!D8 -> Subcontractor | E11: Yes | I11: Imported from current WBS | J11: =IFERROR(MATCH(C11,'Task Plan'!A:A,0),"") -> 11
A12: =Dim_WBS!D9 -> Subcontractor | B12: =Dim_WBS!C9 -> Partitions & Drywall | C12: =Dim_WBS!A9 -> WBS-08 | D12: =Dim_WBS!D9 -> Subcontractor | E12: Yes | I12: Imported from current WBS | J12: =IFERROR(MATCH(C12,'Task Plan'!A:A,0),"") -> 12
A13: =Dim_WBS!D10 -> Material | B13: =Dim_WBS!C10 -> Flooring | C13: =Dim_WBS!A10 -> WBS-09 | D13: =Dim_WBS!D10 -> Material | E13: Yes | I13: Imported from current WBS | J13: =IFERROR(MATCH(C13,'Task Plan'!A:A,0),"") -> 13
A14: =Dim_WBS!D11 -> Material | B14: =Dim_WBS!C11 -> Fixtures & Furniture | C14: =Dim_WBS!A11 -> WBS-10 | D14: =Dim_WBS!D11 -> Material | E14: Yes | I14: Imported from current WBS | J14: =IFERROR(MATCH(C14,'Task Plan'!A:A,0),"") -> 14
A15: =Dim_WBS!D12 -> Labor | B15: =Dim_WBS!C12 -> Testing / Commissioning | C15: =Dim_WBS!A12 -> WBS-11 | D15: =Dim_WBS!D12 -> Labor | E15: Yes | I15: Imported from current WBS | J15: =IFERROR(MATCH(C15,'Task Plan'!A:A,0),"") -> 15
A16: =Dim_WBS!D13 -> Labor | B16: =Dim_WBS!C13 -> Handover & Closeout | C16: =Dim_WBS!A13 -> WBS-12 | D16: =Dim_WBS!D13 -> Labor | E16: Yes | I16: Imported from current WBS | J16: =IFERROR(MATCH(C16,'Task Plan'!A:A,0),"") -> 16
A17: Brainstorm / new | I17: Add new tasks here before sequencing
A18: Brainstorm / new | I18: Add new tasks here before sequencing
A21: Example task-list method from attachment | B21: Garden office example grouped tasks: clear the space, foundations, buy the shed, install shed, legal. Use this area to add unstructured tasks before converting them to WBS.

Sheet EVM Dashboard
A1: OFFICE FIT-OUT - PROJECT CONTROLLING DASHBOARD
A2: EVM Performance Status | Tufte-Compliant Design | Data-Ink Maximized
A4: Status Date: | B4: 46203 | D4: Status Week: | E4: =MATCH(B4,EVM!B5:B16,1) -> 8 | G4: Sector: | H4: Corporate Real Estate | N4: RAG Legend | O4: Rule | P4: Meaning
N5: Green | O5: Good | P5: On/above plan or low exposure
A6: BUDGET AT COMPLETION (BAC) | D6: PLANNED VALUE (PV) | G6: ACTUAL COST (AC) | J6: EARNED VALUE (EV) | N6: Amber | O6: Watch | P6: Near threshold / medium exposure
A7: =Setup!B11 -> 268650 | D7: ='Task Plan'!I17 -> 220233.34 | G7: ='Task Plan'!J17 -> 141985.44 | J7: ='Task Plan'!L17 -> 131468 | N7: Red | O7: Action | P7: Behind plan, overrun, or high exposure
A9: COST VARIANCE (CV) | D9: SCHEDULE VARIANCE (SV) | G9: CPI (COST INDEX) | J9: SPI (SCHEDULE INDEX)
A10: ='Task Plan'!N17 -> -10517.444 | D10: ='Task Plan'!M17 -> -88765.344 | G10: ='Task Plan'!P17 -> 0.9259259 | J10: ='Task Plan'!O17 -> 0.59694865
A12: ESTIMATE AT COMPLETION (EAC) | D12: ESTIMATE TO COMPLETE (ETC) | G12: VARIANCE AT COMPLETION (VAC) | J12: PROJECT PROGRESS %
A13: ='Task Plan'!Q17 -> 290142.01 | D13: ='Task Plan'!R17 -> 148156.57 | G13: ='Task Plan'!S17 -> -21492.009 | J13: ='Task Plan'!K17 -> 0.48936533
A15: WBS Element Performance Breakdown
A17: WBS ID | B17: Activity Name | C17: Type | D17: Budget (BAC) | E17: Planned Value (PV) | F17: Actual Cost (AC) | G17: Progress % | H17: Earned Value (EV) | I17: CV | J17: SV | K17: CPI | L17: SPI | M17: EAC | N17: ETC | O17: VAC | P17: Status
A18: ='Task Plan'!A5 -> WBS-01 | B18: ='Task Plan'!C5 -> Project Management | C18: ='Task Plan'!D5 -> Labor | D18: ='Task Plan'!H5 -> 18000 | E18: ='Task Plan'!I5 -> 13500 | F18: ='Task Plan'!J5 -> 9600 | G18: ='Task Plan'!K5 -> 0.5 | H18: ='Task Plan'!L5 -> 9000 | I18: ='Task Plan'!N5 -> -600 | J18: ='Task Plan'!M5 -> -4500 | K18: ='Task Plan'!P5 -> 0.9375 | L18: ='Task Plan'!O5 -> 0.66666667 | M18: ='Task Plan'!Q5 -> 19200 | N18: ='Task Plan'!R5 -> 9600 | O18: ='Task Plan'!S5 -> -1200 | P18: =IF('Task Plan'!T5="Red","🔴 Overrun",IF('Task Plan'!T5="Amber","🟡 Warning","On Track")) -> 🔴 Overrun
A19: ='Task Plan'!A6 -> WBS-02 | B19: ='Task Plan'!C6 -> Site Survey & Mobilization | C19: ='Task Plan'!D6 -> Labor | D19: ='Task Plan'!H6 -> 8500 | E19: ='Task Plan'!I6 -> 8500 | F19: ='Task Plan'!J6 -> 8700 | G19: ='Task Plan'!K6 -> 1 | H19: ='Task Plan'!L6 -> 8500 | I19: ='Task Plan'!N6 -> -200 | J19: ='Task Plan'!M6 -> 0 | K19: ='Task Plan'!P6 -> 0.97701149 | L19: ='Task Plan'!O6 -> 1 | M19: ='Task Plan'!Q6 -> 8700 | N19: ='Task Plan'!R6 -> 0 | O19: ='Task Plan'!S6 -> -200 | P19: =IF('Task Plan'!T6="Red","🔴 Overrun",IF('Task Plan'!T6="Amber","🟡 Warning","On Track")) -> 🔴 Overrun
A20: ='Task Plan'!A7 -> WBS-03 | B20: ='Task Plan'!C7 -> Design & Engineering | C20: ='Task Plan'!D7 -> Labor | D20: ='Task Plan'!H7 -> 19200 | E20: ='Task Plan'!I7 -> 19200 | F20: ='Task Plan'!J7 -> 18195.04 | G20: ='Task Plan'!K7 -> 1 | H20: ='Task Plan'!L7 -> 19200 | I20: ='Task Plan'!N7 -> 1004.96 | J20: ='Task Plan'!M7 -> 0 | K20: ='Task Plan'!P7 -> 1.0552326 | L20: ='Task Plan'!O7 -> 1 | M20: ='Task Plan'!Q7 -> 18195.04 | N20: ='Task Plan'!R7 -> 0 | O20: ='Task Plan'!S7 -> 1004.96 | P20: =IF('Task Plan'!T7="Red","🔴 Overrun",IF('Task Plan'!T7="Amber","🟡 Warning","On Track")) -> On Track
A21: ='Task Plan'!A8 -> WBS-04 | B21: ='Task Plan'!C8 -> Procurement - Materials | C21: ='Task Plan'!D8 -> Material | D21: ='Task Plan'!H8 -> 42000 | E21: ='Task Plan'!I8 -> 42000 | F21: ='Task Plan'!J8 -> 41300 | G21: ='Task Plan'!K8 -> 1 | H21: ='Task Plan'!L8 -> 42000 | I21: ='Task Plan'!N8 -> 700 | J21: ='Task Plan'!M8 -> 0 | K21: ='Task Plan'!P8 -> 1.0169492 | L21: ='Task Plan'!O8 -> 1 | M21: ='Task Plan'!Q8 -> 41300 | N21: ='Task Plan'!R8 -> 0 | O21: ='Task Plan'!S8 -> 700 | P21: =IF('Task Plan'!T8="Red","🔴 Overrun",IF('Task Plan'!T8="Amber","🟡 Warning","On Track")) -> On Track
A22: ='Task Plan'!A9 -> WBS-05 | B22: ='Task Plan'!C9 -> Demolition & Prep | C22: ='Task Plan'!D9 -> Labor | D22: ='Task Plan'!H9 -> 13200 | E22: ='Task Plan'!I9 -> 13200 | F22: ='Task Plan'!J9 -> 13408.16 | G22: ='Task Plan'!K9 -> 1 | H22: ='Task Plan'!L9 -> 13200 | I22: ='Task Plan'!N9 -> -208.16 | J22: ='Task Plan'!M9 -> 0 | K22: ='Task Plan'!P9 -> 0.98447513 | L22: ='Task Plan'!O9 -> 1 | M22: ='Task Plan'!Q9 -> 13408.16 | N22: ='Task Plan'!R9 -> 0 | O22: ='Task Plan'!S9 -> -208.16 | P22: =IF('Task Plan'!T9="Red","🔴 Overrun",IF('Task Plan'!T9="Amber","🟡 Warning","On Track")) -> 🔴 Overrun
A23: ='Task Plan'!A10 -> WBS-06 | B23: ='Task Plan'!C10 -> Electrical Rough-In | C23: ='Task Plan'!D10 -> Labor | D23: ='Task Plan'!H10 -> 26000 | E23: ='Task Plan'!I10 -> 26000 | F23: ='Task Plan'!J10 -> 26206.24 | G23: ='Task Plan'!K10 -> 0.7 | H23: ='Task Plan'!L10 -> 18200 | I23: ='Task Plan'!N10 -> -8006.24 | J23: ='Task Plan'!M10 -> -7800 | K23: ='Task Plan'!P10 -> 0.69449108 | L23: ='Task Plan'!O10 -> 0.7 | M23: ='Task Plan'!Q10 -> 37437.486 | N23: ='Task Plan'!R10 -> 11231.246 | O23: ='Task Plan'!S10 -> -11437.486 | P23: =IF('Task Plan'!T10="Red","🔴 Overrun",IF('Task Plan'!T10="Amber","🟡 Warning","On Track")) -> 🔴 Overrun
A24: ='Task Plan'!A11 -> WBS-07 | B24: ='Task Plan'!C11 -> HVAC Installation | C24: ='Task Plan'!D11 -> Subcontractor | D24: ='Task Plan'!H11 -> 36000 | E24: ='Task Plan'!I11 -> 36000 | F24: ='Task Plan'!J11 -> 17476.8 | G24: ='Task Plan'!K11 -> 0.4 | H24: ='Task Plan'!L11 -> 14400 | I24: ='Task Plan'!N11 -> -3076.8 | J24: ='Task Plan'!M11 -> -21600 | K24: ='Task Plan'!P11 -> 0.82394946 | L24: ='Task Plan'!O11 -> 0.4 | M24: ='Task Plan'!Q11 -> 43692 | N24: ='Task Plan'!R11 -> 26215.2 | O24: ='Task Plan'!S11 -> -7692 | P24: =IF('Task Plan'!T11="Red","🔴 Overrun",IF('Task Plan'!T11="Amber","🟡 Warning","On Track")) -> 🔴 Overrun
A25: ='Task Plan'!A12 -> WBS-08 | B25: ='Task Plan'!C12 -> Partitions & Drywall | C25: ='Task Plan'!D12 -> Subcontractor | D25: ='Task Plan'!H12 -> 28000 | E25: ='Task Plan'!I12 -> 28000 | F25: ='Task Plan'!J12 -> 7099.2 | G25: ='Task Plan'!K12 -> 0.248857 | H25: ='Task Plan'!L12 -> 6967.996 | I25: ='Task Plan'!N12 -> -131.204 | J25: ='Task Plan'!M12 -> -21032.004 | K25: ='Task Plan'!P12 -> 0.98151848 | L25: ='Task Plan'!O12 -> 0.248857 | M25: ='Task Plan'!Q12 -> 28527.226 | N25: ='Task Plan'!R12 -> 21428.026 | O25: ='Task Plan'!S12 -> -527.22648 | P25: =IF('Task Plan'!T12="Red","🔴 Overrun",IF('Task Plan'!T12="Amber","🟡 Warning","On Track")) -> 🔴 Overrun
A26: ='Task Plan'!A13 -> WBS-09 | B26: ='Task Plan'!C13 -> Flooring | C26: ='Task Plan'!D13 -> Material | D26: ='Task Plan'!H13 -> 35750 | E26: ='Task Plan'!I13 -> 23833.34 | F26: ='Task Plan'!J13 -> 0 | G26: ='Task Plan'!K13 -> 0 | H26: ='Task Plan'!L13 -> 0 | I26: ='Task Plan'!N13 -> 0 | J26: ='Task Plan'!M13 -> -23833.34 | K26: ='Task Plan'!P13 -> 1 | L26: ='Task Plan'!O13 -> 0 | M26: ='Task Plan'!Q13 -> 35750 | N26: ='Task Plan'!R13 -> 35750 | O26: ='Task Plan'!S13 -> 0 | P26: =IF('Task Plan'!T13="Red","🔴 Overrun",IF('Task Plan'!T13="Amber","🟡 Warning","On Track")) -> 🔴 Overrun
A27: ='Task Plan'!A14 -> WBS-10 | B27: ='Task Plan'!C14 -> Fixtures & Furniture | C27: ='Task Plan'!D14 -> Material | D27: ='Task Plan'!H14 -> 30000 | E27: ='Task Plan'!I14 -> 10000 | F27: ='Task Plan'!J14 -> 0 | G27: ='Task Plan'!K14 -> 0 | H27: ='Task Plan'!L14 -> 0 | I27: ='Task Plan'!N14 -> 0 | J27: ='Task Plan'!M14 -> -10000 | K27: ='Task Plan'!P14 -> 1 | L27: ='Task Plan'!O14 -> 0 | M27: ='Task Plan'!Q14 -> 30000 | N27: ='Task Plan'!R14 -> 30000 | O27: ='Task Plan'!S14 -> 0 | P27: =IF('Task Plan'!T14="Red","🔴 Overrun",IF('Task Plan'!T14="Amber","🟡 Warning","On Track")) -> 🔴 Overrun
A28: ='Task Plan'!A15 -> WBS-11 | B28: ='Task Plan'!C15 -> Testing / Commissioning | C28: ='Task Plan'!D15 -> Labor | D28: ='Task Plan'!H15 -> 8400 | E28: ='Task Plan'!I15 -> 0 | F28: ='Task Plan'!J15 -> 0 | G28: ='Task Plan'!K15 -> 0 | H28: ='Task Plan'!L15 -> 0 | I28: ='Task Plan'!N15 -> 0 | J28: ='Task Plan'!M15 -> 0 | K28: ='Task Plan'!P15 -> 1 | L28: ='Task Plan'!O15 -> 1 | M28: ='Task Plan'!Q15 -> 8400 | N28: ='Task Plan'!R15 -> 8400 | O28: ='Task Plan'!S15 -> 0 | P28: =IF('Task Plan'!T15="Red","🔴 Overrun",IF('Task Plan'!T15="Amber","🟡 Warning","On Track")) -> On Track
A29: ='Task Plan'!A16 -> WBS-12 | B29: ='Task Plan'!C16 -> Handover & Closeout | C29: ='Task Plan'!D16 -> Labor | D29: ='Task Plan'!H16 -> 3600 | E29: ='Task Plan'!I16 -> 0 | F29: ='Task Plan'!J16 -> 0 | G29: ='Task Plan'!K16 -> 0 | H29: ='Task Plan'!L16 -> 0 | I29: ='Task Plan'!N16 -> 0 | J29: ='Task Plan'!M16 -> 0 | K29: ='Task Plan'!P16 -> 1 | L29: ='Task Plan'!O16 -> 1 | M29: ='Task Plan'!Q16 -> 3600 | N29: ='Task Plan'!R16 -> 3600 | O29: ='Task Plan'!S16 -> 0 | P29: =IF('Task Plan'!T16="Red","🔴 Overrun",IF('Task Plan'!T16="Amber","🟡 Warning","On Track")) -> On Track
A30: Total / Project Portfolio | D30: ='Task Plan'!H17 -> 268650 | E30: ='Task Plan'!I17 -> 220233.34 | F30: ='Task Plan'!J17 -> 141985.44 | G30: ='Task Plan'!K17 -> 0.48936533 | H30: ='Task Plan'!L17 -> 131468 | I30: ='Task Plan'!N17 -> -10517.444 | J30: ='Task Plan'!M17 -> -88765.344 | K30: ='Task Plan'!P17 -> 0.9259259 | L30: ='Task Plan'!O17 -> 0.59694865 | M30: ='Task Plan'!Q17 -> 290142.01 | N30: ='Task Plan'!R17 -> 148156.57 | O30: ='Task Plan'!S17 -> -21492.009 | P30: =IF('Task Plan'!T17="Red","🔴 Overrun",IF('Task Plan'!T17="Amber","🟡 Warning","On Track")) -> 🔴 Overrun
A33: Weekly Cumulative Performance Trends
A35: Week | B35: Week Date | C35: Weekly PV | D35: Cum PV | E35: Weekly AC | F35: Cum AC | G35: Cum EV | H35: CV | I35: SV | J35: CPI | K35: SPI
A36: 1 | B36: 46146 | C36: =SUMIFS(Fact_Baseline_PV!C:C, Fact_Baseline_PV!A:A, B36) -> 16400 | D36: =SUM(C$36:C36) -> 16400 | E36: =SUMIFS(Fact_Actual_Costs!D:D, Fact_Actual_Costs!A:A, ">="&B36, Fact_Actual_Costs!A:A, "<="&B36+6) -> 16295.04 | F36: =SUM(E$36:E36) -> 16295.04 | G36: =SUMPRODUCT(Dim_WBS!$E$2:$E$13, SUMIFS(Fact_Physical_Progress!$C$2:$C$100, Fact_Physical_Progress!$B$2:$B$100, Dim_WBS!$A$2:$A$13, Fact_Physical_Progress!$A$2:$A$100, "<="&B36+4)) -> 15087.994 | H36: =G36-F36 -> -1207.046 | I36: =G36-D36 -> -1312.006 | J36: =IF(F36>0, G36/F36, 1) -> 0.92592556 | K36: =IF(D36>0, G36/D36, 1) -> 0.91999963
A37: 2 | B37: 46153 | C37: =SUMIFS(Fact_Baseline_PV!C:C, Fact_Baseline_PV!A:A, B37) -> 22800 | D37: =SUM(C$36:C37) -> 39200 | E37: =SUMIFS(Fact_Actual_Costs!D:D, Fact_Actual_Costs!A:A, ">="&B37, Fact_Actual_Costs!A:A, "<="&B37+6) -> 22654.08 | F37: =SUM(E$36:E37) -> 38949.12 | G37: =SUMPRODUCT(Dim_WBS!$E$2:$E$13, SUMIFS(Fact_Physical_Progress!$C$2:$C$100, Fact_Physical_Progress!$B$2:$B$100, Dim_WBS!$A$2:$A$13, Fact_Physical_Progress!$A$2:$A$100, "<="&B37+4)) -> 51151.998 | H37: =G37-F37 -> 12202.878 | I37: =G37-D37 -> 11951.998 | J37: =IF(F37>0, G37/F37, 1) -> 1.313303 | K37: =IF(D37>0, G37/D37, 1) -> 1.3048979
A38: 3 | B38: 46160 | C38: =SUMIFS(Fact_Baseline_PV!C:C, Fact_Baseline_PV!A:A, B38) -> 22800 | D38: =SUM(C$36:C38) -> 62000 | E38: =SUMIFS(Fact_Actual_Costs!D:D, Fact_Actual_Costs!A:A, ">="&B38, Fact_Actual_Costs!A:A, "<="&B38+6) -> 22654.08 | F38: =SUM(E$36:E38) -> 61603.2 | G38: =SUMPRODUCT(Dim_WBS!$E$2:$E$13, SUMIFS(Fact_Physical_Progress!$C$2:$C$100, Fact_Physical_Progress!$B$2:$B$100, Dim_WBS!$A$2:$A$13, Fact_Physical_Progress!$A$2:$A$100, "<="&B38+4)) -> 108192 | H38: =G38-F38 -> 46588.798 | I38: =G38-D38 -> 46191.998 | J38: =IF(F38>0, G38/F38, 1) -> 1.7562724 | K38: =IF(D38>0, G38/D38, 1) -> 1.7450322
A39: 4 | B39: 46167 | C39: =SUMIFS(Fact_Baseline_PV!C:C, Fact_Baseline_PV!A:A, B39) -> 25066.67 | D39: =SUM(C$36:C39) -> 87066.67 | E39: =SUMIFS(Fact_Actual_Costs!D:D, Fact_Actual_Costs!A:A, ">="&B39, Fact_Actual_Costs!A:A, "<="&B39+6) -> 24906.24 | F39: =SUM(E$36:E39) -> 86509.44 | G39: =SUMPRODUCT(Dim_WBS!$E$2:$E$13, SUMIFS(Fact_Physical_Progress!$C$2:$C$100, Fact_Physical_Progress!$B$2:$B$100, Dim_WBS!$A$2:$A$13, Fact_Physical_Progress!$A$2:$A$100, "<="&B39+4)) -> 188293.33 | H39: =G39-F39 -> 101783.89 | I39: =G39-D39 -> 101226.66 | J39: =IF(F39>0, G39/F39, 1) -> 2.1765639 | K39: =IF(D39>0, G39/D39, 1) -> 2.1626338
A40: 5 | B40: 46174 | C40: =SUMIFS(Fact_Baseline_PV!C:C, Fact_Baseline_PV!A:A, B40) -> 29666.67 | D40: =SUM(C$36:C40) -> 116733.34 | E40: =SUMIFS(Fact_Actual_Costs!D:D, Fact_Actual_Costs!A:A, ">="&B40, Fact_Actual_Costs!A:A, "<="&B40+6) -> 29476.8 | F40: =SUM(E$36:E40) -> 115986.24 | G40: =SUMPRODUCT(Dim_WBS!$E$2:$E$13, SUMIFS(Fact_Physical_Progress!$C$2:$C$100, Fact_Physical_Progress!$B$2:$B$100, Dim_WBS!$A$2:$A$13, Fact_Physical_Progress!$A$2:$A$100, "<="&B40+4)) -> 295688 | H40: =G40-F40 -> 179701.76 | I40: =G40-D40 -> 178954.66 | J40: =IF(F40>0, G40/F40, 1) -> 2.5493369 | K40: =IF(D40>0, G40/D40, 1) -> 2.533021
A41: 6 | B41: 46181 | C41: =SUMIFS(Fact_Baseline_PV!C:C, Fact_Baseline_PV!A:A, B41) -> 26166.66 | D41: =SUM(C$36:C41) -> 142900 | E41: =SUMIFS(Fact_Actual_Costs!D:D, Fact_Actual_Costs!A:A, ">="&B41, Fact_Actual_Costs!A:A, "<="&B41+6) -> 25999.2 | F41: =SUM(E$36:E41) -> 141985.44 | G41: =SUMPRODUCT(Dim_WBS!$E$2:$E$13, SUMIFS(Fact_Physical_Progress!$C$2:$C$100, Fact_Physical_Progress!$B$2:$B$100, Dim_WBS!$A$2:$A$13, Fact_Physical_Progress!$A$2:$A$100, "<="&B41+4)) -> 427156 | H41: =G41-F41 -> 285170.56 | I41: =G41-D41 -> 284256 | J41: =IF(F41>0, G41/F41, 1) -> 3.0084493 | K41: =IF(D41>0, G41/D41, 1) -> 2.9891952
A42: 7 | B42: 46188 | C42: =SUMIFS(Fact_Baseline_PV!C:C, Fact_Baseline_PV!A:A, B42) -> 17500 | D42: =SUM(C$36:C42) -> 160400 | E42: =SUMIFS(Fact_Actual_Costs!D:D, Fact_Actual_Costs!A:A, ">="&B42, Fact_Actual_Costs!A:A, "<="&B42+6) -> 0 | F42: =SUM(E$36:E42) -> 141985.44 | G42: =SUMPRODUCT(Dim_WBS!$E$2:$E$13, SUMIFS(Fact_Physical_Progress!$C$2:$C$100, Fact_Physical_Progress!$B$2:$B$100, Dim_WBS!$A$2:$A$13, Fact_Physical_Progress!$A$2:$A$100, "<="&B42+4)) -> 427156 | H42: =G42-F42 -> 285170.56 | I42: =G42-D42 -> 266756 | J42: =IF(F42>0, G42/F42, 1) -> 3.0084493 | K42: =IF(D42>0, G42/D42, 1) -> 2.6630673
A43: 8 | B43: 46195 | C43: =SUMIFS(Fact_Baseline_PV!C:C, Fact_Baseline_PV!A:A, B43) -> 29416.67 | D43: =SUM(C$36:C43) -> 189816.67 | E43: =SUMIFS(Fact_Actual_Costs!D:D, Fact_Actual_Costs!A:A, ">="&B43, Fact_Actual_Costs!A:A, "<="&B43+6) -> 0 | F43: =SUM(E$36:E43) -> 141985.44 | G43: =SUMPRODUCT(Dim_WBS!$E$2:$E$13, SUMIFS(Fact_Physical_Progress!$C$2:$C$100, Fact_Physical_Progress!$B$2:$B$100, Dim_WBS!$A$2:$A$13, Fact_Physical_Progress!$A$2:$A$100, "<="&B43+4)) -> 427156 | H43: =G43-F43 -> 285170.56 | I43: =G43-D43 -> 237339.33 | J43: =IF(F43>0, G43/F43, 1) -> 3.0084493 | K43: =IF(D43>0, G43/D43, 1) -> 2.2503608
A44: 9 | B44: 46202 | C44: =SUMIFS(Fact_Baseline_PV!C:C, Fact_Baseline_PV!A:A, B44) -> 30416.67 | D44: =SUM(C$36:C44) -> 220233.34 | E44: =SUMIFS(Fact_Actual_Costs!D:D, Fact_Actual_Costs!A:A, ">="&B44, Fact_Actual_Costs!A:A, "<="&B44+6) -> 0 | F44: =SUM(E$36:E44) -> 141985.44 | G44: =SUMPRODUCT(Dim_WBS!$E$2:$E$13, SUMIFS(Fact_Physical_Progress!$C$2:$C$100, Fact_Physical_Progress!$B$2:$B$100, Dim_WBS!$A$2:$A$13, Fact_Physical_Progress!$A$2:$A$100, "<="&B44+4)) -> 427156 | H44: =G44-F44 -> 285170.56 | I44: =G44-D44 -> 206922.66 | J44: =IF(F44>0, G44/F44, 1) -> 3.0084493 | K44: =IF(D44>0, G44/D44, 1) -> 1.939561
A45: 10 | B45: 46209 | C45: =SUMIFS(Fact_Baseline_PV!C:C, Fact_Baseline_PV!A:A, B45) -> 23416.66 | D45: =SUM(C$36:C45) -> 243650 | E45: =SUMIFS(Fact_Actual_Costs!D:D, Fact_Actual_Costs!A:A, ">="&B45, Fact_Actual_Costs!A:A, "<="&B45+6) -> 0 | F45: =SUM(E$36:E45) -> 141985.44 | G45: =SUMPRODUCT(Dim_WBS!$E$2:$E$13, SUMIFS(Fact_Physical_Progress!$C$2:$C$100, Fact_Physical_Progress!$B$2:$B$100, Dim_WBS!$A$2:$A$13, Fact_Physical_Progress!$A$2:$A$100, "<="&B45+4)) -> 427156 | H45: =G45-F45 -> 285170.56 | I45: =G45-D45 -> 183506 | J45: =IF(F45>0, G45/F45, 1) -> 3.0084493 | K45: =IF(D45>0, G45/D45, 1) -> 1.7531541
A46: 11 | B46: 46216 | C46: =SUMIFS(Fact_Baseline_PV!C:C, Fact_Baseline_PV!A:A, B46) -> 15700 | D46: =SUM(C$36:C46) -> 259350 | E46: =SUMIFS(Fact_Actual_Costs!D:D, Fact_Actual_Costs!A:A, ">="&B46, Fact_Actual_Costs!A:A, "<="&B46+6) -> 0 | F46: =SUM(E$36:E46) -> 141985.44 | G46: =SUMPRODUCT(Dim_WBS!$E$2:$E$13, SUMIFS(Fact_Physical_Progress!$C$2:$C$100, Fact_Physical_Progress!$B$2:$B$100, Dim_WBS!$A$2:$A$13, Fact_Physical_Progress!$A$2:$A$100, "<="&B46+4)) -> 427156 | H46: =G46-F46 -> 285170.56 | I46: =G46-D46 -> 167806 | J46: =IF(F46>0, G46/F46, 1) -> 3.0084493 | K46: =IF(D46>0, G46/D46, 1) -> 1.6470252
A47: 12 | B47: 46223 | C47: =SUMIFS(Fact_Baseline_PV!C:C, Fact_Baseline_PV!A:A, B47) -> 9300 | D47: =SUM(C$36:C47) -> 268650 | E47: =SUMIFS(Fact_Actual_Costs!D:D, Fact_Actual_Costs!A:A, ">="&B47, Fact_Actual_Costs!A:A, "<="&B47+6) -> 0 | F47: =SUM(E$36:E47) -> 141985.44 | G47: =SUMPRODUCT(Dim_WBS!$E$2:$E$13, SUMIFS(Fact_Physical_Progress!$C$2:$C$100, Fact_Physical_Progress!$B$2:$B$100, Dim_WBS!$A$2:$A$13, Fact_Physical_Progress!$A$2:$A$100, "<="&B47+4)) -> 427156 | H47: =G47-F47 -> 285170.56 | I47: =G47-D47 -> 158506 | J47: =IF(F47>0, G47/F47, 1) -> 3.0084493 | K47: =IF(D47>0, G47/D47, 1) -> 1.5900093

Sheet Resource Grid
A1: Resource Allocation Grid
A2: Weekly hours and cost grid adapted from the attached Gantt template: rows are WBS tasks; columns are reporting weeks; totals are live formulas from actual-cost facts.
A4: WBS ID | B4: Activity | C4: Resource / Role | D4: Measure | E4: Wk1 | F4: Wk2 | G4: Wk3 | H4: Wk4 | I4: Wk5 | J4: Wk6 | K4: Wk7 | L4: Wk8 | M4: Wk9 | N4: Wk10 | O4: Wk11 | P4: Wk12 | Q4: Total | R4: BAC | S4: Actual @ Status | T4: Remaining BAC | U4: CPI | V4: RAG | W4: Template source | X4: Notes
A5: =Dim_WBS!A2 -> WBS-01 | B5: =Dim_WBS!C2 -> Project Management | C5: =Dim_WBS!D2 -> Labor | D5: Hours | E5: =SUMIFS(Fact_Actual_Costs!$E$2:$E$100,Fact_Actual_Costs!$B$2:$B$100,$A5,Fact_Actual_Costs!$A$2:$A$100,">="&MIN(Fact_Baseline_PV!$A$2:$A$44)+(0*7),Fact_Actual_Costs!$A$2:$A$100,"<"&MIN(Fact_Baseline_PV!$A$2:$A$44)+((0+1)*7)) -> 1.05 | F5: =SUMIFS(Fact_Actual_Costs!$E$2:$E$100,Fact_Actual_Costs!$B$2:$B$100,$A5,Fact_Actual_Costs!$A$2:$A$100,">="&MIN(Fact_Baseline_PV!$A$2:$A$44)+(1*7),Fact_Actual_Costs!$A$2:$A$100,"<"&MIN(Fact_Baseline_PV!$A$2:$A$44)+((1+1)*7)) -> 1.05 | G5: =SUMIFS(Fact_Actual_Costs!$E$2:$E$100,Fact_Actual_Costs!$B$2:$B$100,$A5,Fact_Actual_Costs!$A$2:$A$100,">="&MIN(Fact_Baseline_PV!$A$2:$A$44)+(2*7),Fact_Actual_Costs!$A$2:$A$100,"<"&MIN(Fact_Baseline_PV!$A$2:$A$44)+((2+1)*7)) -> 1.05 | H5: =SUMIFS(Fact_Actual_Costs!$E$2:$E$100,Fact_Actual_Costs!$B$2:$B$100,$A5,Fact_Actual_Costs!$A$2:$A$100,">="&MIN(Fact_Baseline_PV!$A$2:$A$44)+(3*7),Fact_Actual_Costs!$A$2:$A$100,"<"&MIN(Fact_Baseline_PV!$A$2:$A$44)+((3+1)*7)) -> 1.05 | I5: =SUMIFS(Fact_Actual_Costs!$E$2:$E$100,Fact_Actual_Costs!$B$2:$B$100,$A5,Fact_Actual_Costs!$A$2:$A$100,">="&MIN(Fact_Baseline_PV!$A$2:$A$44)+(4*7),Fact_Actual_Costs!$A$2:$A$100,"<"&MIN(Fact_Baseline_PV!$A$2:$A$44)+((4+1)*7)) -> 1.05 | J5: =SUMIFS(Fact_Actual_Costs!$E$2:$E$100,Fact_Actual_Costs!$B$2:$B$100,$A5,Fact_Actual_Costs!$A$2:$A$100,">="&MIN(Fact_Baseline_PV!$A$2:$A$44)+(5*7),Fact_Actual_Costs!$A$2:$A$100,"<"&MIN(Fact_Baseline_PV!$A$2:$A$44)+((5+1)*7)) -> 1.05 | K5: =SUMIFS(Fact_Actual_Costs!$E$2:$E$100,Fact_Actual_Costs!$B$2:$B$100,$A5,Fact_Actual_Costs!$A$2:$A$100,">="&MIN(Fact_Baseline_PV!$A$2:$A$44)+(6*7),Fact_Actual_Costs!$A$2:$A$100,"<"&MIN(Fact_Baseline_PV!$A$2:$A$44)+((6+1)*7)) -> 0 | L5: =SUMIFS(Fact_Actual_Costs!$E$2:$E$100,Fact_Actual_Costs!$B$2:$B$100,$A5,Fact_Actual_Costs!$A$2:$A$100,">="&MIN(Fact_Baseline_PV!$A$2:$A$44)+(7*7),Fact_Actual_Costs!$A$2:$A$100,"<"&MIN(Fact_Baseline_PV!$A$2:$A$44)+((7+1)*7)) -> 0 | M5: =SUMIFS(Fact_Actual_Costs!$E$2:$E$100,Fact_Actual_Costs!$B$2:$B$100,$A5,Fact_Actual_Costs!$A$2:$A$100,">="&MIN(Fact_Baseline_PV!$A$2:$A$44)+(8*7),Fact_Actual_Costs!$A$2:$A$100,"<"&MIN(Fact_Baseline_PV!$A$2:$A$44)+((8+1)*7)) -> 0 | N5: =SUMIFS(Fact_Actual_Costs!$E$2:$E$100,Fact_Actual_Costs!$B$2:$B$100,$A5,Fact_Actual_Costs!$A$2:$A$100,">="&MIN(Fact_Baseline_PV!$A$2:$A$44)+(9*7),Fact_Actual_Costs!$A$2:$A$100,"<"&MIN(Fact_Baseline_PV!$A$2:$A$44)+((9+1)*7)) -> 0 | O5: =SUMIFS(Fact_Actual_Costs!$E$2:$E$100,Fact_Actual_Costs!$B$2:$B$100,$A5,Fact_Actual_Costs!$A$2:$A$100,">="&MIN(Fact_Baseline_PV!$A$2:$A$44)+(10*7),Fact_Actual_Costs!$A$2:$A$100,"<"&MIN(Fact_Baseline_PV!$A$2:$A$44)+((10+1)*7)) -> 0 | P5: =SUMIFS(Fact_Actual_Costs!$E$2:$E$100,Fact_Actual_Costs!$B$2:$B$100,$A5,Fact_Actual_Costs!$A$2:$A$100,">="&MIN(Fact_Baseline_PV!$A$2:$A$44)+(11*7),Fact_Actual_Costs!$A$2:$A$100,"<"&MIN(Fact_Baseline_PV!$A$2:$A$44)+((11+1)*7)) -> 0 | Q5: =SUM(E5:P5) -> 6.3 | R5: =VLOOKUP(A5,Dim_WBS!$A$2:$E$13,5,FALSE) -> 18000 | S5: =SUMIFS(Fact_Actual_Costs!$D$2:$D$100,Fact_Actual_Costs!$B$2:$B$100,A5,Fact_Actual_Costs!$A$2:$A$100,"<="&Setup!$B$9) -> 9600 | T5: =R5-S5 -> 8400 | U5: =IFERROR((R5*VLOOKUP(A5,'Task Plan'!$A$5:$K$16,11,FALSE))/S5,1) -> 0.9375 | V5: =IF(U5<Setup!$B$12,"Red",IF(U5<Setup!$B$13,"Amber","Green")) -> Red | W5: 8.1.2 Gantt template from garden office | X5: Hours row
A6: =Dim_WBS!A2 -> WBS-01 | B6: =Dim_WBS!C2 -> Project Management | C6: =Dim_WBS!D2 -> Labor | D6: Cost | E6: =SUMIFS(Fact_Actual_Costs!$D$2:$D$100,Fact_Actual_Costs!$B$2:$B$100,$A6,Fact_Actual_Costs!$A$2:$A$100,">="&MIN(Fact_Baseline_PV!$A$2:$A$44)+(0*7),Fact_Actual_Costs!$A$2:$A$100,"<"&MIN(Fact_Baseline_PV!$A$2:$A$44)+((0+1)*7)) -> 1600 | F6: =SUMIFS(Fact_Actual_Costs!$D$2:$D$100,Fact_Actual_Costs!$B$2:$B$100,$A6,Fact_Actual_Costs!$A$2:$A$100,">="&MIN(Fact_Baseline_PV!$A$2:$A$44)+(1*7),Fact_Actual_Costs!$A$2:$A$100,"<"&MIN(Fact_Baseline_PV!$A$2:$A$44)+((1+1)*7)) -> 1600 | G6: =SUMIFS(Fact_Actual_Costs!$D$2:$D$100,Fact_Actual_Costs!$B$2:$B$100,$A6,Fact_Actual_Costs!$A$2:$A$100,">="&MIN(Fact_Baseline_PV!$A$2:$A$44)+(2*7),Fact_Actual_Costs!$A$2:$A$100,"<"&MIN(Fact_Baseline_PV!$A$2:$A$44)+((2+1)*7)) -> 1600 | H6: =SUMIFS(Fact_Actual_Costs!$D$2:$D$100,Fact_Actual_Costs!$B$2:$B$100,$A6,Fact_Actual_Costs!$A$2:$A$100,">="&MIN(Fact_Baseline_PV!$A$2:$A$44)+(3*7),Fact_Actual_Costs!$A$2:$A$100,"<"&MIN(Fact_Baseline_PV!$A$2:$A$44)+((3+1)*7)) -> 1600 | I6: =SUMIFS(Fact_Actual_Costs!$D$2:$D$100,Fact_Actual_Costs!$B$2:$B$100,$A6,Fact_Actual_Costs!$A$2:$A$100,">="&MIN(Fact_Baseline_PV!$A$2:$A$44)+(4*7),Fact_Actual_Costs!$A$2:$A$100,"<"&MIN(Fact_Baseline_PV!$A$2:$A$44)+((4+1)*7)) -> 1600 | J6: =SUMIFS(Fact_Actual_Costs!$D$2:$D$100,Fact_Actual_Costs!$B$2:$B$100,$A6,Fact_Actual_Costs!$A$2:$A$100,">="&MIN(Fact_Baseline_PV!$A$2:$A$44)+(5*7),Fact_Actual_Costs!$A$2:$A$100,"<"&MIN(Fact_Baseline_PV!$A$2:$A$44)+((5+1)*7)) -> 1600 | K6: =SUMIFS(Fact_Actual_Costs!$D$2:$D$100,Fact_Actual_Costs!$B$2:$B$100,$A6,Fact_Actual_Costs!$A$2:$A$100,">="&MIN(Fact_Baseline_PV!$A$2:$A$44)+(6*7),Fact_Actual_Costs!$A$2:$A$100,"<"&MIN(Fact_Baseline_PV!$A$2:$A$44)+((6+1)*7)) -> 0 | L6: =SUMIFS(Fact_Actual_Costs!$D$2:$D$100,Fact_Actual_Costs!$B$2:$B$100,$A6,Fact_Actual_Costs!$A$2:$A$100,">="&MIN(Fact_Baseline_PV!$A$2:$A$44)+(7*7),Fact_Actual_Costs!$A$2:$A$100,"<"&MIN(Fact_Baseline_PV!$A$2:$A$44)+((7+1)*7)) -> 0 | M6: =SUMIFS(Fact_Actual_Costs!$D$2:$D$100,Fact_Actual_Costs!$B$2:$B$100,$A6,Fact_Actual_Costs!$A$2:$A$100,">="&MIN(Fact_Baseline_PV!$A$2:$A$44)+(8*7),Fact_Actual_Costs!$A$2:$A$100,"<"&MIN(Fact_Baseline_PV!$A$2:$A$44)+((8+1)*7)) -> 0 | N6: =SUMIFS(Fact_Actual_Costs!$D$2:$D$100,Fact_Actual_Costs!$B$2:$B$100,$A6,Fact_Actual_Costs!$A$2:$A$100,">="&MIN(Fact_Baseline_PV!$A$2:$A$44)+(9*7),Fact_Actual_Costs!$A$2:$A$100,"<"&MIN(Fact_Baseline_PV!$A$2:$A$44)+((9+1)*7)) -> 0 | O6: =SUMIFS(Fact_Actual_Costs!$D$2:$D$100,Fact_Actual_Costs!$B$2:$B$100,$A6,Fact_Actual_Costs!$A$2:$A$100,">="&MIN(Fact_Baseline_PV!$A$2:$A$44)+(10*7),Fact_Actual_Costs!$A$2:$A$100,"<"&MIN(Fact_Baseline_PV!$A$2:$A$44)+((10+1)*7)) -> 0 | P6: =SUMIFS(Fact_Actual_Costs!$D$2:$D$100,Fact_Actual_Costs!$B$2:$B$100,$A6,Fact_Actual_Costs!$A$2:$A$100,">="&MIN(Fact_Baseline_PV!$A$2:$A$44)+(11*7),Fact_Actual_Costs!$A$2:$A$100,"<"&MIN(Fact_Baseline_PV!$A$2:$A$44)+((11+1)*7)) -> 0 | Q6: =SUM(E6:P6) -> 9600 | R6: =VLOOKUP(A6,Dim_WBS!$A$2:$E$13,5,FALSE) -> 18000 | S6: =SUMIFS(Fact_Actual_Costs!$D$2:$D$100,Fact_Actual_Costs!$B$2:$B$100,A6,Fact_Actual_Costs!$A$2:$A$100,"<="&Setup!$B$9) -> 9600 | T6: =R6-S6 -> 8400 | U6: =IFERROR((R6*VLOOKUP(A6,'Task Plan'!$A$5:$K$16,11,FALSE))/S6,1) -> 0.9375 | V6: =IF(U6<Setup!$B$12,"Red",IF(U6<Setup!$B$13,"Amber","Green")) -> Red | W6: 8.1.2 Gantt template from garden office | X6: Cost row
A7: =Dim_WBS!A3 -> WBS-02 | B7: =Dim_WBS!C3 -> Site Survey & Mobilization | C7: =Dim_WBS!D3 -> Labor | D7: Hours | E7: =SUMIFS(Fact_Actual_Costs!$E$2:$E$100,Fact_Actual_Costs!$B$2:$B$100,$A7,Fact_Actual_Costs!$A$2:$A$100,">="&MIN(Fact_Baseline_PV!$A$2:$A$44)+(0*7),Fact_Actual_Costs!$A$2:$A$100,"<"&MIN(Fact_Baseline_PV!$A$2:$A$44)+((0+1)*7)) -> 3.95 | F7: =SUMIFS(Fact_Actual_Costs!$E$2:$E$100,Fact_Actual_Costs!$B$2:$B$100,$A7,Fact_Actual_Costs!$A$2:$A$100,">="&MIN(Fact_Baseline_PV!$A$2:$A$44)+(1*7),Fact_Actual_Costs!$A$2:$A$100,"<"&MIN(Fact_Baseline_PV!$A$2:$A$44)+((1+1)*7)) -> 0 | G7: =SUMIFS(Fact_Actual_Costs!$E$2:$E$100,Fact_Actual_Costs!$B$2:$B$100,$A7,Fact_Actual_Costs!$A$2:$A$100,">="&MIN(Fact_Baseline_PV!$A$2:$A$44)+(2*7),Fact_Actual_Costs!$A$2:$A$100,"<"&MIN(Fact_Baseline_PV!$A$2:$A$44)+((2+1)*7)) -> 0 | H7: =SUMIFS(Fact_Actual_Costs!$E$2:$E$100,Fact_Actual_Costs!$B$2:$B$100,$A7,Fact_Actual_Costs!$A$2:$A$100,">="&MIN(Fact_Baseline_PV!$A$2:$A$44)+(3*7),Fact_Actual_Costs!$A$2:$A$100,"<"&MIN(Fact_Baseline_PV!$A$2:$A$44)+((3+1)*7)) -> 0 | I7: =SUMIFS(Fact_Actual_Costs!$E$2:$E$100,Fact_Actual_Costs!$B$2:$B$100,$A7,Fact_Actual_Costs!$A$2:$A$100,">="&MIN(Fact_Baseline_PV!$A$2:$A$44)+(4*7),Fact_Actual_Costs!$A$2:$A$100,"<"&MIN(Fact_Baseline_PV!$A$2:$A$44)+((4+1)*7)) -> 0 | J7: =SUMIFS(Fact_Actual_Costs!$E$2:$E$100,Fact_Actual_Costs!$B$2:$B$100,$A7,Fact_Actual_Costs!$A$2:$A$100,">="&MIN(Fact_Baseline_PV!$A$2:$A$44)+(5*7),Fact_Actual_Costs!$A$2:$A$100,"<"&MIN(Fact_Baseline_PV!$A$2:$A$44)+((5+1)*7)) -> 0 | K7: =SUMIFS(Fact_Actual_Costs!$E$2:$E$100,Fact_Actual_Costs!$B$2:$B$100,$A7,Fact_Actual_Costs!$A$2:$A$100,">="&MIN(Fact_Baseline_PV!$A$2:$A$44)+(6*7),Fact_Actual_Costs!$A$2:$A$100,"<"&MIN(Fact_Baseline_PV!$A$2:$A$44)+((6+1)*7)) -> 0 | L7: =SUMIFS(Fact_Actual_Costs!$E$2:$E$100,Fact_Actual_Costs!$B$2:$B$100,$A7,Fact_Actual_Costs!$A$2:$A$100,">="&MIN(Fact_Baseline_PV!$A$2:$A$44)+(7*7),Fact_Actual_Costs!$A$2:$A$100,"<"&MIN(Fact_Baseline_PV!$A$2:$A$44)+((7+1)*7)) -> 0 | M7: =SUMIFS(Fact_Actual_Costs!$E$2:$E$100,Fact_Actual_Costs!$B$2:$B$100,$A7,Fact_Actual_Costs!$A$2:$A$100,">="&MIN(Fact_Baseline_PV!$A$2:$A$44)+(8*7),Fact_Actual_Costs!$A$2:$A$100,"<"&MIN(Fact_Baseline_PV!$A$2:$A$44)+((8+1)*7)) -> 0 | N7: =SUMIFS(Fact_Actual_Costs!$E$2:$E$100,Fact_Actual_Costs!$B$2:$B$100,$A7,Fact_Actual_Costs!$A$2:$A$100,">="&MIN(Fact_Baseline_PV!$A$2:$A$44)+(9*7),Fact_Actual_Costs!$A$2:$A$100,"<"&MIN(Fact_Baseline_PV!$A$2:$A$44)+((9+1)*7)) -> 0 | O7: =SUMIFS(Fact_Actual_Costs!$E$2:$E$100,Fact_Actual_Costs!$B$2:$B$100,$A7,Fact_Actual_Costs!$A$2:$A$100,">="&MIN(Fact_Baseline_PV!$A$2:$A$44)+(10*7),Fact_Actual_Costs!$A$2:$A$100,"<"&MIN(Fact_Baseline_PV!$A$2:$A$44)+((10+1)*7)) -> 0 | P7: =SUMIFS(Fact_Actual_Costs!$E$2:$E$100,Fact_Actual_Costs!$B$2:$B$100,$A7,Fact_Actual_Costs!$A$2:$A$100,">="&MIN(Fact_Baseline_PV!$A$2:$A$44)+(11*7),Fact_Actual_Costs!$A$2:$A$100,"<"&MIN(Fact_Baseline_PV!$A$2:$A$44)+((11+1)*7)) -> 0 | Q7: =SUM(E7:P7) -> 3.95 | R7: =VLOOKUP(A7,Dim_WBS!$A$2:$E$13,5,FALSE) -> 8500 | S7: =SUMIFS(Fact_Actual_Costs!$D$2:$D$100,Fact_Actual_Costs!$B$2:$B$100,A7,Fact_Actual_Costs!$A$2:$A$100,"<="&Setup!$B$9) -> 8700 | T7: =R7-S7 -> -200 | U7: =IFERROR((R7*VLOOKUP(A7,'Task Plan'!$A$5:$K$16,11,FALSE))/S7,1) -> 0.97701149 | V7: =IF(U7<Setup!$B$12,"Red",IF(U7<Setup!$B$13,"Amber","Green")) -> Amber | W7: 8.1.2 Gantt template from garden office | X7: Hours row
A8: =Dim_WBS!A3 -> WBS-02 | B8: =Dim_WBS!C3 -> Site Survey & Mobilization | C8: =Dim_WBS!D3 -> Labor | D8: Cost | E8: =SUMIFS(Fact_Actual_Costs!$D$2:$D$100,Fact_Actual_Costs!$B$2:$B$100,$A8,Fact_Actual_Costs!$A$2:$A$100,">="&MIN(Fact_Baseline_PV!$A$2:$A$44)+(0*7),Fact_Actual_Costs!$A$2:$A$100,"<"&MIN(Fact_Baseline_PV!$A$2:$A$44)+((0+1)*7)) -> 8700 | F8: =SUMIFS(Fact_Actual_Costs!$D$2:$D$100,Fact_Actual_Costs!$B$2:$B$100,$A8,Fact_Actual_Costs!$A$2:$A$100,">="&MIN(Fact_Baseline_PV!$A$2:$A$44)+(1*7),Fact_Actual_Costs!$A$2:$A$100,"<"&MIN(Fact_Baseline_PV!$A$2:$A$44)+((1+1)*7)) -> 0 | G8: =SUMIFS(Fact_Actual_Costs!$D$2:$D$100,Fact_Actual_Costs!$B$2:$B$100,$A8,Fact_Actual_Costs!$A$2:$A$100,">="&MIN(Fact_Baseline_PV!$A$2:$A$44)+(2*7),Fact_Actual_Costs!$A$2:$A$100,"<"&MIN(Fact_Baseline_PV!$A$2:$A$44)+((2+1)*7)) -> 0 | H8: =SUMIFS(Fact_Actual_Costs!$D$2:$D$100,Fact_Actual_Costs!$B$2:$B$100,$A8,Fact_Actual_Costs!$A$2:$A$100,">="&MIN(Fact_Baseline_PV!$A$2:$A$44)+(3*7),Fact_Actual_Costs!$A$2:$A$100,"<"&MIN(Fact_Baseline_PV!$A$2:$A$44)+((3+1)*7)) -> 0 | I8: =SUMIFS(Fact_Actual_Costs!$D$2:$D$100,Fact_Actual_Costs!$B$2:$B$100,$A8,Fact_Actual_Costs!$A$2:$A$100,">="&MIN(Fact_Baseline_PV!$A$2:$A$44)+(4*7),Fact_Actual_Costs!$A$2:$A$100,"<"&MIN(Fact_Baseline_PV!$A$2:$A$44)+((4+1)*7)) -> 0 | J8: =SUMIFS(Fact_Actual_Costs!$D$2:$D$100,Fact_Actual_Costs!$B$2:$B$100,$A8,Fact_Actual_Costs!$A$2:$A$100,">="&MIN(Fact_Baseline_PV!$A$2:$A$44)+(5*7),Fact_Actual_Costs!$A$2:$A$100,"<"&MIN(Fact_Baseline_PV!$A$2:$A$44)+((5+1)*7)) -> 0 | K8: =SUMIFS(Fact_Actual_Costs!$D$2:$D$100,Fact_Actual_Costs!$B$2:$B$100,$A8,Fact_Actual_Costs!$A$2:$A$100,">="&MIN(Fact_Baseline_PV!$A$2:$A$44)+(6*7),Fact_Actual_Costs!$A$2:$A$100,"<"&MIN(Fact_Baseline_PV!$A$2:$A$44)+((6+1)*7)) -> 0 | L8: =SUMIFS(Fact_Actual_Costs!$D$2:$D$100,Fact_Actual_Costs!$B$2:$B$100,$A8,Fact_Actual_Costs!$A$2:$A$100,">="&MIN(Fact_Baseline_PV!$A$2:$A$44)+(7*7),Fact_Actual_Costs!$A$2:$A$100,"<"&MIN(Fact_Baseline_PV!$A$2:$A$44)+((7+1)*7)) -> 0 | M8: =SUMIFS(Fact_Actual_Costs!$D$2:$D$100,Fact_Actual_Costs!$B$2:$B$100,$A8,Fact_Actual_Costs!$A$2:$A$100,">="&MIN(Fact_Baseline_PV!$A$2:$A$44)+(8*7),Fact_Actual_Costs!$A$2:$A$100,"<"&MIN(Fact_Baseline_PV!$A$2:$A$44)+((8+1)*7)) -> 0 | N8: =SUMIFS(Fact_Actual_Costs!$D$2:$D$100,Fact_Actual_Costs!$B$2:$B$100,$A8,Fact_Actual_Costs!$A$2:$A$100,">="&MIN(Fact_Baseline_PV!$A$2:$A$44)+(9*7),Fact_Actual_Costs!$A$2:$A$100,"<"&MIN(Fact_Baseline_PV!$A$2:$A$44)+((9+1)*7)) -> 0 | O8: =SUMIFS(Fact_Actual_Costs!$D$2:$D$100,Fact_Actual_Costs!$B$2:$B$100,$A8,Fact_Actual_Costs!$A$2:$A$100,">="&MIN(Fact_Baseline_PV!$A$2:$A$44)+(10*7),Fact_Actual_Costs!$A$2:$A$100,"<"&MIN(Fact_Baseline_PV!$A$2:$A$44)+((10+1)*7)) -> 0 | P8: =SUMIFS(Fact_Actual_Costs!$D$2:$D$100,Fact_Actual_Costs!$B$2:$B$100,$A8,Fact_Actual_Costs!$A$2:$A$100,">="&MIN(Fact_Baseline_PV!$A$2:$A$44)+(11*7),Fact_Actual_Costs!$A$2:$A$100,"<"&MIN(Fact_Baseline_PV!$A$2:$A$44)+((11+1)*7)) -> 0 | Q8: =SUM(E8:P8) -> 8700 | R8: =VLOOKUP(A8,Dim_WBS!$A$2:$E$13,5,FALSE) -> 8500 | S8: =SUMIFS(Fact_Actual_Costs!$D$2:$D$100,Fact_Actual_Costs!$B$2:$B$100,A8,Fact_Actual_Costs!$A$2:$A$100,"<="&Setup!$B$9) -> 8700 | T8: =R8-S8 -> -200 | U8: =IFERROR((R8*VLOOKUP(A8,'Task Plan'!$A$5:$K$16,11,FALSE))/S8,1) -> 0.97701149 | V8: =IF(U8<Setup!$B$12,"Red",IF(U8<Setup!$B$13,"Amber","Green")) -> Amber | W8: 8.1.2 Gantt template from garden office | X8: Cost row
A9: =Dim_WBS!A4 -> WBS-03 | B9: =Dim_WBS!C4 -> Design & Engineering | C9: =Dim_WBS!D4 -> Labor | D9: Hours | E9: =SUMIFS(Fact_Actual_Costs!$E$2:$E$100,Fact_Actual_Costs!$B$2:$B$100,$A9,Fact_Actual_Costs!$A$2:$A$100,">="&MIN(Fact_Baseline_PV!$A$2:$A$44)+(0*7),Fact_Actual_Costs!$A$2:$A$100,"<"&MIN(Fact_Baseline_PV!$A$2:$A$44)+((0+1)*7)) -> 2.5 | F9: =SUMIFS(Fact_Actual_Costs!$E$2:$E$100,Fact_Actual_Costs!$B$2:$B$100,$A9,Fact_Actual_Costs!$A$2:$A$100,">="&MIN(Fact_Baseline_PV!$A$2:$A$44)+(1*7),Fact_Actual_Costs!$A$2:$A$100,"<"&MIN(Fact_Baseline_PV!$A$2:$A$44)+((1+1)*7)) -> 2.5 | G9: =SUMIFS(Fact_Actual_Costs!$E$2:$E$100,Fact_Actual_Costs!$B$2:$B$100,$A9,Fact_Actual_Costs!$A$2:$A$100,">="&MIN(Fact_Baseline_PV!$A$2:$A$44)+(2*7),Fact_Actual_Costs!$A$2:$A$100,"<"&MIN(Fact_Baseline_PV!$A$2:$A$44)+((2+1)*7)) -> 2.6 | H9: =SUMIFS(Fact_Actual_Costs!$E$2:$E$100,Fact_Actual_Costs!$B$2:$B$100,$A9,Fact_Actual_Costs!$A$2:$A$100,">="&MIN(Fact_Baseline_PV!$A$2:$A$44)+(3*7),Fact_Actual_Costs!$A$2:$A$100,"<"&MIN(Fact_Baseline_PV!$A$2:$A$44)+((3+1)*7)) -> 0 | I9: =SUMIFS(Fact_Actual_Costs!$E$2:$E$100,Fact_Actual_Costs!$B$2:$B$100,$A9,Fact_Actual_Costs!$A$2:$A$100,">="&MIN(Fact_Baseline_PV!$A$2:$A$44)+(4*7),Fact_Actual_Costs!$A$2:$A$100,"<"&MIN(Fact_Baseline_PV!$A$2:$A$44)+((4+1)*7)) -> 0 | J9: =SUMIFS(Fact_Actual_Costs!$E$2:$E$100,Fact_Actual_Costs!$B$2:$B$100,$A9,Fact_Actual_Costs!$A$2:$A$100,">="&MIN(Fact_Baseline_PV!$A$2:$A$44)+(5*7),Fact_Actual_Costs!$A$2:$A$100,"<"&MIN(Fact_Baseline_PV!$A$2:$A$44)+((5+1)*7)) -> 0 | K9: =SUMIFS(Fact_Actual_Costs!$E$2:$E$100,Fact_Actual_Costs!$B$2:$B$100,$A9,Fact_Actual_Costs!$A$2:$A$100,">="&MIN(Fact_Baseline_PV!$A$2:$A$44)+(6*7),Fact_Actual_Costs!$A$2:$A$100,"<"&MIN(Fact_Baseline_PV!$A$2:$A$44)+((6+1)*7)) -> 0 | L9: =SUMIFS(Fact_Actual_Costs!$E$2:$E$100,Fact_Actual_Costs!$B$2:$B$100,$A9,Fact_Actual_Costs!$A$2:$A$100,">="&MIN(Fact_Baseline_PV!$A$2:$A$44)+(7*7),Fact_Actual_Costs!$A$2:$A$100,"<"&MIN(Fact_Baseline_PV!$A$2:$A$44)+((7+1)*7)) -> 0 | M9: =SUMIFS(Fact_Actual_Costs!$E$2:$E$100,Fact_Actual_Costs!$B$2:$B$100,$A9,Fact_Actual_Costs!$A$2:$A$100,">="&MIN(Fact_Baseline_PV!$A$2:$A$44)+(8*7),Fact_Actual_Costs!$A$2:$A$100,"<"&MIN(Fact_Baseline_PV!$A$2:$A$44)+((8+1)*7)) -> 0 | N9: =SUMIFS(Fact_Actual_Costs!$E$2:$E$100,Fact_Actual_Costs!$B$2:$B$100,$A9,Fact_Actual_Costs!$A$2:$A$100,">="&MIN(Fact_Baseline_PV!$A$2:$A$44)+(9*7),Fact_Actual_Costs!$A$2:$A$100,"<"&MIN(Fact_Baseline_PV!$A$2:$A$44)+((9+1)*7)) -> 0 | O9: =SUMIFS(Fact_Actual_Costs!$E$2:$E$100,Fact_Actual_Costs!$B$2:$B$100,$A9,Fact_Actual_Costs!$A$2:$A$100,">="&MIN(Fact_Baseline_PV!$A$2:$A$44)+(10*7),Fact_Actual_Costs!$A$2:$A$100,"<"&MIN(Fact_Baseline_PV!$A$2:$A$44)+((10+1)*7)) -> 0 | P9: =SUMIFS(Fact_Actual_Costs!$E$2:$E$100,Fact_Actual_Costs!$B$2:$B$100,$A9,Fact_Actual_Costs!$A$2:$A$100,">="&MIN(Fact_Baseline_PV!$A$2:$A$44)+(11*7),Fact_Actual_Costs!$A$2:$A$100,"<"&MIN(Fact_Baseline_PV!$A$2:$A$44)+((11+1)*7)) -> 0 | Q9: =SUM(E9:P9) -> 7.6 | R9: =VLOOKUP(A9,Dim_WBS!$A$2:$E$13,5,FALSE) -> 19200 | S9: =SUMIFS(Fact_Actual_Costs!$D$2:$D$100,Fact_Actual_Costs!$B$2:$B$100,A9,Fact_Actual_Costs!$A$2:$A$100,"<="&Setup!$B$9) -> 18195.04 | T9: =R9-S9 -> 1004.96 | U9: =IFERROR((R9*VLOOKUP(A9,'Task Plan'!$A$5:$K$16,11,FALSE))/S9,1) -> 1.0552326 | V9: =IF(U9<Setup!$B$12,"Red",IF(U9<Setup!$B$13,"Amber","Green")) -> Green | W9: 8.1.2 Gantt template from garden office | X9: Hours row
A10: =Dim_WBS!A4 -> WBS-03 | B10: =Dim_WBS!C4 -> Design & Engineering | C10: =Dim_WBS!D4 -> Labor | D10: Cost | E10: =SUMIFS(Fact_Actual_Costs!$D$2:$D$100,Fact_Actual_Costs!$B$2:$B$100,$A10,Fact_Actual_Costs!$A$2:$A$100,">="&MIN(Fact_Baseline_PV!$A$2:$A$44)+(0*7),Fact_Actual_Costs!$A$2:$A$100,"<"&MIN(Fact_Baseline_PV!$A$2:$A$44)+((0+1)*7)) -> 5995.04 | F10: =SUMIFS(Fact_Actual_Costs!$D$2:$D$100,Fact_Actual_Costs!$B$2:$B$100,$A10,Fact_Actual_Costs!$A$2:$A$100,">="&MIN(Fact_Baseline_PV!$A$2:$A$44)+(1*7),Fact_Actual_Costs!$A$2:$A$100,"<"&MIN(Fact_Baseline_PV!$A$2:$A$44)+((1+1)*7)) -> 6000 | G10: =SUMIFS(Fact_Actual_Costs!$D$2:$D$100,Fact_Actual_Costs!$B$2:$B$100,$A10,Fact_Actual_Costs!$A$2:$A$100,">="&MIN(Fact_Baseline_PV!$A$2:$A$44)+(2*7),Fact_Actual_Costs!$A$2:$A$100,"<"&MIN(Fact_Baseline_PV!$A$2:$A$44)+((2+1)*7)) -> 6200 | H10: =SUMIFS(Fact_Actual_Costs!$D$2:$D$100,Fact_Actual_Costs!$B$2:$B$100,$A10,Fact_Actual_Costs!$A$2:$A$100,">="&MIN(Fact_Baseline_PV!$A$2:$A$44)+(3*7),Fact_Actual_Costs!$A$2:$A$100,"<"&MIN(Fact_Baseline_PV!$A$2:$A$44)+((3+1)*7)) -> 0 | I10: =SUMIFS(Fact_Actual_Costs!$D$2:$D$100,Fact_Actual_Costs!$B$2:$B$100,$A10,Fact_Actual_Costs!$A$2:$A$100,">="&MIN(Fact_Baseline_PV!$A$2:$A$44)+(4*7),Fact_Actual_Costs!$A$2:$A$100,"<"&MIN(Fact_Baseline_PV!$A$2:$A$44)+((4+1)*7)) -> 0 | J10: =SUMIFS(Fact_Actual_Costs!$D$2:$D$100,Fact_Actual_Costs!$B$2:$B$100,$A10,Fact_Actual_Costs!$A$2:$A$100,">="&MIN(Fact_Baseline_PV!$A$2:$A$44)+(5*7),Fact_Actual_Costs!$A$2:$A$100,"<"&MIN(Fact_Baseline_PV!$A$2:$A$44)+((5+1)*7)) -> 0 | K10: =SUMIFS(Fact_Actual_Costs!$D$2:$D$100,Fact_Actual_Costs!$B$2:$B$100,$A10,Fact_Actual_Costs!$A$2:$A$100,">="&MIN(Fact_Baseline_PV!$A$2:$A$44)+(6*7),Fact_Actual_Costs!$A$2:$A$100,"<"&MIN(Fact_Baseline_PV!$A$2:$A$44)+((6+1)*7)) -> 0 | L10: =SUMIFS(Fact_Actual_Costs!$D$2:$D$100,Fact_Actual_Costs!$B$2:$B$100,$A10,Fact_Actual_Costs!$A$2:$A$100,">="&MIN(Fact_Baseline_PV!$A$2:$A$44)+(7*7),Fact_Actual_Costs!$A$2:$A$100,"<"&MIN(Fact_Baseline_PV!$A$2:$A$44)+((7+1)*7)) -> 0 | M10: =SUMIFS(Fact_Actual_Costs!$D$2:$D$100,Fact_Actual_Costs!$B$2:$B$100,$A10,Fact_Actual_Costs!$A$2:$A$100,">="&MIN(Fact_Baseline_PV!$A$2:$A$44)+(8*7),Fact_Actual_Costs!$A$2:$A$100,"<"&MIN(Fact_Baseline_PV!$A$2:$A$44)+((8+1)*7)) -> 0 | N10: =SUMIFS(Fact_Actual_Costs!$D$2:$D$100,Fact_Actual_Costs!$B$2:$B$100,$A10,Fact_Actual_Costs!$A$2:$A$100,">="&MIN(Fact_Baseline_PV!$A$2:$A$44)+(9*7),Fact_Actual_Costs!$A$2:$A$100,"<"&MIN(Fact_Baseline_PV!$A$2:$A$44)+((9+1)*7)) -> 0 | O10: =SUMIFS(Fact_Actual_Costs!$D$2:$D$100,Fact_Actual_Costs!$B$2:$B$100,$A10,Fact_Actual_Costs!$A$2:$A$100,">="&MIN(Fact_Baseline_PV!$A$2:$A$44)+(10*7),Fact_Actual_Costs!$A$2:$A$100,"<"&MIN(Fact_Baseline_PV!$A$2:$A$44)+((10+1)*7)) -> 0 | P10: =SUMIFS(Fact_Actual_Costs!$D$2:$D$100,Fact_Actual_Costs!$B$2:$B$100,$A10,Fact_Actual_Costs!$A$2:$A$100,">="&MIN(Fact_Baseline_PV!$A$2:$A$44)+(11*7),Fact_Actual_Costs!$A$2:$A$100,"<"&MIN(Fact_Baseline_PV!$A$2:$A$44)+((11+1)*7)) -> 0 | Q10: =SUM(E10:P10) -> 18195.04 | R10: =VLOOKUP(A10,Dim_WBS!$A$2:$E$13,5,FALSE) -> 19200 | S10: =SUMIFS(Fact_Actual_Costs!$D$2:$D$100,Fact_Actual_Costs!$B$2:$B$100,A10,Fact_Actual_Costs!$A$2:$A$100,"<="&Setup!$B$9) -> 18195.04 | T10: =R10-S10 -> 1004.96 | U10: =IFERROR((R10*VLOOKUP(A10,'Task Plan'!$A$5:$K$16,11,FALSE))/S10,1) -> 1.0552326 | V10: =IF(U10<Setup!$B$12,"Red",IF(U10<Setup!$B$13,"Amber","Green")) -> Green | W10: 8.1.2 Gantt template from garden office | X10: Cost row
A11: =Dim_WBS!A5 -> WBS-04 | B11: =Dim_WBS!C5 -> Procurement - Materials | C11: =Dim_WBS!D5 -> Material | D11: Hours | E11: =SUMIFS(Fact_Actual_Costs!$E$2:$E$100,Fact_Actual_Costs!$B$2:$B$100,$A11,Fact_Actual_Costs!$A$2:$A$100,">="&MIN(Fact_Baseline_PV!$A$2:$A$44)+(0*7),Fact_Actual_Costs!$A$2:$A$100,"<"&MIN(Fact_Baseline_PV!$A$2:$A$44)+((0+1)*7)) -> 0 | F11: =SUMIFS(Fact_Actual_Costs!$E$2:$E$100,Fact_Actual_Costs!$B$2:$B$100,$A11,Fact_Actual_Costs!$A$2:$A$100,">="&MIN(Fact_Baseline_PV!$A$2:$A$44)+(1*7),Fact_Actual_Costs!$A$2:$A$100,"<"&MIN(Fact_Baseline_PV!$A$2:$A$44)+((1+1)*7)) -> 0 | G11: =SUMIFS(Fact_Actual_Costs!$E$2:$E$100,Fact_Actual_Costs!$B$2:$B$100,$A11,Fact_Actual_Costs!$A$2:$A$100,">="&MIN(Fact_Baseline_PV!$A$2:$A$44)+(2*7),Fact_Actual_Costs!$A$2:$A$100,"<"&MIN(Fact_Baseline_PV!$A$2:$A$44)+((2+1)*7)) -> 0 | H11: =SUMIFS(Fact_Actual_Costs!$E$2:$E$100,Fact_Actual_Costs!$B$2:$B$100,$A11,Fact_Actual_Costs!$A$2:$A$100,">="&MIN(Fact_Baseline_PV!$A$2:$A$44)+(3*7),Fact_Actual_Costs!$A$2:$A$100,"<"&MIN(Fact_Baseline_PV!$A$2:$A$44)+((3+1)*7)) -> 0 | I11: =SUMIFS(Fact_Actual_Costs!$E$2:$E$100,Fact_Actual_Costs!$B$2:$B$100,$A11,Fact_Actual_Costs!$A$2:$A$100,">="&MIN(Fact_Baseline_PV!$A$2:$A$44)+(4*7),Fact_Actual_Costs!$A$2:$A$100,"<"&MIN(Fact_Baseline_PV!$A$2:$A$44)+((4+1)*7)) -> 0 | J11: =SUMIFS(Fact_Actual_Costs!$E$2:$E$100,Fact_Actual_Costs!$B$2:$B$100,$A11,Fact_Actual_Costs!$A$2:$A$100,">="&MIN(Fact_Baseline_PV!$A$2:$A$44)+(5*7),Fact_Actual_Costs!$A$2:$A$100,"<"&MIN(Fact_Baseline_PV!$A$2:$A$44)+((5+1)*7)) -> 0 | K11: =SUMIFS(Fact_Actual_Costs!$E$2:$E$100,Fact_Actual_Costs!$B$2:$B$100,$A11,Fact_Actual_Costs!$A$2:$A$100,">="&MIN(Fact_Baseline_PV!$A$2:$A$44)+(6*7),Fact_Actual_Costs!$A$2:$A$100,"<"&MIN(Fact_Baseline_PV!$A$2:$A$44)+((6+1)*7)) -> 0 | L11: =SUMIFS(Fact_Actual_Costs!$E$2:$E$100,Fact_Actual_Costs!$B$2:$B$100,$A11,Fact_Actual_Costs!$A$2:$A$100,">="&MIN(Fact_Baseline_PV!$A$2:$A$44)+(7*7),Fact_Actual_Costs!$A$2:$A$100,"<"&MIN(Fact_Baseline_PV!$A$2:$A$44)+((7+1)*7)) -> 0 | M11: =SUMIFS(Fact_Actual_Costs!$E$2:$E$100,Fact_Actual_Costs!$B$2:$B$100,$A11,Fact_Actual_Costs!$A$2:$A$100,">="&MIN(Fact_Baseline_PV!$A$2:$A$44)+(8*7),Fact_Actual_Costs!$A$2:$A$100,"<"&MIN(Fact_Baseline_PV!$A$2:$A$44)+((8+1)*7)) -> 0 | N11: =SUMIFS(Fact_Actual_Costs!$E$2:$E$100,Fact_Actual_Costs!$B$2:$B$100,$A11,Fact_Actual_Costs!$A$2:$A$100,">="&MIN(Fact_Baseline_PV!$A$2:$A$44)+(9*7),Fact_Actual_Costs!$A$2:$A$100,"<"&MIN(Fact_Baseline_PV!$A$2:$A$44)+((9+1)*7)) -> 0 | O11: =SUMIFS(Fact_Actual_Costs!$E$2:$E$100,Fact_Actual_Costs!$B$2:$B$100,$A11,Fact_Actual_Costs!$A$2:$A$100,">="&MIN(Fact_Baseline_PV!$A$2:$A$44)+(10*7),Fact_Actual_Costs!$A$2:$A$100,"<"&MIN(Fact_Baseline_PV!$A$2:$A$44)+((10+1)*7)) -> 0 | P11: =SUMIFS(Fact_Actual_Costs!$E$2:$E$100,Fact_Actual_Costs!$B$2:$B$100,$A11,Fact_Actual_Costs!$A$2:$A$100,">="&MIN(Fact_Baseline_PV!$A$2:$A$44)+(11*7),Fact_Actual_Costs!$A$2:$A$100,"<"&MIN(Fact_Baseline_PV!$A$2:$A$44)+((11+1)*7)) -> 0 | Q11: =SUM(E11:P11) -> 0 | R11: =VLOOKUP(A11,Dim_WBS!$A$2:$E$13,5,FALSE) -> 42000 | S11: =SUMIFS(Fact_Actual_Costs!$D$2:$D$100,Fact_Actual_Costs!$B$2:$B$100,A11,Fact_Actual_Costs!$A$2:$A$100,"<="&Setup!$B$9) -> 41300 | T11: =R11-S11 -> 700 | U11: =IFERROR((R11*VLOOKUP(A11,'Task Plan'!$A$5:$K$16,11,FALSE))/S11,1) -> 1.0169492 | V11: =IF(U11<Setup!$B$12,"Red",IF(U11<Setup!$B$13,"Amber","Green")) -> Green | W11: 8.1.2 Gantt template from garden office | X11: Hours row
A12: =Dim_WBS!A5 -> WBS-04 | B12: =Dim_WBS!C5 -> Procurement - Materials | C12: =Dim_WBS!D5 -> Material | D12: Cost | E12: =SUMIFS(Fact_Actual_Costs!$D$2:$D$100,Fact_Actual_Costs!$B$2:$B$100,$A12,Fact_Actual_Costs!$A$2:$A$100,">="&MIN(Fact_Baseline_PV!$A$2:$A$44)+(0*7),Fact_Actual_Costs!$A$2:$A$100,"<"&MIN(Fact_Baseline_PV!$A$2:$A$44)+((0+1)*7)) -> 0 | F12: =SUMIFS(Fact_Actual_Costs!$D$2:$D$100,Fact_Actual_Costs!$B$2:$B$100,$A12,Fact_Actual_Costs!$A$2:$A$100,">="&MIN(Fact_Baseline_PV!$A$2:$A$44)+(1*7),Fact_Actual_Costs!$A$2:$A$100,"<"&MIN(Fact_Baseline_PV!$A$2:$A$44)+((1+1)*7)) -> 10500 | G12: =SUMIFS(Fact_Actual_Costs!$D$2:$D$100,Fact_Actual_Costs!$B$2:$B$100,$A12,Fact_Actual_Costs!$A$2:$A$100,">="&MIN(Fact_Baseline_PV!$A$2:$A$44)+(2*7),Fact_Actual_Costs!$A$2:$A$100,"<"&MIN(Fact_Baseline_PV!$A$2:$A$44)+((2+1)*7)) -> 10200 | H12: =SUMIFS(Fact_Actual_Costs!$D$2:$D$100,Fact_Actual_Costs!$B$2:$B$100,$A12,Fact_Actual_Costs!$A$2:$A$100,">="&MIN(Fact_Baseline_PV!$A$2:$A$44)+(3*7),Fact_Actual_Costs!$A$2:$A$100,"<"&MIN(Fact_Baseline_PV!$A$2:$A$44)+((3+1)*7)) -> 10200 | I12: =SUMIFS(Fact_Actual_Costs!$D$2:$D$100,Fact_Actual_Costs!$B$2:$B$100,$A12,Fact_Actual_Costs!$A$2:$A$100,">="&MIN(Fact_Baseline_PV!$A$2:$A$44)+(4*7),Fact_Actual_Costs!$A$2:$A$100,"<"&MIN(Fact_Baseline_PV!$A$2:$A$44)+((4+1)*7)) -> 10400 | J12: =SUMIFS(Fact_Actual_Costs!$D$2:$D$100,Fact_Actual_Costs!$B$2:$B$100,$A12,Fact_Actual_Costs!$A$2:$A$100,">="&MIN(Fact_Baseline_PV!$A$2:$A$44)+(5*7),Fact_Actual_Costs!$A$2:$A$100,"<"&MIN(Fact_Baseline_PV!$A$2:$A$44)+((5+1)*7)) -> 0 | K12: =SUMIFS(Fact_Actual_Costs!$D$2:$D$100,Fact_Actual_Costs!$B$2:$B$100,$A12,Fact_Actual_Costs!$A$2:$A$100,">="&MIN(Fact_Baseline_PV!$A$2:$A$44)+(6*7),Fact_Actual_Costs!$A$2:$A$100,"<"&MIN(Fact_Baseline_PV!$A$2:$A$44)+((6+1)*7)) -> 0 | L12: =SUMIFS(Fact_Actual_Costs!$D$2:$D$100,Fact_Actual_Costs!$B$2:$B$100,$A12,Fact_Actual_Costs!$A$2:$A$100,">="&MIN(Fact_Baseline_PV!$A$2:$A$44)+(7*7),Fact_Actual_Costs!$A$2:$A$100,"<"&MIN(Fact_Baseline_PV!$A$2:$A$44)+((7+1)*7)) -> 0 | M12: =SUMIFS(Fact_Actual_Costs!$D$2:$D$100,Fact_Actual_Costs!$B$2:$B$100,$A12,Fact_Actual_Costs!$A$2:$A$100,">="&MIN(Fact_Baseline_PV!$A$2:$A$44)+(8*7),Fact_Actual_Costs!$A$2:$A$100,"<"&MIN(Fact_Baseline_PV!$A$2:$A$44)+((8+1)*7)) -> 0 | N12: =SUMIFS(Fact_Actual_Costs!$D$2:$D$100,Fact_Actual_Costs!$B$2:$B$100,$A12,Fact_Actual_Costs!$A$2:$A$100,">="&MIN(Fact_Baseline_PV!$A$2:$A$44)+(9*7),Fact_Actual_Costs!$A$2:$A$100,"<"&MIN(Fact_Baseline_PV!$A$2:$A$44)+((9+1)*7)) -> 0 | O12: =SUMIFS(Fact_Actual_Costs!$D$2:$D$100,Fact_Actual_Costs!$B$2:$B$100,$A12,Fact_Actual_Costs!$A$2:$A$100,">="&MIN(Fact_Baseline_PV!$A$2:$A$44)+(10*7),Fact_Actual_Costs!$A$2:$A$100,"<"&MIN(Fact_Baseline_PV!$A$2:$A$44)+((10+1)*7)) -> 0 | P12: =SUMIFS(Fact_Actual_Costs!$D$2:$D$100,Fact_Actual_Costs!$B$2:$B$100,$A12,Fact_Actual_Costs!$A$2:$A$100,">="&MIN(Fact_Baseline_PV!$A$2:$A$44)+(11*7),Fact_Actual_Costs!$A$2:$A$100,"<"&MIN(Fact_Baseline_PV!$A$2:$A$44)+((11+1)*7)) -> 0 | Q12: =SUM(E12:P12) -> 41300 | R12: =VLOOKUP(A12,Dim_WBS!$A$2:$E$13,5,FALSE) -> 42000 | S12: =SUMIFS(Fact_Actual_Costs!$D$2:$D$100,Fact_Actual_Costs!$B$2:$B$100,A12,Fact_Actual_Costs!$A$2:$A$100,"<="&Setup!$B$9) -> 41300 | T12: =R12-S12 -> 700 | U12: =IFERROR((R12*VLOOKUP(A12,'Task Plan'!$A$5:$K$16,11,FALSE))/S12,1) -> 1.0169492 | V12: =IF(U12<Setup!$B$12,"Red",IF(U12<Setup!$B$13,"Amber","Green")) -> Green | W12: 8.1.2 Gantt template from garden office | X12: Cost row
A13: =Dim_WBS!A6 -> WBS-05 | B13: =Dim_WBS!C6 -> Demolition & Prep | C13: =Dim_WBS!D6 -> Labor | D13: Hours | E13: =SUMIFS(Fact_Actual_Costs!$E$2:$E$100,Fact_Actual_Costs!$B$2:$B$100,$A13,Fact_Actual_Costs!$A$2:$A$100,">="&MIN(Fact_Baseline_PV!$A$2:$A$44)+(0*7),Fact_Actual_Costs!$A$2:$A$100,"<"&MIN(Fact_Baseline_PV!$A$2:$A$44)+((0+1)*7)) -> 0 | F13: =SUMIFS(Fact_Actual_Costs!$E$2:$E$100,Fact_Actual_Costs!$B$2:$B$100,$A13,Fact_Actual_Costs!$A$2:$A$100,">="&MIN(Fact_Baseline_PV!$A$2:$A$44)+(1*7),Fact_Actual_Costs!$A$2:$A$100,"<"&MIN(Fact_Baseline_PV!$A$2:$A$44)+((1+1)*7)) -> 2.05 | G13: =SUMIFS(Fact_Actual_Costs!$E$2:$E$100,Fact_Actual_Costs!$B$2:$B$100,$A13,Fact_Actual_Costs!$A$2:$A$100,">="&MIN(Fact_Baseline_PV!$A$2:$A$44)+(2*7),Fact_Actual_Costs!$A$2:$A$100,"<"&MIN(Fact_Baseline_PV!$A$2:$A$44)+((2+1)*7)) -> 2.1 | H13: =SUMIFS(Fact_Actual_Costs!$E$2:$E$100,Fact_Actual_Costs!$B$2:$B$100,$A13,Fact_Actual_Costs!$A$2:$A$100,">="&MIN(Fact_Baseline_PV!$A$2:$A$44)+(3*7),Fact_Actual_Costs!$A$2:$A$100,"<"&MIN(Fact_Baseline_PV!$A$2:$A$44)+((3+1)*7)) -> 1.9 | I13: =SUMIFS(Fact_Actual_Costs!$E$2:$E$100,Fact_Actual_Costs!$B$2:$B$100,$A13,Fact_Actual_Costs!$A$2:$A$100,">="&MIN(Fact_Baseline_PV!$A$2:$A$44)+(4*7),Fact_Actual_Costs!$A$2:$A$100,"<"&MIN(Fact_Baseline_PV!$A$2:$A$44)+((4+1)*7)) -> 0 | J13: =SUMIFS(Fact_Actual_Costs!$E$2:$E$100,Fact_Actual_Costs!$B$2:$B$100,$A13,Fact_Actual_Costs!$A$2:$A$100,">="&MIN(Fact_Baseline_PV!$A$2:$A$44)+(5*7),Fact_Actual_Costs!$A$2:$A$100,"<"&MIN(Fact_Baseline_PV!$A$2:$A$44)+((5+1)*7)) -> 0 | K13: =SUMIFS(Fact_Actual_Costs!$E$2:$E$100,Fact_Actual_Costs!$B$2:$B$100,$A13,Fact_Actual_Costs!$A$2:$A$100,">="&MIN(Fact_Baseline_PV!$A$2:$A$44)+(6*7),Fact_Actual_Costs!$A$2:$A$100,"<"&MIN(Fact_Baseline_PV!$A$2:$A$44)+((6+1)*7)) -> 0 | L13: =SUMIFS(Fact_Actual_Costs!$E$2:$E$100,Fact_Actual_Costs!$B$2:$B$100,$A13,Fact_Actual_Costs!$A$2:$A$100,">="&MIN(Fact_Baseline_PV!$A$2:$A$44)+(7*7),Fact_Actual_Costs!$A$2:$A$100,"<"&MIN(Fact_Baseline_PV!$A$2:$A$44)+((7+1)*7)) -> 0 | M13: =SUMIFS(Fact_Actual_Costs!$E$2:$E$100,Fact_Actual_Costs!$B$2:$B$100,$A13,Fact_Actual_Costs!$A$2:$A$100,">="&MIN(Fact_Baseline_PV!$A$2:$A$44)+(8*7),Fact_Actual_Costs!$A$2:$A$100,"<"&MIN(Fact_Baseline_PV!$A$2:$A$44)+((8+1)*7)) -> 0 | N13: =SUMIFS(Fact_Actual_Costs!$E$2:$E$100,Fact_Actual_Costs!$B$2:$B$100,$A13,Fact_Actual_Costs!$A$2:$A$100,">="&MIN(Fact_Baseline_PV!$A$2:$A$44)+(9*7),Fact_Actual_Costs!$A$2:$A$100,"<"&MIN(Fact_Baseline_PV!$A$2:$A$44)+((9+1)*7)) -> 0 | O13: =SUMIFS(Fact_Actual_Costs!$E$2:$E$100,Fact_Actual_Costs!$B$2:$B$100,$A13,Fact_Actual_Costs!$A$2:$A$100,">="&MIN(Fact_Baseline_PV!$A$2:$A$44)+(10*7),Fact_Actual_Costs!$A$2:$A$100,"<"&MIN(Fact_Baseline_PV!$A$2:$A$44)+((10+1)*7)) -> 0 | P13: =SUMIFS(Fact_Actual_Costs!$E$2:$E$100,Fact_Actual_Costs!$B$2:$B$100,$A13,Fact_Actual_Costs!$A$2:$A$100,">="&MIN(Fact_Baseline_PV!$A$2:$A$44)+(11*7),Fact_Actual_Costs!$A$2:$A$100,"<"&MIN(Fact_Baseline_PV!$A$2:$A$44)+((11+1)*7)) -> 0 | Q13: =SUM(E13:P13) -> 6.05 | R13: =VLOOKUP(A13,Dim_WBS!$A$2:$E$13,5,FALSE) -> 13200 | S13: =SUMIFS(Fact_Actual_Costs!$D$2:$D$100,Fact_Actual_Costs!$B$2:$B$100,A13,Fact_Actual_Costs!$A$2:$A$100,"<="&Setup!$B$9) -> 13408.16 | T13: =R13-S13 -> -208.16 | U13: =IFERROR((R13*VLOOKUP(A13,'Task Plan'!$A$5:$K$16,11,FALSE))/S13,1) -> 0.98447513 | V13: =IF(U13<Setup!$B$12,"Red",IF(U13<Setup!$B$13,"Amber","Green")) -> Amber | W13: 8.1.2 Gantt template from garden office | X13: Hours row
A14: =Dim_WBS!A6 -> WBS-05 | B14: =Dim_WBS!C6 -> Demolition & Prep | C14: =Dim_WBS!D6 -> Labor | D14: Cost | E14: =SUMIFS(Fact_Actual_Costs!$D$2:$D$100,Fact_Actual_Costs!$B$2:$B$100,$A14,Fact_Actual_Costs!$A$2:$A$100,">="&MIN(Fact_Baseline_PV!$A$2:$A$44)+(0*7),Fact_Actual_Costs!$A$2:$A$100,"<"&MIN(Fact_Baseline_PV!$A$2:$A$44)+((0+1)*7)) -> 0 | F14: =SUMIFS(Fact_Actual_Costs!$D$2:$D$100,Fact_Actual_Costs!$B$2:$B$100,$A14,Fact_Actual_Costs!$A$2:$A$100,">="&MIN(Fact_Baseline_PV!$A$2:$A$44)+(1*7),Fact_Actual_Costs!$A$2:$A$100,"<"&MIN(Fact_Baseline_PV!$A$2:$A$44)+((1+1)*7)) -> 4554.08 | G14: =SUMIFS(Fact_Actual_Costs!$D$2:$D$100,Fact_Actual_Costs!$B$2:$B$100,$A14,Fact_Actual_Costs!$A$2:$A$100,">="&MIN(Fact_Baseline_PV!$A$2:$A$44)+(2*7),Fact_Actual_Costs!$A$2:$A$100,"<"&MIN(Fact_Baseline_PV!$A$2:$A$44)+((2+1)*7)) -> 4654.08 | H14: =SUMIFS(Fact_Actual_Costs!$D$2:$D$100,Fact_Actual_Costs!$B$2:$B$100,$A14,Fact_Actual_Costs!$A$2:$A$100,">="&MIN(Fact_Baseline_PV!$A$2:$A$44)+(3*7),Fact_Actual_Costs!$A$2:$A$100,"<"&MIN(Fact_Baseline_PV!$A$2:$A$44)+((3+1)*7)) -> 4200 | I14: =SUMIFS(Fact_Actual_Costs!$D$2:$D$100,Fact_Actual_Costs!$B$2:$B$100,$A14,Fact_Actual_Costs!$A$2:$A$100,">="&MIN(Fact_Baseline_PV!$A$2:$A$44)+(4*7),Fact_Actual_Costs!$A$2:$A$100,"<"&MIN(Fact_Baseline_PV!$A$2:$A$44)+((4+1)*7)) -> 0 | J14: =SUMIFS(Fact_Actual_Costs!$D$2:$D$100,Fact_Actual_Costs!$B$2:$B$100,$A14,Fact_Actual_Costs!$A$2:$A$100,">="&MIN(Fact_Baseline_PV!$A$2:$A$44)+(5*7),Fact_Actual_Costs!$A$2:$A$100,"<"&MIN(Fact_Baseline_PV!$A$2:$A$44)+((5+1)*7)) -> 0 | K14: =SUMIFS(Fact_Actual_Costs!$D$2:$D$100,Fact_Actual_Costs!$B$2:$B$100,$A14,Fact_Actual_Costs!$A$2:$A$100,">="&MIN(Fact_Baseline_PV!$A$2:$A$44)+(6*7),Fact_Actual_Costs!$A$2:$A$100,"<"&MIN(Fact_Baseline_PV!$A$2:$A$44)+((6+1)*7)) -> 0 | L14: =SUMIFS(Fact_Actual_Costs!$D$2:$D$100,Fact_Actual_Costs!$B$2:$B$100,$A14,Fact_Actual_Costs!$A$2:$A$100,">="&MIN(Fact_Baseline_PV!$A$2:$A$44)+(7*7),Fact_Actual_Costs!$A$2:$A$100,"<"&MIN(Fact_Baseline_PV!$A$2:$A$44)+((7+1)*7)) -> 0 | M14: =SUMIFS(Fact_Actual_Costs!$D$2:$D$100,Fact_Actual_Costs!$B$2:$B$100,$A14,Fact_Actual_Costs!$A$2:$A$100,">="&MIN(Fact_Baseline_PV!$A$2:$A$44)+(8*7),Fact_Actual_Costs!$A$2:$A$100,"<"&MIN(Fact_Baseline_PV!$A$2:$A$44)+((8+1)*7)) -> 0 | N14: =SUMIFS(Fact_Actual_Costs!$D$2:$D$100,Fact_Actual_Costs!$B$2:$B$100,$A14,Fact_Actual_Costs!$A$2:$A$100,">="&MIN(Fact_Baseline_PV!$A$2:$A$44)+(9*7),Fact_Actual_Costs!$A$2:$A$100,"<"&MIN(Fact_Baseline_PV!$A$2:$A$44)+((9+1)*7)) -> 0 | O14: =SUMIFS(Fact_Actual_Costs!$D$2:$D$100,Fact_Actual_Costs!$B$2:$B$100,$A14,Fact_Actual_Costs!$A$2:$A$100,">="&MIN(Fact_Baseline_PV!$A$2:$A$44)+(10*7),Fact_Actual_Costs!$A$2:$A$100,"<"&MIN(Fact_Baseline_PV!$A$2:$A$44)+((10+1)*7)) -> 0 | P14: =SUMIFS(Fact_Actual_Costs!$D$2:$D$100,Fact_Actual_Costs!$B$2:$B$100,$A14,Fact_Actual_Costs!$A$2:$A$100,">="&MIN(Fact_Baseline_PV!$A$2:$A$44)+(11*7),Fact_Actual_Costs!$A$2:$A$100,"<"&MIN(Fact_Baseline_PV!$A$2:$A$44)+((11+1)*7)) -> 0 | Q14: =SUM(E14:P14) -> 13408.16 | R14: =VLOOKUP(A14,Dim_WBS!$A$2:$E$13,5,FALSE) -> 13200 | S14: =SUMIFS(Fact_Actual_Costs!$D$2:$D$100,Fact_Actual_Costs!$B$2:$B$100,A14,Fact_Actual_Costs!$A$2:$A$100,"<="&Setup!$B$9) -> 13408.16 | T14: =R14-S14 -> -208.16 | U14: =IFERROR((R14*VLOOKUP(A14,'Task Plan'!$A$5:$K$16,11,FALSE))/S14,1) -> 0.98447513 | V14: =IF(U14<Setup!$B$12,"Red",IF(U14<Setup!$B$13,"Amber","Green")) -> Amber | W14: 8.1.2 Gantt template from garden office | X14: Cost row
A15: =Dim_WBS!A7 -> WBS-06 | B15: =Dim_WBS!C7 -> Electrical Rough-In | C15: =Dim_WBS!D7 -> Labor | D15: Hours | E15: =SUMIFS(Fact_Actual_Costs!$E$2:$E$100,Fact_Actual_Costs!$B$2:$B$100,$A15,Fact_Actual_Costs!$A$2:$A$100,">="&MIN(Fact_Baseline_PV!$A$2:$A$44)+(0*7),Fact_Actual_Costs!$A$2:$A$100,"<"&MIN(Fact_Baseline_PV!$A$2:$A$44)+((0+1)*7)) -> 0 | F15: =SUMIFS(Fact_Actual_Costs!$E$2:$E$100,Fact_Actual_Costs!$B$2:$B$100,$A15,Fact_Actual_Costs!$A$2:$A$100,">="&MIN(Fact_Baseline_PV!$A$2:$A$44)+(1*7),Fact_Actual_Costs!$A$2:$A$100,"<"&MIN(Fact_Baseline_PV!$A$2:$A$44)+((1+1)*7)) -> 0 | G15: =SUMIFS(Fact_Actual_Costs!$E$2:$E$100,Fact_Actual_Costs!$B$2:$B$100,$A15,Fact_Actual_Costs!$A$2:$A$100,">="&MIN(Fact_Baseline_PV!$A$2:$A$44)+(2*7),Fact_Actual_Costs!$A$2:$A$100,"<"&MIN(Fact_Baseline_PV!$A$2:$A$44)+((2+1)*7)) -> 0 | H15: =SUMIFS(Fact_Actual_Costs!$E$2:$E$100,Fact_Actual_Costs!$B$2:$B$100,$A15,Fact_Actual_Costs!$A$2:$A$100,">="&MIN(Fact_Baseline_PV!$A$2:$A$44)+(3*7),Fact_Actual_Costs!$A$2:$A$100,"<"&MIN(Fact_Baseline_PV!$A$2:$A$44)+((3+1)*7)) -> 3.45 | I15: =SUMIFS(Fact_Actual_Costs!$E$2:$E$100,Fact_Actual_Costs!$B$2:$B$100,$A15,Fact_Actual_Costs!$A$2:$A$100,">="&MIN(Fact_Baseline_PV!$A$2:$A$44)+(4*7),Fact_Actual_Costs!$A$2:$A$100,"<"&MIN(Fact_Baseline_PV!$A$2:$A$44)+((4+1)*7)) -> 3.4 | J15: =SUMIFS(Fact_Actual_Costs!$E$2:$E$100,Fact_Actual_Costs!$B$2:$B$100,$A15,Fact_Actual_Costs!$A$2:$A$100,">="&MIN(Fact_Baseline_PV!$A$2:$A$44)+(5*7),Fact_Actual_Costs!$A$2:$A$100,"<"&MIN(Fact_Baseline_PV!$A$2:$A$44)+((5+1)*7)) -> 3.25 | K15: =SUMIFS(Fact_Actual_Costs!$E$2:$E$100,Fact_Actual_Costs!$B$2:$B$100,$A15,Fact_Actual_Costs!$A$2:$A$100,">="&MIN(Fact_Baseline_PV!$A$2:$A$44)+(6*7),Fact_Actual_Costs!$A$2:$A$100,"<"&MIN(Fact_Baseline_PV!$A$2:$A$44)+((6+1)*7)) -> 0 | L15: =SUMIFS(Fact_Actual_Costs!$E$2:$E$100,Fact_Actual_Costs!$B$2:$B$100,$A15,Fact_Actual_Costs!$A$2:$A$100,">="&MIN(Fact_Baseline_PV!$A$2:$A$44)+(7*7),Fact_Actual_Costs!$A$2:$A$100,"<"&MIN(Fact_Baseline_PV!$A$2:$A$44)+((7+1)*7)) -> 0 | M15: =SUMIFS(Fact_Actual_Costs!$E$2:$E$100,Fact_Actual_Costs!$B$2:$B$100,$A15,Fact_Actual_Costs!$A$2:$A$100,">="&MIN(Fact_Baseline_PV!$A$2:$A$44)+(8*7),Fact_Actual_Costs!$A$2:$A$100,"<"&MIN(Fact_Baseline_PV!$A$2:$A$44)+((8+1)*7)) -> 0 | N15: =SUMIFS(Fact_Actual_Costs!$E$2:$E$100,Fact_Actual_Costs!$B$2:$B$100,$A15,Fact_Actual_Costs!$A$2:$A$100,">="&MIN(Fact_Baseline_PV!$A$2:$A$44)+(9*7),Fact_Actual_Costs!$A$2:$A$100,"<"&MIN(Fact_Baseline_PV!$A$2:$A$44)+((9+1)*7)) -> 0 | O15: =SUMIFS(Fact_Actual_Costs!$E$2:$E$100,Fact_Actual_Costs!$B$2:$B$100,$A15,Fact_Actual_Costs!$A$2:$A$100,">="&MIN(Fact_Baseline_PV!$A$2:$A$44)+(10*7),Fact_Actual_Costs!$A$2:$A$100,"<"&MIN(Fact_Baseline_PV!$A$2:$A$44)+((10+1)*7)) -> 0 | P15: =SUMIFS(Fact_Actual_Costs!$E$2:$E$100,Fact_Actual_Costs!$B$2:$B$100,$A15,Fact_Actual_Costs!$A$2:$A$100,">="&MIN(Fact_Baseline_PV!$A$2:$A$44)+(11*7),Fact_Actual_Costs!$A$2:$A$100,"<"&MIN(Fact_Baseline_PV!$A$2:$A$44)+((11+1)*7)) -> 0 | Q15: =SUM(E15:P15) -> 10.1 | R15: =VLOOKUP(A15,Dim_WBS!$A$2:$E$13,5,FALSE) -> 26000 | S15: =SUMIFS(Fact_Actual_Costs!$D$2:$D$100,Fact_Actual_Costs!$B$2:$B$100,A15,Fact_Actual_Costs!$A$2:$A$100,"<="&Setup!$B$9) -> 26206.24 | T15: =R15-S15 -> -206.24 | U15: =IFERROR((R15*VLOOKUP(A15,'Task Plan'!$A$5:$K$16,11,FALSE))/S15,1) -> 0.69449108 | V15: =IF(U15<Setup!$B$12,"Red",IF(U15<Setup!$B$13,"Amber","Green")) -> Red | W15: 8.1.2 Gantt template from garden office | X15: Hours row
A16: =Dim_WBS!A7 -> WBS-06 | B16: =Dim_WBS!C7 -> Electrical Rough-In | C16: =Dim_WBS!D7 -> Labor | D16: Cost | E16: =SUMIFS(Fact_Actual_Costs!$D$2:$D$100,Fact_Actual_Costs!$B$2:$B$100,$A16,Fact_Actual_Costs!$A$2:$A$100,">="&MIN(Fact_Baseline_PV!$A$2:$A$44)+(0*7),Fact_Actual_Costs!$A$2:$A$100,"<"&MIN(Fact_Baseline_PV!$A$2:$A$44)+((0+1)*7)) -> 0 | F16: =SUMIFS(Fact_Actual_Costs!$D$2:$D$100,Fact_Actual_Costs!$B$2:$B$100,$A16,Fact_Actual_Costs!$A$2:$A$100,">="&MIN(Fact_Baseline_PV!$A$2:$A$44)+(1*7),Fact_Actual_Costs!$A$2:$A$100,"<"&MIN(Fact_Baseline_PV!$A$2:$A$44)+((1+1)*7)) -> 0 | G16: =SUMIFS(Fact_Actual_Costs!$D$2:$D$100,Fact_Actual_Costs!$B$2:$B$100,$A16,Fact_Actual_Costs!$A$2:$A$100,">="&MIN(Fact_Baseline_PV!$A$2:$A$44)+(2*7),Fact_Actual_Costs!$A$2:$A$100,"<"&MIN(Fact_Baseline_PV!$A$2:$A$44)+((2+1)*7)) -> 0 | H16: =SUMIFS(Fact_Actual_Costs!$D$2:$D$100,Fact_Actual_Costs!$B$2:$B$100,$A16,Fact_Actual_Costs!$A$2:$A$100,">="&MIN(Fact_Baseline_PV!$A$2:$A$44)+(3*7),Fact_Actual_Costs!$A$2:$A$100,"<"&MIN(Fact_Baseline_PV!$A$2:$A$44)+((3+1)*7)) -> 8906.24 | I16: =SUMIFS(Fact_Actual_Costs!$D$2:$D$100,Fact_Actual_Costs!$B$2:$B$100,$A16,Fact_Actual_Costs!$A$2:$A$100,">="&MIN(Fact_Baseline_PV!$A$2:$A$44)+(4*7),Fact_Actual_Costs!$A$2:$A$100,"<"&MIN(Fact_Baseline_PV!$A$2:$A$44)+((4+1)*7)) -> 8800 | J16: =SUMIFS(Fact_Actual_Costs!$D$2:$D$100,Fact_Actual_Costs!$B$2:$B$100,$A16,Fact_Actual_Costs!$A$2:$A$100,">="&MIN(Fact_Baseline_PV!$A$2:$A$44)+(5*7),Fact_Actual_Costs!$A$2:$A$100,"<"&MIN(Fact_Baseline_PV!$A$2:$A$44)+((5+1)*7)) -> 8500 | K16: =SUMIFS(Fact_Actual_Costs!$D$2:$D$100,Fact_Actual_Costs!$B$2:$B$100,$A16,Fact_Actual_Costs!$A$2:$A$100,">="&MIN(Fact_Baseline_PV!$A$2:$A$44)+(6*7),Fact_Actual_Costs!$A$2:$A$100,"<"&MIN(Fact_Baseline_PV!$A$2:$A$44)+((6+1)*7)) -> 0 | L16: =SUMIFS(Fact_Actual_Costs!$D$2:$D$100,Fact_Actual_Costs!$B$2:$B$100,$A16,Fact_Actual_Costs!$A$2:$A$100,">="&MIN(Fact_Baseline_PV!$A$2:$A$44)+(7*7),Fact_Actual_Costs!$A$2:$A$100,"<"&MIN(Fact_Baseline_PV!$A$2:$A$44)+((7+1)*7)) -> 0 | M16: =SUMIFS(Fact_Actual_Costs!$D$2:$D$100,Fact_Actual_Costs!$B$2:$B$100,$A16,Fact_Actual_Costs!$A$2:$A$100,">="&MIN(Fact_Baseline_PV!$A$2:$A$44)+(8*7),Fact_Actual_Costs!$A$2:$A$100,"<"&MIN(Fact_Baseline_PV!$A$2:$A$44)+((8+1)*7)) -> 0 | N16: =SUMIFS(Fact_Actual_Costs!$D$2:$D$100,Fact_Actual_Costs!$B$2:$B$100,$A16,Fact_Actual_Costs!$A$2:$A$100,">="&MIN(Fact_Baseline_PV!$A$2:$A$44)+(9*7),Fact_Actual_Costs!$A$2:$A$100,"<"&MIN(Fact_Baseline_PV!$A$2:$A$44)+((9+1)*7)) -> 0 | O16: =SUMIFS(Fact_Actual_Costs!$D$2:$D$100,Fact_Actual_Costs!$B$2:$B$100,$A16,Fact_Actual_Costs!$A$2:$A$100,">="&MIN(Fact_Baseline_PV!$A$2:$A$44)+(10*7),Fact_Actual_Costs!$A$2:$A$100,"<"&MIN(Fact_Baseline_PV!$A$2:$A$44)+((10+1)*7)) -> 0 | P16: =SUMIFS(Fact_Actual_Costs!$D$2:$D$100,Fact_Actual_Costs!$B$2:$B$100,$A16,Fact_Actual_Costs!$A$2:$A$100,">="&MIN(Fact_Baseline_PV!$A$2:$A$44)+(11*7),Fact_Actual_Costs!$A$2:$A$100,"<"&MIN(Fact_Baseline_PV!$A$2:$A$44)+((11+1)*7)) -> 0 | Q16: =SUM(E16:P16) -> 26206.24 | R16: =VLOOKUP(A16,Dim_WBS!$A$2:$E$13,5,FALSE) -> 26000 | S16: =SUMIFS(Fact_Actual_Costs!$D$2:$D$100,Fact_Actual_Costs!$B$2:$B$100,A16,Fact_Actual_Costs!$A$2:$A$100,"<="&Setup!$B$9) -> 26206.24 | T16: =R16-S16 -> -206.24 | U16: =IFERROR((R16*VLOOKUP(A16,'Task Plan'!$A$5:$K$16,11,FALSE))/S16,1) -> 0.69449108 | V16: =IF(U16<Setup!$B$12,"Red",IF(U16<Setup!$B$13,"Amber","Green")) -> Red | W16: 8.1.2 Gantt template from garden office | X16: Cost row
A17: =Dim_WBS!A8 -> WBS-07 | B17: =Dim_WBS!C8 -> HVAC Installation | C17: =Dim_WBS!D8 -> Subcontractor | D17: Hours | E17: =SUMIFS(Fact_Actual_Costs!$E$2:$E$100,Fact_Actual_Costs!$B$2:$B$100,$A17,Fact_Actual_Costs!$A$2:$A$100,">="&MIN(Fact_Baseline_PV!$A$2:$A$44)+(0*7),Fact_Actual_Costs!$A$2:$A$100,"<"&MIN(Fact_Baseline_PV!$A$2:$A$44)+((0+1)*7)) -> 0 | F17: =SUMIFS(Fact_Actual_Costs!$E$2:$E$100,Fact_Actual_Costs!$B$2:$B$100,$A17,Fact_Actual_Costs!$A$2:$A$100,">="&MIN(Fact_Baseline_PV!$A$2:$A$44)+(1*7),Fact_Actual_Costs!$A$2:$A$100,"<"&MIN(Fact_Baseline_PV!$A$2:$A$44)+((1+1)*7)) -> 0 | G17: =SUMIFS(Fact_Actual_Costs!$E$2:$E$100,Fact_Actual_Costs!$B$2:$B$100,$A17,Fact_Actual_Costs!$A$2:$A$100,">="&MIN(Fact_Baseline_PV!$A$2:$A$44)+(2*7),Fact_Actual_Costs!$A$2:$A$100,"<"&MIN(Fact_Baseline_PV!$A$2:$A$44)+((2+1)*7)) -> 0 | H17: =SUMIFS(Fact_Actual_Costs!$E$2:$E$100,Fact_Actual_Costs!$B$2:$B$100,$A17,Fact_Actual_Costs!$A$2:$A$100,">="&MIN(Fact_Baseline_PV!$A$2:$A$44)+(3*7),Fact_Actual_Costs!$A$2:$A$100,"<"&MIN(Fact_Baseline_PV!$A$2:$A$44)+((3+1)*7)) -> 0 | I17: =SUMIFS(Fact_Actual_Costs!$E$2:$E$100,Fact_Actual_Costs!$B$2:$B$100,$A17,Fact_Actual_Costs!$A$2:$A$100,">="&MIN(Fact_Baseline_PV!$A$2:$A$44)+(4*7),Fact_Actual_Costs!$A$2:$A$100,"<"&MIN(Fact_Baseline_PV!$A$2:$A$44)+((4+1)*7)) -> 0 | J17: =SUMIFS(Fact_Actual_Costs!$E$2:$E$100,Fact_Actual_Costs!$B$2:$B$100,$A17,Fact_Actual_Costs!$A$2:$A$100,">="&MIN(Fact_Baseline_PV!$A$2:$A$44)+(5*7),Fact_Actual_Costs!$A$2:$A$100,"<"&MIN(Fact_Baseline_PV!$A$2:$A$44)+((5+1)*7)) -> 0 | K17: =SUMIFS(Fact_Actual_Costs!$E$2:$E$100,Fact_Actual_Costs!$B$2:$B$100,$A17,Fact_Actual_Costs!$A$2:$A$100,">="&MIN(Fact_Baseline_PV!$A$2:$A$44)+(6*7),Fact_Actual_Costs!$A$2:$A$100,"<"&MIN(Fact_Baseline_PV!$A$2:$A$44)+((6+1)*7)) -> 0 | L17: =SUMIFS(Fact_Actual_Costs!$E$2:$E$100,Fact_Actual_Costs!$B$2:$B$100,$A17,Fact_Actual_Costs!$A$2:$A$100,">="&MIN(Fact_Baseline_PV!$A$2:$A$44)+(7*7),Fact_Actual_Costs!$A$2:$A$100,"<"&MIN(Fact_Baseline_PV!$A$2:$A$44)+((7+1)*7)) -> 0 | M17: =SUMIFS(Fact_Actual_Costs!$E$2:$E$100,Fact_Actual_Costs!$B$2:$B$100,$A17,Fact_Actual_Costs!$A$2:$A$100,">="&MIN(Fact_Baseline_PV!$A$2:$A$44)+(8*7),Fact_Actual_Costs!$A$2:$A$100,"<"&MIN(Fact_Baseline_PV!$A$2:$A$44)+((8+1)*7)) -> 0 | N17: =SUMIFS(Fact_Actual_Costs!$E$2:$E$100,Fact_Actual_Costs!$B$2:$B$100,$A17,Fact_Actual_Costs!$A$2:$A$100,">="&MIN(Fact_Baseline_PV!$A$2:$A$44)+(9*7),Fact_Actual_Costs!$A$2:$A$100,"<"&MIN(Fact_Baseline_PV!$A$2:$A$44)+((9+1)*7)) -> 0 | O17: =SUMIFS(Fact_Actual_Costs!$E$2:$E$100,Fact_Actual_Costs!$B$2:$B$100,$A17,Fact_Actual_Costs!$A$2:$A$100,">="&MIN(Fact_Baseline_PV!$A$2:$A$44)+(10*7),Fact_Actual_Costs!$A$2:$A$100,"<"&MIN(Fact_Baseline_PV!$A$2:$A$44)+((10+1)*7)) -> 0 | P17: =SUMIFS(Fact_Actual_Costs!$E$2:$E$100,Fact_Actual_Costs!$B$2:$B$100,$A17,Fact_Actual_Costs!$A$2:$A$100,">="&MIN(Fact_Baseline_PV!$A$2:$A$44)+(11*7),Fact_Actual_Costs!$A$2:$A$100,"<"&MIN(Fact_Baseline_PV!$A$2:$A$44)+((11+1)*7)) -> 0 | Q17: =SUM(E17:P17) -> 0 | R17: =VLOOKUP(A17,Dim_WBS!$A$2:$E$13,5,FALSE) -> 36000 | S17: =SUMIFS(Fact_Actual_Costs!$D$2:$D$100,Fact_Actual_Costs!$B$2:$B$100,A17,Fact_Actual_Costs!$A$2:$A$100,"<="&Setup!$B$9) -> 17476.8 | T17: =R17-S17 -> 18523.2 | U17: =IFERROR((R17*VLOOKUP(A17,'Task Plan'!$A$5:$K$16,11,FALSE))/S17,1) -> 0.82394946 | V17: =IF(U17<Setup!$B$12,"Red",IF(U17<Setup!$B$13,"Amber","Green")) -> Red | W17: 8.1.2 Gantt template from garden office | X17: Hours row
A18: =Dim_WBS!A8 -> WBS-07 | B18: =Dim_WBS!C8 -> HVAC Installation | C18: =Dim_WBS!D8 -> Subcontractor | D18: Cost | E18: =SUMIFS(Fact_Actual_Costs!$D$2:$D$100,Fact_Actual_Costs!$B$2:$B$100,$A18,Fact_Actual_Costs!$A$2:$A$100,">="&MIN(Fact_Baseline_PV!$A$2:$A$44)+(0*7),Fact_Actual_Costs!$A$2:$A$100,"<"&MIN(Fact_Baseline_PV!$A$2:$A$44)+((0+1)*7)) -> 0 | F18: =SUMIFS(Fact_Actual_Costs!$D$2:$D$100,Fact_Actual_Costs!$B$2:$B$100,$A18,Fact_Actual_Costs!$A$2:$A$100,">="&MIN(Fact_Baseline_PV!$A$2:$A$44)+(1*7),Fact_Actual_Costs!$A$2:$A$100,"<"&MIN(Fact_Baseline_PV!$A$2:$A$44)+((1+1)*7)) -> 0 | G18: =SUMIFS(Fact_Actual_Costs!$D$2:$D$100,Fact_Actual_Costs!$B$2:$B$100,$A18,Fact_Actual_Costs!$A$2:$A$100,">="&MIN(Fact_Baseline_PV!$A$2:$A$44)+(2*7),Fact_Actual_Costs!$A$2:$A$100,"<"&MIN(Fact_Baseline_PV!$A$2:$A$44)+((2+1)*7)) -> 0 | H18: =SUMIFS(Fact_Actual_Costs!$D$2:$D$100,Fact_Actual_Costs!$B$2:$B$100,$A18,Fact_Actual_Costs!$A$2:$A$100,">="&MIN(Fact_Baseline_PV!$A$2:$A$44)+(3*7),Fact_Actual_Costs!$A$2:$A$100,"<"&MIN(Fact_Baseline_PV!$A$2:$A$44)+((3+1)*7)) -> 0 | I18: =SUMIFS(Fact_Actual_Costs!$D$2:$D$100,Fact_Actual_Costs!$B$2:$B$100,$A18,Fact_Actual_Costs!$A$2:$A$100,">="&MIN(Fact_Baseline_PV!$A$2:$A$44)+(4*7),Fact_Actual_Costs!$A$2:$A$100,"<"&MIN(Fact_Baseline_PV!$A$2:$A$44)+((4+1)*7)) -> 8676.8 | J18: =SUMIFS(Fact_Actual_Costs!$D$2:$D$100,Fact_Actual_Costs!$B$2:$B$100,$A18,Fact_Actual_Costs!$A$2:$A$100,">="&MIN(Fact_Baseline_PV!$A$2:$A$44)+(5*7),Fact_Actual_Costs!$A$2:$A$100,"<"&MIN(Fact_Baseline_PV!$A$2:$A$44)+((5+1)*7)) -> 8800 | K18: =SUMIFS(Fact_Actual_Costs!$D$2:$D$100,Fact_Actual_Costs!$B$2:$B$100,$A18,Fact_Actual_Costs!$A$2:$A$100,">="&MIN(Fact_Baseline_PV!$A$2:$A$44)+(6*7),Fact_Actual_Costs!$A$2:$A$100,"<"&MIN(Fact_Baseline_PV!$A$2:$A$44)+((6+1)*7)) -> 0 | L18: =SUMIFS(Fact_Actual_Costs!$D$2:$D$100,Fact_Actual_Costs!$B$2:$B$100,$A18,Fact_Actual_Costs!$A$2:$A$100,">="&MIN(Fact_Baseline_PV!$A$2:$A$44)+(7*7),Fact_Actual_Costs!$A$2:$A$100,"<"&MIN(Fact_Baseline_PV!$A$2:$A$44)+((7+1)*7)) -> 0 | M18: =SUMIFS(Fact_Actual_Costs!$D$2:$D$100,Fact_Actual_Costs!$B$2:$B$100,$A18,Fact_Actual_Costs!$A$2:$A$100,">="&MIN(Fact_Baseline_PV!$A$2:$A$44)+(8*7),Fact_Actual_Costs!$A$2:$A$100,"<"&MIN(Fact_Baseline_PV!$A$2:$A$44)+((8+1)*7)) -> 0 | N18: =SUMIFS(Fact_Actual_Costs!$D$2:$D$100,Fact_Actual_Costs!$B$2:$B$100,$A18,Fact_Actual_Costs!$A$2:$A$100,">="&MIN(Fact_Baseline_PV!$A$2:$A$44)+(9*7),Fact_Actual_Costs!$A$2:$A$100,"<"&MIN(Fact_Baseline_PV!$A$2:$A$44)+((9+1)*7)) -> 0 | O18: =SUMIFS(Fact_Actual_Costs!$D$2:$D$100,Fact_Actual_Costs!$B$2:$B$100,$A18,Fact_Actual_Costs!$A$2:$A$100,">="&MIN(Fact_Baseline_PV!$A$2:$A$44)+(10*7),Fact_Actual_Costs!$A$2:$A$100,"<"&MIN(Fact_Baseline_PV!$A$2:$A$44)+((10+1)*7)) -> 0 | P18: =SUMIFS(Fact_Actual_Costs!$D$2:$D$100,Fact_Actual_Costs!$B$2:$B$100,$A18,Fact_Actual_Costs!$A$2:$A$100,">="&MIN(Fact_Baseline_PV!$A$2:$A$44)+(11*7),Fact_Actual_Costs!$A$2:$A$100,"<"&MIN(Fact_Baseline_PV!$A$2:$A$44)+((11+1)*7)) -> 0 | Q18: =SUM(E18:P18) -> 17476.8 | R18: =VLOOKUP(A18,Dim_WBS!$A$2:$E$13,5,FALSE) -> 36000 | S18: =SUMIFS(Fact_Actual_Costs!$D$2:$D$100,Fact_Actual_Costs!$B$2:$B$100,A18,Fact_Actual_Costs!$A$2:$A$100,"<="&Setup!$B$9) -> 17476.8 | T18: =R18-S18 -> 18523.2 | U18: =IFERROR((R18*VLOOKUP(A18,'Task Plan'!$A$5:$K$16,11,FALSE))/S18,1) -> 0.82394946 | V18: =IF(U18<Setup!$B$12,"Red",IF(U18<Setup!$B$13,"Amber","Green")) -> Red | W18: 8.1.2 Gantt template from garden office | X18: Cost row
A19: =Dim_WBS!A9 -> WBS-08 | B19: =Dim_WBS!C9 -> Partitions & Drywall | C19: =Dim_WBS!D9 -> Subcontractor | D19: Hours | E19: =SUMIFS(Fact_Actual_Costs!$E$2:$E$100,Fact_Actual_Costs!$B$2:$B$100,$A19,Fact_Actual_Costs!$A$2:$A$100,">="&MIN(Fact_Baseline_PV!$A$2:$A$44)+(0*7),Fact_Actual_Costs!$A$2:$A$100,"<"&MIN(Fact_Baseline_PV!$A$2:$A$44)+((0+1)*7)) -> 0 | F19: =SUMIFS(Fact_Actual_Costs!$E$2:$E$100,Fact_Actual_Costs!$B$2:$B$100,$A19,Fact_Actual_Costs!$A$2:$A$100,">="&MIN(Fact_Baseline_PV!$A$2:$A$44)+(1*7),Fact_Actual_Costs!$A$2:$A$100,"<"&MIN(Fact_Baseline_PV!$A$2:$A$44)+((1+1)*7)) -> 0 | G19: =SUMIFS(Fact_Actual_Costs!$E$2:$E$100,Fact_Actual_Costs!$B$2:$B$100,$A19,Fact_Actual_Costs!$A$2:$A$100,">="&MIN(Fact_Baseline_PV!$A$2:$A$44)+(2*7),Fact_Actual_Costs!$A$2:$A$100,"<"&MIN(Fact_Baseline_PV!$A$2:$A$44)+((2+1)*7)) -> 0 | H19: =SUMIFS(Fact_Actual_Costs!$E$2:$E$100,Fact_Actual_Costs!$B$2:$B$100,$A19,Fact_Actual_Costs!$A$2:$A$100,">="&MIN(Fact_Baseline_PV!$A$2:$A$44)+(3*7),Fact_Actual_Costs!$A$2:$A$100,"<"&MIN(Fact_Baseline_PV!$A$2:$A$44)+((3+1)*7)) -> 0 | I19: =SUMIFS(Fact_Actual_Costs!$E$2:$E$100,Fact_Actual_Costs!$B$2:$B$100,$A19,Fact_Actual_Costs!$A$2:$A$100,">="&MIN(Fact_Baseline_PV!$A$2:$A$44)+(4*7),Fact_Actual_Costs!$A$2:$A$100,"<"&MIN(Fact_Baseline_PV!$A$2:$A$44)+((4+1)*7)) -> 0 | J19: =SUMIFS(Fact_Actual_Costs!$E$2:$E$100,Fact_Actual_Costs!$B$2:$B$100,$A19,Fact_Actual_Costs!$A$2:$A$100,">="&MIN(Fact_Baseline_PV!$A$2:$A$44)+(5*7),Fact_Actual_Costs!$A$2:$A$100,"<"&MIN(Fact_Baseline_PV!$A$2:$A$44)+((5+1)*7)) -> 0 | K19: =SUMIFS(Fact_Actual_Costs!$E$2:$E$100,Fact_Actual_Costs!$B$2:$B$100,$A19,Fact_Actual_Costs!$A$2:$A$100,">="&MIN(Fact_Baseline_PV!$A$2:$A$44)+(6*7),Fact_Actual_Costs!$A$2:$A$100,"<"&MIN(Fact_Baseline_PV!$A$2:$A$44)+((6+1)*7)) -> 0 | L19: =SUMIFS(Fact_Actual_Costs!$E$2:$E$100,Fact_Actual_Costs!$B$2:$B$100,$A19,Fact_Actual_Costs!$A$2:$A$100,">="&MIN(Fact_Baseline_PV!$A$2:$A$44)+(7*7),Fact_Actual_Costs!$A$2:$A$100,"<"&MIN(Fact_Baseline_PV!$A$2:$A$44)+((7+1)*7)) -> 0 | M19: =SUMIFS(Fact_Actual_Costs!$E$2:$E$100,Fact_Actual_Costs!$B$2:$B$100,$A19,Fact_Actual_Costs!$A$2:$A$100,">="&MIN(Fact_Baseline_PV!$A$2:$A$44)+(8*7),Fact_Actual_Costs!$A$2:$A$100,"<"&MIN(Fact_Baseline_PV!$A$2:$A$44)+((8+1)*7)) -> 0 | N19: =SUMIFS(Fact_Actual_Costs!$E$2:$E$100,Fact_Actual_Costs!$B$2:$B$100,$A19,Fact_Actual_Costs!$A$2:$A$100,">="&MIN(Fact_Baseline_PV!$A$2:$A$44)+(9*7),Fact_Actual_Costs!$A$2:$A$100,"<"&MIN(Fact_Baseline_PV!$A$2:$A$44)+((9+1)*7)) -> 0 | O19: =SUMIFS(Fact_Actual_Costs!$E$2:$E$100,Fact_Actual_Costs!$B$2:$B$100,$A19,Fact_Actual_Costs!$A$2:$A$100,">="&MIN(Fact_Baseline_PV!$A$2:$A$44)+(10*7),Fact_Actual_Costs!$A$2:$A$100,"<"&MIN(Fact_Baseline_PV!$A$2:$A$44)+((10+1)*7)) -> 0 | P19: =SUMIFS(Fact_Actual_Costs!$E$2:$E$100,Fact_Actual_Costs!$B$2:$B$100,$A19,Fact_Actual_Costs!$A$2:$A$100,">="&MIN(Fact_Baseline_PV!$A$2:$A$44)+(11*7),Fact_Actual_Costs!$A$2:$A$100,"<"&MIN(Fact_Baseline_PV!$A$2:$A$44)+((11+1)*7)) -> 0 | Q19: =SUM(E19:P19) -> 0 | R19: =VLOOKUP(A19,Dim_WBS!$A$2:$E$13,5,FALSE) -> 28000 | S19: =SUMIFS(Fact_Actual_Costs!$D$2:$D$100,Fact_Actual_Costs!$B$2:$B$100,A19,Fact_Actual_Costs!$A$2:$A$100,"<="&Setup!$B$9) -> 7099.2 | T19: =R19-S19 -> 20900.8 | U19: =IFERROR((R19*VLOOKUP(A19,'Task Plan'!$A$5:$K$16,11,FALSE))/S19,1) -> 0.98151848 | V19: =IF(U19<Setup!$B$12,"Red",IF(U19<Setup!$B$13,"Amber","Green")) -> Amber | W19: 8.1.2 Gantt template from garden office | X19: Hours row
A20: =Dim_WBS!A9 -> WBS-08 | B20: =Dim_WBS!C9 -> Partitions & Drywall | C20: =Dim_WBS!D9 -> Subcontractor | D20: Cost | E20: =SUMIFS(Fact_Actual_Costs!$D$2:$D$100,Fact_Actual_Costs!$B$2:$B$100,$A20,Fact_Actual_Costs!$A$2:$A$100,">="&MIN(Fact_Baseline_PV!$A$2:$A$44)+(0*7),Fact_Actual_Costs!$A$2:$A$100,"<"&MIN(Fact_Baseline_PV!$A$2:$A$44)+((0+1)*7)) -> 0 | F20: =SUMIFS(Fact_Actual_Costs!$D$2:$D$100,Fact_Actual_Costs!$B$2:$B$100,$A20,Fact_Actual_Costs!$A$2:$A$100,">="&MIN(Fact_Baseline_PV!$A$2:$A$44)+(1*7),Fact_Actual_Costs!$A$2:$A$100,"<"&MIN(Fact_Baseline_PV!$A$2:$A$44)+((1+1)*7)) -> 0 | G20: =SUMIFS(Fact_Actual_Costs!$D$2:$D$100,Fact_Actual_Costs!$B$2:$B$100,$A20,Fact_Actual_Costs!$A$2:$A$100,">="&MIN(Fact_Baseline_PV!$A$2:$A$44)+(2*7),Fact_Actual_Costs!$A$2:$A$100,"<"&MIN(Fact_Baseline_PV!$A$2:$A$44)+((2+1)*7)) -> 0 | H20: =SUMIFS(Fact_Actual_Costs!$D$2:$D$100,Fact_Actual_Costs!$B$2:$B$100,$A20,Fact_Actual_Costs!$A$2:$A$100,">="&MIN(Fact_Baseline_PV!$A$2:$A$44)+(3*7),Fact_Actual_Costs!$A$2:$A$100,"<"&MIN(Fact_Baseline_PV!$A$2:$A$44)+((3+1)*7)) -> 0 | I20: =SUMIFS(Fact_Actual_Costs!$D$2:$D$100,Fact_Actual_Costs!$B$2:$B$100,$A20,Fact_Actual_Costs!$A$2:$A$100,">="&MIN(Fact_Baseline_PV!$A$2:$A$44)+(4*7),Fact_Actual_Costs!$A$2:$A$100,"<"&MIN(Fact_Baseline_PV!$A$2:$A$44)+((4+1)*7)) -> 0 | J20: =SUMIFS(Fact_Actual_Costs!$D$2:$D$100,Fact_Actual_Costs!$B$2:$B$100,$A20,Fact_Actual_Costs!$A$2:$A$100,">="&MIN(Fact_Baseline_PV!$A$2:$A$44)+(5*7),Fact_Actual_Costs!$A$2:$A$100,"<"&MIN(Fact_Baseline_PV!$A$2:$A$44)+((5+1)*7)) -> 7099.2 | K20: =SUMIFS(Fact_Actual_Costs!$D$2:$D$100,Fact_Actual_Costs!$B$2:$B$100,$A20,Fact_Actual_Costs!$A$2:$A$100,">="&MIN(Fact_Baseline_PV!$A$2:$A$44)+(6*7),Fact_Actual_Costs!$A$2:$A$100,"<"&MIN(Fact_Baseline_PV!$A$2:$A$44)+((6+1)*7)) -> 0 | L20: =SUMIFS(Fact_Actual_Costs!$D$2:$D$100,Fact_Actual_Costs!$B$2:$B$100,$A20,Fact_Actual_Costs!$A$2:$A$100,">="&MIN(Fact_Baseline_PV!$A$2:$A$44)+(7*7),Fact_Actual_Costs!$A$2:$A$100,"<"&MIN(Fact_Baseline_PV!$A$2:$A$44)+((7+1)*7)) -> 0 | M20: =SUMIFS(Fact_Actual_Costs!$D$2:$D$100,Fact_Actual_Costs!$B$2:$B$100,$A20,Fact_Actual_Costs!$A$2:$A$100,">="&MIN(Fact_Baseline_PV!$A$2:$A$44)+(8*7),Fact_Actual_Costs!$A$2:$A$100,"<"&MIN(Fact_Baseline_PV!$A$2:$A$44)+((8+1)*7)) -> 0 | N20: =SUMIFS(Fact_Actual_Costs!$D$2:$D$100,Fact_Actual_Costs!$B$2:$B$100,$A20,Fact_Actual_Costs!$A$2:$A$100,">="&MIN(Fact_Baseline_PV!$A$2:$A$44)+(9*7),Fact_Actual_Costs!$A$2:$A$100,"<"&MIN(Fact_Baseline_PV!$A$2:$A$44)+((9+1)*7)) -> 0 | O20: =SUMIFS(Fact_Actual_Costs!$D$2:$D$100,Fact_Actual_Costs!$B$2:$B$100,$A20,Fact_Actual_Costs!$A$2:$A$100,">="&MIN(Fact_Baseline_PV!$A$2:$A$44)+(10*7),Fact_Actual_Costs!$A$2:$A$100,"<"&MIN(Fact_Baseline_PV!$A$2:$A$44)+((10+1)*7)) -> 0 | P20: =SUMIFS(Fact_Actual_Costs!$D$2:$D$100,Fact_Actual_Costs!$B$2:$B$100,$A20,Fact_Actual_Costs!$A$2:$A$100,">="&MIN(Fact_Baseline_PV!$A$2:$A$44)+(11*7),Fact_Actual_Costs!$A$2:$A$100,"<"&MIN(Fact_Baseline_PV!$A$2:$A$44)+((11+1)*7)) -> 0 | Q20: =SUM(E20:P20) -> 7099.2 | R20: =VLOOKUP(A20,Dim_WBS!$A$2:$E$13,5,FALSE) -> 28000 | S20: =SUMIFS(Fact_Actual_Costs!$D$2:$D$100,Fact_Actual_Costs!$B$2:$B$100,A20,Fact_Actual_Costs!$A$2:$A$100,"<="&Setup!$B$9) -> 7099.2 | T20: =R20-S20 -> 20900.8 | U20: =IFERROR((R20*VLOOKUP(A20,'Task Plan'!$A$5:$K$16,11,FALSE))/S20,1) -> 0.98151848 | V20: =IF(U20<Setup!$B$12,"Red",IF(U20<Setup!$B$13,"Amber","Green")) -> Amber | W20: 8.1.2 Gantt template from garden office | X20: Cost row
A21: =Dim_WBS!A10 -> WBS-09 | B21: =Dim_WBS!C10 -> Flooring | C21: =Dim_WBS!D10 -> Material | D21: Hours | E21: =SUMIFS(Fact_Actual_Costs!$E$2:$E$100,Fact_Actual_Costs!$B$2:$B$100,$A21,Fact_Actual_Costs!$A$2:$A$100,">="&MIN(Fact_Baseline_PV!$A$2:$A$44)+(0*7),Fact_Actual_Costs!$A$2:$A$100,"<"&MIN(Fact_Baseline_PV!$A$2:$A$44)+((0+1)*7)) -> 0 | F21: =SUMIFS(Fact_Actual_Costs!$E$2:$E$100,Fact_Actual_Costs!$B$2:$B$100,$A21,Fact_Actual_Costs!$A$2:$A$100,">="&MIN(Fact_Baseline_PV!$A$2:$A$44)+(1*7),Fact_Actual_Costs!$A$2:$A$100,"<"&MIN(Fact_Baseline_PV!$A$2:$A$44)+((1+1)*7)) -> 0 | G21: =SUMIFS(Fact_Actual_Costs!$E$2:$E$100,Fact_Actual_Costs!$B$2:$B$100,$A21,Fact_Actual_Costs!$A$2:$A$100,">="&MIN(Fact_Baseline_PV!$A$2:$A$44)+(2*7),Fact_Actual_Costs!$A$2:$A$100,"<"&MIN(Fact_Baseline_PV!$A$2:$A$44)+((2+1)*7)) -> 0 | H21: =SUMIFS(Fact_Actual_Costs!$E$2:$E$100,Fact_Actual_Costs!$B$2:$B$100,$A21,Fact_Actual_Costs!$A$2:$A$100,">="&MIN(Fact_Baseline_PV!$A$2:$A$44)+(3*7),Fact_Actual_Costs!$A$2:$A$100,"<"&MIN(Fact_Baseline_PV!$A$2:$A$44)+((3+1)*7)) -> 0 | I21: =SUMIFS(Fact_Actual_Costs!$E$2:$E$100,Fact_Actual_Costs!$B$2:$B$100,$A21,Fact_Actual_Costs!$A$2:$A$100,">="&MIN(Fact_Baseline_PV!$A$2:$A$44)+(4*7),Fact_Actual_Costs!$A$2:$A$100,"<"&MIN(Fact_Baseline_PV!$A$2:$A$44)+((4+1)*7)) -> 0 | J21: =SUMIFS(Fact_Actual_Costs!$E$2:$E$100,Fact_Actual_Costs!$B$2:$B$100,$A21,Fact_Actual_Costs!$A$2:$A$100,">="&MIN(Fact_Baseline_PV!$A$2:$A$44)+(5*7),Fact_Actual_Costs!$A$2:$A$100,"<"&MIN(Fact_Baseline_PV!$A$2:$A$44)+((5+1)*7)) -> 0 | K21: =SUMIFS(Fact_Actual_Costs!$E$2:$E$100,Fact_Actual_Costs!$B$2:$B$100,$A21,Fact_Actual_Costs!$A$2:$A$100,">="&MIN(Fact_Baseline_PV!$A$2:$A$44)+(6*7),Fact_Actual_Costs!$A$2:$A$100,"<"&MIN(Fact_Baseline_PV!$A$2:$A$44)+((6+1)*7)) -> 0 | L21: =SUMIFS(Fact_Actual_Costs!$E$2:$E$100,Fact_Actual_Costs!$B$2:$B$100,$A21,Fact_Actual_Costs!$A$2:$A$100,">="&MIN(Fact_Baseline_PV!$A$2:$A$44)+(7*7),Fact_Actual_Costs!$A$2:$A$100,"<"&MIN(Fact_Baseline_PV!$A$2:$A$44)+((7+1)*7)) -> 0 | M21: =SUMIFS(Fact_Actual_Costs!$E$2:$E$100,Fact_Actual_Costs!$B$2:$B$100,$A21,Fact_Actual_Costs!$A$2:$A$100,">="&MIN(Fact_Baseline_PV!$A$2:$A$44)+(8*7),Fact_Actual_Costs!$A$2:$A$100,"<"&MIN(Fact_Baseline_PV!$A$2:$A$44)+((8+1)*7)) -> 0 | N21: =SUMIFS(Fact_Actual_Costs!$E$2:$E$100,Fact_Actual_Costs!$B$2:$B$100,$A21,Fact_Actual_Costs!$A$2:$A$100,">="&MIN(Fact_Baseline_PV!$A$2:$A$44)+(9*7),Fact_Actual_Costs!$A$2:$A$100,"<"&MIN(Fact_Baseline_PV!$A$2:$A$44)+((9+1)*7)) -> 0 | O21: =SUMIFS(Fact_Actual_Costs!$E$2:$E$100,Fact_Actual_Costs!$B$2:$B$100,$A21,Fact_Actual_Costs!$A$2:$A$100,">="&MIN(Fact_Baseline_PV!$A$2:$A$44)+(10*7),Fact_Actual_Costs!$A$2:$A$100,"<"&MIN(Fact_Baseline_PV!$A$2:$A$44)+((10+1)*7)) -> 0 | P21: =SUMIFS(Fact_Actual_Costs!$E$2:$E$100,Fact_Actual_Costs!$B$2:$B$100,$A21,Fact_Actual_Costs!$A$2:$A$100,">="&MIN(Fact_Baseline_PV!$A$2:$A$44)+(11*7),Fact_Actual_Costs!$A$2:$A$100,"<"&MIN(Fact_Baseline_PV!$A$2:$A$44)+((11+1)*7)) -> 0 | Q21: =SUM(E21:P21) -> 0 | R21: =VLOOKUP(A21,Dim_WBS!$A$2:$E$13,5,FALSE) -> 35750 | S21: =SUMIFS(Fact_Actual_Costs!$D$2:$D$100,Fact_Actual_Costs!$B$2:$B$100,A21,Fact_Actual_Costs!$A$2:$A$100,"<="&Setup!$B$9) -> 0 | T21: =R21-S21 -> 35750 | U21: =IFERROR((R21*VLOOKUP(A21,'Task Plan'!$A$5:$K$16,11,FALSE))/S21,1) -> 1 | V21: =IF(U21<Setup!$B$12,"Red",IF(U21<Setup!$B$13,"Amber","Green")) -> Green | W21: 8.1.2 Gantt template from garden office | X21: Hours row
A22: =Dim_WBS!A10 -> WBS-09 | B22: =Dim_WBS!C10 -> Flooring | C22: =Dim_WBS!D10 -> Material | D22: Cost | E22: =SUMIFS(Fact_Actual_Costs!$D$2:$D$100,Fact_Actual_Costs!$B$2:$B$100,$A22,Fact_Actual_Costs!$A$2:$A$100,">="&MIN(Fact_Baseline_PV!$A$2:$A$44)+(0*7),Fact_Actual_Costs!$A$2:$A$100,"<"&MIN(Fact_Baseline_PV!$A$2:$A$44)+((0+1)*7)) -> 0 | F22: =SUMIFS(Fact_Actual_Costs!$D$2:$D$100,Fact_Actual_Costs!$B$2:$B$100,$A22,Fact_Actual_Costs!$A$2:$A$100,">="&MIN(Fact_Baseline_PV!$A$2:$A$44)+(1*7),Fact_Actual_Costs!$A$2:$A$100,"<"&MIN(Fact_Baseline_PV!$A$2:$A$44)+((1+1)*7)) -> 0 | G22: =SUMIFS(Fact_Actual_Costs!$D$2:$D$100,Fact_Actual_Costs!$B$2:$B$100,$A22,Fact_Actual_Costs!$A$2:$A$100,">="&MIN(Fact_Baseline_PV!$A$2:$A$44)+(2*7),Fact_Actual_Costs!$A$2:$A$100,"<"&MIN(Fact_Baseline_PV!$A$2:$A$44)+((2+1)*7)) -> 0 | H22: =SUMIFS(Fact_Actual_Costs!$D$2:$D$100,Fact_Actual_Costs!$B$2:$B$100,$A22,Fact_Actual_Costs!$A$2:$A$100,">="&MIN(Fact_Baseline_PV!$A$2:$A$44)+(3*7),Fact_Actual_Costs!$A$2:$A$100,"<"&MIN(Fact_Baseline_PV!$A$2:$A$44)+((3+1)*7)) -> 0 | I22: =SUMIFS(Fact_Actual_Costs!$D$2:$D$100,Fact_Actual_Costs!$B$2:$B$100,$A22,Fact_Actual_Costs!$A$2:$A$100,">="&MIN(Fact_Baseline_PV!$A$2:$A$44)+(4*7),Fact_Actual_Costs!$A$2:$A$100,"<"&MIN(Fact_Baseline_PV!$A$2:$A$44)+((4+1)*7)) -> 0 | J22: =SUMIFS(Fact_Actual_Costs!$D$2:$D$100,Fact_Actual_Costs!$B$2:$B$100,$A22,Fact_Actual_Costs!$A$2:$A$100,">="&MIN(Fact_Baseline_PV!$A$2:$A$44)+(5*7),Fact_Actual_Costs!$A$2:$A$100,"<"&MIN(Fact_Baseline_PV!$A$2:$A$44)+((5+1)*7)) -> 0 | K22: =SUMIFS(Fact_Actual_Costs!$D$2:$D$100,Fact_Actual_Costs!$B$2:$B$100,$A22,Fact_Actual_Costs!$A$2:$A$100,">="&MIN(Fact_Baseline_PV!$A$2:$A$44)+(6*7),Fact_Actual_Costs!$A$2:$A$100,"<"&MIN(Fact_Baseline_PV!$A$2:$A$44)+((6+1)*7)) -> 0 | L22: =SUMIFS(Fact_Actual_Costs!$D$2:$D$100,Fact_Actual_Costs!$B$2:$B$100,$A22,Fact_Actual_Costs!$A$2:$A$100,">="&MIN(Fact_Baseline_PV!$A$2:$A$44)+(7*7),Fact_Actual_Costs!$A$2:$A$100,"<"&MIN(Fact_Baseline_PV!$A$2:$A$44)+((7+1)*7)) -> 0 | M22: =SUMIFS(Fact_Actual_Costs!$D$2:$D$100,Fact_Actual_Costs!$B$2:$B$100,$A22,Fact_Actual_Costs!$A$2:$A$100,">="&MIN(Fact_Baseline_PV!$A$2:$A$44)+(8*7),Fact_Actual_Costs!$A$2:$A$100,"<"&MIN(Fact_Baseline_PV!$A$2:$A$44)+((8+1)*7)) -> 0 | N22: =SUMIFS(Fact_Actual_Costs!$D$2:$D$100,Fact_Actual_Costs!$B$2:$B$100,$A22,Fact_Actual_Costs!$A$2:$A$100,">="&MIN(Fact_Baseline_PV!$A$2:$A$44)+(9*7),Fact_Actual_Costs!$A$2:$A$100,"<"&MIN(Fact_Baseline_PV!$A$2:$A$44)+((9+1)*7)) -> 0 | O22: =SUMIFS(Fact_Actual_Costs!$D$2:$D$100,Fact_Actual_Costs!$B$2:$B$100,$A22,Fact_Actual_Costs!$A$2:$A$100,">="&MIN(Fact_Baseline_PV!$A$2:$A$44)+(10*7),Fact_Actual_Costs!$A$2:$A$100,"<"&MIN(Fact_Baseline_PV!$A$2:$A$44)+((10+1)*7)) -> 0 | P22: =SUMIFS(Fact_Actual_Costs!$D$2:$D$100,Fact_Actual_Costs!$B$2:$B$100,$A22,Fact_Actual_Costs!$A$2:$A$100,">="&MIN(Fact_Baseline_PV!$A$2:$A$44)+(11*7),Fact_Actual_Costs!$A$2:$A$100,"<"&MIN(Fact_Baseline_PV!$A$2:$A$44)+((11+1)*7)) -> 0 | Q22: =SUM(E22:P22) -> 0 | R22: =VLOOKUP(A22,Dim_WBS!$A$2:$E$13,5,FALSE) -> 35750 | S22: =SUMIFS(Fact_Actual_Costs!$D$2:$D$100,Fact_Actual_Costs!$B$2:$B$100,A22,Fact_Actual_Costs!$A$2:$A$100,"<="&Setup!$B$9) -> 0 | T22: =R22-S22 -> 35750 | U22: =IFERROR((R22*VLOOKUP(A22,'Task Plan'!$A$5:$K$16,11,FALSE))/S22,1) -> 1 | V22: =IF(U22<Setup!$B$12,"Red",IF(U22<Setup!$B$13,"Amber","Green")) -> Green | W22: 8.1.2 Gantt template from garden office | X22: Cost row
A23: =Dim_WBS!A11 -> WBS-10 | B23: =Dim_WBS!C11 -> Fixtures & Furniture | C23: =Dim_WBS!D11 -> Material | D23: Hours | E23: =SUMIFS(Fact_Actual_Costs!$E$2:$E$100,Fact_Actual_Costs!$B$2:$B$100,$A23,Fact_Actual_Costs!$A$2:$A$100,">="&MIN(Fact_Baseline_PV!$A$2:$A$44)+(0*7),Fact_Actual_Costs!$A$2:$A$100,"<"&MIN(Fact_Baseline_PV!$A$2:$A$44)+((0+1)*7)) -> 0 | F23: =SUMIFS(Fact_Actual_Costs!$E$2:$E$100,Fact_Actual_Costs!$B$2:$B$100,$A23,Fact_Actual_Costs!$A$2:$A$100,">="&MIN(Fact_Baseline_PV!$A$2:$A$44)+(1*7),Fact_Actual_Costs!$A$2:$A$100,"<"&MIN(Fact_Baseline_PV!$A$2:$A$44)+((1+1)*7)) -> 0 | G23: =SUMIFS(Fact_Actual_Costs!$E$2:$E$100,Fact_Actual_Costs!$B$2:$B$100,$A23,Fact_Actual_Costs!$A$2:$A$100,">="&MIN(Fact_Baseline_PV!$A$2:$A$44)+(2*7),Fact_Actual_Costs!$A$2:$A$100,"<"&MIN(Fact_Baseline_PV!$A$2:$A$44)+((2+1)*7)) -> 0 | H23: =SUMIFS(Fact_Actual_Costs!$E$2:$E$100,Fact_Actual_Costs!$B$2:$B$100,$A23,Fact_Actual_Costs!$A$2:$A$100,">="&MIN(Fact_Baseline_PV!$A$2:$A$44)+(3*7),Fact_Actual_Costs!$A$2:$A$100,"<"&MIN(Fact_Baseline_PV!$A$2:$A$44)+((3+1)*7)) -> 0 | I23: =SUMIFS(Fact_Actual_Costs!$E$2:$E$100,Fact_Actual_Costs!$B$2:$B$100,$A23,Fact_Actual_Costs!$A$2:$A$100,">="&MIN(Fact_Baseline_PV!$A$2:$A$44)+(4*7),Fact_Actual_Costs!$A$2:$A$100,"<"&MIN(Fact_Baseline_PV!$A$2:$A$44)+((4+1)*7)) -> 0 | J23: =SUMIFS(Fact_Actual_Costs!$E$2:$E$100,Fact_Actual_Costs!$B$2:$B$100,$A23,Fact_Actual_Costs!$A$2:$A$100,">="&MIN(Fact_Baseline_PV!$A$2:$A$44)+(5*7),Fact_Actual_Costs!$A$2:$A$100,"<"&MIN(Fact_Baseline_PV!$A$2:$A$44)+((5+1)*7)) -> 0 | K23: =SUMIFS(Fact_Actual_Costs!$E$2:$E$100,Fact_Actual_Costs!$B$2:$B$100,$A23,Fact_Actual_Costs!$A$2:$A$100,">="&MIN(Fact_Baseline_PV!$A$2:$A$44)+(6*7),Fact_Actual_Costs!$A$2:$A$100,"<"&MIN(Fact_Baseline_PV!$A$2:$A$44)+((6+1)*7)) -> 0 | L23: =SUMIFS(Fact_Actual_Costs!$E$2:$E$100,Fact_Actual_Costs!$B$2:$B$100,$A23,Fact_Actual_Costs!$A$2:$A$100,">="&MIN(Fact_Baseline_PV!$A$2:$A$44)+(7*7),Fact_Actual_Costs!$A$2:$A$100,"<"&MIN(Fact_Baseline_PV!$A$2:$A$44)+((7+1)*7)) -> 0 | M23: =SUMIFS(Fact_Actual_Costs!$E$2:$E$100,Fact_Actual_Costs!$B$2:$B$100,$A23,Fact_Actual_Costs!$A$2:$A$100,">="&MIN(Fact_Baseline_PV!$A$2:$A$44)+(8*7),Fact_Actual_Costs!$A$2:$A$100,"<"&MIN(Fact_Baseline_PV!$A$2:$A$44)+((8+1)*7)) -> 0 | N23: =SUMIFS(Fact_Actual_Costs!$E$2:$E$100,Fact_Actual_Costs!$B$2:$B$100,$A23,Fact_Actual_Costs!$A$2:$A$100,">="&MIN(Fact_Baseline_PV!$A$2:$A$44)+(9*7),Fact_Actual_Costs!$A$2:$A$100,"<"&MIN(Fact_Baseline_PV!$A$2:$A$44)+((9+1)*7)) -> 0 | O23: =SUMIFS(Fact_Actual_Costs!$E$2:$E$100,Fact_Actual_Costs!$B$2:$B$100,$A23,Fact_Actual_Costs!$A$2:$A$100,">="&MIN(Fact_Baseline_PV!$A$2:$A$44)+(10*7),Fact_Actual_Costs!$A$2:$A$100,"<"&MIN(Fact_Baseline_PV!$A$2:$A$44)+((10+1)*7)) -> 0 | P23: =SUMIFS(Fact_Actual_Costs!$E$2:$E$100,Fact_Actual_Costs!$B$2:$B$100,$A23,Fact_Actual_Costs!$A$2:$A$100,">="&MIN(Fact_Baseline_PV!$A$2:$A$44)+(11*7),Fact_Actual_Costs!$A$2:$A$100,"<"&MIN(Fact_Baseline_PV!$A$2:$A$44)+((11+1)*7)) -> 0 | Q23: =SUM(E23:P23) -> 0 | R23: =VLOOKUP(A23,Dim_WBS!$A$2:$E$13,5,FALSE) -> 30000 | S23: =SUMIFS(Fact_Actual_Costs!$D$2:$D$100,Fact_Actual_Costs!$B$2:$B$100,A23,Fact_Actual_Costs!$A$2:$A$100,"<="&Setup!$B$9) -> 0 | T23: =R23-S23 -> 30000 | U23: =IFERROR((R23*VLOOKUP(A23,'Task Plan'!$A$5:$K$16,11,FALSE))/S23,1) -> 1 | V23: =IF(U23<Setup!$B$12,"Red",IF(U23<Setup!$B$13,"Amber","Green")) -> Green | W23: 8.1.2 Gantt template from garden office | X23: Hours row
A24: =Dim_WBS!A11 -> WBS-10 | B24: =Dim_WBS!C11 -> Fixtures & Furniture | C24: =Dim_WBS!D11 -> Material | D24: Cost | E24: =SUMIFS(Fact_Actual_Costs!$D$2:$D$100,Fact_Actual_Costs!$B$2:$B$100,$A24,Fact_Actual_Costs!$A$2:$A$100,">="&MIN(Fact_Baseline_PV!$A$2:$A$44)+(0*7),Fact_Actual_Costs!$A$2:$A$100,"<"&MIN(Fact_Baseline_PV!$A$2:$A$44)+((0+1)*7)) -> 0 | F24: =SUMIFS(Fact_Actual_Costs!$D$2:$D$100,Fact_Actual_Costs!$B$2:$B$100,$A24,Fact_Actual_Costs!$A$2:$A$100,">="&MIN(Fact_Baseline_PV!$A$2:$A$44)+(1*7),Fact_Actual_Costs!$A$2:$A$100,"<"&MIN(Fact_Baseline_PV!$A$2:$A$44)+((1+1)*7)) -> 0 | G24: =SUMIFS(Fact_Actual_Costs!$D$2:$D$100,Fact_Actual_Costs!$B$2:$B$100,$A24,Fact_Actual_Costs!$A$2:$A$100,">="&MIN(Fact_Baseline_PV!$A$2:$A$44)+(2*7),Fact_Actual_Costs!$A$2:$A$100,"<"&MIN(Fact_Baseline_PV!$A$2:$A$44)+((2+1)*7)) -> 0 | H24: =SUMIFS(Fact_Actual_Costs!$D$2:$D$100,Fact_Actual_Costs!$B$2:$B$100,$A24,Fact_Actual_Costs!$A$2:$A$100,">="&MIN(Fact_Baseline_PV!$A$2:$A$44)+(3*7),Fact_Actual_Costs!$A$2:$A$100,"<"&MIN(Fact_Baseline_PV!$A$2:$A$44)+((3+1)*7)) -> 0 | I24: =SUMIFS(Fact_Actual_Costs!$D$2:$D$100,Fact_Actual_Costs!$B$2:$B$100,$A24,Fact_Actual_Costs!$A$2:$A$100,">="&MIN(Fact_Baseline_PV!$A$2:$A$44)+(4*7),Fact_Actual_Costs!$A$2:$A$100,"<"&MIN(Fact_Baseline_PV!$A$2:$A$44)+((4+1)*7)) -> 0 | J24: =SUMIFS(Fact_Actual_Costs!$D$2:$D$100,Fact_Actual_Costs!$B$2:$B$100,$A24,Fact_Actual_Costs!$A$2:$A$100,">="&MIN(Fact_Baseline_PV!$A$2:$A$44)+(5*7),Fact_Actual_Costs!$A$2:$A$100,"<"&MIN(Fact_Baseline_PV!$A$2:$A$44)+((5+1)*7)) -> 0 | K24: =SUMIFS(Fact_Actual_Costs!$D$2:$D$100,Fact_Actual_Costs!$B$2:$B$100,$A24,Fact_Actual_Costs!$A$2:$A$100,">="&MIN(Fact_Baseline_PV!$A$2:$A$44)+(6*7),Fact_Actual_Costs!$A$2:$A$100,"<"&MIN(Fact_Baseline_PV!$A$2:$A$44)+((6+1)*7)) -> 0 | L24: =SUMIFS(Fact_Actual_Costs!$D$2:$D$100,Fact_Actual_Costs!$B$2:$B$100,$A24,Fact_Actual_Costs!$A$2:$A$100,">="&MIN(Fact_Baseline_PV!$A$2:$A$44)+(7*7),Fact_Actual_Costs!$A$2:$A$100,"<"&MIN(Fact_Baseline_PV!$A$2:$A$44)+((7+1)*7)) -> 0 | M24: =SUMIFS(Fact_Actual_Costs!$D$2:$D$100,Fact_Actual_Costs!$B$2:$B$100,$A24,Fact_Actual_Costs!$A$2:$A$100,">="&MIN(Fact_Baseline_PV!$A$2:$A$44)+(8*7),Fact_Actual_Costs!$A$2:$A$100,"<"&MIN(Fact_Baseline_PV!$A$2:$A$44)+((8+1)*7)) -> 0 | N24: =SUMIFS(Fact_Actual_Costs!$D$2:$D$100,Fact_Actual_Costs!$B$2:$B$100,$A24,Fact_Actual_Costs!$A$2:$A$100,">="&MIN(Fact_Baseline_PV!$A$2:$A$44)+(9*7),Fact_Actual_Costs!$A$2:$A$100,"<"&MIN(Fact_Baseline_PV!$A$2:$A$44)+((9+1)*7)) -> 0 | O24: =SUMIFS(Fact_Actual_Costs!$D$2:$D$100,Fact_Actual_Costs!$B$2:$B$100,$A24,Fact_Actual_Costs!$A$2:$A$100,">="&MIN(Fact_Baseline_PV!$A$2:$A$44)+(10*7),Fact_Actual_Costs!$A$2:$A$100,"<"&MIN(Fact_Baseline_PV!$A$2:$A$44)+((10+1)*7)) -> 0 | P24: =SUMIFS(Fact_Actual_Costs!$D$2:$D$100,Fact_Actual_Costs!$B$2:$B$100,$A24,Fact_Actual_Costs!$A$2:$A$100,">="&MIN(Fact_Baseline_PV!$A$2:$A$44)+(11*7),Fact_Actual_Costs!$A$2:$A$100,"<"&MIN(Fact_Baseline_PV!$A$2:$A$44)+((11+1)*7)) -> 0 | Q24: =SUM(E24:P24) -> 0 | R24: =VLOOKUP(A24,Dim_WBS!$A$2:$E$13,5,FALSE) -> 30000 | S24: =SUMIFS(Fact_Actual_Costs!$D$2:$D$100,Fact_Actual_Costs!$B$2:$B$100,A24,Fact_Actual_Costs!$A$2:$A$100,"<="&Setup!$B$9) -> 0 | T24: =R24-S24 -> 30000 | U24: =IFERROR((R24*VLOOKUP(A24,'Task Plan'!$A$5:$K$16,11,FALSE))/S24,1) -> 1 | V24: =IF(U24<Setup!$B$12,"Red",IF(U24<Setup!$B$13,"Amber","Green")) -> Green | W24: 8.1.2 Gantt template from garden office | X24: Cost row
A25: =Dim_WBS!A12 -> WBS-11 | B25: =Dim_WBS!C12 -> Testing / Commissioning | C25: =Dim_WBS!D12 -> Labor | D25: Hours | E25: =SUMIFS(Fact_Actual_Costs!$E$2:$E$100,Fact_Actual_Costs!$B$2:$B$100,$A25,Fact_Actual_Costs!$A$2:$A$100,">="&MIN(Fact_Baseline_PV!$A$2:$A$44)+(0*7),Fact_Actual_Costs!$A$2:$A$100,"<"&MIN(Fact_Baseline_PV!$A$2:$A$44)+((0+1)*7)) -> 0 | F25: =SUMIFS(Fact_Actual_Costs!$E$2:$E$100,Fact_Actual_Costs!$B$2:$B$100,$A25,Fact_Actual_Costs!$A$2:$A$100,">="&MIN(Fact_Baseline_PV!$A$2:$A$44)+(1*7),Fact_Actual_Costs!$A$2:$A$100,"<"&MIN(Fact_Baseline_PV!$A$2:$A$44)+((1+1)*7)) -> 0 | G25: =SUMIFS(Fact_Actual_Costs!$E$2:$E$100,Fact_Actual_Costs!$B$2:$B$100,$A25,Fact_Actual_Costs!$A$2:$A$100,">="&MIN(Fact_Baseline_PV!$A$2:$A$44)+(2*7),Fact_Actual_Costs!$A$2:$A$100,"<"&MIN(Fact_Baseline_PV!$A$2:$A$44)+((2+1)*7)) -> 0 | H25: =SUMIFS(Fact_Actual_Costs!$E$2:$E$100,Fact_Actual_Costs!$B$2:$B$100,$A25,Fact_Actual_Costs!$A$2:$A$100,">="&MIN(Fact_Baseline_PV!$A$2:$A$44)+(3*7),Fact_Actual_Costs!$A$2:$A$100,"<"&MIN(Fact_Baseline_PV!$A$2:$A$44)+((3+1)*7)) -> 0 | I25: =SUMIFS(Fact_Actual_Costs!$E$2:$E$100,Fact_Actual_Costs!$B$2:$B$100,$A25,Fact_Actual_Costs!$A$2:$A$100,">="&MIN(Fact_Baseline_PV!$A$2:$A$44)+(4*7),Fact_Actual_Costs!$A$2:$A$100,"<"&MIN(Fact_Baseline_PV!$A$2:$A$44)+((4+1)*7)) -> 0 | J25: =SUMIFS(Fact_Actual_Costs!$E$2:$E$100,Fact_Actual_Costs!$B$2:$B$100,$A25,Fact_Actual_Costs!$A$2:$A$100,">="&MIN(Fact_Baseline_PV!$A$2:$A$44)+(5*7),Fact_Actual_Costs!$A$2:$A$100,"<"&MIN(Fact_Baseline_PV!$A$2:$A$44)+((5+1)*7)) -> 0 | K25: =SUMIFS(Fact_Actual_Costs!$E$2:$E$100,Fact_Actual_Costs!$B$2:$B$100,$A25,Fact_Actual_Costs!$A$2:$A$100,">="&MIN(Fact_Baseline_PV!$A$2:$A$44)+(6*7),Fact_Actual_Costs!$A$2:$A$100,"<"&MIN(Fact_Baseline_PV!$A$2:$A$44)+((6+1)*7)) -> 0 | L25: =SUMIFS(Fact_Actual_Costs!$E$2:$E$100,Fact_Actual_Costs!$B$2:$B$100,$A25,Fact_Actual_Costs!$A$2:$A$100,">="&MIN(Fact_Baseline_PV!$A$2:$A$44)+(7*7),Fact_Actual_Costs!$A$2:$A$100,"<"&MIN(Fact_Baseline_PV!$A$2:$A$44)+((7+1)*7)) -> 0 | M25: =SUMIFS(Fact_Actual_Costs!$E$2:$E$100,Fact_Actual_Costs!$B$2:$B$100,$A25,Fact_Actual_Costs!$A$2:$A$100,">="&MIN(Fact_Baseline_PV!$A$2:$A$44)+(8*7),Fact_Actual_Costs!$A$2:$A$100,"<"&MIN(Fact_Baseline_PV!$A$2:$A$44)+((8+1)*7)) -> 0 | N25: =SUMIFS(Fact_Actual_Costs!$E$2:$E$100,Fact_Actual_Costs!$B$2:$B$100,$A25,Fact_Actual_Costs!$A$2:$A$100,">="&MIN(Fact_Baseline_PV!$A$2:$A$44)+(9*7),Fact_Actual_Costs!$A$2:$A$100,"<"&MIN(Fact_Baseline_PV!$A$2:$A$44)+((9+1)*7)) -> 0 | O25: =SUMIFS(Fact_Actual_Costs!$E$2:$E$100,Fact_Actual_Costs!$B$2:$B$100,$A25,Fact_Actual_Costs!$A$2:$A$100,">="&MIN(Fact_Baseline_PV!$A$2:$A$44)+(10*7),Fact_Actual_Costs!$A$2:$A$100,"<"&MIN(Fact_Baseline_PV!$A$2:$A$44)+((10+1)*7)) -> 0 | P25: =SUMIFS(Fact_Actual_Costs!$E$2:$E$100,Fact_Actual_Costs!$B$2:$B$100,$A25,Fact_Actual_Costs!$A$2:$A$100,">="&MIN(Fact_Baseline_PV!$A$2:$A$44)+(11*7),Fact_Actual_Costs!$A$2:$A$100,"<"&MIN(Fact_Baseline_PV!$A$2:$A$44)+((11+1)*7)) -> 0 | Q25: =SUM(E25:P25) -> 0 | R25: =VLOOKUP(A25,Dim_WBS!$A$2:$E$13,5,FALSE) -> 8400 | S25: =SUMIFS(Fact_Actual_Costs!$D$2:$D$100,Fact_Actual_Costs!$B$2:$B$100,A25,Fact_Actual_Costs!$A$2:$A$100,"<="&Setup!$B$9) -> 0 | T25: =R25-S25 -> 8400 | U25: =IFERROR((R25*VLOOKUP(A25,'Task Plan'!$A$5:$K$16,11,FALSE))/S25,1) -> 1 | V25: =IF(U25<Setup!$B$12,"Red",IF(U25<Setup!$B$13,"Amber","Green")) -> Green | W25: 8.1.2 Gantt template from garden office | X25: Hours row
A26: =Dim_WBS!A12 -> WBS-11 | B26: =Dim_WBS!C12 -> Testing / Commissioning | C26: =Dim_WBS!D12 -> Labor | D26: Cost | E26: =SUMIFS(Fact_Actual_Costs!$D$2:$D$100,Fact_Actual_Costs!$B$2:$B$100,$A26,Fact_Actual_Costs!$A$2:$A$100,">="&MIN(Fact_Baseline_PV!$A$2:$A$44)+(0*7),Fact_Actual_Costs!$A$2:$A$100,"<"&MIN(Fact_Baseline_PV!$A$2:$A$44)+((0+1)*7)) -> 0 | F26: =SUMIFS(Fact_Actual_Costs!$D$2:$D$100,Fact_Actual_Costs!$B$2:$B$100,$A26,Fact_Actual_Costs!$A$2:$A$100,">="&MIN(Fact_Baseline_PV!$A$2:$A$44)+(1*7),Fact_Actual_Costs!$A$2:$A$100,"<"&MIN(Fact_Baseline_PV!$A$2:$A$44)+((1+1)*7)) -> 0 | G26: =SUMIFS(Fact_Actual_Costs!$D$2:$D$100,Fact_Actual_Costs!$B$2:$B$100,$A26,Fact_Actual_Costs!$A$2:$A$100,">="&MIN(Fact_Baseline_PV!$A$2:$A$44)+(2*7),Fact_Actual_Costs!$A$2:$A$100,"<"&MIN(Fact_Baseline_PV!$A$2:$A$44)+((2+1)*7)) -> 0 | H26: =SUMIFS(Fact_Actual_Costs!$D$2:$D$100,Fact_Actual_Costs!$B$2:$B$100,$A26,Fact_Actual_Costs!$A$2:$A$100,">="&MIN(Fact_Baseline_PV!$A$2:$A$44)+(3*7),Fact_Actual_Costs!$A$2:$A$100,"<"&MIN(Fact_Baseline_PV!$A$2:$A$44)+((3+1)*7)) -> 0 | I26: =SUMIFS(Fact_Actual_Costs!$D$2:$D$100,Fact_Actual_Costs!$B$2:$B$100,$A26,Fact_Actual_Costs!$A$2:$A$100,">="&MIN(Fact_Baseline_PV!$A$2:$A$44)+(4*7),Fact_Actual_Costs!$A$2:$A$100,"<"&MIN(Fact_Baseline_PV!$A$2:$A$44)+((4+1)*7)) -> 0 | J26: =SUMIFS(Fact_Actual_Costs!$D$2:$D$100,Fact_Actual_Costs!$B$2:$B$100,$A26,Fact_Actual_Costs!$A$2:$A$100,">="&MIN(Fact_Baseline_PV!$A$2:$A$44)+(5*7),Fact_Actual_Costs!$A$2:$A$100,"<"&MIN(Fact_Baseline_PV!$A$2:$A$44)+((5+1)*7)) -> 0 | K26: =SUMIFS(Fact_Actual_Costs!$D$2:$D$100,Fact_Actual_Costs!$B$2:$B$100,$A26,Fact_Actual_Costs!$A$2:$A$100,">="&MIN(Fact_Baseline_PV!$A$2:$A$44)+(6*7),Fact_Actual_Costs!$A$2:$A$100,"<"&MIN(Fact_Baseline_PV!$A$2:$A$44)+((6+1)*7)) -> 0 | L26: =SUMIFS(Fact_Actual_Costs!$D$2:$D$100,Fact_Actual_Costs!$B$2:$B$100,$A26,Fact_Actual_Costs!$A$2:$A$100,">="&MIN(Fact_Baseline_PV!$A$2:$A$44)+(7*7),Fact_Actual_Costs!$A$2:$A$100,"<"&MIN(Fact_Baseline_PV!$A$2:$A$44)+((7+1)*7)) -> 0 | M26: =SUMIFS(Fact_Actual_Costs!$D$2:$D$100,Fact_Actual_Costs!$B$2:$B$100,$A26,Fact_Actual_Costs!$A$2:$A$100,">="&MIN(Fact_Baseline_PV!$A$2:$A$44)+(8*7),Fact_Actual_Costs!$A$2:$A$100,"<"&MIN(Fact_Baseline_PV!$A$2:$A$44)+((8+1)*7)) -> 0 | N26: =SUMIFS(Fact_Actual_Costs!$D$2:$D$100,Fact_Actual_Costs!$B$2:$B$100,$A26,Fact_Actual_Costs!$A$2:$A$100,">="&MIN(Fact_Baseline_PV!$A$2:$A$44)+(9*7),Fact_Actual_Costs!$A$2:$A$100,"<"&MIN(Fact_Baseline_PV!$A$2:$A$44)+((9+1)*7)) -> 0 | O26: =SUMIFS(Fact_Actual_Costs!$D$2:$D$100,Fact_Actual_Costs!$B$2:$B$100,$A26,Fact_Actual_Costs!$A$2:$A$100,">="&MIN(Fact_Baseline_PV!$A$2:$A$44)+(10*7),Fact_Actual_Costs!$A$2:$A$100,"<"&MIN(Fact_Baseline_PV!$A$2:$A$44)+((10+1)*7)) -> 0 | P26: =SUMIFS(Fact_Actual_Costs!$D$2:$D$100,Fact_Actual_Costs!$B$2:$B$100,$A26,Fact_Actual_Costs!$A$2:$A$100,">="&MIN(Fact_Baseline_PV!$A$2:$A$44)+(11*7),Fact_Actual_Costs!$A$2:$A$100,"<"&MIN(Fact_Baseline_PV!$A$2:$A$44)+((11+1)*7)) -> 0 | Q26: =SUM(E26:P26) -> 0 | R26: =VLOOKUP(A26,Dim_WBS!$A$2:$E$13,5,FALSE) -> 8400 | S26: =SUMIFS(Fact_Actual_Costs!$D$2:$D$100,Fact_Actual_Costs!$B$2:$B$100,A26,Fact_Actual_Costs!$A$2:$A$100,"<="&Setup!$B$9) -> 0 | T26: =R26-S26 -> 8400 | U26: =IFERROR((R26*VLOOKUP(A26,'Task Plan'!$A$5:$K$16,11,FALSE))/S26,1) -> 1 | V26: =IF(U26<Setup!$B$12,"Red",IF(U26<Setup!$B$13,"Amber","Green")) -> Green | W26: 8.1.2 Gantt template from garden office | X26: Cost row
A27: =Dim_WBS!A13 -> WBS-12 | B27: =Dim_WBS!C13 -> Handover & Closeout | C27: =Dim_WBS!D13 -> Labor | D27: Hours | E27: =SUMIFS(Fact_Actual_Costs!$E$2:$E$100,Fact_Actual_Costs!$B$2:$B$100,$A27,Fact_Actual_Costs!$A$2:$A$100,">="&MIN(Fact_Baseline_PV!$A$2:$A$44)+(0*7),Fact_Actual_Costs!$A$2:$A$100,"<"&MIN(Fact_Baseline_PV!$A$2:$A$44)+((0+1)*7)) -> 0 | F27: =SUMIFS(Fact_Actual_Costs!$E$2:$E$100,Fact_Actual_Costs!$B$2:$B$100,$A27,Fact_Actual_Costs!$A$2:$A$100,">="&MIN(Fact_Baseline_PV!$A$2:$A$44)+(1*7),Fact_Actual_Costs!$A$2:$A$100,"<"&MIN(Fact_Baseline_PV!$A$2:$A$44)+((1+1)*7)) -> 0 | G27: =SUMIFS(Fact_Actual_Costs!$E$2:$E$100,Fact_Actual_Costs!$B$2:$B$100,$A27,Fact_Actual_Costs!$A$2:$A$100,">="&MIN(Fact_Baseline_PV!$A$2:$A$44)+(2*7),Fact_Actual_Costs!$A$2:$A$100,"<"&MIN(Fact_Baseline_PV!$A$2:$A$44)+((2+1)*7)) -> 0 | H27: =SUMIFS(Fact_Actual_Costs!$E$2:$E$100,Fact_Actual_Costs!$B$2:$B$100,$A27,Fact_Actual_Costs!$A$2:$A$100,">="&MIN(Fact_Baseline_PV!$A$2:$A$44)+(3*7),Fact_Actual_Costs!$A$2:$A$100,"<"&MIN(Fact_Baseline_PV!$A$2:$A$44)+((3+1)*7)) -> 0 | I27: =SUMIFS(Fact_Actual_Costs!$E$2:$E$100,Fact_Actual_Costs!$B$2:$B$100,$A27,Fact_Actual_Costs!$A$2:$A$100,">="&MIN(Fact_Baseline_PV!$A$2:$A$44)+(4*7),Fact_Actual_Costs!$A$2:$A$100,"<"&MIN(Fact_Baseline_PV!$A$2:$A$44)+((4+1)*7)) -> 0 | J27: =SUMIFS(Fact_Actual_Costs!$E$2:$E$100,Fact_Actual_Costs!$B$2:$B$100,$A27,Fact_Actual_Costs!$A$2:$A$100,">="&MIN(Fact_Baseline_PV!$A$2:$A$44)+(5*7),Fact_Actual_Costs!$A$2:$A$100,"<"&MIN(Fact_Baseline_PV!$A$2:$A$44)+((5+1)*7)) -> 0 | K27: =SUMIFS(Fact_Actual_Costs!$E$2:$E$100,Fact_Actual_Costs!$B$2:$B$100,$A27,Fact_Actual_Costs!$A$2:$A$100,">="&MIN(Fact_Baseline_PV!$A$2:$A$44)+(6*7),Fact_Actual_Costs!$A$2:$A$100,"<"&MIN(Fact_Baseline_PV!$A$2:$A$44)+((6+1)*7)) -> 0 | L27: =SUMIFS(Fact_Actual_Costs!$E$2:$E$100,Fact_Actual_Costs!$B$2:$B$100,$A27,Fact_Actual_Costs!$A$2:$A$100,">="&MIN(Fact_Baseline_PV!$A$2:$A$44)+(7*7),Fact_Actual_Costs!$A$2:$A$100,"<"&MIN(Fact_Baseline_PV!$A$2:$A$44)+((7+1)*7)) -> 0 | M27: =SUMIFS(Fact_Actual_Costs!$E$2:$E$100,Fact_Actual_Costs!$B$2:$B$100,$A27,Fact_Actual_Costs!$A$2:$A$100,">="&MIN(Fact_Baseline_PV!$A$2:$A$44)+(8*7),Fact_Actual_Costs!$A$2:$A$100,"<"&MIN(Fact_Baseline_PV!$A$2:$A$44)+((8+1)*7)) -> 0 | N27: =SUMIFS(Fact_Actual_Costs!$E$2:$E$100,Fact_Actual_Costs!$B$2:$B$100,$A27,Fact_Actual_Costs!$A$2:$A$100,">="&MIN(Fact_Baseline_PV!$A$2:$A$44)+(9*7),Fact_Actual_Costs!$A$2:$A$100,"<"&MIN(Fact_Baseline_PV!$A$2:$A$44)+((9+1)*7)) -> 0 | O27: =SUMIFS(Fact_Actual_Costs!$E$2:$E$100,Fact_Actual_Costs!$B$2:$B$100,$A27,Fact_Actual_Costs!$A$2:$A$100,">="&MIN(Fact_Baseline_PV!$A$2:$A$44)+(10*7),Fact_Actual_Costs!$A$2:$A$100,"<"&MIN(Fact_Baseline_PV!$A$2:$A$44)+((10+1)*7)) -> 0 | P27: =SUMIFS(Fact_Actual_Costs!$E$2:$E$100,Fact_Actual_Costs!$B$2:$B$100,$A27,Fact_Actual_Costs!$A$2:$A$100,">="&MIN(Fact_Baseline_PV!$A$2:$A$44)+(11*7),Fact_Actual_Costs!$A$2:$A$100,"<"&MIN(Fact_Baseline_PV!$A$2:$A$44)+((11+1)*7)) -> 0 | Q27: =SUM(E27:P27) -> 0 | R27: =VLOOKUP(A27,Dim_WBS!$A$2:$E$13,5,FALSE) -> 3600 | S27: =SUMIFS(Fact_Actual_Costs!$D$2:$D$100,Fact_Actual_Costs!$B$2:$B$100,A27,Fact_Actual_Costs!$A$2:$A$100,"<="&Setup!$B$9) -> 0 | T27: =R27-S27 -> 3600 | U27: =IFERROR((R27*VLOOKUP(A27,'Task Plan'!$A$5:$K$16,11,FALSE))/S27,1) -> 1 | V27: =IF(U27<Setup!$B$12,"Red",IF(U27<Setup!$B$13,"Amber","Green")) -> Green | W27: 8.1.2 Gantt template from garden office | X27: Hours row
A28: =Dim_WBS!A13 -> WBS-12 | B28: =Dim_WBS!C13 -> Handover & Closeout | C28: =Dim_WBS!D13 -> Labor | D28: Cost | E28: =SUMIFS(Fact_Actual_Costs!$D$2:$D$100,Fact_Actual_Costs!$B$2:$B$100,$A28,Fact_Actual_Costs!$A$2:$A$100,">="&MIN(Fact_Baseline_PV!$A$2:$A$44)+(0*7),Fact_Actual_Costs!$A$2:$A$100,"<"&MIN(Fact_Baseline_PV!$A$2:$A$44)+((0+1)*7)) -> 0 | F28: =SUMIFS(Fact_Actual_Costs!$D$2:$D$100,Fact_Actual_Costs!$B$2:$B$100,$A28,Fact_Actual_Costs!$A$2:$A$100,">="&MIN(Fact_Baseline_PV!$A$2:$A$44)+(1*7),Fact_Actual_Costs!$A$2:$A$100,"<"&MIN(Fact_Baseline_PV!$A$2:$A$44)+((1+1)*7)) -> 0 | G28: =SUMIFS(Fact_Actual_Costs!$D$2:$D$100,Fact_Actual_Costs!$B$2:$B$100,$A28,Fact_Actual_Costs!$A$2:$A$100,">="&MIN(Fact_Baseline_PV!$A$2:$A$44)+(2*7),Fact_Actual_Costs!$A$2:$A$100,"<"&MIN(Fact_Baseline_PV!$A$2:$A$44)+((2+1)*7)) -> 0 | H28: =SUMIFS(Fact_Actual_Costs!$D$2:$D$100,Fact_Actual_Costs!$B$2:$B$100,$A28,Fact_Actual_Costs!$A$2:$A$100,">="&MIN(Fact_Baseline_PV!$A$2:$A$44)+(3*7),Fact_Actual_Costs!$A$2:$A$100,"<"&MIN(Fact_Baseline_PV!$A$2:$A$44)+((3+1)*7)) -> 0 | I28: =SUMIFS(Fact_Actual_Costs!$D$2:$D$100,Fact_Actual_Costs!$B$2:$B$100,$A28,Fact_Actual_Costs!$A$2:$A$100,">="&MIN(Fact_Baseline_PV!$A$2:$A$44)+(4*7),Fact_Actual_Costs!$A$2:$A$100,"<"&MIN(Fact_Baseline_PV!$A$2:$A$44)+((4+1)*7)) -> 0 | J28: =SUMIFS(Fact_Actual_Costs!$D$2:$D$100,Fact_Actual_Costs!$B$2:$B$100,$A28,Fact_Actual_Costs!$A$2:$A$100,">="&MIN(Fact_Baseline_PV!$A$2:$A$44)+(5*7),Fact_Actual_Costs!$A$2:$A$100,"<"&MIN(Fact_Baseline_PV!$A$2:$A$44)+((5+1)*7)) -> 0 | K28: =SUMIFS(Fact_Actual_Costs!$D$2:$D$100,Fact_Actual_Costs!$B$2:$B$100,$A28,Fact_Actual_Costs!$A$2:$A$100,">="&MIN(Fact_Baseline_PV!$A$2:$A$44)+(6*7),Fact_Actual_Costs!$A$2:$A$100,"<"&MIN(Fact_Baseline_PV!$A$2:$A$44)+((6+1)*7)) -> 0 | L28: =SUMIFS(Fact_Actual_Costs!$D$2:$D$100,Fact_Actual_Costs!$B$2:$B$100,$A28,Fact_Actual_Costs!$A$2:$A$100,">="&MIN(Fact_Baseline_PV!$A$2:$A$44)+(7*7),Fact_Actual_Costs!$A$2:$A$100,"<"&MIN(Fact_Baseline_PV!$A$2:$A$44)+((7+1)*7)) -> 0 | M28: =SUMIFS(Fact_Actual_Costs!$D$2:$D$100,Fact_Actual_Costs!$B$2:$B$100,$A28,Fact_Actual_Costs!$A$2:$A$100,">="&MIN(Fact_Baseline_PV!$A$2:$A$44)+(8*7),Fact_Actual_Costs!$A$2:$A$100,"<"&MIN(Fact_Baseline_PV!$A$2:$A$44)+((8+1)*7)) -> 0 | N28: =SUMIFS(Fact_Actual_Costs!$D$2:$D$100,Fact_Actual_Costs!$B$2:$B$100,$A28,Fact_Actual_Costs!$A$2:$A$100,">="&MIN(Fact_Baseline_PV!$A$2:$A$44)+(9*7),Fact_Actual_Costs!$A$2:$A$100,"<"&MIN(Fact_Baseline_PV!$A$2:$A$44)+((9+1)*7)) -> 0 | O28: =SUMIFS(Fact_Actual_Costs!$D$2:$D$100,Fact_Actual_Costs!$B$2:$B$100,$A28,Fact_Actual_Costs!$A$2:$A$100,">="&MIN(Fact_Baseline_PV!$A$2:$A$44)+(10*7),Fact_Actual_Costs!$A$2:$A$100,"<"&MIN(Fact_Baseline_PV!$A$2:$A$44)+((10+1)*7)) -> 0 | P28: =SUMIFS(Fact_Actual_Costs!$D$2:$D$100,Fact_Actual_Costs!$B$2:$B$100,$A28,Fact_Actual_Costs!$A$2:$A$100,">="&MIN(Fact_Baseline_PV!$A$2:$A$44)+(11*7),Fact_Actual_Costs!$A$2:$A$100,"<"&MIN(Fact_Baseline_PV!$A$2:$A$44)+((11+1)*7)) -> 0 | Q28: =SUM(E28:P28) -> 0 | R28: =VLOOKUP(A28,Dim_WBS!$A$2:$E$13,5,FALSE) -> 3600 | S28: =SUMIFS(Fact_Actual_Costs!$D$2:$D$100,Fact_Actual_Costs!$B$2:$B$100,A28,Fact_Actual_Costs!$A$2:$A$100,"<="&Setup!$B$9) -> 0 | T28: =R28-S28 -> 3600 | U28: =IFERROR((R28*VLOOKUP(A28,'Task Plan'!$A$5:$K$16,11,FALSE))/S28,1) -> 1 | V28: =IF(U28<Setup!$B$12,"Red",IF(U28<Setup!$B$13,"Amber","Green")) -> Green | W28: 8.1.2 Gantt template from garden office | X28: Cost row
A31: Gantt of Gantts / monthly workload summary | B31: 46143 | C31: 46174 | D31: 46204 | E31: 46235 | F31: 46266 | G31: 46296 | H31: 46327 | I31: 46357 | J31: Total | K31: Source | L31: Interpretation
A32: Planned PV | B32: =SUMIFS(Fact_Baseline_PV!$C$2:$C$44,Fact_Baseline_PV!$A$2:$A$44,">="&DATE(2026,5,1),Fact_Baseline_PV!$A$2:$A$44,"<"&DATE(2026,6,1)) -> 87066.67 | C32: =SUMIFS(Fact_Baseline_PV!$C$2:$C$44,Fact_Baseline_PV!$A$2:$A$44,">="&DATE(2026,6,1),Fact_Baseline_PV!$A$2:$A$44,"<"&DATE(2026,7,1)) -> 133166.67 | D32: =SUMIFS(Fact_Baseline_PV!$C$2:$C$44,Fact_Baseline_PV!$A$2:$A$44,">="&DATE(2026,7,1),Fact_Baseline_PV!$A$2:$A$44,"<"&DATE(2026,8,1)) -> 48416.66 | E32: 0 | F32: 0 | G32: 0 | H32: 0 | I32: 0 | J32: =SUM(B32:I32) -> 268650 | K32: 8.1.2 Gantt of Gantts template | L32: Monthly portfolio-style total from current project PV
A33: Actual Cost | B33: =SUMIFS(Fact_Actual_Costs!$D$2:$D$100,Fact_Actual_Costs!$A$2:$A$100,">="&DATE(2026,5,1),Fact_Actual_Costs!$A$2:$A$100,"<"&DATE(2026,6,1)) -> 86509.44 | C33: =SUMIFS(Fact_Actual_Costs!$D$2:$D$100,Fact_Actual_Costs!$A$2:$A$100,">="&DATE(2026,6,1),Fact_Actual_Costs!$A$2:$A$100,"<"&DATE(2026,7,1)) -> 55476 | D33: =SUMIFS(Fact_Actual_Costs!$D$2:$D$100,Fact_Actual_Costs!$A$2:$A$100,">="&DATE(2026,7,1),Fact_Actual_Costs!$A$2:$A$100,"<"&DATE(2026,8,1)) -> 0 | E33: 0 | F33: 0 | G33: 0 | H33: 0 | I33: 0 | J33: =SUM(B33:I33) -> 141985.44 | K33: 8.1.2 Gantt of Gantts template | L33: Monthly portfolio-style total from actual costs
A34: Active WBS count | B34: =SUM(--(B32>0)) -> 1 | C34: =SUM(--(C32>0)) -> 1 | D34: =SUM(--(D32>0)) -> 1 | E34: 0 | F34: 0 | G34: 0 | H34: 0 | I34: 0 | J34: =SUM(B34:I34) -> 3 | K34: 8.1.2 Gantt of Gantts template | L34: Simple monthly activity indicator

Sheet Dim_Project
A1: Project_ID | B1: Project_Name | C1: Start_Date | D1: End_Date | E1: BAC | F1: Sector
A2: P101 | B2: Office Fit-Out | C2: 46146 | D2: 46229 | E2: 268650 | F2: Corporate Real Estate

Sheet Dim_WBS
A1: WBS_ID | B1: WBS_Code | C1: Activity_Name | D1: Type | E1: Total_Budget
A2: WBS-01 | B2: 1 | C2: Project Management | D2: Labor | E2: 18000
A3: WBS-02 | B3: 2 | C3: Site Survey & Mobilization | D3: Labor | E3: 8500
A4: WBS-03 | B4: 3 | C4: Design & Engineering | D4: Labor | E4: 19200
A5: WBS-04 | B5: 4 | C5: Procurement - Materials | D5: Material | E5: 42000
A6: WBS-05 | B6: 5 | C6: Demolition & Prep | D6: Labor | E6: 13200
A7: WBS-06 | B7: 6 | C7: Electrical Rough-In | D7: Labor | E7: 26000
A8: WBS-07 | B8: 7 | C8: HVAC Installation | D8: Subcontractor | E8: 36000
A9: WBS-08 | B9: 8 | C9: Partitions & Drywall | D9: Subcontractor | E9: 28000
A10: WBS-09 | B10: 9 | C10: Flooring | D10: Material | E10: 35750
A11: WBS-10 | B11: 10 | C11: Fixtures & Furniture | D11: Material | E11: 30000
A12: WBS-11 | B12: 11 | C12: Testing / Commissioning | D12: Labor | E12: 8400
A13: WBS-12 | B13: 12 | C13: Handover & Closeout | D13: Labor | E13: 3600

Sheet Dim_Resource
A1: Resource_ID | B1: Resource_Name | C1: Role | D1: Hourly_Rate
A2: R01 | B2: Project Manager | C2: Management | D2: 1500
A3: R02 | B3: Lead Engineer | C3: Engineering | D3: 2400
A4: R03 | B4: Electrician | C4: Trades | D4: 2600
A5: R04 | B5: Demolition Crew | C5: Labor | D5: 2200
A6: R05 | B6: Testing Engineer | C6: QA | D6: 2100
A7: R06 | B7: Closeout Specialist | C7: QA | D7: 1800
A8: R07 | B8: Materials Vendor | C8: Vendor | D8: 0
A9: R08 | B9: HVAC Contractor | C9: Contractor | D9: 0
A10: R09 | B10: Drywall Contractor | C10: Contractor | D10: 0
A11: R10 | B11: Flooring Supplier | C11: Vendor | D11: 0
A12: R11 | B12: Furniture Supplier | C12: Vendor | D12: 0

Sheet Dim_Calendar
A1: Date | B1: Year | C1: Month | D1: Month_Name | E1: Quarter | F1: Week_Number | G1: Is_Weekday
A2: 46146 | B2: 2026 | C2: 5 | D2: May | E2: 2 | F2: 1 | G2: 1
A3: 46147 | B3: 2026 | C3: 5 | D3: May | E3: 2 | F3: 1 | G3: 1
A4: 46148 | B4: 2026 | C4: 5 | D4: May | E4: 2 | F4: 1 | G4: 1
A5: 46149 | B5: 2026 | C5: 5 | D5: May | E5: 2 | F5: 1 | G5: 1
A6: 46150 | B6: 2026 | C6: 5 | D6: May | E6: 2 | F6: 1 | G6: 1
A7: 46151 | B7: 2026 | C7: 5 | D7: May | E7: 2 | F7: 1 | G7: 0
A8: 46152 | B8: 2026 | C8: 5 | D8: May | E8: 2 | F8: 1 | G8: 0
A9: 46153 | B9: 2026 | C9: 5 | D9: May | E9: 2 | F9: 2 | G9: 1
A10: 46154 | B10: 2026 | C10: 5 | D10: May | E10: 2 | F10: 2 | G10: 1
A11: 46155 | B11: 2026 | C11: 5 | D11: May | E11: 2 | F11: 2 | G11: 1
A12: 46156 | B12: 2026 | C12: 5 | D12: May | E12: 2 | F12: 2 | G12: 1
A13: 46157 | B13: 2026 | C13: 5 | D13: May | E13: 2 | F13: 2 | G13: 1
... A85: 46229 | B85: 2026 | C85: 7 | D85: July | E85: 3 | F85: 12 | G85: 0

Sheet Fact_Baseline_PV
A1: Date | B1: WBS_ID | C1: Planned_Value
A2: 46146 | B2: WBS-01 | C2: 1500
A3: 46153 | B3: WBS-01 | C3: 1500
A4: 46160 | B4: WBS-01 | C4: 1500
A5: 46167 | B5: WBS-01 | C5: 1500
A6: 46174 | B6: WBS-01 | C6: 1500
A7: 46181 | B7: WBS-01 | C7: 1500
A8: 46188 | B8: WBS-01 | C8: 1500
A9: 46195 | B9: WBS-01 | C9: 1500
A10: 46202 | B10: WBS-01 | C10: 1500
A11: 46209 | B11: WBS-01 | C11: 1500
A12: 46216 | B12: WBS-01 | C12: 1500
A13: 46223 | B13: WBS-01 | C13: 1500
... A44: 46223 | B44: WBS-12 | C44: 3600

Sheet Fact_Actual_Costs
A1: Date | B1: WBS_ID | C1: Resource_ID | D1: Actual_Cost | E1: Hours_Worked
A2: 46146 | B2: WBS-01 | C2: R01 | D2: 320 | E2: 0.21
A3: 46147 | B3: WBS-01 | C3: R01 | D3: 320 | E3: 0.21
A4: 46148 | B4: WBS-01 | C4: R01 | D4: 320 | E4: 0.21
A5: 46149 | B5: WBS-01 | C5: R01 | D5: 320 | E5: 0.21
A6: 46150 | B6: WBS-01 | C6: R01 | D6: 320 | E6: 0.21
A7: 46146 | B7: WBS-02 | C7: R04 | D7: 1740 | E7: 0.79
A8: 46147 | B8: WBS-02 | C8: R04 | D8: 1740 | E8: 0.79
A9: 46148 | B9: WBS-02 | C9: R04 | D9: 1740 | E9: 0.79
A10: 46149 | B10: WBS-02 | C10: R04 | D10: 1740 | E10: 0.79
A11: 46150 | B11: WBS-02 | C11: R04 | D11: 1740 | E11: 0.79
A12: 46146 | B12: WBS-03 | C12: R02 | D12: 1199.01 | E12: 0.5
A13: 46147 | B13: WBS-03 | C13: R02 | D13: 1199.01 | E13: 0.5
... A100: 46185 | B100: WBS-08 | C100: R09 | D100: 1419.84 | E100: 0

Sheet Fact_Physical_Progress
A1: Date | B1: WBS_ID | C1: Physical_Progress_Pct
A2: 46150 | B2: WBS-01 | C2: 0.083333
A3: 46150 | B3: WBS-02 | C3: 1
A4: 46150 | B4: WBS-03 | C4: 0.265
A5: 46157 | B5: WBS-01 | C5: 0.166667
A6: 46157 | B6: WBS-02 | C6: 1
A7: 46157 | B7: WBS-03 | C7: 0.6
A8: 46157 | B8: WBS-04 | C8: 0.2
A9: 46157 | B9: WBS-05 | C9: 0.351818
A10: 46164 | B10: WBS-01 | C10: 0.25
A11: 46164 | B11: WBS-02 | C11: 1
A12: 46164 | B12: WBS-03 | C12: 1
A13: 46164 | B13: WBS-04 | C13: 0.45
... A35: 46185 | B35: WBS-08 | C35: 0.248857

Sheet EVM
A1: EVM Reporting
A2: Weekly earned value reporting table using the guideline formulas: PV, AC, EV, SV, CV, SPI, CPI, BAC, EAC, ETC, and VAC.
A4: Week | B4: Week Date | C4: Cum PV | D4: Cum AC | E4: Cum EV | F4: SV | G4: CV | H4: SPI | I4: CPI | J4: BAC | K4: EAC | L4: ETC | M4: VAC | N4: Status
A5: 1 | B5: =MIN(Fact_Baseline_PV!$A:$A)+4+(0*7) -> 46150 | C5: =SUMIFS(Fact_Baseline_PV!$C:$C,Fact_Baseline_PV!$A:$A,"<="&B5) -> 16400 | D5: =SUMIFS(Fact_Actual_Costs!$D:$D,Fact_Actual_Costs!$A:$A,"<="&B5) -> 16295.04 | E5: {=SUM(IFERROR(LOOKUP(2,1/(Fact_Physical_Progress!$B$2:$B$35=Dim_WBS!$A$2)/(Fact_Physical_Progress!$A$2:$A$35<=B5),Fact_Physical_Progress!$C$2:$C$35),0)*Dim_WBS!$E$2,IFERROR(LOOKUP(2,1/(Fact_Physical_Progress!$B$2:$B$35=Dim_WBS!$A$3)/(Fact_Physical_Progress!$A$2:$A$35<=B5),Fact_Physical_Progress!$C$2:$C$35),0)*Dim_WBS!$E$3,IFERROR(LOOKUP(2,1/(Fact_Physical_Progress!$B$2:$B$35=Dim_WBS!$A$4)/(Fact_Physical_Progress!$A$2:$A$35<=B5),Fact_Physical_Progress!$C$2:$C$35),0)*Dim_WBS!$E$4,IFERROR(LOOKUP(2,1/(Fact_Physical_Progress!$B$2:$B$35=Dim_WBS!$A$5)/(Fact_Physical_Progress!$A$2:$A$35<=B5),Fact_Physical_Progress!$C$2:$C$35),0)*Dim_WBS!$E$5,IFERROR(LOOKUP(2,1/(Fact_Physical_Progress!$B$2:$B$35=Dim_WBS!$A$6)/(Fact_Physical_Progress!$A$2:$A$35<=B5),Fact_Physical_Progress!$C$2:$C$35),0)*Dim_WBS!$E$6,IFERROR(LOOKUP(2,1/(Fact_Physical_Progress!$B$2:$B$35=Dim_WBS!$A$7)/(Fact_Physical_Progress!$A$2:$A$35<=B5),Fact_Physical_Progress!$C$2:$C$35),0)*Dim_WBS!$E$7,IFERROR(LOOKUP(2,1/(Fact_Physical_Progress!$B$2:$B$35=Dim_WBS!$A$8)/(Fact_Physical_Progress!$A$2:$A$35<=B5),Fact_Physical_Progress!$C$2:$C$35),0)*Dim_WBS!$E$8,IFERROR(LOOKUP(2,1/(Fact_Physical_Progress!$B$2:$B$35=Dim_WBS!$A$9)/(Fact_Physical_Progress!$A$2:$A$35<=B5),Fact_Physical_Progress!$C$2:$C$35),0)*Dim_WBS!$E$9,IFERROR(LOOKUP(2,1/(Fact_Physical_Progress!$B$2:$B$35=Dim_WBS!$A$10)/(Fact_Physical_Progress!$A$2:$A$35<=B5),Fact_Physical_Progress!$C$2:$C$35),0)*Dim_WBS!$E$10,IFERROR(LOOKUP(2,1/(Fact_Physical_Progress!$B$2:$B$35=Dim_WBS!$A$11)/(Fact_Physical_Progress!$A$2:$A$35<=B5),Fact_Physical_Progress!$C$2:$C$35),0)*Dim_WBS!$E$11,IFERROR(LOOKUP(2,1/(Fact_Physical_Progress!$B$2:$B$35=Dim_WBS!$A$12)/(Fact_Physical_Progress!$A$2:$A$35<=B5),Fact_Physical_Progress!$C$2:$C$35),0)*Dim_WBS!$E$12,IFERROR(LOOKUP(2,1/(Fact_Physical_Progress!$B$2:$B$35=Dim_WBS!$A$13)/(Fact_Physical_Progress!$A$2:$A$35<=B5),Fact_Physical_Progress!$C$2:$C$35),0)*Dim_WBS!$E$13)} -> 15087.994 | F5: =E5-C5 -> -1312.006 | G5: =E5-D5 -> -1207.046 | H5: =IFERROR(E5/C5,1) -> 0.91999963 | I5: =IFERROR(E5/D5,1) -> 0.92592556 | J5: =Setup!$B$11 -> 268650 | K5: =IF(I5>0,J5/I5,J5) -> 290142.12 | L5: =K5-D5 -> 273847.08 | M5: =J5-K5 -> -21492.115 | N5: =IF(OR(F5<0,G5<0,H5<Setup!$B$12,I5<Setup!$B$12),"Red",IF(OR(H5<Setup!$B$13,I5<Setup!$B$13),"Amber","Green")) -> Red
A6: 2 | B6: =MIN(Fact_Baseline_PV!$A:$A)+4+(1*7) -> 46157 | C6: =SUMIFS(Fact_Baseline_PV!$C:$C,Fact_Baseline_PV!$A:$A,"<="&B6) -> 39200 | D6: =SUMIFS(Fact_Actual_Costs!$D:$D,Fact_Actual_Costs!$A:$A,"<="&B6) -> 38949.12 | E6: {=SUM(IFERROR(LOOKUP(2,1/(Fact_Physical_Progress!$B$2:$B$35=Dim_WBS!$A$2)/(Fact_Physical_Progress!$A$2:$A$35<=B6),Fact_Physical_Progress!$C$2:$C$35),0)*Dim_WBS!$E$2,IFERROR(LOOKUP(2,1/(Fact_Physical_Progress!$B$2:$B$35=Dim_WBS!$A$3)/(Fact_Physical_Progress!$A$2:$A$35<=B6),Fact_Physical_Progress!$C$2:$C$35),0)*Dim_WBS!$E$3,IFERROR(LOOKUP(2,1/(Fact_Physical_Progress!$B$2:$B$35=Dim_WBS!$A$4)/(Fact_Physical_Progress!$A$2:$A$35<=B6),Fact_Physical_Progress!$C$2:$C$35),0)*Dim_WBS!$E$4,IFERROR(LOOKUP(2,1/(Fact_Physical_Progress!$B$2:$B$35=Dim_WBS!$A$5)/(Fact_Physical_Progress!$A$2:$A$35<=B6),Fact_Physical_Progress!$C$2:$C$35),0)*Dim_WBS!$E$5,IFERROR(LOOKUP(2,1/(Fact_Physical_Progress!$B$2:$B$35=Dim_WBS!$A$6)/(Fact_Physical_Progress!$A$2:$A$35<=B6),Fact_Physical_Progress!$C$2:$C$35),0)*Dim_WBS!$E$6,IFERROR(LOOKUP(2,1/(Fact_Physical_Progress!$B$2:$B$35=Dim_WBS!$A$7)/(Fact_Physical_Progress!$A$2:$A$35<=B6),Fact_Physical_Progress!$C$2:$C$35),0)*Dim_WBS!$E$7,IFERROR(LOOKUP(2,1/(Fact_Physical_Progress!$B$2:$B$35=Dim_WBS!$A$8)/(Fact_Physical_Progress!$A$2:$A$35<=B6),Fact_Physical_Progress!$C$2:$C$35),0)*Dim_WBS!$E$8,IFERROR(LOOKUP(2,1/(Fact_Physical_Progress!$B$2:$B$35=Dim_WBS!$A$9)/(Fact_Physical_Progress!$A$2:$A$35<=B6),Fact_Physical_Progress!$C$2:$C$35),0)*Dim_WBS!$E$9,IFERROR(LOOKUP(2,1/(Fact_Physical_Progress!$B$2:$B$35=Dim_WBS!$A$10)/(Fact_Physical_Progress!$A$2:$A$35<=B6),Fact_Physical_Progress!$C$2:$C$35),0)*Dim_WBS!$E$10,IFERROR(LOOKUP(2,1/(Fact_Physical_Progress!$B$2:$B$35=Dim_WBS!$A$11)/(Fact_Physical_Progress!$A$2:$A$35<=B6),Fact_Physical_Progress!$C$2:$C$35),0)*Dim_WBS!$E$11,IFERROR(LOOKUP(2,1/(Fact_Physical_Progress!$B$2:$B$35=Dim_WBS!$A$12)/(Fact_Physical_Progress!$A$2:$A$35<=B6),Fact_Physical_Progress!$C$2:$C$35),0)*Dim_WBS!$E$12,IFERROR(LOOKUP(2,1/(Fact_Physical_Progress!$B$2:$B$35=Dim_WBS!$A$13)/(Fact_Physical_Progress!$A$2:$A$35<=B6),Fact_Physical_Progress!$C$2:$C$35),0)*Dim_WBS!$E$13)} -> 36064.004 | F6: =E6-C6 -> -3135.9964 | G6: =E6-D6 -> -2885.1164 | H6: =IFERROR(E6/C6,1) -> 0.92000009 | I6: =IFERROR(E6/D6,1) -> 0.92592602 | J6: =Setup!$B$11 -> 268650 | K6: =IF(I6>0,J6/I6,J6) -> 290141.97 | L6: =K6-D6 -> 251192.85 | M6: =J6-K6 -> -21491.971 | N6: =IF(OR(F6<0,G6<0,H6<Setup!$B$12,I6<Setup!$B$12),"Red",IF(OR(H6<Setup!$B$13,I6<Setup!$B$13),"Amber","Green")) -> Red
A7: 3 | B7: =MIN(Fact_Baseline_PV!$A:$A)+4+(2*7) -> 46164 | C7: =SUMIFS(Fact_Baseline_PV!$C:$C,Fact_Baseline_PV!$A:$A,"<="&B7) -> 62000 | D7: =SUMIFS(Fact_Actual_Costs!$D:$D,Fact_Actual_Costs!$A:$A,"<="&B7) -> 61603.2 | E7: {=SUM(IFERROR(LOOKUP(2,1/(Fact_Physical_Progress!$B$2:$B$35=Dim_WBS!$A$2)/(Fact_Physical_Progress!$A$2:$A$35<=B7),Fact_Physical_Progress!$C$2:$C$35),0)*Dim_WBS!$E$2,IFERROR(LOOKUP(2,1/(Fact_Physical_Progress!$B$2:$B$35=Dim_WBS!$A$3)/(Fact_Physical_Progress!$A$2:$A$35<=B7),Fact_Physical_Progress!$C$2:$C$35),0)*Dim_WBS!$E$3,IFERROR(LOOKUP(2,1/(Fact_Physical_Progress!$B$2:$B$35=Dim_WBS!$A$4)/(Fact_Physical_Progress!$A$2:$A$35<=B7),Fact_Physical_Progress!$C$2:$C$35),0)*Dim_WBS!$E$4,IFERROR(LOOKUP(2,1/(Fact_Physical_Progress!$B$2:$B$35=Dim_WBS!$A$5)/(Fact_Physical_Progress!$A$2:$A$35<=B7),Fact_Physical_Progress!$C$2:$C$35),0)*Dim_WBS!$E$5,IFERROR(LOOKUP(2,1/(Fact_Physical_Progress!$B$2:$B$35=Dim_WBS!$A$6)/(Fact_Physical_Progress!$A$2:$A$35<=B7),Fact_Physical_Progress!$C$2:$C$35),0)*Dim_WBS!$E$6,IFERROR(LOOKUP(2,1/(Fact_Physical_Progress!$B$2:$B$35=Dim_WBS!$A$7)/(Fact_Physical_Progress!$A$2:$A$35<=B7),Fact_Physical_Progress!$C$2:$C$35),0)*Dim_WBS!$E$7,IFERROR(LOOKUP(2,1/(Fact_Physical_Progress!$B$2:$B$35=Dim_WBS!$A$8)/(Fact_Physical_Progress!$A$2:$A$35<=B7),Fact_Physical_Progress!$C$2:$C$35),0)*Dim_WBS!$E$8,IFERROR(LOOKUP(2,1/(Fact_Physical_Progress!$B$2:$B$35=Dim_WBS!$A$9)/(Fact_Physical_Progress!$A$2:$A$35<=B7),Fact_Physical_Progress!$C$2:$C$35),0)*Dim_WBS!$E$9,IFERROR(LOOKUP(2,1/(Fact_Physical_Progress!$B$2:$B$35=Dim_WBS!$A$10)/(Fact_Physical_Progress!$A$2:$A$35<=B7),Fact_Physical_Progress!$C$2:$C$35),0)*Dim_WBS!$E$10,IFERROR(LOOKUP(2,1/(Fact_Physical_Progress!$B$2:$B$35=Dim_WBS!$A$11)/(Fact_Physical_Progress!$A$2:$A$35<=B7),Fact_Physical_Progress!$C$2:$C$35),0)*Dim_WBS!$E$11,IFERROR(LOOKUP(2,1/(Fact_Physical_Progress!$B$2:$B$35=Dim_WBS!$A$12)/(Fact_Physical_Progress!$A$2:$A$35<=B7),Fact_Physical_Progress!$C$2:$C$35),0)*Dim_WBS!$E$12,IFERROR(LOOKUP(2,1/(Fact_Physical_Progress!$B$2:$B$35=Dim_WBS!$A$13)/(Fact_Physical_Progress!$A$2:$A$35<=B7),Fact_Physical_Progress!$C$2:$C$35),0)*Dim_WBS!$E$13)} -> 57040 | F7: =E7-C7 -> -4960 | G7: =E7-D7 -> -4563.2 | H7: =IFERROR(E7/C7,1) -> 0.92 | I7: =IFERROR(E7/D7,1) -> 0.92592593 | J7: =Setup!$B$11 -> 268650 | K7: =IF(I7>0,J7/I7,J7) -> 290142 | L7: =K7-D7 -> 228538.8 | M7: =J7-K7 -> -21492 | N7: =IF(OR(F7<0,G7<0,H7<Setup!$B$12,I7<Setup!$B$12),"Red",IF(OR(H7<Setup!$B$13,I7<Setup!$B$13),"Amber","Green")) -> Red
A8: 4 | B8: =MIN(Fact_Baseline_PV!$A:$A)+4+(3*7) -> 46171 | C8: =SUMIFS(Fact_Baseline_PV!$C:$C,Fact_Baseline_PV!$A:$A,"<="&B8) -> 87066.67 | D8: =SUMIFS(Fact_Actual_Costs!$D:$D,Fact_Actual_Costs!$A:$A,"<="&B8) -> 86509.44 | E8: {=SUM(IFERROR(LOOKUP(2,1/(Fact_Physical_Progress!$B$2:$B$35=Dim_WBS!$A$2)/(Fact_Physical_Progress!$A$2:$A$35<=B8),Fact_Physical_Progress!$C$2:$C$35),0)*Dim_WBS!$E$2,IFERROR(LOOKUP(2,1/(Fact_Physical_Progress!$B$2:$B$35=Dim_WBS!$A$3)/(Fact_Physical_Progress!$A$2:$A$35<=B8),Fact_Physical_Progress!$C$2:$C$35),0)*Dim_WBS!$E$3,IFERROR(LOOKUP(2,1/(Fact_Physical_Progress!$B$2:$B$35=Dim_WBS!$A$4)/(Fact_Physical_Progress!$A$2:$A$35<=B8),Fact_Physical_Progress!$C$2:$C$35),0)*Dim_WBS!$E$4,IFERROR(LOOKUP(2,1/(Fact_Physical_Progress!$B$2:$B$35=Dim_WBS!$A$5)/(Fact_Physical_Progress!$A$2:$A$35<=B8),Fact_Physical_Progress!$C$2:$C$35),0)*Dim_WBS!$E$5,IFERROR(LOOKUP(2,1/(Fact_Physical_Progress!$B$2:$B$35=Dim_WBS!$A$6)/(Fact_Physical_Progress!$A$2:$A$35<=B8),Fact_Physical_Progress!$C$2:$C$35),0)*Dim_WBS!$E$6,IFERROR(LOOKUP(2,1/(Fact_Physical_Progress!$B$2:$B$35=Dim_WBS!$A$7)/(Fact_Physical_Progress!$A$2:$A$35<=B8),Fact_Physical_Progress!$C$2:$C$35),0)*Dim_WBS!$E$7,IFERROR(LOOKUP(2,1/(Fact_Physical_Progress!$B$2:$B$35=Dim_WBS!$A$8)/(Fact_Physical_Progress!$A$2:$A$35<=B8),Fact_Physical_Progress!$C$2:$C$35),0)*Dim_WBS!$E$8,IFERROR(LOOKUP(2,1/(Fact_Physical_Progress!$B$2:$B$35=Dim_WBS!$A$9)/(Fact_Physical_Progress!$A$2:$A$35<=B8),Fact_Physical_Progress!$C$2:$C$35),0)*Dim_WBS!$E$9,IFERROR(LOOKUP(2,1/(Fact_Physical_Progress!$B$2:$B$35=Dim_WBS!$A$10)/(Fact_Physical_Progress!$A$2:$A$35<=B8),Fact_Physical_Progress!$C$2:$C$35),0)*Dim_WBS!$E$10,IFERROR(LOOKUP(2,1/(Fact_Physical_Progress!$B$2:$B$35=Dim_WBS!$A$11)/(Fact_Physical_Progress!$A$2:$A$35<=B8),Fact_Physical_Progress!$C$2:$C$35),0)*Dim_WBS!$E$11,IFERROR(LOOKUP(2,1/(Fact_Physical_Progress!$B$2:$B$35=Dim_WBS!$A$12)/(Fact_Physical_Progress!$A$2:$A$35<=B8),Fact_Physical_Progress!$C$2:$C$35),0)*Dim_WBS!$E$12,IFERROR(LOOKUP(2,1/(Fact_Physical_Progress!$B$2:$B$35=Dim_WBS!$A$13)/(Fact_Physical_Progress!$A$2:$A$35<=B8),Fact_Physical_Progress!$C$2:$C$35),0)*Dim_WBS!$E$13)} -> 80101.328 | F8: =E8-C8 -> -6965.342 | G8: =E8-D8 -> -6408.112 | H8: =IFERROR(E8/C8,1) -> 0.9199999 | I8: =IFERROR(E8/D8,1) -> 0.92592586 | J8: =Setup!$B$11 -> 268650 | K8: =IF(I8>0,J8/I8,J8) -> 290142.02 | L8: =K8-D8 -> 203632.58 | M8: =J8-K8 -> -21492.019 | N8: =IF(OR(F8<0,G8<0,H8<Setup!$B$12,I8<Setup!$B$12),"Red",IF(OR(H8<Setup!$B$13,I8<Setup!$B$13),"Amber","Green")) -> Red
A9: 5 | B9: =MIN(Fact_Baseline_PV!$A:$A)+4+(4*7) -> 46178 | C9: =SUMIFS(Fact_Baseline_PV!$C:$C,Fact_Baseline_PV!$A:$A,"<="&B9) -> 116733.34 | D9: =SUMIFS(Fact_Actual_Costs!$D:$D,Fact_Actual_Costs!$A:$A,"<="&B9) -> 115986.24 | E9: {=SUM(IFERROR(LOOKUP(2,1/(Fact_Physical_Progress!$B$2:$B$35=Dim_WBS!$A$2)/(Fact_Physical_Progress!$A$2:$A$35<=B9),Fact_Physical_Progress!$C$2:$C$35),0)*Dim_WBS!$E$2,IFERROR(LOOKUP(2,1/(Fact_Physical_Progress!$B$2:$B$35=Dim_WBS!$A$3)/(Fact_Physical_Progress!$A$2:$A$35<=B9),Fact_Physical_Progress!$C$2:$C$35),0)*Dim_WBS!$E$3,IFERROR(LOOKUP(2,1/(Fact_Physical_Progress!$B$2:$B$35=Dim_WBS!$A$4)/(Fact_Physical_Progress!$A$2:$A$35<=B9),Fact_Physical_Progress!$C$2:$C$35),0)*Dim_WBS!$E$4,IFERROR(LOOKUP(2,1/(Fact_Physical_Progress!$B$2:$B$35=Dim_WBS!$A$5)/(Fact_Physical_Progress!$A$2:$A$35<=B9),Fact_Physical_Progress!$C$2:$C$35),0)*Dim_WBS!$E$5,IFERROR(LOOKUP(2,1/(Fact_Physical_Progress!$B$2:$B$35=Dim_WBS!$A$6)/(Fact_Physical_Progress!$A$2:$A$35<=B9),Fact_Physical_Progress!$C$2:$C$35),0)*Dim_WBS!$E$6,IFERROR(LOOKUP(2,1/(Fact_Physical_Progress!$B$2:$B$35=Dim_WBS!$A$7)/(Fact_Physical_Progress!$A$2:$A$35<=B9),Fact_Physical_Progress!$C$2:$C$35),0)*Dim_WBS!$E$7,IFERROR(LOOKUP(2,1/(Fact_Physical_Progress!$B$2:$B$35=Dim_WBS!$A$8)/(Fact_Physical_Progress!$A$2:$A$35<=B9),Fact_Physical_Progress!$C$2:$C$35),0)*Dim_WBS!$E$8,IFERROR(LOOKUP(2,1/(Fact_Physical_Progress!$B$2:$B$35=Dim_WBS!$A$9)/(Fact_Physical_Progress!$A$2:$A$35<=B9),Fact_Physical_Progress!$C$2:$C$35),0)*Dim_WBS!$E$9,IFERROR(LOOKUP(2,1/(Fact_Physical_Progress!$B$2:$B$35=Dim_WBS!$A$10)/(Fact_Physical_Progress!$A$2:$A$35<=B9),Fact_Physical_Progress!$C$2:$C$35),0)*Dim_WBS!$E$10,IFERROR(LOOKUP(2,1/(Fact_Physical_Progress!$B$2:$B$35=Dim_WBS!$A$11)/(Fact_Physical_Progress!$A$2:$A$35<=B9),Fact_Physical_Progress!$C$2:$C$35),0)*Dim_WBS!$E$11,IFERROR(LOOKUP(2,1/(Fact_Physical_Progress!$B$2:$B$35=Dim_WBS!$A$12)/(Fact_Physical_Progress!$A$2:$A$35<=B9),Fact_Physical_Progress!$C$2:$C$35),0)*Dim_WBS!$E$12,IFERROR(LOOKUP(2,1/(Fact_Physical_Progress!$B$2:$B$35=Dim_WBS!$A$13)/(Fact_Physical_Progress!$A$2:$A$35<=B9),Fact_Physical_Progress!$C$2:$C$35),0)*Dim_WBS!$E$13)} -> 107394.67 | F9: =E9-C9 -> -9338.666 | G9: =E9-D9 -> -8591.566 | H9: =IFERROR(E9/C9,1) -> 0.92000001 | I9: =IFERROR(E9/D9,1) -> 0.92592599 | J9: =Setup!$B$11 -> 268650 | K9: =IF(I9>0,J9/I9,J9) -> 290141.98 | L9: =K9-D9 -> 174155.74 | M9: =J9-K9 -> -21491.98 | N9: =IF(OR(F9<0,G9<0,H9<Setup!$B$12,I9<Setup!$B$12),"Red",IF(OR(H9<Setup!$B$13,I9<Setup!$B$13),"Amber","Green")) -> Red
A10: 6 | B10: =MIN(Fact_Baseline_PV!$A:$A)+4+(5*7) -> 46185 | C10: =SUMIFS(Fact_Baseline_PV!$C:$C,Fact_Baseline_PV!$A:$A,"<="&B10) -> 142900 | D10: =SUMIFS(Fact_Actual_Costs!$D:$D,Fact_Actual_Costs!$A:$A,"<="&B10) -> 141985.44 | E10: {=SUM(IFERROR(LOOKUP(2,1/(Fact_Physical_Progress!$B$2:$B$35=Dim_WBS!$A$2)/(Fact_Physical_Progress!$A$2:$A$35<=B10),Fact_Physical_Progress!$C$2:$C$35),0)*Dim_WBS!$E$2,IFERROR(LOOKUP(2,1/(Fact_Physical_Progress!$B$2:$B$35=Dim_WBS!$A$3)/(Fact_Physical_Progress!$A$2:$A$35<=B10),Fact_Physical_Progress!$C$2:$C$35),0)*Dim_WBS!$E$3,IFERROR(LOOKUP(2,1/(Fact_Physical_Progress!$B$2:$B$35=Dim_WBS!$A$4)/(Fact_Physical_Progress!$A$2:$A$35<=B10),Fact_Physical_Progress!$C$2:$C$35),0)*Dim_WBS!$E$4,IFERROR(LOOKUP(2,1/(Fact_Physical_Progress!$B$2:$B$35=Dim_WBS!$A$5)/(Fact_Physical_Progress!$A$2:$A$35<=B10),Fact_Physical_Progress!$C$2:$C$35),0)*Dim_WBS!$E$5,IFERROR(LOOKUP(2,1/(Fact_Physical_Progress!$B$2:$B$35=Dim_WBS!$A$6)/(Fact_Physical_Progress!$A$2:$A$35<=B10),Fact_Physical_Progress!$C$2:$C$35),0)*Dim_WBS!$E$6,IFERROR(LOOKUP(2,1/(Fact_Physical_Progress!$B$2:$B$35=Dim_WBS!$A$7)/(Fact_Physical_Progress!$A$2:$A$35<=B10),Fact_Physical_Progress!$C$2:$C$35),0)*Dim_WBS!$E$7,IFERROR(LOOKUP(2,1/(Fact_Physical_Progress!$B$2:$B$35=Dim_WBS!$A$8)/(Fact_Physical_Progress!$A$2:$A$35<=B10),Fact_Physical_Progress!$C$2:$C$35),0)*Dim_WBS!$E$8,IFERROR(LOOKUP(2,1/(Fact_Physical_Progress!$B$2:$B$35=Dim_WBS!$A$9)/(Fact_Physical_Progress!$A$2:$A$35<=B10),Fact_Physical_Progress!$C$2:$C$35),0)*Dim_WBS!$E$9,IFERROR(LOOKUP(2,1/(Fact_Physical_Progress!$B$2:$B$35=Dim_WBS!$A$10)/(Fact_Physical_Progress!$A$2:$A$35<=B10),Fact_Physical_Progress!$C$2:$C$35),0)*Dim_WBS!$E$10,IFERROR(LOOKUP(2,1/(Fact_Physical_Progress!$B$2:$B$35=Dim_WBS!$A$11)/(Fact_Physical_Progress!$A$2:$A$35<=B10),Fact_Physical_Progress!$C$2:$C$35),0)*Dim_WBS!$E$11,IFERROR(LOOKUP(2,1/(Fact_Physical_Progress!$B$2:$B$35=Dim_WBS!$A$12)/(Fact_Physical_Progress!$A$2:$A$35<=B10),Fact_Physical_Progress!$C$2:$C$35),0)*Dim_WBS!$E$12,IFERROR(LOOKUP(2,1/(Fact_Physical_Progress!$B$2:$B$35=Dim_WBS!$A$13)/(Fact_Physical_Progress!$A$2:$A$35<=B10),Fact_Physical_Progress!$C$2:$C$35),0)*Dim_WBS!$E$13)} -> 131468 | F10: =E10-C10 -> -11432.004 | G10: =E10-D10 -> -10517.444 | H10: =IFERROR(E10/C10,1) -> 0.91999997 | I10: =IFERROR(E10/D10,1) -> 0.9259259 | J10: =Setup!$B$11 -> 268650 | K10: =IF(I10>0,J10/I10,J10) -> 290142.01 | L10: =K10-D10 -> 148156.57 | M10: =J10-K10 -> -21492.009 | N10: =IF(OR(F10<0,G10<0,H10<Setup!$B$12,I10<Setup!$B$12),"Red",IF(OR(H10<Setup!$B$13,I10<Setup!$B$13),"Amber","Green")) -> Red
A11: 7 | B11: =MIN(Fact_Baseline_PV!$A:$A)+4+(6*7) -> 46192 | C11: =SUMIFS(Fact_Baseline_PV!$C:$C,Fact_Baseline_PV!$A:$A,"<="&B11) -> 160400 | D11: =SUMIFS(Fact_Actual_Costs!$D:$D,Fact_Actual_Costs!$A:$A,"<="&B11) -> 141985.44 | E11: {=SUM(IFERROR(LOOKUP(2,1/(Fact_Physical_Progress!$B$2:$B$35=Dim_WBS!$A$2)/(Fact_Physical_Progress!$A$2:$A$35<=B11),Fact_Physical_Progress!$C$2:$C$35),0)*Dim_WBS!$E$2,IFERROR(LOOKUP(2,1/(Fact_Physical_Progress!$B$2:$B$35=Dim_WBS!$A$3)/(Fact_Physical_Progress!$A$2:$A$35<=B11),Fact_Physical_Progress!$C$2:$C$35),0)*Dim_WBS!$E$3,IFERROR(LOOKUP(2,1/(Fact_Physical_Progress!$B$2:$B$35=Dim_WBS!$A$4)/(Fact_Physical_Progress!$A$2:$A$35<=B11),Fact_Physical_Progress!$C$2:$C$35),0)*Dim_WBS!$E$4,IFERROR(LOOKUP(2,1/(Fact_Physical_Progress!$B$2:$B$35=Dim_WBS!$A$5)/(Fact_Physical_Progress!$A$2:$A$35<=B11),Fact_Physical_Progress!$C$2:$C$35),0)*Dim_WBS!$E$5,IFERROR(LOOKUP(2,1/(Fact_Physical_Progress!$B$2:$B$35=Dim_WBS!$A$6)/(Fact_Physical_Progress!$A$2:$A$35<=B11),Fact_Physical_Progress!$C$2:$C$35),0)*Dim_WBS!$E$6,IFERROR(LOOKUP(2,1/(Fact_Physical_Progress!$B$2:$B$35=Dim_WBS!$A$7)/(Fact_Physical_Progress!$A$2:$A$35<=B11),Fact_Physical_Progress!$C$2:$C$35),0)*Dim_WBS!$E$7,IFERROR(LOOKUP(2,1/(Fact_Physical_Progress!$B$2:$B$35=Dim_WBS!$A$8)/(Fact_Physical_Progress!$A$2:$A$35<=B11),Fact_Physical_Progress!$C$2:$C$35),0)*Dim_WBS!$E$8,IFERROR(LOOKUP(2,1/(Fact_Physical_Progress!$B$2:$B$35=Dim_WBS!$A$9)/(Fact_Physical_Progress!$A$2:$A$35<=B11),Fact_Physical_Progress!$C$2:$C$35),0)*Dim_WBS!$E$9,IFERROR(LOOKUP(2,1/(Fact_Physical_Progress!$B$2:$B$35=Dim_WBS!$A$10)/(Fact_Physical_Progress!$A$2:$A$35<=B11),Fact_Physical_Progress!$C$2:$C$35),0)*Dim_WBS!$E$10,IFERROR(LOOKUP(2,1/(Fact_Physical_Progress!$B$2:$B$35=Dim_WBS!$A$11)/(Fact_Physical_Progress!$A$2:$A$35<=B11),Fact_Physical_Progress!$C$2:$C$35),0)*Dim_WBS!$E$11,IFERROR(LOOKUP(2,1/(Fact_Physical_Progress!$B$2:$B$35=Dim_WBS!$A$12)/(Fact_Physical_Progress!$A$2:$A$35<=B11),Fact_Physical_Progress!$C$2:$C$35),0)*Dim_WBS!$E$12,IFERROR(LOOKUP(2,1/(Fact_Physical_Progress!$B$2:$B$35=Dim_WBS!$A$13)/(Fact_Physical_Progress!$A$2:$A$35<=B11),Fact_Physical_Progress!$C$2:$C$35),0)*Dim_WBS!$E$13)} -> 131468 | F11: =E11-C11 -> -28932.004 | G11: =E11-D11 -> -10517.444 | H11: =IFERROR(E11/C11,1) -> 0.81962591 | I11: =IFERROR(E11/D11,1) -> 0.9259259 | J11: =Setup!$B$11 -> 268650 | K11: =IF(I11>0,J11/I11,J11) -> 290142.01 | L11: =K11-D11 -> 148156.57 | M11: =J11-K11 -> -21492.009 | N11: =IF(OR(F11<0,G11<0,H11<Setup!$B$12,I11<Setup!$B$12),"Red",IF(OR(H11<Setup!$B$13,I11<Setup!$B$13),"Amber","Green")) -> Red
A12: 8 | B12: =MIN(Fact_Baseline_PV!$A:$A)+4+(7*7) -> 46199 | C12: =SUMIFS(Fact_Baseline_PV!$C:$C,Fact_Baseline_PV!$A:$A,"<="&B12) -> 189816.67 | D12: =SUMIFS(Fact_Actual_Costs!$D:$D,Fact_Actual_Costs!$A:$A,"<="&B12) -> 141985.44 | E12: {=SUM(IFERROR(LOOKUP(2,1/(Fact_Physical_Progress!$B$2:$B$35=Dim_WBS!$A$2)/(Fact_Physical_Progress!$A$2:$A$35<=B12),Fact_Physical_Progress!$C$2:$C$35),0)*Dim_WBS!$E$2,IFERROR(LOOKUP(2,1/(Fact_Physical_Progress!$B$2:$B$35=Dim_WBS!$A$3)/(Fact_Physical_Progress!$A$2:$A$35<=B12),Fact_Physical_Progress!$C$2:$C$35),0)*Dim_WBS!$E$3,IFERROR(LOOKUP(2,1/(Fact_Physical_Progress!$B$2:$B$35=Dim_WBS!$A$4)/(Fact_Physical_Progress!$A$2:$A$35<=B12),Fact_Physical_Progress!$C$2:$C$35),0)*Dim_WBS!$E$4,IFERROR(LOOKUP(2,1/(Fact_Physical_Progress!$B$2:$B$35=Dim_WBS!$A$5)/(Fact_Physical_Progress!$A$2:$A$35<=B12),Fact_Physical_Progress!$C$2:$C$35),0)*Dim_WBS!$E$5,IFERROR(LOOKUP(2,1/(Fact_Physical_Progress!$B$2:$B$35=Dim_WBS!$A$6)/(Fact_Physical_Progress!$A$2:$A$35<=B12),Fact_Physical_Progress!$C$2:$C$35),0)*Dim_WBS!$E$6,IFERROR(LOOKUP(2,1/(Fact_Physical_Progress!$B$2:$B$35=Dim_WBS!$A$7)/(Fact_Physical_Progress!$A$2:$A$35<=B12),Fact_Physical_Progress!$C$2:$C$35),0)*Dim_WBS!$E$7,IFERROR(LOOKUP(2,1/(Fact_Physical_Progress!$B$2:$B$35=Dim_WBS!$A$8)/(Fact_Physical_Progress!$A$2:$A$35<=B12),Fact_Physical_Progress!$C$2:$C$35),0)*Dim_WBS!$E$8,IFERROR(LOOKUP(2,1/(Fact_Physical_Progress!$B$2:$B$35=Dim_WBS!$A$9)/(Fact_Physical_Progress!$A$2:$A$35<=B12),Fact_Physical_Progress!$C$2:$C$35),0)*Dim_WBS!$E$9,IFERROR(LOOKUP(2,1/(Fact_Physical_Progress!$B$2:$B$35=Dim_WBS!$A$10)/(Fact_Physical_Progress!$A$2:$A$35<=B12),Fact_Physical_Progress!$C$2:$C$35),0)*Dim_WBS!$E$10,IFERROR(LOOKUP(2,1/(Fact_Physical_Progress!$B$2:$B$35=Dim_WBS!$A$11)/(Fact_Physical_Progress!$A$2:$A$35<=B12),Fact_Physical_Progress!$C$2:$C$35),0)*Dim_WBS!$E$11,IFERROR(LOOKUP(2,1/(Fact_Physical_Progress!$B$2:$B$35=Dim_WBS!$A$12)/(Fact_Physical_Progress!$A$2:$A$35<=B12),Fact_Physical_Progress!$C$2:$C$35),0)*Dim_WBS!$E$12,IFERROR(LOOKUP(2,1/(Fact_Physical_Progress!$B$2:$B$35=Dim_WBS!$A$13)/(Fact_Physical_Progress!$A$2:$A$35<=B12),Fact_Physical_Progress!$C$2:$C$35),0)*Dim_WBS!$E$13)} -> 131468 | F12: =E12-C12 -> -58348.674 | G12: =E12-D12 -> -10517.444 | H12: =IFERROR(E12/C12,1) -> 0.69260511 | I12: =IFERROR(E12/D12,1) -> 0.9259259 | J12: =Setup!$B$11 -> 268650 | K12: =IF(I12>0,J12/I12,J12) -> 290142.01 | L12: =K12-D12 -> 148156.57 | M12: =J12-K12 -> -21492.009 | N12: =IF(OR(F12<0,G12<0,H12<Setup!$B$12,I12<Setup!$B$12),"Red",IF(OR(H12<Setup!$B$13,I12<Setup!$B$13),"Amber","Green")) -> Red
A13: 9 | B13: =MIN(Fact_Baseline_PV!$A:$A)+4+(8*7) -> 46206 | C13: =SUMIFS(Fact_Baseline_PV!$C:$C,Fact_Baseline_PV!$A:$A,"<="&B13) -> 220233.34 | D13: =SUMIFS(Fact_Actual_Costs!$D:$D,Fact_Actual_Costs!$A:$A,"<="&B13) -> 141985.44 | E13: {=SUM(IFERROR(LOOKUP(2,1/(Fact_Physical_Progress!$B$2:$B$35=Dim_WBS!$A$2)/(Fact_Physical_Progress!$A$2:$A$35<=B13),Fact_Physical_Progress!$C$2:$C$35),0)*Dim_WBS!$E$2,IFERROR(LOOKUP(2,1/(Fact_Physical_Progress!$B$2:$B$35=Dim_WBS!$A$3)/(Fact_Physical_Progress!$A$2:$A$35<=B13),Fact_Physical_Progress!$C$2:$C$35),0)*Dim_WBS!$E$3,IFERROR(LOOKUP(2,1/(Fact_Physical_Progress!$B$2:$B$35=Dim_WBS!$A$4)/(Fact_Physical_Progress!$A$2:$A$35<=B13),Fact_Physical_Progress!$C$2:$C$35),0)*Dim_WBS!$E$4,IFERROR(LOOKUP(2,1/(Fact_Physical_Progress!$B$2:$B$35=Dim_WBS!$A$5)/(Fact_Physical_Progress!$A$2:$A$35<=B13),Fact_Physical_Progress!$C$2:$C$35),0)*Dim_WBS!$E$5,IFERROR(LOOKUP(2,1/(Fact_Physical_Progress!$B$2:$B$35=Dim_WBS!$A$6)/(Fact_Physical_Progress!$A$2:$A$35<=B13),Fact_Physical_Progress!$C$2:$C$35),0)*Dim_WBS!$E$6,IFERROR(LOOKUP(2,1/(Fact_Physical_Progress!$B$2:$B$35=Dim_WBS!$A$7)/(Fact_Physical_Progress!$A$2:$A$35<=B13),Fact_Physical_Progress!$C$2:$C$35),0)*Dim_WBS!$E$7,IFERROR(LOOKUP(2,1/(Fact_Physical_Progress!$B$2:$B$35=Dim_WBS!$A$8)/(Fact_Physical_Progress!$A$2:$A$35<=B13),Fact_Physical_Progress!$C$2:$C$35),0)*Dim_WBS!$E$8,IFERROR(LOOKUP(2,1/(Fact_Physical_Progress!$B$2:$B$35=Dim_WBS!$A$9)/(Fact_Physical_Progress!$A$2:$A$35<=B13),Fact_Physical_Progress!$C$2:$C$35),0)*Dim_WBS!$E$9,IFERROR(LOOKUP(2,1/(Fact_Physical_Progress!$B$2:$B$35=Dim_WBS!$A$10)/(Fact_Physical_Progress!$A$2:$A$35<=B13),Fact_Physical_Progress!$C$2:$C$35),0)*Dim_WBS!$E$10,IFERROR(LOOKUP(2,1/(Fact_Physical_Progress!$B$2:$B$35=Dim_WBS!$A$11)/(Fact_Physical_Progress!$A$2:$A$35<=B13),Fact_Physical_Progress!$C$2:$C$35),0)*Dim_WBS!$E$11,IFERROR(LOOKUP(2,1/(Fact_Physical_Progress!$B$2:$B$35=Dim_WBS!$A$12)/(Fact_Physical_Progress!$A$2:$A$35<=B13),Fact_Physical_Progress!$C$2:$C$35),0)*Dim_WBS!$E$12,IFERROR(LOOKUP(2,1/(Fact_Physical_Progress!$B$2:$B$35=Dim_WBS!$A$13)/(Fact_Physical_Progress!$A$2:$A$35<=B13),Fact_Physical_Progress!$C$2:$C$35),0)*Dim_WBS!$E$13)} -> 131468 | F13: =E13-C13 -> -88765.344 | G13: =E13-D13 -> -10517.444 | H13: =IFERROR(E13/C13,1) -> 0.59694865 | I13: =IFERROR(E13/D13,1) -> 0.9259259 | J13: =Setup!$B$11 -> 268650 | K13: =IF(I13>0,J13/I13,J13) -> 290142.01 | L13: =K13-D13 -> 148156.57 | M13: =J13-K13 -> -21492.009 | N13: =IF(OR(F13<0,G13<0,H13<Setup!$B$12,I13<Setup!$B$12),"Red",IF(OR(H13<Setup!$B$13,I13<Setup!$B$13),"Amber","Green")) -> Red
A14: 10 | B14: =MIN(Fact_Baseline_PV!$A:$A)+4+(9*7) -> 46213 | C14: =SUMIFS(Fact_Baseline_PV!$C:$C,Fact_Baseline_PV!$A:$A,"<="&B14) -> 243650 | D14: =SUMIFS(Fact_Actual_Costs!$D:$D,Fact_Actual_Costs!$A:$A,"<="&B14) -> 141985.44 | E14: {=SUM(IFERROR(LOOKUP(2,1/(Fact_Physical_Progress!$B$2:$B$35=Dim_WBS!$A$2)/(Fact_Physical_Progress!$A$2:$A$35<=B14),Fact_Physical_Progress!$C$2:$C$35),0)*Dim_WBS!$E$2,IFERROR(LOOKUP(2,1/(Fact_Physical_Progress!$B$2:$B$35=Dim_WBS!$A$3)/(Fact_Physical_Progress!$A$2:$A$35<=B14),Fact_Physical_Progress!$C$2:$C$35),0)*Dim_WBS!$E$3,IFERROR(LOOKUP(2,1/(Fact_Physical_Progress!$B$2:$B$35=Dim_WBS!$A$4)/(Fact_Physical_Progress!$A$2:$A$35<=B14),Fact_Physical_Progress!$C$2:$C$35),0)*Dim_WBS!$E$4,IFERROR(LOOKUP(2,1/(Fact_Physical_Progress!$B$2:$B$35=Dim_WBS!$A$5)/(Fact_Physical_Progress!$A$2:$A$35<=B14),Fact_Physical_Progress!$C$2:$C$35),0)*Dim_WBS!$E$5,IFERROR(LOOKUP(2,1/(Fact_Physical_Progress!$B$2:$B$35=Dim_WBS!$A$6)/(Fact_Physical_Progress!$A$2:$A$35<=B14),Fact_Physical_Progress!$C$2:$C$35),0)*Dim_WBS!$E$6,IFERROR(LOOKUP(2,1/(Fact_Physical_Progress!$B$2:$B$35=Dim_WBS!$A$7)/(Fact_Physical_Progress!$A$2:$A$35<=B14),Fact_Physical_Progress!$C$2:$C$35),0)*Dim_WBS!$E$7,IFERROR(LOOKUP(2,1/(Fact_Physical_Progress!$B$2:$B$35=Dim_WBS!$A$8)/(Fact_Physical_Progress!$A$2:$A$35<=B14),Fact_Physical_Progress!$C$2:$C$35),0)*Dim_WBS!$E$8,IFERROR(LOOKUP(2,1/(Fact_Physical_Progress!$B$2:$B$35=Dim_WBS!$A$9)/(Fact_Physical_Progress!$A$2:$A$35<=B14),Fact_Physical_Progress!$C$2:$C$35),0)*Dim_WBS!$E$9,IFERROR(LOOKUP(2,1/(Fact_Physical_Progress!$B$2:$B$35=Dim_WBS!$A$10)/(Fact_Physical_Progress!$A$2:$A$35<=B14),Fact_Physical_Progress!$C$2:$C$35),0)*Dim_WBS!$E$10,IFERROR(LOOKUP(2,1/(Fact_Physical_Progress!$B$2:$B$35=Dim_WBS!$A$11)/(Fact_Physical_Progress!$A$2:$A$35<=B14),Fact_Physical_Progress!$C$2:$C$35),0)*Dim_WBS!$E$11,IFERROR(LOOKUP(2,1/(Fact_Physical_Progress!$B$2:$B$35=Dim_WBS!$A$12)/(Fact_Physical_Progress!$A$2:$A$35<=B14),Fact_Physical_Progress!$C$2:$C$35),0)*Dim_WBS!$E$12,IFERROR(LOOKUP(2,1/(Fact_Physical_Progress!$B$2:$B$35=Dim_WBS!$A$13)/(Fact_Physical_Progress!$A$2:$A$35<=B14),Fact_Physical_Progress!$C$2:$C$35),0)*Dim_WBS!$E$13)} -> 131468 | F14: =E14-C14 -> -112182 | G14: =E14-D14 -> -10517.444 | H14: =IFERROR(E14/C14,1) -> 0.53957725 | I14: =IFERROR(E14/D14,1) -> 0.9259259 | J14: =Setup!$B$11 -> 268650 | K14: =IF(I14>0,J14/I14,J14) -> 290142.01 | L14: =K14-D14 -> 148156.57 | M14: =J14-K14 -> -21492.009 | N14: =IF(OR(F14<0,G14<0,H14<Setup!$B$12,I14<Setup!$B$12),"Red",IF(OR(H14<Setup!$B$13,I14<Setup!$B$13),"Amber","Green")) -> Red
A15: 11 | B15: =MIN(Fact_Baseline_PV!$A:$A)+4+(10*7) -> 46220 | C15: =SUMIFS(Fact_Baseline_PV!$C:$C,Fact_Baseline_PV!$A:$A,"<="&B15) -> 259350 | D15: =SUMIFS(Fact_Actual_Costs!$D:$D,Fact_Actual_Costs!$A:$A,"<="&B15) -> 141985.44 | E15: {=SUM(IFERROR(LOOKUP(2,1/(Fact_Physical_Progress!$B$2:$B$35=Dim_WBS!$A$2)/(Fact_Physical_Progress!$A$2:$A$35<=B15),Fact_Physical_Progress!$C$2:$C$35),0)*Dim_WBS!$E$2,IFERROR(LOOKUP(2,1/(Fact_Physical_Progress!$B$2:$B$35=Dim_WBS!$A$3)/(Fact_Physical_Progress!$A$2:$A$35<=B15),Fact_Physical_Progress!$C$2:$C$35),0)*Dim_WBS!$E$3,IFERROR(LOOKUP(2,1/(Fact_Physical_Progress!$B$2:$B$35=Dim_WBS!$A$4)/(Fact_Physical_Progress!$A$2:$A$35<=B15),Fact_Physical_Progress!$C$2:$C$35),0)*Dim_WBS!$E$4,IFERROR(LOOKUP(2,1/(Fact_Physical_Progress!$B$2:$B$35=Dim_WBS!$A$5)/(Fact_Physical_Progress!$A$2:$A$35<=B15),Fact_Physical_Progress!$C$2:$C$35),0)*Dim_WBS!$E$5,IFERROR(LOOKUP(2,1/(Fact_Physical_Progress!$B$2:$B$35=Dim_WBS!$A$6)/(Fact_Physical_Progress!$A$2:$A$35<=B15),Fact_Physical_Progress!$C$2:$C$35),0)*Dim_WBS!$E$6,IFERROR(LOOKUP(2,1/(Fact_Physical_Progress!$B$2:$B$35=Dim_WBS!$A$7)/(Fact_Physical_Progress!$A$2:$A$35<=B15),Fact_Physical_Progress!$C$2:$C$35),0)*Dim_WBS!$E$7,IFERROR(LOOKUP(2,1/(Fact_Physical_Progress!$B$2:$B$35=Dim_WBS!$A$8)/(Fact_Physical_Progress!$A$2:$A$35<=B15),Fact_Physical_Progress!$C$2:$C$35),0)*Dim_WBS!$E$8,IFERROR(LOOKUP(2,1/(Fact_Physical_Progress!$B$2:$B$35=Dim_WBS!$A$9)/(Fact_Physical_Progress!$A$2:$A$35<=B15),Fact_Physical_Progress!$C$2:$C$35),0)*Dim_WBS!$E$9,IFERROR(LOOKUP(2,1/(Fact_Physical_Progress!$B$2:$B$35=Dim_WBS!$A$10)/(Fact_Physical_Progress!$A$2:$A$35<=B15),Fact_Physical_Progress!$C$2:$C$35),0)*Dim_WBS!$E$10,IFERROR(LOOKUP(2,1/(Fact_Physical_Progress!$B$2:$B$35=Dim_WBS!$A$11)/(Fact_Physical_Progress!$A$2:$A$35<=B15),Fact_Physical_Progress!$C$2:$C$35),0)*Dim_WBS!$E$11,IFERROR(LOOKUP(2,1/(Fact_Physical_Progress!$B$2:$B$35=Dim_WBS!$A$12)/(Fact_Physical_Progress!$A$2:$A$35<=B15),Fact_Physical_Progress!$C$2:$C$35),0)*Dim_WBS!$E$12,IFERROR(LOOKUP(2,1/(Fact_Physical_Progress!$B$2:$B$35=Dim_WBS!$A$13)/(Fact_Physical_Progress!$A$2:$A$35<=B15),Fact_Physical_Progress!$C$2:$C$35),0)*Dim_WBS!$E$13)} -> 131468 | F15: =E15-C15 -> -127882 | G15: =E15-D15 -> -10517.444 | H15: =IFERROR(E15/C15,1) -> 0.50691342 | I15: =IFERROR(E15/D15,1) -> 0.9259259 | J15: =Setup!$B$11 -> 268650 | K15: =IF(I15>0,J15/I15,J15) -> 290142.01 | L15: =K15-D15 -> 148156.57 | M15: =J15-K15 -> -21492.009 | N15: =IF(OR(F15<0,G15<0,H15<Setup!$B$12,I15<Setup!$B$12),"Red",IF(OR(H15<Setup!$B$13,I15<Setup!$B$13),"Amber","Green")) -> Red
A16: 12 | B16: =MIN(Fact_Baseline_PV!$A:$A)+4+(11*7) -> 46227 | C16: =SUMIFS(Fact_Baseline_PV!$C:$C,Fact_Baseline_PV!$A:$A,"<="&B16) -> 268650 | D16: =SUMIFS(Fact_Actual_Costs!$D:$D,Fact_Actual_Costs!$A:$A,"<="&B16) -> 141985.44 | E16: {=SUM(IFERROR(LOOKUP(2,1/(Fact_Physical_Progress!$B$2:$B$35=Dim_WBS!$A$2)/(Fact_Physical_Progress!$A$2:$A$35<=B16),Fact_Physical_Progress!$C$2:$C$35),0)*Dim_WBS!$E$2,IFERROR(LOOKUP(2,1/(Fact_Physical_Progress!$B$2:$B$35=Dim_WBS!$A$3)/(Fact_Physical_Progress!$A$2:$A$35<=B16),Fact_Physical_Progress!$C$2:$C$35),0)*Dim_WBS!$E$3,IFERROR(LOOKUP(2,1/(Fact_Physical_Progress!$B$2:$B$35=Dim_WBS!$A$4)/(Fact_Physical_Progress!$A$2:$A$35<=B16),Fact_Physical_Progress!$C$2:$C$35),0)*Dim_WBS!$E$4,IFERROR(LOOKUP(2,1/(Fact_Physical_Progress!$B$2:$B$35=Dim_WBS!$A$5)/(Fact_Physical_Progress!$A$2:$A$35<=B16),Fact_Physical_Progress!$C$2:$C$35),0)*Dim_WBS!$E$5,IFERROR(LOOKUP(2,1/(Fact_Physical_Progress!$B$2:$B$35=Dim_WBS!$A$6)/(Fact_Physical_Progress!$A$2:$A$35<=B16),Fact_Physical_Progress!$C$2:$C$35),0)*Dim_WBS!$E$6,IFERROR(LOOKUP(2,1/(Fact_Physical_Progress!$B$2:$B$35=Dim_WBS!$A$7)/(Fact_Physical_Progress!$A$2:$A$35<=B16),Fact_Physical_Progress!$C$2:$C$35),0)*Dim_WBS!$E$7,IFERROR(LOOKUP(2,1/(Fact_Physical_Progress!$B$2:$B$35=Dim_WBS!$A$8)/(Fact_Physical_Progress!$A$2:$A$35<=B16),Fact_Physical_Progress!$C$2:$C$35),0)*Dim_WBS!$E$8,IFERROR(LOOKUP(2,1/(Fact_Physical_Progress!$B$2:$B$35=Dim_WBS!$A$9)/(Fact_Physical_Progress!$A$2:$A$35<=B16),Fact_Physical_Progress!$C$2:$C$35),0)*Dim_WBS!$E$9,IFERROR(LOOKUP(2,1/(Fact_Physical_Progress!$B$2:$B$35=Dim_WBS!$A$10)/(Fact_Physical_Progress!$A$2:$A$35<=B16),Fact_Physical_Progress!$C$2:$C$35),0)*Dim_WBS!$E$10,IFERROR(LOOKUP(2,1/(Fact_Physical_Progress!$B$2:$B$35=Dim_WBS!$A$11)/(Fact_Physical_Progress!$A$2:$A$35<=B16),Fact_Physical_Progress!$C$2:$C$35),0)*Dim_WBS!$E$11,IFERROR(LOOKUP(2,1/(Fact_Physical_Progress!$B$2:$B$35=Dim_WBS!$A$12)/(Fact_Physical_Progress!$A$2:$A$35<=B16),Fact_Physical_Progress!$C$2:$C$35),0)*Dim_WBS!$E$12,IFERROR(LOOKUP(2,1/(Fact_Physical_Progress!$B$2:$B$35=Dim_WBS!$A$13)/(Fact_Physical_Progress!$A$2:$A$35<=B16),Fact_Physical_Progress!$C$2:$C$35),0)*Dim_WBS!$E$13)} -> 131468 | F16: =E16-C16 -> -137182 | G16: =E16-D16 -> -10517.444 | H16: =IFERROR(E16/C16,1) -> 0.48936533 | I16: =IFERROR(E16/D16,1) -> 0.9259259 | J16: =Setup!$B$11 -> 268650 | K16: =IF(I16>0,J16/I16,J16) -> 290142.01 | L16: =K16-D16 -> 148156.57 | M16: =J16-K16 -> -21492.009 | N16: =IF(OR(F16<0,G16<0,H16<Setup!$B$12,I16<Setup!$B$12),"Red",IF(OR(H16<Setup!$B$13,I16<Setup!$B$13),"Amber","Green")) -> Red
A19: Formula | B19: Workbook implementation | C19: Guideline meaning | D19: Current status-date value | E19: Check | F19: Source | H19: Status tie-out | I19: Dashboard value | J19: Task Plan value | K19: Variance | L19: Check | M19: Source
A20: SV = EV - PV | B20: =INDEX(E5:E16,MATCH(Setup!$B$9,B5:B16,0))-INDEX(C5:C16,MATCH(Setup!$B$9,B5:B16,0)) -> #N/A | C20: Schedule variance at status date | D20: =B20 -> #N/A | E20: Live | F20: PM-EVM.md lines 145-150 | H20: PV | I20: ='EVM Dashboard'!D7 -> 220233.34 | J20: ='Task Plan'!I17 -> 220233.34 | K20: =J20-I20 -> 0 | L20: =IF(ABS(K20)<0.01,"OK","Review") -> OK | M20: Task Plan!I17
A21: CV = EV - AC | B21: =INDEX(E5:E16,MATCH(Setup!$B$9,B5:B16,0))-INDEX(D5:D16,MATCH(Setup!$B$9,B5:B16,0)) -> #N/A | C21: Cost variance at status date | D21: =B21 -> #N/A | E21: Live | F21: PM-EVM.md lines 145-150 | H21: AC | I21: ='EVM Dashboard'!G7 -> 141985.44 | J21: ='Task Plan'!J17 -> 141985.44 | K21: =J21-I21 -> 0 | L21: =IF(ABS(K21)<0.01,"OK","Review") -> OK | M21: Task Plan!J17
A22: SPI = EV / PV | B22: =INDEX(E5:E16,MATCH(Setup!$B$9,B5:B16,0))/INDEX(C5:C16,MATCH(Setup!$B$9,B5:B16,0)) -> #N/A | C22: Schedule efficiency | D22: =B22 -> #N/A | E22: Live | F22: PM-EVM.md lines 145-150 | H22: EV | I22: ='EVM Dashboard'!J7 -> 131468 | J22: ='Task Plan'!L17 -> 131468 | K22: =J22-I22 -> 0 | L22: =IF(ABS(K22)<0.01,"OK","Review") -> OK | M22: Task Plan!L17
A23: CPI = EV / AC | B23: =INDEX(E5:E16,MATCH(Setup!$B$9,B5:B16,0))/INDEX(D5:D16,MATCH(Setup!$B$9,B5:B16,0)) -> #N/A | C23: Cost efficiency | D23: =B23 -> #N/A | E23: Live | F23: PM-EVM.md lines 145-150 | H23: SPI | I23: ='EVM Dashboard'!J10 -> 0.59694865 | J23: ='Task Plan'!O17 -> 0.59694865 | K23: =J23-I23 -> 0 | L23: =IF(ABS(K23)<0.01,"OK","Review") -> OK | M23: Task Plan!O17
A24: EAC = BAC / CPI | B24: =Setup!$B$11/B23 -> #N/A | C24: Forecast final cost | D24: =B24 -> #N/A | E24: Live | F24: PM-EVM.md lines 203-214 | H24: CPI | I24: ='EVM Dashboard'!G10 -> 0.9259259 | J24: ='Task Plan'!P17 -> 0.9259259 | K24: =J24-I24 -> 0 | L24: =IF(ABS(K24)<0.01,"OK","Review") -> OK | M24: Task Plan!P17
A25: VAC = BAC - EAC | B25: =Setup!$B$11/B23*-1+Setup!$B$11 -> #N/A | C25: Expected budget variance at completion | D25: =B25 -> #N/A | E25: Live | F25: PM-EVM.md lines 203-214 | H25: VAC | I25: ='EVM Dashboard'!G13 -> -21492.009 | J25: ='Task Plan'!S17 -> -21492.009 | K25: =J25-I25 -> 0 | L25: =IF(ABS(K25)<0.01,"OK","Review") -> OK | M25: Task Plan!S17

Sheet EVM Charts
A1: Project Schedule & EVM Curves | N1: Project Start | O1: =MIN(Fact_Baseline_PV!A:A) -> 46146
A2: Gantt schedule is derived from baseline PV dates by WBS; the S-curve uses cumulative PV, actual cost, and earned value as of each weekly status date. | N2: Project Finish | O2: =MAX(Fact_Baseline_PV!A:A)+6 -> 46229
N3: Status Date | O3: ='EVM Dashboard'!B4 -> 46203
A4: WBS ID | B4: Activity | C4: Start | D4: Finish | E4: Start Offset | F4: Duration Days | G4: Progress % | H4: RAG
A5: =Dim_WBS!A2 -> WBS-01 | B5: =Dim_WBS!C2 -> Project Management | C5: =_xlfn.MINIFS(Fact_Baseline_PV!$A:$A,Fact_Baseline_PV!$B:$B,A5) -> 46146 | D5: =_xlfn.MAXIFS(Fact_Baseline_PV!$A:$A,Fact_Baseline_PV!$B:$B,A5)+6 -> 46229 | E5: =C5-$O$1 -> 0 | F5: =D5-C5+1 -> 84 | G5: {=IFERROR(LOOKUP(2,1/(Fact_Physical_Progress!$B$2:$B$35=A5)/(Fact_Physical_Progress!$A$2:$A$35<=$O$3),Fact_Physical_Progress!$C$2:$C$35),0)} -> 0.5 | H5: =IF(G5<0.5,"Red",IF(G5<0.8,"Amber","Green")) -> Amber | N5: RAG Legend | O5: Rule | P5: Used in charts
A6: =Dim_WBS!A3 -> WBS-02 | B6: =Dim_WBS!C3 -> Site Survey & Mobilization | C6: =_xlfn.MINIFS(Fact_Baseline_PV!$A:$A,Fact_Baseline_PV!$B:$B,A6) -> 46146 | D6: =_xlfn.MAXIFS(Fact_Baseline_PV!$A:$A,Fact_Baseline_PV!$B:$B,A6)+6 -> 46152 | E6: =C6-$O$1 -> 0 | F6: =D6-C6+1 -> 7 | G6: {=IFERROR(LOOKUP(2,1/(Fact_Physical_Progress!$B$2:$B$35=A6)/(Fact_Physical_Progress!$A$2:$A$35<=$O$3),Fact_Physical_Progress!$C$2:$C$35),0)} -> 1 | H6: =IF(G6<0.5,"Red",IF(G6<0.8,"Amber","Green")) -> Green | N6: Green | O6: Good / baseline target | P6: Gantt good bars; PV line
A7: =Dim_WBS!A4 -> WBS-03 | B7: =Dim_WBS!C4 -> Design & Engineering | C7: =_xlfn.MINIFS(Fact_Baseline_PV!$A:$A,Fact_Baseline_PV!$B:$B,A7) -> 46146 | D7: =_xlfn.MAXIFS(Fact_Baseline_PV!$A:$A,Fact_Baseline_PV!$B:$B,A7)+6 -> 46166 | E7: =C7-$O$1 -> 0 | F7: =D7-C7+1 -> 21 | G7: {=IFERROR(LOOKUP(2,1/(Fact_Physical_Progress!$B$2:$B$35=A7)/(Fact_Physical_Progress!$A$2:$A$35<=$O$3),Fact_Physical_Progress!$C$2:$C$35),0)} -> 1 | H7: =IF(G7<0.5,"Red",IF(G7<0.8,"Amber","Green")) -> Green | N7: Amber | O7: Watch / earned progress | P7: Gantt watch bars; EV line
A8: =Dim_WBS!A5 -> WBS-04 | B8: =Dim_WBS!C5 -> Procurement - Materials | C8: =_xlfn.MINIFS(Fact_Baseline_PV!$A:$A,Fact_Baseline_PV!$B:$B,A8) -> 46153 | D8: =_xlfn.MAXIFS(Fact_Baseline_PV!$A:$A,Fact_Baseline_PV!$B:$B,A8)+6 -> 46180 | E8: =C8-$O$1 -> 7 | F8: =D8-C8+1 -> 28 | G8: {=IFERROR(LOOKUP(2,1/(Fact_Physical_Progress!$B$2:$B$35=A8)/(Fact_Physical_Progress!$A$2:$A$35<=$O$3),Fact_Physical_Progress!$C$2:$C$35),0)} -> 1 | H8: =IF(G8<0.5,"Red",IF(G8<0.8,"Amber","Green")) -> Green | N8: Red | O8: Action / cost exposure | P8: Gantt action bars; AC line
A9: =Dim_WBS!A6 -> WBS-05 | B9: =Dim_WBS!C6 -> Demolition & Prep | C9: =_xlfn.MINIFS(Fact_Baseline_PV!$A:$A,Fact_Baseline_PV!$B:$B,A9) -> 46153 | D9: =_xlfn.MAXIFS(Fact_Baseline_PV!$A:$A,Fact_Baseline_PV!$B:$B,A9)+6 -> 46173 | E9: =C9-$O$1 -> 7 | F9: =D9-C9+1 -> 21 | G9: {=IFERROR(LOOKUP(2,1/(Fact_Physical_Progress!$B$2:$B$35=A9)/(Fact_Physical_Progress!$A$2:$A$35<=$O$3),Fact_Physical_Progress!$C$2:$C$35),0)} -> 1 | H9: =IF(G9<0.5,"Red",IF(G9<0.8,"Amber","Green")) -> Green | N9: White | O9: Hidden helper | P9: Gantt start-offset series
A10: =Dim_WBS!A7 -> WBS-06 | B10: =Dim_WBS!C7 -> Electrical Rough-In | C10: =_xlfn.MINIFS(Fact_Baseline_PV!$A:$A,Fact_Baseline_PV!$B:$B,A10) -> 46167 | D10: =_xlfn.MAXIFS(Fact_Baseline_PV!$A:$A,Fact_Baseline_PV!$B:$B,A10)+6 -> 46187 | E10: =C10-$O$1 -> 21 | F10: =D10-C10+1 -> 21 | G10: {=IFERROR(LOOKUP(2,1/(Fact_Physical_Progress!$B$2:$B$35=A10)/(Fact_Physical_Progress!$A$2:$A$35<=$O$3),Fact_Physical_Progress!$C$2:$C$35),0)} -> 0.7 | H10: =IF(G10<0.5,"Red",IF(G10<0.8,"Amber","Green")) -> Amber | N10: Red dotted | O10: Status date | P10: Vertical marker at 2026-06-30
A11: =Dim_WBS!A8 -> WBS-07 | B11: =Dim_WBS!C8 -> HVAC Installation | C11: =_xlfn.MINIFS(Fact_Baseline_PV!$A:$A,Fact_Baseline_PV!$B:$B,A11) -> 46174 | D11: =_xlfn.MAXIFS(Fact_Baseline_PV!$A:$A,Fact_Baseline_PV!$B:$B,A11)+6 -> 46201 | E11: =C11-$O$1 -> 28 | F11: =D11-C11+1 -> 28 | G11: {=IFERROR(LOOKUP(2,1/(Fact_Physical_Progress!$B$2:$B$35=A11)/(Fact_Physical_Progress!$A$2:$A$35<=$O$3),Fact_Physical_Progress!$C$2:$C$35),0)} -> 0.4 | H11: =IF(G11<0.5,"Red",IF(G11<0.8,"Amber","Green")) -> Red
A12: =Dim_WBS!A9 -> WBS-08 | B12: =Dim_WBS!C9 -> Partitions & Drywall | C12: =_xlfn.MINIFS(Fact_Baseline_PV!$A:$A,Fact_Baseline_PV!$B:$B,A12) -> 46181 | D12: =_xlfn.MAXIFS(Fact_Baseline_PV!$A:$A,Fact_Baseline_PV!$B:$B,A12)+6 -> 46208 | E12: =C12-$O$1 -> 35 | F12: =D12-C12+1 -> 28 | G12: {=IFERROR(LOOKUP(2,1/(Fact_Physical_Progress!$B$2:$B$35=A12)/(Fact_Physical_Progress!$A$2:$A$35<=$O$3),Fact_Physical_Progress!$C$2:$C$35),0)} -> 0.248857 | H12: =IF(G12<0.5,"Red",IF(G12<0.8,"Amber","Green")) -> Red
A13: =Dim_WBS!A10 -> WBS-09 | B13: =Dim_WBS!C10 -> Flooring | C13: =_xlfn.MINIFS(Fact_Baseline_PV!$A:$A,Fact_Baseline_PV!$B:$B,A13) -> 46195 | D13: =_xlfn.MAXIFS(Fact_Baseline_PV!$A:$A,Fact_Baseline_PV!$B:$B,A13)+6 -> 46215 | E13: =C13-$O$1 -> 49 | F13: =D13-C13+1 -> 21 | G13: {=IFERROR(LOOKUP(2,1/(Fact_Physical_Progress!$B$2:$B$35=A13)/(Fact_Physical_Progress!$A$2:$A$35<=$O$3),Fact_Physical_Progress!$C$2:$C$35),0)} -> 0 | H13: =IF(G13<0.5,"Red",IF(G13<0.8,"Amber","Green")) -> Red
A14: =Dim_WBS!A11 -> WBS-10 | B14: =Dim_WBS!C11 -> Fixtures & Furniture | C14: =_xlfn.MINIFS(Fact_Baseline_PV!$A:$A,Fact_Baseline_PV!$B:$B,A14) -> 46202 | D14: =_xlfn.MAXIFS(Fact_Baseline_PV!$A:$A,Fact_Baseline_PV!$B:$B,A14)+6 -> 46222 | E14: =C14-$O$1 -> 56 | F14: =D14-C14+1 -> 21 | G14: {=IFERROR(LOOKUP(2,1/(Fact_Physical_Progress!$B$2:$B$35=A14)/(Fact_Physical_Progress!$A$2:$A$35<=$O$3),Fact_Physical_Progress!$C$2:$C$35),0)} -> 0 | H14: =IF(G14<0.5,"Red",IF(G14<0.8,"Amber","Green")) -> Red
A15: =Dim_WBS!A12 -> WBS-11 | B15: =Dim_WBS!C12 -> Testing / Commissioning | C15: =_xlfn.MINIFS(Fact_Baseline_PV!$A:$A,Fact_Baseline_PV!$B:$B,A15) -> 46216 | D15: =_xlfn.MAXIFS(Fact_Baseline_PV!$A:$A,Fact_Baseline_PV!$B:$B,A15)+6 -> 46229 | E15: =C15-$O$1 -> 70 | F15: =D15-C15+1 -> 14 | G15: {=IFERROR(LOOKUP(2,1/(Fact_Physical_Progress!$B$2:$B$35=A15)/(Fact_Physical_Progress!$A$2:$A$35<=$O$3),Fact_Physical_Progress!$C$2:$C$35),0)} -> 0 | H15: =IF(G15<0.5,"Red",IF(G15<0.8,"Amber","Green")) -> Red
A16: =Dim_WBS!A13 -> WBS-12 | B16: =Dim_WBS!C13 -> Handover & Closeout | C16: =_xlfn.MINIFS(Fact_Baseline_PV!$A:$A,Fact_Baseline_PV!$B:$B,A16) -> 46223 | D16: =_xlfn.MAXIFS(Fact_Baseline_PV!$A:$A,Fact_Baseline_PV!$B:$B,A16)+6 -> 46229 | E16: =C16-$O$1 -> 77 | F16: =D16-C16+1 -> 7 | G16: {=IFERROR(LOOKUP(2,1/(Fact_Physical_Progress!$B$2:$B$35=A16)/(Fact_Physical_Progress!$A$2:$A$35<=$O$3),Fact_Physical_Progress!$C$2:$C$35),0)} -> 0 | H16: =IF(G16<0.5,"Red",IF(G16<0.8,"Amber","Green")) -> Red
A23: Week | B23: Week Date | C23: Cum PV | D23: Cum AC | E23: Cum EV | F23: CPI | G23: SPI
A24: 1 | B24: =MIN(Fact_Baseline_PV!$A:$A)+4+(0*7) -> 46150 | C24: =SUMIFS(Fact_Baseline_PV!$C:$C,Fact_Baseline_PV!$A:$A,"<="&B24) -> 16400 | D24: =SUMIFS(Fact_Actual_Costs!$D:$D,Fact_Actual_Costs!$A:$A,"<="&B24) -> 16295.04 | E24: {=SUM(IFERROR(LOOKUP(2,1/(Fact_Physical_Progress!$B$2:$B$35=Dim_WBS!$A$2)/(Fact_Physical_Progress!$A$2:$A$35<=B24),Fact_Physical_Progress!$C$2:$C$35),0)*Dim_WBS!$E$2,IFERROR(LOOKUP(2,1/(Fact_Physical_Progress!$B$2:$B$35=Dim_WBS!$A$3)/(Fact_Physical_Progress!$A$2:$A$35<=B24),Fact_Physical_Progress!$C$2:$C$35),0)*Dim_WBS!$E$3,IFERROR(LOOKUP(2,1/(Fact_Physical_Progress!$B$2:$B$35=Dim_WBS!$A$4)/(Fact_Physical_Progress!$A$2:$A$35<=B24),Fact_Physical_Progress!$C$2:$C$35),0)*Dim_WBS!$E$4,IFERROR(LOOKUP(2,1/(Fact_Physical_Progress!$B$2:$B$35=Dim_WBS!$A$5)/(Fact_Physical_Progress!$A$2:$A$35<=B24),Fact_Physical_Progress!$C$2:$C$35),0)*Dim_WBS!$E$5,IFERROR(LOOKUP(2,1/(Fact_Physical_Progress!$B$2:$B$35=Dim_WBS!$A$6)/(Fact_Physical_Progress!$A$2:$A$35<=B24),Fact_Physical_Progress!$C$2:$C$35),0)*Dim_WBS!$E$6,IFERROR(LOOKUP(2,1/(Fact_Physical_Progress!$B$2:$B$35=Dim_WBS!$A$7)/(Fact_Physical_Progress!$A$2:$A$35<=B24),Fact_Physical_Progress!$C$2:$C$35),0)*Dim_WBS!$E$7,IFERROR(LOOKUP(2,1/(Fact_Physical_Progress!$B$2:$B$35=Dim_WBS!$A$8)/(Fact_Physical_Progress!$A$2:$A$35<=B24),Fact_Physical_Progress!$C$2:$C$35),0)*Dim_WBS!$E$8,IFERROR(LOOKUP(2,1/(Fact_Physical_Progress!$B$2:$B$35=Dim_WBS!$A$9)/(Fact_Physical_Progress!$A$2:$A$35<=B24),Fact_Physical_Progress!$C$2:$C$35),0)*Dim_WBS!$E$9,IFERROR(LOOKUP(2,1/(Fact_Physical_Progress!$B$2:$B$35=Dim_WBS!$A$10)/(Fact_Physical_Progress!$A$2:$A$35<=B24),Fact_Physical_Progress!$C$2:$C$35),0)*Dim_WBS!$E$10,IFERROR(LOOKUP(2,1/(Fact_Physical_Progress!$B$2:$B$35=Dim_WBS!$A$11)/(Fact_Physical_Progress!$A$2:$A$35<=B24),Fact_Physical_Progress!$C$2:$C$35),0)*Dim_WBS!$E$11,IFERROR(LOOKUP(2,1/(Fact_Physical_Progress!$B$2:$B$35=Dim_WBS!$A$12)/(Fact_Physical_Progress!$A$2:$A$35<=B24),Fact_Physical_Progress!$C$2:$C$35),0)*Dim_WBS!$E$12,IFERROR(LOOKUP(2,1/(Fact_Physical_Progress!$B$2:$B$35=Dim_WBS!$A$13)/(Fact_Physical_Progress!$A$2:$A$35<=B24),Fact_Physical_Progress!$C$2:$C$35),0)*Dim_WBS!$E$13)} -> 15087.994 | F24: =IFERROR(E24/D24,0) -> 0.92592556 | G24: =IFERROR(E24/C24,0) -> 0.91999963
A25: 2 | B25: =MIN(Fact_Baseline_PV!$A:$A)+4+(1*7) -> 46157 | C25: =SUMIFS(Fact_Baseline_PV!$C:$C,Fact_Baseline_PV!$A:$A,"<="&B25) -> 39200 | D25: =SUMIFS(Fact_Actual_Costs!$D:$D,Fact_Actual_Costs!$A:$A,"<="&B25) -> 38949.12 | E25: {=SUM(IFERROR(LOOKUP(2,1/(Fact_Physical_Progress!$B$2:$B$35=Dim_WBS!$A$2)/(Fact_Physical_Progress!$A$2:$A$35<=B25),Fact_Physical_Progress!$C$2:$C$35),0)*Dim_WBS!$E$2,IFERROR(LOOKUP(2,1/(Fact_Physical_Progress!$B$2:$B$35=Dim_WBS!$A$3)/(Fact_Physical_Progress!$A$2:$A$35<=B25),Fact_Physical_Progress!$C$2:$C$35),0)*Dim_WBS!$E$3,IFERROR(LOOKUP(2,1/(Fact_Physical_Progress!$B$2:$B$35=Dim_WBS!$A$4)/(Fact_Physical_Progress!$A$2:$A$35<=B25),Fact_Physical_Progress!$C$2:$C$35),0)*Dim_WBS!$E$4,IFERROR(LOOKUP(2,1/(Fact_Physical_Progress!$B$2:$B$35=Dim_WBS!$A$5)/(Fact_Physical_Progress!$A$2:$A$35<=B25),Fact_Physical_Progress!$C$2:$C$35),0)*Dim_WBS!$E$5,IFERROR(LOOKUP(2,1/(Fact_Physical_Progress!$B$2:$B$35=Dim_WBS!$A$6)/(Fact_Physical_Progress!$A$2:$A$35<=B25),Fact_Physical_Progress!$C$2:$C$35),0)*Dim_WBS!$E$6,IFERROR(LOOKUP(2,1/(Fact_Physical_Progress!$B$2:$B$35=Dim_WBS!$A$7)/(Fact_Physical_Progress!$A$2:$A$35<=B25),Fact_Physical_Progress!$C$2:$C$35),0)*Dim_WBS!$E$7,IFERROR(LOOKUP(2,1/(Fact_Physical_Progress!$B$2:$B$35=Dim_WBS!$A$8)/(Fact_Physical_Progress!$A$2:$A$35<=B25),Fact_Physical_Progress!$C$2:$C$35),0)*Dim_WBS!$E$8,IFERROR(LOOKUP(2,1/(Fact_Physical_Progress!$B$2:$B$35=Dim_WBS!$A$9)/(Fact_Physical_Progress!$A$2:$A$35<=B25),Fact_Physical_Progress!$C$2:$C$35),0)*Dim_WBS!$E$9,IFERROR(LOOKUP(2,1/(Fact_Physical_Progress!$B$2:$B$35=Dim_WBS!$A$10)/(Fact_Physical_Progress!$A$2:$A$35<=B25),Fact_Physical_Progress!$C$2:$C$35),0)*Dim_WBS!$E$10,IFERROR(LOOKUP(2,1/(Fact_Physical_Progress!$B$2:$B$35=Dim_WBS!$A$11)/(Fact_Physical_Progress!$A$2:$A$35<=B25),Fact_Physical_Progress!$C$2:$C$35),0)*Dim_WBS!$E$11,IFERROR(LOOKUP(2,1/(Fact_Physical_Progress!$B$2:$B$35=Dim_WBS!$A$12)/(Fact_Physical_Progress!$A$2:$A$35<=B25),Fact_Physical_Progress!$C$2:$C$35),0)*Dim_WBS!$E$12,IFERROR(LOOKUP(2,1/(Fact_Physical_Progress!$B$2:$B$35=Dim_WBS!$A$13)/(Fact_Physical_Progress!$A$2:$A$35<=B25),Fact_Physical_Progress!$C$2:$C$35),0)*Dim_WBS!$E$13)} -> 36064.004 | F25: =IFERROR(E25/D25,0) -> 0.92592602 | G25: =IFERROR(E25/C25,0) -> 0.92000009
A26: 3 | B26: =MIN(Fact_Baseline_PV!$A:$A)+4+(2*7) -> 46164 | C26: =SUMIFS(Fact_Baseline_PV!$C:$C,Fact_Baseline_PV!$A:$A,"<="&B26) -> 62000 | D26: =SUMIFS(Fact_Actual_Costs!$D:$D,Fact_Actual_Costs!$A:$A,"<="&B26) -> 61603.2 | E26: {=SUM(IFERROR(LOOKUP(2,1/(Fact_Physical_Progress!$B$2:$B$35=Dim_WBS!$A$2)/(Fact_Physical_Progress!$A$2:$A$35<=B26),Fact_Physical_Progress!$C$2:$C$35),0)*Dim_WBS!$E$2,IFERROR(LOOKUP(2,1/(Fact_Physical_Progress!$B$2:$B$35=Dim_WBS!$A$3)/(Fact_Physical_Progress!$A$2:$A$35<=B26),Fact_Physical_Progress!$C$2:$C$35),0)*Dim_WBS!$E$3,IFERROR(LOOKUP(2,1/(Fact_Physical_Progress!$B$2:$B$35=Dim_WBS!$A$4)/(Fact_Physical_Progress!$A$2:$A$35<=B26),Fact_Physical_Progress!$C$2:$C$35),0)*Dim_WBS!$E$4,IFERROR(LOOKUP(2,1/(Fact_Physical_Progress!$B$2:$B$35=Dim_WBS!$A$5)/(Fact_Physical_Progress!$A$2:$A$35<=B26),Fact_Physical_Progress!$C$2:$C$35),0)*Dim_WBS!$E$5,IFERROR(LOOKUP(2,1/(Fact_Physical_Progress!$B$2:$B$35=Dim_WBS!$A$6)/(Fact_Physical_Progress!$A$2:$A$35<=B26),Fact_Physical_Progress!$C$2:$C$35),0)*Dim_WBS!$E$6,IFERROR(LOOKUP(2,1/(Fact_Physical_Progress!$B$2:$B$35=Dim_WBS!$A$7)/(Fact_Physical_Progress!$A$2:$A$35<=B26),Fact_Physical_Progress!$C$2:$C$35),0)*Dim_WBS!$E$7,IFERROR(LOOKUP(2,1/(Fact_Physical_Progress!$B$2:$B$35=Dim_WBS!$A$8)/(Fact_Physical_Progress!$A$2:$A$35<=B26),Fact_Physical_Progress!$C$2:$C$35),0)*Dim_WBS!$E$8,IFERROR(LOOKUP(2,1/(Fact_Physical_Progress!$B$2:$B$35=Dim_WBS!$A$9)/(Fact_Physical_Progress!$A$2:$A$35<=B26),Fact_Physical_Progress!$C$2:$C$35),0)*Dim_WBS!$E$9,IFERROR(LOOKUP(2,1/(Fact_Physical_Progress!$B$2:$B$35=Dim_WBS!$A$10)/(Fact_Physical_Progress!$A$2:$A$35<=B26),Fact_Physical_Progress!$C$2:$C$35),0)*Dim_WBS!$E$10,IFERROR(LOOKUP(2,1/(Fact_Physical_Progress!$B$2:$B$35=Dim_WBS!$A$11)/(Fact_Physical_Progress!$A$2:$A$35<=B26),Fact_Physical_Progress!$C$2:$C$35),0)*Dim_WBS!$E$11,IFERROR(LOOKUP(2,1/(Fact_Physical_Progress!$B$2:$B$35=Dim_WBS!$A$12)/(Fact_Physical_Progress!$A$2:$A$35<=B26),Fact_Physical_Progress!$C$2:$C$35),0)*Dim_WBS!$E$12,IFERROR(LOOKUP(2,1/(Fact_Physical_Progress!$B$2:$B$35=Dim_WBS!$A$13)/(Fact_Physical_Progress!$A$2:$A$35<=B26),Fact_Physical_Progress!$C$2:$C$35),0)*Dim_WBS!$E$13)} -> 57040 | F26: =IFERROR(E26/D26,0) -> 0.92592593 | G26: =IFERROR(E26/C26,0) -> 0.92
A27: 4 | B27: =MIN(Fact_Baseline_PV!$A:$A)+4+(3*7) -> 46171 | C27: =SUMIFS(Fact_Baseline_PV!$C:$C,Fact_Baseline_PV!$A:$A,"<="&B27) -> 87066.67 | D27: =SUMIFS(Fact_Actual_Costs!$D:$D,Fact_Actual_Costs!$A:$A,"<="&B27) -> 86509.44 | E27: {=SUM(IFERROR(LOOKUP(2,1/(Fact_Physical_Progress!$B$2:$B$35=Dim_WBS!$A$2)/(Fact_Physical_Progress!$A$2:$A$35<=B27),Fact_Physical_Progress!$C$2:$C$35),0)*Dim_WBS!$E$2,IFERROR(LOOKUP(2,1/(Fact_Physical_Progress!$B$2:$B$35=Dim_WBS!$A$3)/(Fact_Physical_Progress!$A$2:$A$35<=B27),Fact_Physical_Progress!$C$2:$C$35),0)*Dim_WBS!$E$3,IFERROR(LOOKUP(2,1/(Fact_Physical_Progress!$B$2:$B$35=Dim_WBS!$A$4)/(Fact_Physical_Progress!$A$2:$A$35<=B27),Fact_Physical_Progress!$C$2:$C$35),0)*Dim_WBS!$E$4,IFERROR(LOOKUP(2,1/(Fact_Physical_Progress!$B$2:$B$35=Dim_WBS!$A$5)/(Fact_Physical_Progress!$A$2:$A$35<=B27),Fact_Physical_Progress!$C$2:$C$35),0)*Dim_WBS!$E$5,IFERROR(LOOKUP(2,1/(Fact_Physical_Progress!$B$2:$B$35=Dim_WBS!$A$6)/(Fact_Physical_Progress!$A$2:$A$35<=B27),Fact_Physical_Progress!$C$2:$C$35),0)*Dim_WBS!$E$6,IFERROR(LOOKUP(2,1/(Fact_Physical_Progress!$B$2:$B$35=Dim_WBS!$A$7)/(Fact_Physical_Progress!$A$2:$A$35<=B27),Fact_Physical_Progress!$C$2:$C$35),0)*Dim_WBS!$E$7,IFERROR(LOOKUP(2,1/(Fact_Physical_Progress!$B$2:$B$35=Dim_WBS!$A$8)/(Fact_Physical_Progress!$A$2:$A$35<=B27),Fact_Physical_Progress!$C$2:$C$35),0)*Dim_WBS!$E$8,IFERROR(LOOKUP(2,1/(Fact_Physical_Progress!$B$2:$B$35=Dim_WBS!$A$9)/(Fact_Physical_Progress!$A$2:$A$35<=B27),Fact_Physical_Progress!$C$2:$C$35),0)*Dim_WBS!$E$9,IFERROR(LOOKUP(2,1/(Fact_Physical_Progress!$B$2:$B$35=Dim_WBS!$A$10)/(Fact_Physical_Progress!$A$2:$A$35<=B27),Fact_Physical_Progress!$C$2:$C$35),0)*Dim_WBS!$E$10,IFERROR(LOOKUP(2,1/(Fact_Physical_Progress!$B$2:$B$35=Dim_WBS!$A$11)/(Fact_Physical_Progress!$A$2:$A$35<=B27),Fact_Physical_Progress!$C$2:$C$35),0)*Dim_WBS!$E$11,IFERROR(LOOKUP(2,1/(Fact_Physical_Progress!$B$2:$B$35=Dim_WBS!$A$12)/(Fact_Physical_Progress!$A$2:$A$35<=B27),Fact_Physical_Progress!$C$2:$C$35),0)*Dim_WBS!$E$12,IFERROR(LOOKUP(2,1/(Fact_Physical_Progress!$B$2:$B$35=Dim_WBS!$A$13)/(Fact_Physical_Progress!$A$2:$A$35<=B27),Fact_Physical_Progress!$C$2:$C$35),0)*Dim_WBS!$E$13)} -> 80101.328 | F27: =IFERROR(E27/D27,0) -> 0.92592586 | G27: =IFERROR(E27/C27,0) -> 0.9199999
A28: 5 | B28: =MIN(Fact_Baseline_PV!$A:$A)+4+(4*7) -> 46178 | C28: =SUMIFS(Fact_Baseline_PV!$C:$C,Fact_Baseline_PV!$A:$A,"<="&B28) -> 116733.34 | D28: =SUMIFS(Fact_Actual_Costs!$D:$D,Fact_Actual_Costs!$A:$A,"<="&B28) -> 115986.24 | E28: {=SUM(IFERROR(LOOKUP(2,1/(Fact_Physical_Progress!$B$2:$B$35=Dim_WBS!$A$2)/(Fact_Physical_Progress!$A$2:$A$35<=B28),Fact_Physical_Progress!$C$2:$C$35),0)*Dim_WBS!$E$2,IFERROR(LOOKUP(2,1/(Fact_Physical_Progress!$B$2:$B$35=Dim_WBS!$A$3)/(Fact_Physical_Progress!$A$2:$A$35<=B28),Fact_Physical_Progress!$C$2:$C$35),0)*Dim_WBS!$E$3,IFERROR(LOOKUP(2,1/(Fact_Physical_Progress!$B$2:$B$35=Dim_WBS!$A$4)/(Fact_Physical_Progress!$A$2:$A$35<=B28),Fact_Physical_Progress!$C$2:$C$35),0)*Dim_WBS!$E$4,IFERROR(LOOKUP(2,1/(Fact_Physical_Progress!$B$2:$B$35=Dim_WBS!$A$5)/(Fact_Physical_Progress!$A$2:$A$35<=B28),Fact_Physical_Progress!$C$2:$C$35),0)*Dim_WBS!$E$5,IFERROR(LOOKUP(2,1/(Fact_Physical_Progress!$B$2:$B$35=Dim_WBS!$A$6)/(Fact_Physical_Progress!$A$2:$A$35<=B28),Fact_Physical_Progress!$C$2:$C$35),0)*Dim_WBS!$E$6,IFERROR(LOOKUP(2,1/(Fact_Physical_Progress!$B$2:$B$35=Dim_WBS!$A$7)/(Fact_Physical_Progress!$A$2:$A$35<=B28),Fact_Physical_Progress!$C$2:$C$35),0)*Dim_WBS!$E$7,IFERROR(LOOKUP(2,1/(Fact_Physical_Progress!$B$2:$B$35=Dim_WBS!$A$8)/(Fact_Physical_Progress!$A$2:$A$35<=B28),Fact_Physical_Progress!$C$2:$C$35),0)*Dim_WBS!$E$8,IFERROR(LOOKUP(2,1/(Fact_Physical_Progress!$B$2:$B$35=Dim_WBS!$A$9)/(Fact_Physical_Progress!$A$2:$A$35<=B28),Fact_Physical_Progress!$C$2:$C$35),0)*Dim_WBS!$E$9,IFERROR(LOOKUP(2,1/(Fact_Physical_Progress!$B$2:$B$35=Dim_WBS!$A$10)/(Fact_Physical_Progress!$A$2:$A$35<=B28),Fact_Physical_Progress!$C$2:$C$35),0)*Dim_WBS!$E$10,IFERROR(LOOKUP(2,1/(Fact_Physical_Progress!$B$2:$B$35=Dim_WBS!$A$11)/(Fact_Physical_Progress!$A$2:$A$35<=B28),Fact_Physical_Progress!$C$2:$C$35),0)*Dim_WBS!$E$11,IFERROR(LOOKUP(2,1/(Fact_Physical_Progress!$B$2:$B$35=Dim_WBS!$A$12)/(Fact_Physical_Progress!$A$2:$A$35<=B28),Fact_Physical_Progress!$C$2:$C$35),0)*Dim_WBS!$E$12,IFERROR(LOOKUP(2,1/(Fact_Physical_Progress!$B$2:$B$35=Dim_WBS!$A$13)/(Fact_Physical_Progress!$A$2:$A$35<=B28),Fact_Physical_Progress!$C$2:$C$35),0)*Dim_WBS!$E$13)} -> 107394.67 | F28: =IFERROR(E28/D28,0) -> 0.92592599 | G28: =IFERROR(E28/C28,0) -> 0.92000001
A29: 6 | B29: =MIN(Fact_Baseline_PV!$A:$A)+4+(5*7) -> 46185 | C29: =SUMIFS(Fact_Baseline_PV!$C:$C,Fact_Baseline_PV!$A:$A,"<="&B29) -> 142900 | D29: =SUMIFS(Fact_Actual_Costs!$D:$D,Fact_Actual_Costs!$A:$A,"<="&B29) -> 141985.44 | E29: {=SUM(IFERROR(LOOKUP(2,1/(Fact_Physical_Progress!$B$2:$B$35=Dim_WBS!$A$2)/(Fact_Physical_Progress!$A$2:$A$35<=B29),Fact_Physical_Progress!$C$2:$C$35),0)*Dim_WBS!$E$2,IFERROR(LOOKUP(2,1/(Fact_Physical_Progress!$B$2:$B$35=Dim_WBS!$A$3)/(Fact_Physical_Progress!$A$2:$A$35<=B29),Fact_Physical_Progress!$C$2:$C$35),0)*Dim_WBS!$E$3,IFERROR(LOOKUP(2,1/(Fact_Physical_Progress!$B$2:$B$35=Dim_WBS!$A$4)/(Fact_Physical_Progress!$A$2:$A$35<=B29),Fact_Physical_Progress!$C$2:$C$35),0)*Dim_WBS!$E$4,IFERROR(LOOKUP(2,1/(Fact_Physical_Progress!$B$2:$B$35=Dim_WBS!$A$5)/(Fact_Physical_Progress!$A$2:$A$35<=B29),Fact_Physical_Progress!$C$2:$C$35),0)*Dim_WBS!$E$5,IFERROR(LOOKUP(2,1/(Fact_Physical_Progress!$B$2:$B$35=Dim_WBS!$A$6)/(Fact_Physical_Progress!$A$2:$A$35<=B29),Fact_Physical_Progress!$C$2:$C$35),0)*Dim_WBS!$E$6,IFERROR(LOOKUP(2,1/(Fact_Physical_Progress!$B$2:$B$35=Dim_WBS!$A$7)/(Fact_Physical_Progress!$A$2:$A$35<=B29),Fact_Physical_Progress!$C$2:$C$35),0)*Dim_WBS!$E$7,IFERROR(LOOKUP(2,1/(Fact_Physical_Progress!$B$2:$B$35=Dim_WBS!$A$8)/(Fact_Physical_Progress!$A$2:$A$35<=B29),Fact_Physical_Progress!$C$2:$C$35),0)*Dim_WBS!$E$8,IFERROR(LOOKUP(2,1/(Fact_Physical_Progress!$B$2:$B$35=Dim_WBS!$A$9)/(Fact_Physical_Progress!$A$2:$A$35<=B29),Fact_Physical_Progress!$C$2:$C$35),0)*Dim_WBS!$E$9,IFERROR(LOOKUP(2,1/(Fact_Physical_Progress!$B$2:$B$35=Dim_WBS!$A$10)/(Fact_Physical_Progress!$A$2:$A$35<=B29),Fact_Physical_Progress!$C$2:$C$35),0)*Dim_WBS!$E$10,IFERROR(LOOKUP(2,1/(Fact_Physical_Progress!$B$2:$B$35=Dim_WBS!$A$11)/(Fact_Physical_Progress!$A$2:$A$35<=B29),Fact_Physical_Progress!$C$2:$C$35),0)*Dim_WBS!$E$11,IFERROR(LOOKUP(2,1/(Fact_Physical_Progress!$B$2:$B$35=Dim_WBS!$A$12)/(Fact_Physical_Progress!$A$2:$A$35<=B29),Fact_Physical_Progress!$C$2:$C$35),0)*Dim_WBS!$E$12,IFERROR(LOOKUP(2,1/(Fact_Physical_Progress!$B$2:$B$35=Dim_WBS!$A$13)/(Fact_Physical_Progress!$A$2:$A$35<=B29),Fact_Physical_Progress!$C$2:$C$35),0)*Dim_WBS!$E$13)} -> 131468 | F29: =IFERROR(E29/D29,0) -> 0.9259259 | G29: =IFERROR(E29/C29,0) -> 0.91999997
A30: 7 | B30: =MIN(Fact_Baseline_PV!$A:$A)+4+(6*7) -> 46192 | C30: =SUMIFS(Fact_Baseline_PV!$C:$C,Fact_Baseline_PV!$A:$A,"<="&B30) -> 160400 | D30: =SUMIFS(Fact_Actual_Costs!$D:$D,Fact_Actual_Costs!$A:$A,"<="&B30) -> 141985.44 | E30: {=SUM(IFERROR(LOOKUP(2,1/(Fact_Physical_Progress!$B$2:$B$35=Dim_WBS!$A$2)/(Fact_Physical_Progress!$A$2:$A$35<=B30),Fact_Physical_Progress!$C$2:$C$35),0)*Dim_WBS!$E$2,IFERROR(LOOKUP(2,1/(Fact_Physical_Progress!$B$2:$B$35=Dim_WBS!$A$3)/(Fact_Physical_Progress!$A$2:$A$35<=B30),Fact_Physical_Progress!$C$2:$C$35),0)*Dim_WBS!$E$3,IFERROR(LOOKUP(2,1/(Fact_Physical_Progress!$B$2:$B$35=Dim_WBS!$A$4)/(Fact_Physical_Progress!$A$2:$A$35<=B30),Fact_Physical_Progress!$C$2:$C$35),0)*Dim_WBS!$E$4,IFERROR(LOOKUP(2,1/(Fact_Physical_Progress!$B$2:$B$35=Dim_WBS!$A$5)/(Fact_Physical_Progress!$A$2:$A$35<=B30),Fact_Physical_Progress!$C$2:$C$35),0)*Dim_WBS!$E$5,IFERROR(LOOKUP(2,1/(Fact_Physical_Progress!$B$2:$B$35=Dim_WBS!$A$6)/(Fact_Physical_Progress!$A$2:$A$35<=B30),Fact_Physical_Progress!$C$2:$C$35),0)*Dim_WBS!$E$6,IFERROR(LOOKUP(2,1/(Fact_Physical_Progress!$B$2:$B$35=Dim_WBS!$A$7)/(Fact_Physical_Progress!$A$2:$A$35<=B30),Fact_Physical_Progress!$C$2:$C$35),0)*Dim_WBS!$E$7,IFERROR(LOOKUP(2,1/(Fact_Physical_Progress!$B$2:$B$35=Dim_WBS!$A$8)/(Fact_Physical_Progress!$A$2:$A$35<=B30),Fact_Physical_Progress!$C$2:$C$35),0)*Dim_WBS!$E$8,IFERROR(LOOKUP(2,1/(Fact_Physical_Progress!$B$2:$B$35=Dim_WBS!$A$9)/(Fact_Physical_Progress!$A$2:$A$35<=B30),Fact_Physical_Progress!$C$2:$C$35),0)*Dim_WBS!$E$9,IFERROR(LOOKUP(2,1/(Fact_Physical_Progress!$B$2:$B$35=Dim_WBS!$A$10)/(Fact_Physical_Progress!$A$2:$A$35<=B30),Fact_Physical_Progress!$C$2:$C$35),0)*Dim_WBS!$E$10,IFERROR(LOOKUP(2,1/(Fact_Physical_Progress!$B$2:$B$35=Dim_WBS!$A$11)/(Fact_Physical_Progress!$A$2:$A$35<=B30),Fact_Physical_Progress!$C$2:$C$35),0)*Dim_WBS!$E$11,IFERROR(LOOKUP(2,1/(Fact_Physical_Progress!$B$2:$B$35=Dim_WBS!$A$12)/(Fact_Physical_Progress!$A$2:$A$35<=B30),Fact_Physical_Progress!$C$2:$C$35),0)*Dim_WBS!$E$12,IFERROR(LOOKUP(2,1/(Fact_Physical_Progress!$B$2:$B$35=Dim_WBS!$A$13)/(Fact_Physical_Progress!$A$2:$A$35<=B30),Fact_Physical_Progress!$C$2:$C$35),0)*Dim_WBS!$E$13)} -> 131468 | F30: =IFERROR(E30/D30,0) -> 0.9259259 | G30: =IFERROR(E30/C30,0) -> 0.81962591
